Workbook

Sheet GHID
B2: FRYDAY · DASHBOARD FOOD COST — ghid de utilizare
B3: Fișierul pornește de la vânzările reale din săptămâna 03–09.08.2026 (PMIX, 30 magazine) și proiectează food cost-ul până în decembrie. Toate cifrele se recalculează automat — nu trebuie să modifici nimic manual în afara celulelor colorate.
B5: CUM CIRCULĂ DATELE PRIN FIȘIER
B6: Lanțul de calcul | C6: NOMENCLATOR (prețul materiei prime) → REȚETAR (cantități per produs) → SIMULARE PE PRODUS (cost și preț per produs, pe fiecare lună) → cele trei taburi MASTER FC + TOP SALES + TOP FC.
B7: Unde intervii | C7: Doar în celulele colorate. GALBEN = input direct (preț materie primă, cantitate din rețetă, ajustări de preț). ALBASTRU = parametri de calendar și volum. Restul sunt formule — dacă le suprascrii, se rupe lanțul.
B8: Regula de aur | C8: AUGUST este realizat și nu se modifică. Vine din PMIX-ul real. Tot ce se poate ajusta sunt lunile septembrie–decembrie.
B10: TABURILE, IN ORDINEA IN CARE LE FOLOSESTI
B11: CE S-A INTAMPLAT — taburile 2, 3, 4 | C11: Rezultatele realizate si proiectia. Nu se editeaza nimic aici.
B12: 2. MASTER FC SAPTAMANA | C12: Fotografia saptamanii 03–09.08, exact cum a fost. Sus, blocul de indicatori pe trei coloane — TOTAL / InStore / Delivery: food cost, vanzari nete, cost material, profit brut, bucati si ponderea fiecarui canal. Dedesubt, aceleasi cifre pe fiecare categorie. Include si promotiile care au rulat doar in acea saptamana.
B13: 3. MASTER FC LUNA | C13: Aceeasi structura, pe luna august intreaga. Produsele care continua se inmultesc cu saptamanile lunii si cu corectia de volum; promotiile de o saptamana raman la cantitatea reala. Procentul de food cost este identic cu cel saptamanal — proratarea multiplica proportional si costul, si vanzarile.
B14: 4. MASTER FC PERIOADA | C14: Toate cele cinci luni, august → decembrie, pe categorii: vanzari nete si food cost pentru fiecare. La final, trei coloane verzi arata castigul din cresterile de pret — decembrie fata de august, cumulatul pe septembrie–decembrie si procentul. Aici NU sunt incluse economiile la furnizor: vezi efectul pur al preturilor.
B15: UNDE SUNT SI UNDE SE PIERD BANII — taburile 5, 6 | C15: Doua liste care se citesc impreuna.
B16: 5. TOP SALES | C16: Produsele ordonate dupa vanzari nete, descrescator. Vezi imediat ce aduce cei mai multi bani, ce pondere are din total si cu ce food cost.
B17: 6. TOP FC | C17: Aceleasi produse, ordonate dupa food cost de la mare la mic. In capul listei sunt cele mai putin rentabile. Rosu peste 55%, galben 45–55%, verde sub 45%. Incruciseaza-l cu TOP SALES: un produs sus in ambele liste este cea mai mare pierdere.
B18: CE POTI SCHIMBA — taburile 7, 8, 9 | C18: Aici intervii ca sa testezi scenarii.
B19: 7. SCENARIU ← panoul de control | C19: Inima fisierului. Patru zone: corectia de volum a saptamanii; zilele calendaristice si indexul de volum pe luna; grila de ajustari de pret pe categorie; blocul de rezultat cu vanzari, cost, economii, food cost cu si fara economii, marja bruta. Orice modifici aici se propaga instantaneu in toate celelalte taburi.
B20: 8. SIMULARE PE PRODUS | C20: Detaliul complet: bucati pe canal, cost unitar, cost material, pretul din iulie ca referinta, apoi pretul pe fiecare luna cu vanzarile si food cost-ul aferent. La capatul din dreapta, coloanele verzi arata cresterea fata de luna anterioara. Coloana Continua? spune daca produsul ramane in meniu dupa august — pune 0 pentru promotii limitate.
B21: 9. ECONOMII | C21: Renegocierile cu furnizorii: spend lunar, procent de economie si luna din care se aplica. Rezultatul intra automat in SCENARIU si scade food cost-ul. Diferenta dintre FC cu economii si FC fara economii iti arata exact cat valoreaza.
B22: DE UNDE VINE COSTUL — taburile 10, 11 | C22: Sursele primare. Orice modificare aici se propaga in tot fisierul.
... B24: 11. NOMENCLATOR | C24: Cele ~200 de materii prime cu pretul pe unitatea de baza. Este singurul input primar din tot fisierul — schimbi un pret aici si se recalculeaza costul fiecarui produs care contine acea materie prima.
B26: CUM FACI O SIMULARE — pas cu pas
B27: Pasul 1 — vreau să văd unde pierd bani | C27: Deschide TOP FC. Produsele din capul listei au food cost-ul cel mai prost. Compară-le cu TOP SALES: dacă un produs e sus în ambele, acolo pierzi cel mai mult.
B28: Pasul 2 — vreau să testez o creștere de preț | C28: Mergi în SCENARIU, în grila de ajustări. Găsește categoria, pune suma în lei (cu TVA) pe luna dorită. Sumele se cumulează: dacă pui 0,50 în septembrie, produsele rămân cu +0,50 și în octombrie, noiembrie, decembrie. Dacă vrei încă 0,50 în decembrie, mai adaugi 0,50 acolo.
B29: Pasul 3 — vreau să văd efectul | C29: Rezultatul apare imediat în SCENARIU (blocul de jos), în MASTER FC PERIOADĂ pe categoria respectivă, și în SIMULARE PE PRODUS la fiecare produs din acea categorie.
B30: Pasul 4 — vreau să testez o renegociere | C30: În tabul ECONOMII schimbi procentul de economie sau luna din care se aplică. Diferența dintre rândul "FC cu economii" și "FC fără economii" din SCENARIU îți arată exact cât valorează renegocierea, în puncte de food cost.
B31: Pasul 5 — vreau să schimb o rețetă | C31: În REȚETAR modifici cantitatea. Costul produsului se recalculează automat, la fel food cost-ul lui, al categoriei și cel general. Dacă schimbi prețul unei materii prime, o faci în NOMENCLATOR.
B33: LUCRURI DE ȘTIUT CÂND CITEȘTI CIFRELE
B34: Food cost-ul nu depinde de volum | C34: Dacă modifici indexul de volum sau zilele din lună, procentul de food cost rămâne același — se schimbă doar sumele absolute. Volumul multiplică proporțional și costul, și vânzările. Food cost-ul se mișcă doar din preț, din rețetă sau din economii.
B35: De ce diferă FC-ul între taburi | C35: MASTER FC PERIOADĂ arată food cost-ul FĂRĂ economiile la furnizor. SCENARIU le include. Diferența dintre cele două rânduri din SCENARIU îți spune exact cât aduc renegocierile.
B36: Prețul din iulie | C36: Este referința de plecare, luată din PMIX-ul real din iulie. Nu are vânzări sau food cost propriu în fișier — servește doar ca să vezi cât a crescut prețul de atunci.
B37: Coloana "Continuă?" | C37: Pune 0 la un produs care iese din meniu sau care a fost promoție limitată. Rămâne în luna în care s-a vândut, dar nu se mai extrapolează în lunile următoare. Pune 1 pentru produsele care rămân în meniu.
B38: Garanțiile SGR | C38: Apar cu food cost 121% — este normal. Sunt sume recuperabile, nu vânzare, și costul lor este egal cu prețul. Le păstrăm ca să se potrivească cu raportul din NBO.
B40: CODUL CULORILOR
B41: GALBEN | C41: Celulă editabilă — input direct: preț materie primă, cantitate din rețetă, ajustare de preț, procent de economie.
B42: ALBASTRU | C42: Parametru de calendar sau volum: zile în lună, corecție de volum, index de volum.
B43: VERDE | C43: Rezultat calculat pe care îl citești: creșteri de preț, câștiguri, food cost sub 45%.
B44: PORTOCALIU | C44: Atenție: food cost peste 55%, sau produs care nu continuă după august.
B45: GRI | C45: Referință istorică — prețul din iulie, august realizat. Nu se modifică.
B47: Sursa datelor: PMIX 4.7 Sales Mix (03–09.08.2026, 30 magazine România) · rețetar și nomenclator NBO · plan de prețuri august–decembrie 2026.

Sheet MASTER FC SĂPTĂMÂNĂ
A1: MASTER FC SĂPTĂMÂNĂ — food cost pe categorie
A2: August, săptămâna 03–09.08.2026 — exact volumele din PMIX, fără scalare. Include și promoțiile care au rulat doar în această săptămână.
C3: TOTAL | D3: InStore | E3: Delivery
A4: FOOD COST | C4: =IFERROR($J$34/$H$34,"") -> 0.45829146 | D4: =$L$34 -> 0.46830754 | E4: =$M$34 -> 0.45193279 | H4: =$L$34 -> 0.46830754 | J4: =$M$34 -> 0.45193279
A5: Vânzări nete | C5: =$H$34 -> 4747683.6 | D5: =$F$34 -> 3209348.7 | E5: =$G$34 -> 1538334.9 | H5: =$J$34 -> 2175822.9 | J5: =$N$34 -> 2571860.7
A6: Cost material | C6: =$J$34 -> 2175822.9 | D6: =IFERROR($D$4*$D$5,"") -> 1502962.2 | E6: =IFERROR($E$4*$E$5,"") -> 695224
A7: Profit brut | C7: =$N$34 -> 2571860.7 | D7: =$D$5-$D$6 -> 1706386.5 | E7: =$E$5-$E$6 -> 843110.93
A8: Bucăți | C8: =$D$34 -> 437155 | D8: =$B$34 -> 269792 | E8: =$C$34 -> 167363
A9: % din vânzări | C9: =1 -> 1 | D9: =IFERROR($D$5/$C$5,"") -> 0.675982 | E9: =IFERROR($E$5/$C$5,"") -> 0.324018
A10: % din bucăți | C10: =1 -> 1 | D10: =IFERROR($D$8/$C$8,"") -> 0.6171541 | E10: =IFERROR($E$8/$C$8,"") -> 0.3828459
A13: Categorie | B13: Buc InStore | C13: Buc Delivery | D13: Buc TOTAL | E13: % din buc | F13: Net InStore | G13: Net Delivery | H13: Net TOTAL | I13: % din vânzări | J13: Cost material | K13: FOOD COST | L13: FC InStore | M13: FC Delivery | N13: Profit brut
A14: BURGERI CORE VITĂ | B14: =SUMIFS('SIMULARE PE PRODUS'!$F$6:$F$243,'SIMULARE PE PRODUS'!$C$6:$C$243,$A14,'SIMULARE PE PRODUS'!$D$6:$D$243,"<2")*1 -> 38959 | C14: =SUMIFS('SIMULARE PE PRODUS'!$G$6:$G$243,'SIMULARE PE PRODUS'!$C$6:$C$243,$A14,'SIMULARE PE PRODUS'!$D$6:$D$243,"<2")*1 -> 17803 | D14: =$B14+$C14 -> 56762 | E14: =IFERROR($D14/$D$34,"") -> 0.12984411 | F14: =SUMIFS('SIMULARE PE PRODUS'!R$6:R$243,'SIMULARE PE PRODUS'!$C$6:$C$243,$A14,'SIMULARE PE PRODUS'!$D$6:$D$243,"<2")*1 -> 479827.5 | G14: =SUMIFS('SIMULARE PE PRODUS'!S$6:S$243,'SIMULARE PE PRODUS'!$C$6:$C$243,$A14,'SIMULARE PE PRODUS'!$D$6:$D$243,"<2")*1 -> 307625.56 | H14: =$F14+$G14 -> 787453.05 | I14: =IFERROR($H14/$H$34,"") -> 0.16586047 | J14: =SUMIFS('SIMULARE PE PRODUS'!$L$6:$L$243,'SIMULARE PE PRODUS'!$C$6:$C$243,$A14,'SIMULARE PE PRODUS'!$D$6:$D$243,"<2")*1 -> 551793.05 | K14: =IFERROR($J14/$H14,"") -> 0.70073136 | L14: =IFERROR(SUMIFS('SIMULARE PE PRODUS'!$J$6:$J$243,'SIMULARE PE PRODUS'!$C$6:$C$243,$A14)/$F14,"") -> 0.7411331 | M14: =IFERROR(SUMIFS('SIMULARE PE PRODUS'!$K$6:$K$243,'SIMULARE PE PRODUS'!$C$6:$C$243,$A14)/$G14,"") -> 0.63771362 | N14: =$H14-$J14 -> 235660.01
A15: BURGERI CORE PUI | B15: =SUMIFS('SIMULARE PE PRODUS'!$F$6:$F$243,'SIMULARE PE PRODUS'!$C$6:$C$243,$A15,'SIMULARE PE PRODUS'!$D$6:$D$243,"<2")*1 -> 9584 | C15: =SUMIFS('SIMULARE PE PRODUS'!$G$6:$G$243,'SIMULARE PE PRODUS'!$C$6:$C$243,$A15,'SIMULARE PE PRODUS'!$D$6:$D$243,"<2")*1 -> 2792 | D15: =$B15+$C15 -> 12376 | E15: =IFERROR($D15/$D$34,"") -> 0.028310325 | F15: =SUMIFS('SIMULARE PE PRODUS'!R$6:R$243,'SIMULARE PE PRODUS'!$C$6:$C$243,$A15,'SIMULARE PE PRODUS'!$D$6:$D$243,"<2")*1 -> 69200 | G15: =SUMIFS('SIMULARE PE PRODUS'!S$6:S$243,'SIMULARE PE PRODUS'!$C$6:$C$243,$A15,'SIMULARE PE PRODUS'!$D$6:$D$243,"<2")*1 -> 31425.045 | H15: =$F15+$G15 -> 100625.05 | I15: =IFERROR($H15/$H$34,"") -> 0.021194556 | J15: =SUMIFS('SIMULARE PE PRODUS'!$L$6:$L$243,'SIMULARE PE PRODUS'!$C$6:$C$243,$A15,'SIMULARE PE PRODUS'!$D$6:$D$243,"<2")*1 -> 56934.195 | K15: =IFERROR($J15/$H15,"") -> 0.56580541 | L15: =IFERROR(SUMIFS('SIMULARE PE PRODUS'!$J$6:$J$243,'SIMULARE PE PRODUS'!$C$6:$C$243,$A15)/$F15,"") -> 0.62609109 | M15: =IFERROR(SUMIFS('SIMULARE PE PRODUS'!$K$6:$K$243,'SIMULARE PE PRODUS'!$C$6:$C$243,$A15)/$G15,"") -> 0.4330524 | N15: =$H15-$J15 -> 43690.85
A16: BURGERI NON-CORE VITĂ | B16: =SUMIFS('SIMULARE PE PRODUS'!$F$6:$F$243,'SIMULARE PE PRODUS'!$C$6:$C$243,$A16,'SIMULARE PE PRODUS'!$D$6:$D$243,"<2")*1 -> 24688 | C16: =SUMIFS('SIMULARE PE PRODUS'!$G$6:$G$243,'SIMULARE PE PRODUS'!$C$6:$C$243,$A16,'SIMULARE PE PRODUS'!$D$6:$D$243,"<2")*1 -> 12372 | D16: =$B16+$C16 -> 37060 | E16: =IFERROR($D16/$D$34,"") -> 0.084775423 | F16: =SUMIFS('SIMULARE PE PRODUS'!R$6:R$243,'SIMULARE PE PRODUS'!$C$6:$C$243,$A16,'SIMULARE PE PRODUS'!$D$6:$D$243,"<2")*1 -> 590440.65 | G16: =SUMIFS('SIMULARE PE PRODUS'!S$6:S$243,'SIMULARE PE PRODUS'!$C$6:$C$243,$A16,'SIMULARE PE PRODUS'!$D$6:$D$243,"<2")*1 -> 334103.41 | H16: =$F16+$G16 -> 924544.05 | I16: =IFERROR($H16/$H$34,"") -> 0.19473582 | J16: =SUMIFS('SIMULARE PE PRODUS'!$L$6:$L$243,'SIMULARE PE PRODUS'!$C$6:$C$243,$A16,'SIMULARE PE PRODUS'!$D$6:$D$243,"<2")*1 -> 433567.01 | K16: =IFERROR($J16/$H16,"") -> 0.46895225 | L16: =IFERROR(SUMIFS('SIMULARE PE PRODUS'!$J$6:$J$243,'SIMULARE PE PRODUS'!$C$6:$C$243,$A16)/$F16,"") -> 0.48424039 | M16: =IFERROR(SUMIFS('SIMULARE PE PRODUS'!$K$6:$K$243,'SIMULARE PE PRODUS'!$C$6:$C$243,$A16)/$G16,"") -> 0.44193443 | N16: =$H16-$J16 -> 490977.04
A17: BURGERI NON-CORE PUI | B17: =SUMIFS('SIMULARE PE PRODUS'!$F$6:$F$243,'SIMULARE PE PRODUS'!$C$6:$C$243,$A17,'SIMULARE PE PRODUS'!$D$6:$D$243,"<2")*1 -> 12344 | C17: =SUMIFS('SIMULARE PE PRODUS'!$G$6:$G$243,'SIMULARE PE PRODUS'!$C$6:$C$243,$A17,'SIMULARE PE PRODUS'!$D$6:$D$243,"<2")*1 -> 6038 | D17: =$B17+$C17 -> 18382 | E17: =IFERROR($D17/$D$34,"") -> 0.042049159 | F17: =SUMIFS('SIMULARE PE PRODUS'!R$6:R$243,'SIMULARE PE PRODUS'!$C$6:$C$243,$A17,'SIMULARE PE PRODUS'!$D$6:$D$243,"<2")*1 -> 215697.54 | G17: =SUMIFS('SIMULARE PE PRODUS'!S$6:S$243,'SIMULARE PE PRODUS'!$C$6:$C$243,$A17,'SIMULARE PE PRODUS'!$D$6:$D$243,"<2")*1 -> 117302.36 | H17: =$F17+$G17 -> 332999.9 | I17: =IFERROR($H17/$H$34,"") -> 0.070139447 | J17: =SUMIFS('SIMULARE PE PRODUS'!$L$6:$L$243,'SIMULARE PE PRODUS'!$C$6:$C$243,$A17,'SIMULARE PE PRODUS'!$D$6:$D$243,"<2")*1 -> 126780.89 | K17: =IFERROR($J17/$H17,"") -> 0.38072352 | L17: =IFERROR(SUMIFS('SIMULARE PE PRODUS'!$J$6:$J$243,'SIMULARE PE PRODUS'!$C$6:$C$243,$A17)/$F17,"") -> 0.39295887 | M17: =IFERROR(SUMIFS('SIMULARE PE PRODUS'!$K$6:$K$243,'SIMULARE PE PRODUS'!$C$6:$C$243,$A17)/$G17,"") -> 0.35822495 | N17: =$H17-$J17 -> 206219.01
A18: CREVEȚI | B18: =SUMIFS('SIMULARE PE PRODUS'!$F$6:$F$243,'SIMULARE PE PRODUS'!$C$6:$C$243,$A18,'SIMULARE PE PRODUS'!$D$6:$D$243,"<2")*1 -> 470 | C18: =SUMIFS('SIMULARE PE PRODUS'!$G$6:$G$243,'SIMULARE PE PRODUS'!$C$6:$C$243,$A18,'SIMULARE PE PRODUS'!$D$6:$D$243,"<2")*1 -> 268 | D18: =$B18+$C18 -> 738 | E18: =IFERROR($D18/$D$34,"") -> 0.0016881884 | F18: =SUMIFS('SIMULARE PE PRODUS'!R$6:R$243,'SIMULARE PE PRODUS'!$C$6:$C$243,$A18,'SIMULARE PE PRODUS'!$D$6:$D$243,"<2")*1 -> 11004.775 | G18: =SUMIFS('SIMULARE PE PRODUS'!S$6:S$243,'SIMULARE PE PRODUS'!$C$6:$C$243,$A18,'SIMULARE PE PRODUS'!$D$6:$D$243,"<2")*1 -> 6999.3874 | H18: =$F18+$G18 -> 18004.162 | I18: =IFERROR($H18/$H$34,"") -> 0.0037921992 | J18: =SUMIFS('SIMULARE PE PRODUS'!$L$6:$L$243,'SIMULARE PE PRODUS'!$C$6:$C$243,$A18,'SIMULARE PE PRODUS'!$D$6:$D$243,"<2")*1 -> 7952.2225 | K18: =IFERROR($J18/$H18,"") -> 0.44168801 | L18: =IFERROR(SUMIFS('SIMULARE PE PRODUS'!$J$6:$J$243,'SIMULARE PE PRODUS'!$C$6:$C$243,$A18)/$F18,"") -> 0.46020238 | M18: =IFERROR(SUMIFS('SIMULARE PE PRODUS'!$K$6:$K$243,'SIMULARE PE PRODUS'!$C$6:$C$243,$A18)/$G18,"") -> 0.41257881 | N18: =$H18-$J18 -> 10051.94
A19: VEGETARIAN | B19: =SUMIFS('SIMULARE PE PRODUS'!$F$6:$F$243,'SIMULARE PE PRODUS'!$C$6:$C$243,$A19,'SIMULARE PE PRODUS'!$D$6:$D$243,"<2")*1 -> 739 | C19: =SUMIFS('SIMULARE PE PRODUS'!$G$6:$G$243,'SIMULARE PE PRODUS'!$C$6:$C$243,$A19,'SIMULARE PE PRODUS'!$D$6:$D$243,"<2")*1 -> 253 | D19: =$B19+$C19 -> 992 | E19: =IFERROR($D19/$D$34,"") -> 0.002269218 | F19: =SUMIFS('SIMULARE PE PRODUS'!R$6:R$243,'SIMULARE PE PRODUS'!$C$6:$C$243,$A19,'SIMULARE PE PRODUS'!$D$6:$D$243,"<2")*1 -> 13974.423 | G19: =SUMIFS('SIMULARE PE PRODUS'!S$6:S$243,'SIMULARE PE PRODUS'!$C$6:$C$243,$A19,'SIMULARE PE PRODUS'!$D$6:$D$243,"<2")*1 -> 5467.991 | H19: =$F19+$G19 -> 19442.414 | I19: =IFERROR($H19/$H$34,"") -> 0.0040951369 | J19: =SUMIFS('SIMULARE PE PRODUS'!$L$6:$L$243,'SIMULARE PE PRODUS'!$C$6:$C$243,$A19,'SIMULARE PE PRODUS'!$D$6:$D$243,"<2")*1 -> 7133.8174 | K19: =IFERROR($J19/$H19,"") -> 0.36692035 | L19: =IFERROR(SUMIFS('SIMULARE PE PRODUS'!$J$6:$J$243,'SIMULARE PE PRODUS'!$C$6:$C$243,$A19)/$F19,"") -> 0.38029521 | M19: =IFERROR(SUMIFS('SIMULARE PE PRODUS'!$K$6:$K$243,'SIMULARE PE PRODUS'!$C$6:$C$243,$A19)/$G19,"") -> 0.3327385 | N19: =$H19-$J19 -> 12308.597
A20: FRIED CHICKEN | B20: =SUMIFS('SIMULARE PE PRODUS'!$F$6:$F$243,'SIMULARE PE PRODUS'!$C$6:$C$243,$A20,'SIMULARE PE PRODUS'!$D$6:$D$243,"<2")*1 -> 12271 | C20: =SUMIFS('SIMULARE PE PRODUS'!$G$6:$G$243,'SIMULARE PE PRODUS'!$C$6:$C$243,$A20,'SIMULARE PE PRODUS'!$D$6:$D$243,"<2")*1 -> 5947 | D20: =$B20+$C20 -> 18218 | E20: =IFERROR($D20/$D$34,"") -> 0.041674006 | F20: =SUMIFS('SIMULARE PE PRODUS'!R$6:R$243,'SIMULARE PE PRODUS'!$C$6:$C$243,$A20,'SIMULARE PE PRODUS'!$D$6:$D$243,"<2")*1 -> 270446.61 | G20: =SUMIFS('SIMULARE PE PRODUS'!S$6:S$243,'SIMULARE PE PRODUS'!$C$6:$C$243,$A20,'SIMULARE PE PRODUS'!$D$6:$D$243,"<2")*1 -> 154496.63 | H20: =$F20+$G20 -> 424943.24 | I20: =IFERROR($H20/$H$34,"") -> 0.089505384 | J20: =SUMIFS('SIMULARE PE PRODUS'!$L$6:$L$243,'SIMULARE PE PRODUS'!$C$6:$C$243,$A20,'SIMULARE PE PRODUS'!$D$6:$D$243,"<2")*1 -> 194883.48 | K20: =IFERROR($J20/$H20,"") -> 0.45861062 | L20: =IFERROR(SUMIFS('SIMULARE PE PRODUS'!$J$6:$J$243,'SIMULARE PE PRODUS'!$C$6:$C$243,$A20)/$F20,"") -> 0.4887162 | M20: =IFERROR(SUMIFS('SIMULARE PE PRODUS'!$K$6:$K$243,'SIMULARE PE PRODUS'!$C$6:$C$243,$A20)/$G20,"") -> 0.40591074 | N20: =$H20-$J20 -> 230059.76
A21: CARTOFI | B21: =SUMIFS('SIMULARE PE PRODUS'!$F$6:$F$243,'SIMULARE PE PRODUS'!$C$6:$C$243,$A21,'SIMULARE PE PRODUS'!$D$6:$D$243,"<2")*1 -> 52640 | C21: =SUMIFS('SIMULARE PE PRODUS'!$G$6:$G$243,'SIMULARE PE PRODUS'!$C$6:$C$243,$A21,'SIMULARE PE PRODUS'!$D$6:$D$243,"<2")*1 -> 19959 | D21: =$B21+$C21 -> 72599 | E21: =IFERROR($D21/$D$34,"") -> 0.16607153 | F21: =SUMIFS('SIMULARE PE PRODUS'!R$6:R$243,'SIMULARE PE PRODUS'!$C$6:$C$243,$A21,'SIMULARE PE PRODUS'!$D$6:$D$243,"<2")*1 -> 615916.94 | G21: =SUMIFS('SIMULARE PE PRODUS'!S$6:S$243,'SIMULARE PE PRODUS'!$C$6:$C$243,$A21,'SIMULARE PE PRODUS'!$D$6:$D$243,"<2")*1 -> 264921.7 | H21: =$F21+$G21 -> 880838.64 | I21: =IFERROR($H21/$H$34,"") -> 0.18553019 | J21: =SUMIFS('SIMULARE PE PRODUS'!$L$6:$L$243,'SIMULARE PE PRODUS'!$C$6:$C$243,$A21,'SIMULARE PE PRODUS'!$D$6:$D$243,"<2")*1 -> 265056.2 | K21: =IFERROR($J21/$H21,"") -> 0.30091345 | L21: =IFERROR(SUMIFS('SIMULARE PE PRODUS'!$J$6:$J$243,'SIMULARE PE PRODUS'!$C$6:$C$243,$A21)/$F21,"") -> 0.31297184 | M21: =IFERROR(SUMIFS('SIMULARE PE PRODUS'!$K$6:$K$243,'SIMULARE PE PRODUS'!$C$6:$C$243,$A21)/$G21,"") -> 0.35729377 | N21: =$H21-$J21 -> 615782.44
A22: SOSURI | B22: =SUMIFS('SIMULARE PE PRODUS'!$F$6:$F$243,'SIMULARE PE PRODUS'!$C$6:$C$243,$A22,'SIMULARE PE PRODUS'!$D$6:$D$243,"<2")*1 -> 40547 | C22: =SUMIFS('SIMULARE PE PRODUS'!$G$6:$G$243,'SIMULARE PE PRODUS'!$C$6:$C$243,$A22,'SIMULARE PE PRODUS'!$D$6:$D$243,"<2")*1 -> 16944 | D22: =$B22+$C22 -> 57491 | E22: =IFERROR($D22/$D$34,"") -> 0.13151171 | F22: =SUMIFS('SIMULARE PE PRODUS'!R$6:R$243,'SIMULARE PE PRODUS'!$C$6:$C$243,$A22,'SIMULARE PE PRODUS'!$D$6:$D$243,"<2")*1 -> 317648.5 | G22: =SUMIFS('SIMULARE PE PRODUS'!S$6:S$243,'SIMULARE PE PRODUS'!$C$6:$C$243,$A22,'SIMULARE PE PRODUS'!$D$6:$D$243,"<2")*1 -> 154358.2 | H22: =$F22+$G22 -> 472006.7 | I22: =IFERROR($H22/$H$34,"") -> 0.099418315 | J22: =SUMIFS('SIMULARE PE PRODUS'!$L$6:$L$243,'SIMULARE PE PRODUS'!$C$6:$C$243,$A22,'SIMULARE PE PRODUS'!$D$6:$D$243,"<2")*1 -> 147187.95 | K22: =IFERROR($J22/$H22,"") -> 0.31183446 | L22: =IFERROR(SUMIFS('SIMULARE PE PRODUS'!$J$6:$J$243,'SIMULARE PE PRODUS'!$C$6:$C$243,$A22)/$F22,"") -> 0.31123007 | M22: =IFERROR(SUMIFS('SIMULARE PE PRODUS'!$K$6:$K$243,'SIMULARE PE PRODUS'!$C$6:$C$243,$A22)/$G22,"") -> 0.3130782 | N22: =$H22-$J22 -> 324818.75
A23: DRINKS | B23: =SUMIFS('SIMULARE PE PRODUS'!$F$6:$F$243,'SIMULARE PE PRODUS'!$C$6:$C$243,$A23,'SIMULARE PE PRODUS'!$D$6:$D$243,"<2")*1 -> 44484 | C23: =SUMIFS('SIMULARE PE PRODUS'!$G$6:$G$243,'SIMULARE PE PRODUS'!$C$6:$C$243,$A23,'SIMULARE PE PRODUS'!$D$6:$D$243,"<2")*1 -> 2445 | D23: =$B23+$C23 -> 46929 | E23: =IFERROR($D23/$D$34,"") -> 0.10735094 | F23: =SUMIFS('SIMULARE PE PRODUS'!R$6:R$243,'SIMULARE PE PRODUS'!$C$6:$C$243,$A23,'SIMULARE PE PRODUS'!$D$6:$D$243,"<2")*1 -> 361462.66 | G23: =SUMIFS('SIMULARE PE PRODUS'!S$6:S$243,'SIMULARE PE PRODUS'!$C$6:$C$243,$A23,'SIMULARE PE PRODUS'!$D$6:$D$243,"<2")*1 -> 20702.934 | H23: =$F23+$G23 -> 382165.6 | I23: =IFERROR($H23/$H$34,"") -> 0.080495169 | J23: =SUMIFS('SIMULARE PE PRODUS'!$L$6:$L$243,'SIMULARE PE PRODUS'!$C$6:$C$243,$A23,'SIMULARE PE PRODUS'!$D$6:$D$243,"<2")*1 -> 186619.56 | K23: =IFERROR($J23/$H23,"") -> 0.48832119 | L23: =IFERROR(SUMIFS('SIMULARE PE PRODUS'!$J$6:$J$243,'SIMULARE PE PRODUS'!$C$6:$C$243,$A23)/$F23,"") -> 0.49394444 | M23: =IFERROR(SUMIFS('SIMULARE PE PRODUS'!$K$6:$K$243,'SIMULARE PE PRODUS'!$C$6:$C$243,$A23)/$G23,"") -> 0.39014208 | N23: =$H23-$J23 -> 195546.04
A24: FRYCAFE | B24: =SUMIFS('SIMULARE PE PRODUS'!$F$6:$F$243,'SIMULARE PE PRODUS'!$C$6:$C$243,$A24,'SIMULARE PE PRODUS'!$D$6:$D$243,"<2")*1 -> 3873 | C24: =SUMIFS('SIMULARE PE PRODUS'!$G$6:$G$243,'SIMULARE PE PRODUS'!$C$6:$C$243,$A24,'SIMULARE PE PRODUS'!$D$6:$D$243,"<2")*1 -> 755 | D24: =$B24+$C24 -> 4628 | E24: =IFERROR($D24/$D$34,"") -> 0.010586634 | F24: =SUMIFS('SIMULARE PE PRODUS'!R$6:R$243,'SIMULARE PE PRODUS'!$C$6:$C$243,$A24,'SIMULARE PE PRODUS'!$D$6:$D$243,"<2")*1 -> 44957.052 | G24: =SUMIFS('SIMULARE PE PRODUS'!S$6:S$243,'SIMULARE PE PRODUS'!$C$6:$C$243,$A24,'SIMULARE PE PRODUS'!$D$6:$D$243,"<2")*1 -> 11044.374 | H24: =$F24+$G24 -> 56001.426 | I24: =IFERROR($H24/$H$34,"") -> 0.011795526 | J24: =SUMIFS('SIMULARE PE PRODUS'!$L$6:$L$243,'SIMULARE PE PRODUS'!$C$6:$C$243,$A24,'SIMULARE PE PRODUS'!$D$6:$D$243,"<2")*1 -> 23561.386 | K24: =IFERROR($J24/$H24,"") -> 0.42072833 | L24: =IFERROR(SUMIFS('SIMULARE PE PRODUS'!$J$6:$J$243,'SIMULARE PE PRODUS'!$C$6:$C$243,$A24)/$F24,"") -> 0.41733902 | M24: =IFERROR(SUMIFS('SIMULARE PE PRODUS'!$K$6:$K$243,'SIMULARE PE PRODUS'!$C$6:$C$243,$A24)/$G24,"") -> 0.43452479 | N24: =$H24-$J24 -> 32440.04
A25: MILKSHAKE & DESERT | B25: =SUMIFS('SIMULARE PE PRODUS'!$F$6:$F$243,'SIMULARE PE PRODUS'!$C$6:$C$243,$A25,'SIMULARE PE PRODUS'!$D$6:$D$243,"<2")*1 -> 8146 | C25: =SUMIFS('SIMULARE PE PRODUS'!$G$6:$G$243,'SIMULARE PE PRODUS'!$C$6:$C$243,$A25,'SIMULARE PE PRODUS'!$D$6:$D$243,"<2")*1 -> 2818 | D25: =$B25+$C25 -> 10964 | E25: =IFERROR($D25/$D$34,"") -> 0.025080349 | F25: =SUMIFS('SIMULARE PE PRODUS'!R$6:R$243,'SIMULARE PE PRODUS'!$C$6:$C$243,$A25,'SIMULARE PE PRODUS'!$D$6:$D$243,"<2")*1 -> 99635.586 | G25: =SUMIFS('SIMULARE PE PRODUS'!S$6:S$243,'SIMULARE PE PRODUS'!$C$6:$C$243,$A25,'SIMULARE PE PRODUS'!$D$6:$D$243,"<2")*1 -> 35581.081 | H25: =$F25+$G25 -> 135216.67 | I25: =IFERROR($H25/$H$34,"") -> 0.028480556 | J25: =SUMIFS('SIMULARE PE PRODUS'!$L$6:$L$243,'SIMULARE PE PRODUS'!$C$6:$C$243,$A25,'SIMULARE PE PRODUS'!$D$6:$D$243,"<2")*1 -> 52972.115 | K25: =IFERROR($J25/$H25,"") -> 0.39175729 | L25: =IFERROR(SUMIFS('SIMULARE PE PRODUS'!$J$6:$J$243,'SIMULARE PE PRODUS'!$C$6:$C$243,$A25)/$F25,"") -> 0.38264722 | M25: =IFERROR(SUMIFS('SIMULARE PE PRODUS'!$K$6:$K$243,'SIMULARE PE PRODUS'!$C$6:$C$243,$A25)/$G25,"") -> 0.41726769 | N25: =$H25-$J25 -> 82244.552
... A33: GARANTII SGR | B33: =SUMIFS('SIMULARE PE PRODUS'!$F$6:$F$243,'SIMULARE PE PRODUS'!$C$6:$C$243,$A33,'SIMULARE PE PRODUS'!$D$6:$D$243,"<2")*1 -> 0 | C33: =SUMIFS('SIMULARE PE PRODUS'!$G$6:$G$243,'SIMULARE PE PRODUS'!$C$6:$C$243,$A33,'SIMULARE PE PRODUS'!$D$6:$D$243,"<2")*1 -> 6124 | D33: =$B33+$C33 -> 6124 | E33: =IFERROR($D33/$D$34,"") -> 0.014008761 | F33: =SUMIFS('SIMULARE PE PRODUS'!R$6:R$243,'SIMULARE PE PRODUS'!$C$6:$C$243,$A33,'SIMULARE PE PRODUS'!$D$6:$D$243,"<2")*1 -> 0 | G33: =SUMIFS('SIMULARE PE PRODUS'!S$6:S$243,'SIMULARE PE PRODUS'!$C$6:$C$243,$A33,'SIMULARE PE PRODUS'!$D$6:$D$243,"<2")*1 -> 2530.5785 | H33: =$F33+$G33 -> 2530.5785 | I33: =IFERROR($H33/$H$34,"") -> 0.0005330133 | J33: =SUMIFS('SIMULARE PE PRODUS'!$L$6:$L$243,'SIMULARE PE PRODUS'!$C$6:$C$243,$A33,'SIMULARE PE PRODUS'!$D$6:$D$243,"<2")*1 -> 3062 | K33: =IFERROR($J33/$H33,"") -> 1.21 | L33: =IFERROR(SUMIFS('SIMULARE PE PRODUS'!$J$6:$J$243,'SIMULARE PE PRODUS'!$C$6:$C$243,$A33)/$F33,"") | M33: =IFERROR(SUMIFS('SIMULARE PE PRODUS'!$K$6:$K$243,'SIMULARE PE PRODUS'!$C$6:$C$243,$A33)/$G33,"") -> 1.21 | N33: =$H33-$J33 -> -531.42149
A34: TOTAL | B34: =SUM(B14:B33) -> 269792 | C34: =SUM(C14:C33) -> 167363 | D34: =SUM(D14:D33) -> 437155 | E34: =D34/D34 -> 1 | F34: =SUM(F14:F33) -> 3209348.7 | G34: =SUM(G14:G33) -> 1538334.9 | H34: =SUM(H14:H33) -> 4747683.6 | I34: =H34/H34 -> 1 | J34: =SUM(J14:J33) -> 2175822.9 | K34: =IFERROR($J34/$H34,"") -> 0.45829146 | L34: =IFERROR(SUMPRODUCT(ISNUMBER('SIMULARE PE PRODUS'!$A$6:$A$243)*'SIMULARE PE PRODUS'!$J$6:$J$243)/$F34,"") -> 0.46830754 | M34: =IFERROR(SUMPRODUCT(ISNUMBER('SIMULARE PE PRODUS'!$A$6:$A$243)*'SIMULARE PE PRODUS'!$K$6:$K$243)/$G34,"") -> 0.45193279 | N34: =SUM(N14:N33) -> 2571860.7

Sheet MASTER FC LUNĂ
A1: MASTER FC LUNĂ — food cost pe categorie
A2: August pe lună întreagă. Produsele care continuă sunt proratate (× săptămâni/lună × corecție); promoțiile de o săptămână intră la cantitatea reală, neproratate.
C3: TOTAL | D3: InStore | E3: Delivery
A4: FOOD COST | C4: =IFERROR($J$34/$H$34,"") -> 0.45791945 | D4: =$L$34 -> 0.46786244 | E4: =$M$34 -> 0.43730877 | H4: =$L$34 -> 0.46786244 | J4: =$M$34 -> 0.43730877
A5: Vânzări nete | C5: =$H$34 -> 19821304 | D5: =$F$34 -> 13370916 | E5: =$G$34 -> 6450387.9 | H5: =$J$34 -> 9076560.8 | J5: =$N$34 -> 10744744
A6: Cost material | C6: =$J$34 -> 9076560.8 | D6: =IFERROR($D$4*$D$5,"") -> 6255749.6 | E6: =IFERROR($E$4*$E$5,"") -> 2820811.2
A7: Profit brut | C7: =$N$34 -> 10744744 | D7: =$D$5-$D$6 -> 7115166.9 | E7: =$E$5-$E$6 -> 3629576.7
A8: Bucăți | C8: =$D$34 -> 1829382.8 | D8: =$B$34 -> 1127733.8 | E8: =$C$34 -> 701648.99
A9: % din vânzări | C9: =1 -> 1 | D9: =IFERROR($D$5/$C$5,"") -> 0.67457299 | E9: =IFERROR($E$5/$C$5,"") -> 0.32542701
A10: % din bucăți | C10: =1 -> 1 | D10: =IFERROR($D$8/$C$8,"") -> 0.6164559 | E10: =IFERROR($E$8/$C$8,"") -> 0.3835441
A13: Categorie | B13: Buc InStore | C13: Buc Delivery | D13: Buc TOTAL | E13: % din buc | F13: Net InStore | G13: Net Delivery | H13: Net TOTAL | I13: % din vânzări | J13: Cost material | K13: FOOD COST | L13: FC InStore | M13: FC Delivery | N13: Profit brut
A14: BURGERI CORE VITĂ | B14: =SUMIFS('SIMULARE PE PRODUS'!$F$6:$F$243,'SIMULARE PE PRODUS'!$C$6:$C$243,$A14,'SIMULARE PE PRODUS'!$D$6:$D$243,">0")*SCENARIU!$B$10*SCENARIU!$B$5+SUMIFS('SIMULARE PE PRODUS'!$F$6:$F$243,'SIMULARE PE PRODUS'!$C$6:$C$243,$A14,'SIMULARE PE PRODUS'!$D$6:$D$243,0) -> 163271.16 | C14: =SUMIFS('SIMULARE PE PRODUS'!$G$6:$G$243,'SIMULARE PE PRODUS'!$C$6:$C$243,$A14,'SIMULARE PE PRODUS'!$D$6:$D$243,">0")*SCENARIU!$B$10*SCENARIU!$B$5+SUMIFS('SIMULARE PE PRODUS'!$G$6:$G$243,'SIMULARE PE PRODUS'!$C$6:$C$243,$A14,'SIMULARE PE PRODUS'!$D$6:$D$243,0) -> 74609.626 | D14: =$B14+$C14 -> 237880.78 | E14: =IFERROR($D14/$D$34,"") -> 0.13003335 | F14: =SUMIFS('SIMULARE PE PRODUS'!R$6:R$243,'SIMULARE PE PRODUS'!$C$6:$C$243,$A14,'SIMULARE PE PRODUS'!$D$6:$D$243,">0")*SCENARIU!$B$10*SCENARIU!$B$5+SUMIFS('SIMULARE PE PRODUS'!R$6:R$243,'SIMULARE PE PRODUS'!$C$6:$C$243,$A14,'SIMULARE PE PRODUS'!$D$6:$D$243,0) -> 2010883 | G14: =SUMIFS('SIMULARE PE PRODUS'!S$6:S$243,'SIMULARE PE PRODUS'!$C$6:$C$243,$A14,'SIMULARE PE PRODUS'!$D$6:$D$243,">0")*SCENARIU!$B$10*SCENARIU!$B$5+SUMIFS('SIMULARE PE PRODUS'!S$6:S$243,'SIMULARE PE PRODUS'!$C$6:$C$243,$A14,'SIMULARE PE PRODUS'!$D$6:$D$243,0) -> 1289211.3 | H14: =$F14+$G14 -> 3300094.3 | I14: =IFERROR($H14/$H$34,"") -> 0.16649228 | J14: =SUMIFS('SIMULARE PE PRODUS'!$L$6:$L$243,'SIMULARE PE PRODUS'!$C$6:$C$243,$A14,'SIMULARE PE PRODUS'!$D$6:$D$243,">0")*SCENARIU!$B$10*SCENARIU!$B$5+SUMIFS('SIMULARE PE PRODUS'!$L$6:$L$243,'SIMULARE PE PRODUS'!$C$6:$C$243,$A14,'SIMULARE PE PRODUS'!$D$6:$D$243,0) -> 2312479.5 | K14: =IFERROR($J14/$H14,"") -> 0.70073136 | L14: =IFERROR((SUMIFS('SIMULARE PE PRODUS'!$J$6:$J$243,'SIMULARE PE PRODUS'!$C$6:$C$243,$A14,'SIMULARE PE PRODUS'!$D$6:$D$243,">0")*SCENARIU!$B$10*SCENARIU!$B$5+SUMIFS('SIMULARE PE PRODUS'!$J$6:$J$243,'SIMULARE PE PRODUS'!$C$6:$C$243,$A14,'SIMULARE PE PRODUS'!$D$6:$D$243,0))/$F14,"") -> 0.7411331 | M14: =IFERROR((SUMIFS('SIMULARE PE PRODUS'!$K$6:$K$243,'SIMULARE PE PRODUS'!$C$6:$C$243,$A14,'SIMULARE PE PRODUS'!$D$6:$D$243,">0")*SCENARIU!$B$10*SCENARIU!$B$5+SUMIFS('SIMULARE PE PRODUS'!$K$6:$K$243,'SIMULARE PE PRODUS'!$C$6:$C$243,$A14,'SIMULARE PE PRODUS'!$D$6:$D$243,0))/$G14,"") -> 0.63771362 | N14: =$H14-$J14 -> 987614.73
A15: BURGERI CORE PUI | B15: =SUMIFS('SIMULARE PE PRODUS'!$F$6:$F$243,'SIMULARE PE PRODUS'!$C$6:$C$243,$A15,'SIMULARE PE PRODUS'!$D$6:$D$243,">0")*SCENARIU!$B$10*SCENARIU!$B$5+SUMIFS('SIMULARE PE PRODUS'!$F$6:$F$243,'SIMULARE PE PRODUS'!$C$6:$C$243,$A15,'SIMULARE PE PRODUS'!$D$6:$D$243,0) -> 40165.065 | C15: =SUMIFS('SIMULARE PE PRODUS'!$G$6:$G$243,'SIMULARE PE PRODUS'!$C$6:$C$243,$A15,'SIMULARE PE PRODUS'!$D$6:$D$243,">0")*SCENARIU!$B$10*SCENARIU!$B$5+SUMIFS('SIMULARE PE PRODUS'!$G$6:$G$243,'SIMULARE PE PRODUS'!$C$6:$C$243,$A15,'SIMULARE PE PRODUS'!$D$6:$D$243,0) -> 11700.841 | D15: =$B15+$C15 -> 51865.907 | E15: =IFERROR($D15/$D$34,"") -> 0.028351587 | F15: =SUMIFS('SIMULARE PE PRODUS'!R$6:R$243,'SIMULARE PE PRODUS'!$C$6:$C$243,$A15,'SIMULARE PE PRODUS'!$D$6:$D$243,">0")*SCENARIU!$B$10*SCENARIU!$B$5+SUMIFS('SIMULARE PE PRODUS'!R$6:R$243,'SIMULARE PE PRODUS'!$C$6:$C$243,$A15,'SIMULARE PE PRODUS'!$D$6:$D$243,0) -> 290006.52 | G15: =SUMIFS('SIMULARE PE PRODUS'!S$6:S$243,'SIMULARE PE PRODUS'!$C$6:$C$243,$A15,'SIMULARE PE PRODUS'!$D$6:$D$243,">0")*SCENARIU!$B$10*SCENARIU!$B$5+SUMIFS('SIMULARE PE PRODUS'!S$6:S$243,'SIMULARE PE PRODUS'!$C$6:$C$243,$A15,'SIMULARE PE PRODUS'!$D$6:$D$243,0) -> 131697.52 | H15: =$F15+$G15 -> 421704.04 | I15: =IFERROR($H15/$H$34,"") -> 0.021275292 | J15: =SUMIFS('SIMULARE PE PRODUS'!$L$6:$L$243,'SIMULARE PE PRODUS'!$C$6:$C$243,$A15,'SIMULARE PE PRODUS'!$D$6:$D$243,">0")*SCENARIU!$B$10*SCENARIU!$B$5+SUMIFS('SIMULARE PE PRODUS'!$L$6:$L$243,'SIMULARE PE PRODUS'!$C$6:$C$243,$A15,'SIMULARE PE PRODUS'!$D$6:$D$243,0) -> 238602.43 | K15: =IFERROR($J15/$H15,"") -> 0.56580541 | L15: =IFERROR((SUMIFS('SIMULARE PE PRODUS'!$J$6:$J$243,'SIMULARE PE PRODUS'!$C$6:$C$243,$A15,'SIMULARE PE PRODUS'!$D$6:$D$243,">0")*SCENARIU!$B$10*SCENARIU!$B$5+SUMIFS('SIMULARE PE PRODUS'!$J$6:$J$243,'SIMULARE PE PRODUS'!$C$6:$C$243,$A15,'SIMULARE PE PRODUS'!$D$6:$D$243,0))/$F15,"") -> 0.62609109 | M15: =IFERROR((SUMIFS('SIMULARE PE PRODUS'!$K$6:$K$243,'SIMULARE PE PRODUS'!$C$6:$C$243,$A15,'SIMULARE PE PRODUS'!$D$6:$D$243,">0")*SCENARIU!$B$10*SCENARIU!$B$5+SUMIFS('SIMULARE PE PRODUS'!$K$6:$K$243,'SIMULARE PE PRODUS'!$C$6:$C$243,$A15,'SIMULARE PE PRODUS'!$D$6:$D$243,0))/$G15,"") -> 0.4330524 | N15: =$H15-$J15 -> 183101.61
A16: BURGERI NON-CORE VITĂ | B16: =SUMIFS('SIMULARE PE PRODUS'!$F$6:$F$243,'SIMULARE PE PRODUS'!$C$6:$C$243,$A16,'SIMULARE PE PRODUS'!$D$6:$D$243,">0")*SCENARIU!$B$10*SCENARIU!$B$5+SUMIFS('SIMULARE PE PRODUS'!$F$6:$F$243,'SIMULARE PE PRODUS'!$C$6:$C$243,$A16,'SIMULARE PE PRODUS'!$D$6:$D$243,0) -> 103463.6 | C16: =SUMIFS('SIMULARE PE PRODUS'!$G$6:$G$243,'SIMULARE PE PRODUS'!$C$6:$C$243,$A16,'SIMULARE PE PRODUS'!$D$6:$D$243,">0")*SCENARIU!$B$10*SCENARIU!$B$5+SUMIFS('SIMULARE PE PRODUS'!$G$6:$G$243,'SIMULARE PE PRODUS'!$C$6:$C$243,$A16,'SIMULARE PE PRODUS'!$D$6:$D$243,0) -> 51849.143 | D16: =$B16+$C16 -> 155312.74 | E16: =IFERROR($D16/$D$34,"") -> 0.084898984 | F16: =SUMIFS('SIMULARE PE PRODUS'!R$6:R$243,'SIMULARE PE PRODUS'!$C$6:$C$243,$A16,'SIMULARE PE PRODUS'!$D$6:$D$243,">0")*SCENARIU!$B$10*SCENARIU!$B$5+SUMIFS('SIMULARE PE PRODUS'!R$6:R$243,'SIMULARE PE PRODUS'!$C$6:$C$243,$A16,'SIMULARE PE PRODUS'!$D$6:$D$243,0) -> 2474445.7 | G16: =SUMIFS('SIMULARE PE PRODUS'!S$6:S$243,'SIMULARE PE PRODUS'!$C$6:$C$243,$A16,'SIMULARE PE PRODUS'!$D$6:$D$243,">0")*SCENARIU!$B$10*SCENARIU!$B$5+SUMIFS('SIMULARE PE PRODUS'!S$6:S$243,'SIMULARE PE PRODUS'!$C$6:$C$243,$A16,'SIMULARE PE PRODUS'!$D$6:$D$243,0) -> 1400175.8 | H16: =$F16+$G16 -> 3874621.5 | I16: =IFERROR($H16/$H$34,"") -> 0.19547762 | J16: =SUMIFS('SIMULARE PE PRODUS'!$L$6:$L$243,'SIMULARE PE PRODUS'!$C$6:$C$243,$A16,'SIMULARE PE PRODUS'!$D$6:$D$243,">0")*SCENARIU!$B$10*SCENARIU!$B$5+SUMIFS('SIMULARE PE PRODUS'!$L$6:$L$243,'SIMULARE PE PRODUS'!$C$6:$C$243,$A16,'SIMULARE PE PRODUS'!$D$6:$D$243,0) -> 1817012.4 | K16: =IFERROR($J16/$H16,"") -> 0.46895225 | L16: =IFERROR((SUMIFS('SIMULARE PE PRODUS'!$J$6:$J$243,'SIMULARE PE PRODUS'!$C$6:$C$243,$A16,'SIMULARE PE PRODUS'!$D$6:$D$243,">0")*SCENARIU!$B$10*SCENARIU!$B$5+SUMIFS('SIMULARE PE PRODUS'!$J$6:$J$243,'SIMULARE PE PRODUS'!$C$6:$C$243,$A16,'SIMULARE PE PRODUS'!$D$6:$D$243,0))/$F16,"") -> 0.48424039 | M16: =IFERROR((SUMIFS('SIMULARE PE PRODUS'!$K$6:$K$243,'SIMULARE PE PRODUS'!$C$6:$C$243,$A16,'SIMULARE PE PRODUS'!$D$6:$D$243,">0")*SCENARIU!$B$10*SCENARIU!$B$5+SUMIFS('SIMULARE PE PRODUS'!$K$6:$K$243,'SIMULARE PE PRODUS'!$C$6:$C$243,$A16,'SIMULARE PE PRODUS'!$D$6:$D$243,0))/$G16,"") -> 0.44193443 | N16: =$H16-$J16 -> 2057609
A17: BURGERI NON-CORE PUI | B17: =SUMIFS('SIMULARE PE PRODUS'!$F$6:$F$243,'SIMULARE PE PRODUS'!$C$6:$C$243,$A17,'SIMULARE PE PRODUS'!$D$6:$D$243,">0")*SCENARIU!$B$10*SCENARIU!$B$5+SUMIFS('SIMULARE PE PRODUS'!$F$6:$F$243,'SIMULARE PE PRODUS'!$C$6:$C$243,$A17,'SIMULARE PE PRODUS'!$D$6:$D$243,0) -> 51731.799 | C17: =SUMIFS('SIMULARE PE PRODUS'!$G$6:$G$243,'SIMULARE PE PRODUS'!$C$6:$C$243,$A17,'SIMULARE PE PRODUS'!$D$6:$D$243,">0")*SCENARIU!$B$10*SCENARIU!$B$5+SUMIFS('SIMULARE PE PRODUS'!$G$6:$G$243,'SIMULARE PE PRODUS'!$C$6:$C$243,$A17,'SIMULARE PE PRODUS'!$D$6:$D$243,0) -> 25304.326 | D17: =$B17+$C17 -> 77036.126 | E17: =IFERROR($D17/$D$34,"") -> 0.042110446 | F17: =SUMIFS('SIMULARE PE PRODUS'!R$6:R$243,'SIMULARE PE PRODUS'!$C$6:$C$243,$A17,'SIMULARE PE PRODUS'!$D$6:$D$243,">0")*SCENARIU!$B$10*SCENARIU!$B$5+SUMIFS('SIMULARE PE PRODUS'!R$6:R$243,'SIMULARE PE PRODUS'!$C$6:$C$243,$A17,'SIMULARE PE PRODUS'!$D$6:$D$243,0) -> 903955.11 | G17: =SUMIFS('SIMULARE PE PRODUS'!S$6:S$243,'SIMULARE PE PRODUS'!$C$6:$C$243,$A17,'SIMULARE PE PRODUS'!$D$6:$D$243,">0")*SCENARIU!$B$10*SCENARIU!$B$5+SUMIFS('SIMULARE PE PRODUS'!S$6:S$243,'SIMULARE PE PRODUS'!$C$6:$C$243,$A17,'SIMULARE PE PRODUS'!$D$6:$D$243,0) -> 491596.09 | H17: =$F17+$G17 -> 1395551.2 | I17: =IFERROR($H17/$H$34,"") -> 0.070406628 | J17: =SUMIFS('SIMULARE PE PRODUS'!$L$6:$L$243,'SIMULARE PE PRODUS'!$C$6:$C$243,$A17,'SIMULARE PE PRODUS'!$D$6:$D$243,">0")*SCENARIU!$B$10*SCENARIU!$B$5+SUMIFS('SIMULARE PE PRODUS'!$L$6:$L$243,'SIMULARE PE PRODUS'!$C$6:$C$243,$A17,'SIMULARE PE PRODUS'!$D$6:$D$243,0) -> 531319.17 | K17: =IFERROR($J17/$H17,"") -> 0.38072352 | L17: =IFERROR((SUMIFS('SIMULARE PE PRODUS'!$J$6:$J$243,'SIMULARE PE PRODUS'!$C$6:$C$243,$A17,'SIMULARE PE PRODUS'!$D$6:$D$243,">0")*SCENARIU!$B$10*SCENARIU!$B$5+SUMIFS('SIMULARE PE PRODUS'!$J$6:$J$243,'SIMULARE PE PRODUS'!$C$6:$C$243,$A17,'SIMULARE PE PRODUS'!$D$6:$D$243,0))/$F17,"") -> 0.39295887 | M17: =IFERROR((SUMIFS('SIMULARE PE PRODUS'!$K$6:$K$243,'SIMULARE PE PRODUS'!$C$6:$C$243,$A17,'SIMULARE PE PRODUS'!$D$6:$D$243,">0")*SCENARIU!$B$10*SCENARIU!$B$5+SUMIFS('SIMULARE PE PRODUS'!$K$6:$K$243,'SIMULARE PE PRODUS'!$C$6:$C$243,$A17,'SIMULARE PE PRODUS'!$D$6:$D$243,0))/$G17,"") -> 0.35822495 | N17: =$H17-$J17 -> 864232.04
A18: CREVEȚI | B18: =SUMIFS('SIMULARE PE PRODUS'!$F$6:$F$243,'SIMULARE PE PRODUS'!$C$6:$C$243,$A18,'SIMULARE PE PRODUS'!$D$6:$D$243,">0")*SCENARIU!$B$10*SCENARIU!$B$5+SUMIFS('SIMULARE PE PRODUS'!$F$6:$F$243,'SIMULARE PE PRODUS'!$C$6:$C$243,$A18,'SIMULARE PE PRODUS'!$D$6:$D$243,0) -> 1969.6975 | C18: =SUMIFS('SIMULARE PE PRODUS'!$G$6:$G$243,'SIMULARE PE PRODUS'!$C$6:$C$243,$A18,'SIMULARE PE PRODUS'!$D$6:$D$243,">0")*SCENARIU!$B$10*SCENARIU!$B$5+SUMIFS('SIMULARE PE PRODUS'!$G$6:$G$243,'SIMULARE PE PRODUS'!$C$6:$C$243,$A18,'SIMULARE PE PRODUS'!$D$6:$D$243,0) -> 1123.1467 | D18: =$B18+$C18 -> 3092.8441 | E18: =IFERROR($D18/$D$34,"") -> 0.0016906489 | F18: =SUMIFS('SIMULARE PE PRODUS'!R$6:R$243,'SIMULARE PE PRODUS'!$C$6:$C$243,$A18,'SIMULARE PE PRODUS'!$D$6:$D$243,">0")*SCENARIU!$B$10*SCENARIU!$B$5+SUMIFS('SIMULARE PE PRODUS'!R$6:R$243,'SIMULARE PE PRODUS'!$C$6:$C$243,$A18,'SIMULARE PE PRODUS'!$D$6:$D$243,0) -> 46119.313 | G18: =SUMIFS('SIMULARE PE PRODUS'!S$6:S$243,'SIMULARE PE PRODUS'!$C$6:$C$243,$A18,'SIMULARE PE PRODUS'!$D$6:$D$243,">0")*SCENARIU!$B$10*SCENARIU!$B$5+SUMIFS('SIMULARE PE PRODUS'!S$6:S$243,'SIMULARE PE PRODUS'!$C$6:$C$243,$A18,'SIMULARE PE PRODUS'!$D$6:$D$243,0) -> 29333.353 | H18: =$F18+$G18 -> 75452.666 | I18: =IFERROR($H18/$H$34,"") -> 0.0038066448 | J18: =SUMIFS('SIMULARE PE PRODUS'!$L$6:$L$243,'SIMULARE PE PRODUS'!$C$6:$C$243,$A18,'SIMULARE PE PRODUS'!$D$6:$D$243,">0")*SCENARIU!$B$10*SCENARIU!$B$5+SUMIFS('SIMULARE PE PRODUS'!$L$6:$L$243,'SIMULARE PE PRODUS'!$C$6:$C$243,$A18,'SIMULARE PE PRODUS'!$D$6:$D$243,0) -> 33326.537 | K18: =IFERROR($J18/$H18,"") -> 0.44168801 | L18: =IFERROR((SUMIFS('SIMULARE PE PRODUS'!$J$6:$J$243,'SIMULARE PE PRODUS'!$C$6:$C$243,$A18,'SIMULARE PE PRODUS'!$D$6:$D$243,">0")*SCENARIU!$B$10*SCENARIU!$B$5+SUMIFS('SIMULARE PE PRODUS'!$J$6:$J$243,'SIMULARE PE PRODUS'!$C$6:$C$243,$A18,'SIMULARE PE PRODUS'!$D$6:$D$243,0))/$F18,"") -> 0.46020238 | M18: =IFERROR((SUMIFS('SIMULARE PE PRODUS'!$K$6:$K$243,'SIMULARE PE PRODUS'!$C$6:$C$243,$A18,'SIMULARE PE PRODUS'!$D$6:$D$243,">0")*SCENARIU!$B$10*SCENARIU!$B$5+SUMIFS('SIMULARE PE PRODUS'!$K$6:$K$243,'SIMULARE PE PRODUS'!$C$6:$C$243,$A18,'SIMULARE PE PRODUS'!$D$6:$D$243,0))/$G18,"") -> 0.41257881 | N18: =$H18-$J18 -> 42126.128
A19: VEGETARIAN | B19: =SUMIFS('SIMULARE PE PRODUS'!$F$6:$F$243,'SIMULARE PE PRODUS'!$C$6:$C$243,$A19,'SIMULARE PE PRODUS'!$D$6:$D$243,">0")*SCENARIU!$B$10*SCENARIU!$B$5+SUMIFS('SIMULARE PE PRODUS'!$F$6:$F$243,'SIMULARE PE PRODUS'!$C$6:$C$243,$A19,'SIMULARE PE PRODUS'!$D$6:$D$243,0) -> 3097.035 | C19: =SUMIFS('SIMULARE PE PRODUS'!$G$6:$G$243,'SIMULARE PE PRODUS'!$C$6:$C$243,$A19,'SIMULARE PE PRODUS'!$D$6:$D$243,">0")*SCENARIU!$B$10*SCENARIU!$B$5+SUMIFS('SIMULARE PE PRODUS'!$G$6:$G$243,'SIMULARE PE PRODUS'!$C$6:$C$243,$A19,'SIMULARE PE PRODUS'!$D$6:$D$243,0) -> 1060.284 | D19: =$B19+$C19 -> 4157.3189 | E19: =IFERROR($D19/$D$34,"") -> 0.0022725254 | F19: =SUMIFS('SIMULARE PE PRODUS'!R$6:R$243,'SIMULARE PE PRODUS'!$C$6:$C$243,$A19,'SIMULARE PE PRODUS'!$D$6:$D$243,">0")*SCENARIU!$B$10*SCENARIU!$B$5+SUMIFS('SIMULARE PE PRODUS'!R$6:R$243,'SIMULARE PE PRODUS'!$C$6:$C$243,$A19,'SIMULARE PE PRODUS'!$D$6:$D$243,0) -> 58564.653 | G19: =SUMIFS('SIMULARE PE PRODUS'!S$6:S$243,'SIMULARE PE PRODUS'!$C$6:$C$243,$A19,'SIMULARE PE PRODUS'!$D$6:$D$243,">0")*SCENARIU!$B$10*SCENARIU!$B$5+SUMIFS('SIMULARE PE PRODUS'!S$6:S$243,'SIMULARE PE PRODUS'!$C$6:$C$243,$A19,'SIMULARE PE PRODUS'!$D$6:$D$243,0) -> 22915.507 | H19: =$F19+$G19 -> 81480.159 | I19: =IFERROR($H19/$H$34,"") -> 0.0041107365 | J19: =SUMIFS('SIMULARE PE PRODUS'!$L$6:$L$243,'SIMULARE PE PRODUS'!$C$6:$C$243,$A19,'SIMULARE PE PRODUS'!$D$6:$D$243,">0")*SCENARIU!$B$10*SCENARIU!$B$5+SUMIFS('SIMULARE PE PRODUS'!$L$6:$L$243,'SIMULARE PE PRODUS'!$C$6:$C$243,$A19,'SIMULARE PE PRODUS'!$D$6:$D$243,0) -> 29896.728 | K19: =IFERROR($J19/$H19,"") -> 0.36692035 | L19: =IFERROR((SUMIFS('SIMULARE PE PRODUS'!$J$6:$J$243,'SIMULARE PE PRODUS'!$C$6:$C$243,$A19,'SIMULARE PE PRODUS'!$D$6:$D$243,">0")*SCENARIU!$B$10*SCENARIU!$B$5+SUMIFS('SIMULARE PE PRODUS'!$J$6:$J$243,'SIMULARE PE PRODUS'!$C$6:$C$243,$A19,'SIMULARE PE PRODUS'!$D$6:$D$243,0))/$F19,"") -> 0.38029521 | M19: =IFERROR((SUMIFS('SIMULARE PE PRODUS'!$K$6:$K$243,'SIMULARE PE PRODUS'!$C$6:$C$243,$A19,'SIMULARE PE PRODUS'!$D$6:$D$243,">0")*SCENARIU!$B$10*SCENARIU!$B$5+SUMIFS('SIMULARE PE PRODUS'!$K$6:$K$243,'SIMULARE PE PRODUS'!$C$6:$C$243,$A19,'SIMULARE PE PRODUS'!$D$6:$D$243,0))/$G19,"") -> 0.3327385 | N19: =$H19-$J19 -> 51583.431
A20: FRIED CHICKEN | B20: =SUMIFS('SIMULARE PE PRODUS'!$F$6:$F$243,'SIMULARE PE PRODUS'!$C$6:$C$243,$A20,'SIMULARE PE PRODUS'!$D$6:$D$243,">0")*SCENARIU!$B$10*SCENARIU!$B$5+SUMIFS('SIMULARE PE PRODUS'!$F$6:$F$243,'SIMULARE PE PRODUS'!$C$6:$C$243,$A20,'SIMULARE PE PRODUS'!$D$6:$D$243,0) -> 51425.868 | C20: =SUMIFS('SIMULARE PE PRODUS'!$G$6:$G$243,'SIMULARE PE PRODUS'!$C$6:$C$243,$A20,'SIMULARE PE PRODUS'!$D$6:$D$243,">0")*SCENARIU!$B$10*SCENARIU!$B$5+SUMIFS('SIMULARE PE PRODUS'!$G$6:$G$243,'SIMULARE PE PRODUS'!$C$6:$C$243,$A20,'SIMULARE PE PRODUS'!$D$6:$D$243,0) -> 24922.959 | D20: =$B20+$C20 -> 76348.827 | E20: =IFERROR($D20/$D$34,"") -> 0.041734746 | F20: =SUMIFS('SIMULARE PE PRODUS'!R$6:R$243,'SIMULARE PE PRODUS'!$C$6:$C$243,$A20,'SIMULARE PE PRODUS'!$D$6:$D$243,">0")*SCENARIU!$B$10*SCENARIU!$B$5+SUMIFS('SIMULARE PE PRODUS'!R$6:R$243,'SIMULARE PE PRODUS'!$C$6:$C$243,$A20,'SIMULARE PE PRODUS'!$D$6:$D$243,0) -> 1133400 | G20: =SUMIFS('SIMULARE PE PRODUS'!S$6:S$243,'SIMULARE PE PRODUS'!$C$6:$C$243,$A20,'SIMULARE PE PRODUS'!$D$6:$D$243,">0")*SCENARIU!$B$10*SCENARIU!$B$5+SUMIFS('SIMULARE PE PRODUS'!S$6:S$243,'SIMULARE PE PRODUS'!$C$6:$C$243,$A20,'SIMULARE PE PRODUS'!$D$6:$D$243,0) -> 647471.54 | H20: =$F20+$G20 -> 1780871.6 | I20: =IFERROR($H20/$H$34,"") -> 0.089846336 | J20: =SUMIFS('SIMULARE PE PRODUS'!$L$6:$L$243,'SIMULARE PE PRODUS'!$C$6:$C$243,$A20,'SIMULARE PE PRODUS'!$D$6:$D$243,">0")*SCENARIU!$B$10*SCENARIU!$B$5+SUMIFS('SIMULARE PE PRODUS'!$L$6:$L$243,'SIMULARE PE PRODUS'!$C$6:$C$243,$A20,'SIMULARE PE PRODUS'!$D$6:$D$243,0) -> 816726.61 | K20: =IFERROR($J20/$H20,"") -> 0.45861062 | L20: =IFERROR((SUMIFS('SIMULARE PE PRODUS'!$J$6:$J$243,'SIMULARE PE PRODUS'!$C$6:$C$243,$A20,'SIMULARE PE PRODUS'!$D$6:$D$243,">0")*SCENARIU!$B$10*SCENARIU!$B$5+SUMIFS('SIMULARE PE PRODUS'!$J$6:$J$243,'SIMULARE PE PRODUS'!$C$6:$C$243,$A20,'SIMULARE PE PRODUS'!$D$6:$D$243,0))/$F20,"") -> 0.4887162 | M20: =IFERROR((SUMIFS('SIMULARE PE PRODUS'!$K$6:$K$243,'SIMULARE PE PRODUS'!$C$6:$C$243,$A20,'SIMULARE PE PRODUS'!$D$6:$D$243,">0")*SCENARIU!$B$10*SCENARIU!$B$5+SUMIFS('SIMULARE PE PRODUS'!$K$6:$K$243,'SIMULARE PE PRODUS'!$C$6:$C$243,$A20,'SIMULARE PE PRODUS'!$D$6:$D$243,0))/$G20,"") -> 0.40591074 | N20: =$H20-$J20 -> 964144.96
A21: CARTOFI | B21: =SUMIFS('SIMULARE PE PRODUS'!$F$6:$F$243,'SIMULARE PE PRODUS'!$C$6:$C$243,$A21,'SIMULARE PE PRODUS'!$D$6:$D$243,">0")*SCENARIU!$B$10*SCENARIU!$B$5+SUMIFS('SIMULARE PE PRODUS'!$F$6:$F$243,'SIMULARE PE PRODUS'!$C$6:$C$243,$A21,'SIMULARE PE PRODUS'!$D$6:$D$243,0) -> 220606.12 | C21: =SUMIFS('SIMULARE PE PRODUS'!$G$6:$G$243,'SIMULARE PE PRODUS'!$C$6:$C$243,$A21,'SIMULARE PE PRODUS'!$D$6:$D$243,">0")*SCENARIU!$B$10*SCENARIU!$B$5+SUMIFS('SIMULARE PE PRODUS'!$G$6:$G$243,'SIMULARE PE PRODUS'!$C$6:$C$243,$A21,'SIMULARE PE PRODUS'!$D$6:$D$243,0) -> 83901.567 | D21: =$B21+$C21 -> 304507.69 | E21: =IFERROR($D21/$D$34,"") -> 0.16645378 | F21: =SUMIFS('SIMULARE PE PRODUS'!R$6:R$243,'SIMULARE PE PRODUS'!$C$6:$C$243,$A21,'SIMULARE PE PRODUS'!$D$6:$D$243,">0")*SCENARIU!$B$10*SCENARIU!$B$5+SUMIFS('SIMULARE PE PRODUS'!R$6:R$243,'SIMULARE PE PRODUS'!$C$6:$C$243,$A21,'SIMULARE PE PRODUS'!$D$6:$D$243,0) -> 2581212.9 | G21: =SUMIFS('SIMULARE PE PRODUS'!S$6:S$243,'SIMULARE PE PRODUS'!$C$6:$C$243,$A21,'SIMULARE PE PRODUS'!$D$6:$D$243,">0")*SCENARIU!$B$10*SCENARIU!$B$5+SUMIFS('SIMULARE PE PRODUS'!S$6:S$243,'SIMULARE PE PRODUS'!$C$6:$C$243,$A21,'SIMULARE PE PRODUS'!$D$6:$D$243,0) -> 1113709.6 | H21: =$F21+$G21 -> 3694922.4 | I21: =IFERROR($H21/$H$34,"") -> 0.18641167 | J21: =SUMIFS('SIMULARE PE PRODUS'!$L$6:$L$243,'SIMULARE PE PRODUS'!$C$6:$C$243,$A21,'SIMULARE PE PRODUS'!$D$6:$D$243,">0")*SCENARIU!$B$10*SCENARIU!$B$5+SUMIFS('SIMULARE PE PRODUS'!$L$6:$L$243,'SIMULARE PE PRODUS'!$C$6:$C$243,$A21,'SIMULARE PE PRODUS'!$D$6:$D$243,0) -> 1111765.6 | K21: =IFERROR($J21/$H21,"") -> 0.3008901 | L21: =IFERROR((SUMIFS('SIMULARE PE PRODUS'!$J$6:$J$243,'SIMULARE PE PRODUS'!$C$6:$C$243,$A21,'SIMULARE PE PRODUS'!$D$6:$D$243,">0")*SCENARIU!$B$10*SCENARIU!$B$5+SUMIFS('SIMULARE PE PRODUS'!$J$6:$J$243,'SIMULARE PE PRODUS'!$C$6:$C$243,$A21,'SIMULARE PE PRODUS'!$D$6:$D$243,0))/$F21,"") -> 0.31297184 | M21: =IFERROR((SUMIFS('SIMULARE PE PRODUS'!$K$6:$K$243,'SIMULARE PE PRODUS'!$C$6:$C$243,$A21,'SIMULARE PE PRODUS'!$D$6:$D$243,">0")*SCENARIU!$B$10*SCENARIU!$B$5+SUMIFS('SIMULARE PE PRODUS'!$K$6:$K$243,'SIMULARE PE PRODUS'!$C$6:$C$243,$A21,'SIMULARE PE PRODUS'!$D$6:$D$243,0))/$G21,"") -> 0.2728886 | N21: =$H21-$J21 -> 2583156.9
A22: SOSURI | B22: =SUMIFS('SIMULARE PE PRODUS'!$F$6:$F$243,'SIMULARE PE PRODUS'!$C$6:$C$243,$A22,'SIMULARE PE PRODUS'!$D$6:$D$243,">0")*SCENARIU!$B$10*SCENARIU!$B$5+SUMIFS('SIMULARE PE PRODUS'!$F$6:$F$243,'SIMULARE PE PRODUS'!$C$6:$C$243,$A22,'SIMULARE PE PRODUS'!$D$6:$D$243,0) -> 169926.22 | C22: =SUMIFS('SIMULARE PE PRODUS'!$G$6:$G$243,'SIMULARE PE PRODUS'!$C$6:$C$243,$A22,'SIMULARE PE PRODUS'!$D$6:$D$243,">0")*SCENARIU!$B$10*SCENARIU!$B$5+SUMIFS('SIMULARE PE PRODUS'!$G$6:$G$243,'SIMULARE PE PRODUS'!$C$6:$C$243,$A22,'SIMULARE PE PRODUS'!$D$6:$D$243,0) -> 71009.69 | D22: =$B22+$C22 -> 240935.91 | E22: =IFERROR($D22/$D$34,"") -> 0.13170339 | F22: =SUMIFS('SIMULARE PE PRODUS'!R$6:R$243,'SIMULARE PE PRODUS'!$C$6:$C$243,$A22,'SIMULARE PE PRODUS'!$D$6:$D$243,">0")*SCENARIU!$B$10*SCENARIU!$B$5+SUMIFS('SIMULARE PE PRODUS'!R$6:R$243,'SIMULARE PE PRODUS'!$C$6:$C$243,$A22,'SIMULARE PE PRODUS'!$D$6:$D$243,0) -> 1331215.9 | G22: =SUMIFS('SIMULARE PE PRODUS'!S$6:S$243,'SIMULARE PE PRODUS'!$C$6:$C$243,$A22,'SIMULARE PE PRODUS'!$D$6:$D$243,">0")*SCENARIU!$B$10*SCENARIU!$B$5+SUMIFS('SIMULARE PE PRODUS'!S$6:S$243,'SIMULARE PE PRODUS'!$C$6:$C$243,$A22,'SIMULARE PE PRODUS'!$D$6:$D$243,0) -> 646891.39 | H22: =$F22+$G22 -> 1978107.3 | I22: =IFERROR($H22/$H$34,"") -> 0.099797028 | J22: =SUMIFS('SIMULARE PE PRODUS'!$L$6:$L$243,'SIMULARE PE PRODUS'!$C$6:$C$243,$A22,'SIMULARE PE PRODUS'!$D$6:$D$243,">0")*SCENARIU!$B$10*SCENARIU!$B$5+SUMIFS('SIMULARE PE PRODUS'!$L$6:$L$243,'SIMULARE PE PRODUS'!$C$6:$C$243,$A22,'SIMULARE PE PRODUS'!$D$6:$D$243,0) -> 616842.01 | K22: =IFERROR($J22/$H22,"") -> 0.31183446 | L22: =IFERROR((SUMIFS('SIMULARE PE PRODUS'!$J$6:$J$243,'SIMULARE PE PRODUS'!$C$6:$C$243,$A22,'SIMULARE PE PRODUS'!$D$6:$D$243,">0")*SCENARIU!$B$10*SCENARIU!$B$5+SUMIFS('SIMULARE PE PRODUS'!$J$6:$J$243,'SIMULARE PE PRODUS'!$C$6:$C$243,$A22,'SIMULARE PE PRODUS'!$D$6:$D$243,0))/$F22,"") -> 0.31123007 | M22: =IFERROR((SUMIFS('SIMULARE PE PRODUS'!$K$6:$K$243,'SIMULARE PE PRODUS'!$C$6:$C$243,$A22,'SIMULARE PE PRODUS'!$D$6:$D$243,">0")*SCENARIU!$B$10*SCENARIU!$B$5+SUMIFS('SIMULARE PE PRODUS'!$K$6:$K$243,'SIMULARE PE PRODUS'!$C$6:$C$243,$A22,'SIMULARE PE PRODUS'!$D$6:$D$243,0))/$G22,"") -> 0.3130782 | N22: =$H22-$J22 -> 1361265.3
A23: DRINKS | B23: =SUMIFS('SIMULARE PE PRODUS'!$F$6:$F$243,'SIMULARE PE PRODUS'!$C$6:$C$243,$A23,'SIMULARE PE PRODUS'!$D$6:$D$243,">0")*SCENARIU!$B$10*SCENARIU!$B$5+SUMIFS('SIMULARE PE PRODUS'!$F$6:$F$243,'SIMULARE PE PRODUS'!$C$6:$C$243,$A23,'SIMULARE PE PRODUS'!$D$6:$D$243,0) -> 186425.58 | C23: =SUMIFS('SIMULARE PE PRODUS'!$G$6:$G$243,'SIMULARE PE PRODUS'!$C$6:$C$243,$A23,'SIMULARE PE PRODUS'!$D$6:$D$243,">0")*SCENARIU!$B$10*SCENARIU!$B$5+SUMIFS('SIMULARE PE PRODUS'!$G$6:$G$243,'SIMULARE PE PRODUS'!$C$6:$C$243,$A23,'SIMULARE PE PRODUS'!$D$6:$D$243,0) -> 10246.618 | D23: =$B23+$C23 -> 196672.2 | E23: =IFERROR($D23/$D$34,"") -> 0.1075074 | F23: =SUMIFS('SIMULARE PE PRODUS'!R$6:R$243,'SIMULARE PE PRODUS'!$C$6:$C$243,$A23,'SIMULARE PE PRODUS'!$D$6:$D$243,">0")*SCENARIU!$B$10*SCENARIU!$B$5+SUMIFS('SIMULARE PE PRODUS'!R$6:R$243,'SIMULARE PE PRODUS'!$C$6:$C$243,$A23,'SIMULARE PE PRODUS'!$D$6:$D$243,0) -> 1514834.2 | G23: =SUMIFS('SIMULARE PE PRODUS'!S$6:S$243,'SIMULARE PE PRODUS'!$C$6:$C$243,$A23,'SIMULARE PE PRODUS'!$D$6:$D$243,">0")*SCENARIU!$B$10*SCENARIU!$B$5+SUMIFS('SIMULARE PE PRODUS'!S$6:S$243,'SIMULARE PE PRODUS'!$C$6:$C$243,$A23,'SIMULARE PE PRODUS'!$D$6:$D$243,0) -> 86762.802 | H23: =$F23+$G23 -> 1601597 | I23: =IFERROR($H23/$H$34,"") -> 0.080801799 | J23: =SUMIFS('SIMULARE PE PRODUS'!$L$6:$L$243,'SIMULARE PE PRODUS'!$C$6:$C$243,$A23,'SIMULARE PE PRODUS'!$D$6:$D$243,">0")*SCENARIU!$B$10*SCENARIU!$B$5+SUMIFS('SIMULARE PE PRODUS'!$L$6:$L$243,'SIMULARE PE PRODUS'!$C$6:$C$243,$A23,'SIMULARE PE PRODUS'!$D$6:$D$243,0) -> 782093.77 | K23: =IFERROR($J23/$H23,"") -> 0.48832119 | L23: =IFERROR((SUMIFS('SIMULARE PE PRODUS'!$J$6:$J$243,'SIMULARE PE PRODUS'!$C$6:$C$243,$A23,'SIMULARE PE PRODUS'!$D$6:$D$243,">0")*SCENARIU!$B$10*SCENARIU!$B$5+SUMIFS('SIMULARE PE PRODUS'!$J$6:$J$243,'SIMULARE PE PRODUS'!$C$6:$C$243,$A23,'SIMULARE PE PRODUS'!$D$6:$D$243,0))/$F23,"") -> 0.49394444 | M23: =IFERROR((SUMIFS('SIMULARE PE PRODUS'!$K$6:$K$243,'SIMULARE PE PRODUS'!$C$6:$C$243,$A23,'SIMULARE PE PRODUS'!$D$6:$D$243,">0")*SCENARIU!$B$10*SCENARIU!$B$5+SUMIFS('SIMULARE PE PRODUS'!$K$6:$K$243,'SIMULARE PE PRODUS'!$C$6:$C$243,$A23,'SIMULARE PE PRODUS'!$D$6:$D$243,0))/$G23,"") -> 0.39014208 | N23: =$H23-$J23 -> 819503.27
A24: FRYCAFE | B24: =SUMIFS('SIMULARE PE PRODUS'!$F$6:$F$243,'SIMULARE PE PRODUS'!$C$6:$C$243,$A24,'SIMULARE PE PRODUS'!$D$6:$D$243,">0")*SCENARIU!$B$10*SCENARIU!$B$5+SUMIFS('SIMULARE PE PRODUS'!$F$6:$F$243,'SIMULARE PE PRODUS'!$C$6:$C$243,$A24,'SIMULARE PE PRODUS'!$D$6:$D$243,0) -> 16231.145 | C24: =SUMIFS('SIMULARE PE PRODUS'!$G$6:$G$243,'SIMULARE PE PRODUS'!$C$6:$C$243,$A24,'SIMULARE PE PRODUS'!$D$6:$D$243,">0")*SCENARIU!$B$10*SCENARIU!$B$5+SUMIFS('SIMULARE PE PRODUS'!$G$6:$G$243,'SIMULARE PE PRODUS'!$C$6:$C$243,$A24,'SIMULARE PE PRODUS'!$D$6:$D$243,0) -> 3164.0885 | D24: =$B24+$C24 -> 19395.234 | E24: =IFERROR($D24/$D$34,"") -> 0.010602064 | F24: =SUMIFS('SIMULARE PE PRODUS'!R$6:R$243,'SIMULARE PE PRODUS'!$C$6:$C$243,$A24,'SIMULARE PE PRODUS'!$D$6:$D$243,">0")*SCENARIU!$B$10*SCENARIU!$B$5+SUMIFS('SIMULARE PE PRODUS'!R$6:R$243,'SIMULARE PE PRODUS'!$C$6:$C$243,$A24,'SIMULARE PE PRODUS'!$D$6:$D$243,0) -> 188408.07 | G24: =SUMIFS('SIMULARE PE PRODUS'!S$6:S$243,'SIMULARE PE PRODUS'!$C$6:$C$243,$A24,'SIMULARE PE PRODUS'!$D$6:$D$243,">0")*SCENARIU!$B$10*SCENARIU!$B$5+SUMIFS('SIMULARE PE PRODUS'!S$6:S$243,'SIMULARE PE PRODUS'!$C$6:$C$243,$A24,'SIMULARE PE PRODUS'!$D$6:$D$243,0) -> 46285.269 | H24: =$F24+$G24 -> 234693.34 | I24: =IFERROR($H24/$H$34,"") -> 0.011840459 | J24: =SUMIFS('SIMULARE PE PRODUS'!$L$6:$L$243,'SIMULARE PE PRODUS'!$C$6:$C$243,$A24,'SIMULARE PE PRODUS'!$D$6:$D$243,">0")*SCENARIU!$B$10*SCENARIU!$B$5+SUMIFS('SIMULARE PE PRODUS'!$L$6:$L$243,'SIMULARE PE PRODUS'!$C$6:$C$243,$A24,'SIMULARE PE PRODUS'!$D$6:$D$243,0) -> 98742.134 | K24: =IFERROR($J24/$H24,"") -> 0.42072833 | L24: =IFERROR((SUMIFS('SIMULARE PE PRODUS'!$J$6:$J$243,'SIMULARE PE PRODUS'!$C$6:$C$243,$A24,'SIMULARE PE PRODUS'!$D$6:$D$243,">0")*SCENARIU!$B$10*SCENARIU!$B$5+SUMIFS('SIMULARE PE PRODUS'!$J$6:$J$243,'SIMULARE PE PRODUS'!$C$6:$C$243,$A24,'SIMULARE PE PRODUS'!$D$6:$D$243,0))/$F24,"") -> 0.41733902 | M24: =IFERROR((SUMIFS('SIMULARE PE PRODUS'!$K$6:$K$243,'SIMULARE PE PRODUS'!$C$6:$C$243,$A24,'SIMULARE PE PRODUS'!$D$6:$D$243,">0")*SCENARIU!$B$10*SCENARIU!$B$5+SUMIFS('SIMULARE PE PRODUS'!$K$6:$K$243,'SIMULARE PE PRODUS'!$C$6:$C$243,$A24,'SIMULARE PE PRODUS'!$D$6:$D$243,0))/$G24,"") -> 0.43452479 | N24: =$H24-$J24 -> 135951.2
A25: MILKSHAKE & DESERT | B25: =SUMIFS('SIMULARE PE PRODUS'!$F$6:$F$243,'SIMULARE PE PRODUS'!$C$6:$C$243,$A25,'SIMULARE PE PRODUS'!$D$6:$D$243,">0")*SCENARIU!$B$10*SCENARIU!$B$5+SUMIFS('SIMULARE PE PRODUS'!$F$6:$F$243,'SIMULARE PE PRODUS'!$C$6:$C$243,$A25,'SIMULARE PE PRODUS'!$D$6:$D$243,0) -> 34138.629 | C25: =SUMIFS('SIMULARE PE PRODUS'!$G$6:$G$243,'SIMULARE PE PRODUS'!$C$6:$C$243,$A25,'SIMULARE PE PRODUS'!$D$6:$D$243,">0")*SCENARIU!$B$10*SCENARIU!$B$5+SUMIFS('SIMULARE PE PRODUS'!$G$6:$G$243,'SIMULARE PE PRODUS'!$C$6:$C$243,$A25,'SIMULARE PE PRODUS'!$D$6:$D$243,0) -> 11809.803 | D25: =$B25+$C25 -> 45948.432 | E25: =IFERROR($D25/$D$34,"") -> 0.025116904 | F25: =SUMIFS('SIMULARE PE PRODUS'!R$6:R$243,'SIMULARE PE PRODUS'!$C$6:$C$243,$A25,'SIMULARE PE PRODUS'!$D$6:$D$243,">0")*SCENARIU!$B$10*SCENARIU!$B$5+SUMIFS('SIMULARE PE PRODUS'!R$6:R$243,'SIMULARE PE PRODUS'!$C$6:$C$243,$A25,'SIMULARE PE PRODUS'!$D$6:$D$243,0) -> 417557.37 | G25: =SUMIFS('SIMULARE PE PRODUS'!S$6:S$243,'SIMULARE PE PRODUS'!$C$6:$C$243,$A25,'SIMULARE PE PRODUS'!$D$6:$D$243,">0")*SCENARIU!$B$10*SCENARIU!$B$5+SUMIFS('SIMULARE PE PRODUS'!S$6:S$243,'SIMULARE PE PRODUS'!$C$6:$C$243,$A25,'SIMULARE PE PRODUS'!$D$6:$D$243,0) -> 149114.82 | H25: =$F25+$G25 -> 566672.19 | I25: =IFERROR($H25/$H$34,"") -> 0.028589046 | J25: =SUMIFS('SIMULARE PE PRODUS'!$L$6:$L$243,'SIMULARE PE PRODUS'!$C$6:$C$243,$A25,'SIMULARE PE PRODUS'!$D$6:$D$243,">0")*SCENARIU!$B$10*SCENARIU!$B$5+SUMIFS('SIMULARE PE PRODUS'!$L$6:$L$243,'SIMULARE PE PRODUS'!$C$6:$C$243,$A25,'SIMULARE PE PRODUS'!$D$6:$D$243,0) -> 221997.96 | K25: =IFERROR($J25/$H25,"") -> 0.39175729 | L25: =IFERROR((SUMIFS('SIMULARE PE PRODUS'!$J$6:$J$243,'SIMULARE PE PRODUS'!$C$6:$C$243,$A25,'SIMULARE PE PRODUS'!$D$6:$D$243,">0")*SCENARIU!$B$10*SCENARIU!$B$5+SUMIFS('SIMULARE PE PRODUS'!$J$6:$J$243,'SIMULARE PE PRODUS'!$C$6:$C$243,$A25,'SIMULARE PE PRODUS'!$D$6:$D$243,0))/$F25,"") -> 0.38264722 | M25: =IFERROR((SUMIFS('SIMULARE PE PRODUS'!$K$6:$K$243,'SIMULARE PE PRODUS'!$C$6:$C$243,$A25,'SIMULARE PE PRODUS'!$D$6:$D$243,">0")*SCENARIU!$B$10*SCENARIU!$B$5+SUMIFS('SIMULARE PE PRODUS'!$K$6:$K$243,'SIMULARE PE PRODUS'!$C$6:$C$243,$A25,'SIMULARE PE PRODUS'!$D$6:$D$243,0))/$G25,"") -> 0.41726769 | N25: =$H25-$J25 -> 344674.23
... A33: GARANTII SGR | B33: =SUMIFS('SIMULARE PE PRODUS'!$F$6:$F$243,'SIMULARE PE PRODUS'!$C$6:$C$243,$A33,'SIMULARE PE PRODUS'!$D$6:$D$243,">0")*SCENARIU!$B$10*SCENARIU!$B$5+SUMIFS('SIMULARE PE PRODUS'!$F$6:$F$243,'SIMULARE PE PRODUS'!$C$6:$C$243,$A33,'SIMULARE PE PRODUS'!$D$6:$D$243,0) -> 0 | C33: =SUMIFS('SIMULARE PE PRODUS'!$G$6:$G$243,'SIMULARE PE PRODUS'!$C$6:$C$243,$A33,'SIMULARE PE PRODUS'!$D$6:$D$243,">0")*SCENARIU!$B$10*SCENARIU!$B$5+SUMIFS('SIMULARE PE PRODUS'!$G$6:$G$243,'SIMULARE PE PRODUS'!$C$6:$C$243,$A33,'SIMULARE PE PRODUS'!$D$6:$D$243,0) -> 25664.739 | D33: =$B33+$C33 -> 25664.739 | E33: =IFERROR($D33/$D$34,"") -> 0.014029179 | F33: =SUMIFS('SIMULARE PE PRODUS'!R$6:R$243,'SIMULARE PE PRODUS'!$C$6:$C$243,$A33,'SIMULARE PE PRODUS'!$D$6:$D$243,">0")*SCENARIU!$B$10*SCENARIU!$B$5+SUMIFS('SIMULARE PE PRODUS'!R$6:R$243,'SIMULARE PE PRODUS'!$C$6:$C$243,$A33,'SIMULARE PE PRODUS'!$D$6:$D$243,0) -> 0 | G33: =SUMIFS('SIMULARE PE PRODUS'!S$6:S$243,'SIMULARE PE PRODUS'!$C$6:$C$243,$A33,'SIMULARE PE PRODUS'!$D$6:$D$243,">0")*SCENARIU!$B$10*SCENARIU!$B$5+SUMIFS('SIMULARE PE PRODUS'!S$6:S$243,'SIMULARE PE PRODUS'!$C$6:$C$243,$A33,'SIMULARE PE PRODUS'!$D$6:$D$243,0) -> 10605.264 | H33: =$F33+$G33 -> 10605.264 | I33: =IFERROR($H33/$H$34,"") -> 0.0005350437 | J33: =SUMIFS('SIMULARE PE PRODUS'!$L$6:$L$243,'SIMULARE PE PRODUS'!$C$6:$C$243,$A33,'SIMULARE PE PRODUS'!$D$6:$D$243,">0")*SCENARIU!$B$10*SCENARIU!$B$5+SUMIFS('SIMULARE PE PRODUS'!$L$6:$L$243,'SIMULARE PE PRODUS'!$C$6:$C$243,$A33,'SIMULARE PE PRODUS'!$D$6:$D$243,0) -> 12832.37 | K33: =IFERROR($J33/$H33,"") -> 1.21 | L33: =IFERROR((SUMIFS('SIMULARE PE PRODUS'!$J$6:$J$243,'SIMULARE PE PRODUS'!$C$6:$C$243,$A33,'SIMULARE PE PRODUS'!$D$6:$D$243,">0")*SCENARIU!$B$10*SCENARIU!$B$5+SUMIFS('SIMULARE PE PRODUS'!$J$6:$J$243,'SIMULARE PE PRODUS'!$C$6:$C$243,$A33,'SIMULARE PE PRODUS'!$D$6:$D$243,0))/$F33,"") | M33: =IFERROR((SUMIFS('SIMULARE PE PRODUS'!$K$6:$K$243,'SIMULARE PE PRODUS'!$C$6:$C$243,$A33,'SIMULARE PE PRODUS'!$D$6:$D$243,">0")*SCENARIU!$B$10*SCENARIU!$B$5+SUMIFS('SIMULARE PE PRODUS'!$K$6:$K$243,'SIMULARE PE PRODUS'!$C$6:$C$243,$A33,'SIMULARE PE PRODUS'!$D$6:$D$243,0))/$G33,"") -> 1.21 | N33: =$H33-$J33 -> -2227.1055
A34: TOTAL | B34: =SUM(B14:B33) -> 1127733.8 | C34: =SUM(C14:C33) -> 701648.99 | D34: =SUM(D14:D33) -> 1829382.8 | E34: =D34/D34 -> 1 | F34: =SUM(F14:F33) -> 13370916 | G34: =SUM(G14:G33) -> 6450387.9 | H34: =SUM(H14:H33) -> 19821304 | I34: =H34/H34 -> 1 | J34: =SUM(J14:J33) -> 9076560.8 | K34: =IFERROR($J34/$H34,"") -> 0.45791945 | L34: =IFERROR((SUMPRODUCT(ISNUMBER('SIMULARE PE PRODUS'!$A$6:$A$243)*('SIMULARE PE PRODUS'!$D$6:$D$243>0)*'SIMULARE PE PRODUS'!$J$6:$J$243)*SCENARIU!$B$10*SCENARIU!$B$5+SUMPRODUCT(ISNUMBER('SIMULARE PE PRODUS'!$A$6:$A$243)*('SIMULARE PE PRODUS'!$D$6:$D$243=0)*'SIMULARE PE PRODUS'!$J$6:$J$243))/$F34,"") -> 0.46786244 | M34: =IFERROR((SUMPRODUCT(ISNUMBER('SIMULARE PE PRODUS'!$A$6:$A$243)*('SIMULARE PE PRODUS'!$D$6:$D$243>0)*'SIMULARE PE PRODUS'!$K$6:$K$243)*SCENARIU!$B$10*SCENARIU!$B$5+SUMPRODUCT(ISNUMBER('SIMULARE PE PRODUS'!$A$6:$A$243)*('SIMULARE PE PRODUS'!$D$6:$D$243=0)*'SIMULARE PE PRODUS'!$K$6:$K$243))/$G34,"") -> 0.43730877 | N34: =SUM(N14:N33) -> 10744744

Sheet MASTER FC PERIOADĂ
A1: MASTER FC PERIOADĂ — august → decembrie 2026, pe lună
A2: Valorile sunt pe lună întreagă, cu indexul de volum din SCENARIU aplicat pe fiecare lună. Economiile la furnizor NU sunt incluse aici (sunt în SCENARIU, la nivel de total).
A4: FC AUGUST | D4: =$D$27 -> 0.45791945 | G4: FC DECEMBRIE | I4: =$L$27 -> 0.42329054 | L4: CÂȘTIG | M4: =$L$27-$D$27 -> -0.034628913 | O4: CÂȘTIG DIN CREȘTERI DE PREȚ
A6: Categorie | B6: Buc/lună | C6: AUGUST Net | D6: AUGUST FC | E6: SEPT Net | F6: SEPT FC | G6: OCT Net | H6: OCT FC | I6: NOV Net | J6: NOV FC | K6: DEC Net | L6: DEC FC | M6: Δ FC aug→dec | N6: % din vânzări | O6: Câștig SALES dec vs aug | P6: Câștig CUMULAT sep→dec | Q6: Creștere sales %
A7: BURGERI CORE VITĂ | B7: =SUMIFS('SIMULARE PE PRODUS'!$F$6:$F$243,'SIMULARE PE PRODUS'!$C$6:$C$243,$A7,'SIMULARE PE PRODUS'!$D$6:$D$243,">0")*SCENARIU!$B$10*SCENARIU!$B$5+SUMIFS('SIMULARE PE PRODUS'!$G$6:$G$243,'SIMULARE PE PRODUS'!$C$6:$C$243,$A7,'SIMULARE PE PRODUS'!$D$6:$D$243,">0")*SCENARIU!$B$10*SCENARIU!$B$5+SUMIFS('SIMULARE PE PRODUS'!$F$6:$F$243,'SIMULARE PE PRODUS'!$C$6:$C$243,$A7,'SIMULARE PE PRODUS'!$D$6:$D$243,0)+SUMIFS('SIMULARE PE PRODUS'!$G$6:$G$243,'SIMULARE PE PRODUS'!$C$6:$C$243,$A7,'SIMULARE PE PRODUS'!$D$6:$D$243,0) -> 237880.78 | C7: =SUMIFS('SIMULARE PE PRODUS'!T$6:T$243,'SIMULARE PE PRODUS'!$C$6:$C$243,$A7,'SIMULARE PE PRODUS'!$D$6:$D$243,">0")*SCENARIU!$B$10*SCENARIU!$B$5*SCENARIU!$B$14+SUMIFS('SIMULARE PE PRODUS'!T$6:T$243,'SIMULARE PE PRODUS'!$C$6:$C$243,$A7,'SIMULARE PE PRODUS'!$D$6:$D$243,0) -> 3300094.3 | D7: =IFERROR((SUMIFS('SIMULARE PE PRODUS'!$L$6:$L$243,'SIMULARE PE PRODUS'!$C$6:$C$243,$A7,'SIMULARE PE PRODUS'!$D$6:$D$243,">0")*SCENARIU!$B$10*SCENARIU!$B$5*SCENARIU!$B$14+SUMIFS('SIMULARE PE PRODUS'!$L$6:$L$243,'SIMULARE PE PRODUS'!$C$6:$C$243,$A7,'SIMULARE PE PRODUS'!$D$6:$D$243,0))/C7,"") -> 0.70073136 | E7: =SUMIFS('SIMULARE PE PRODUS'!AB$6:AB$243,'SIMULARE PE PRODUS'!$C$6:$C$243,$A7,'SIMULARE PE PRODUS'!$D$6:$D$243,">0")*SCENARIU!$C$10*SCENARIU!$B$5*SCENARIU!$C$14 -> 3009000.9 | F7: =IFERROR((SUMIFS('SIMULARE PE PRODUS'!$L$6:$L$243,'SIMULARE PE PRODUS'!$C$6:$C$243,$A7,'SIMULARE PE PRODUS'!$D$6:$D$243,">0")*SCENARIU!$C$10*SCENARIU!$B$5*SCENARIU!$C$14)/E7,"") -> 0.67700973 | G7: =SUMIFS('SIMULARE PE PRODUS'!AJ$6:AJ$243,'SIMULARE PE PRODUS'!$C$6:$C$243,$A7,'SIMULARE PE PRODUS'!$D$6:$D$243,">0")*SCENARIU!$D$10*SCENARIU!$B$5*SCENARIU!$D$14 -> 3272504.3 | H7: =IFERROR((SUMIFS('SIMULARE PE PRODUS'!$L$6:$L$243,'SIMULARE PE PRODUS'!$C$6:$C$243,$A7,'SIMULARE PE PRODUS'!$D$6:$D$243,">0")*SCENARIU!$D$10*SCENARIU!$B$5*SCENARIU!$D$14)/G7,"") -> 0.67700973 | I7: =SUMIFS('SIMULARE PE PRODUS'!AR$6:AR$243,'SIMULARE PE PRODUS'!$C$6:$C$243,$A7,'SIMULARE PE PRODUS'!$D$6:$D$243,">0")*SCENARIU!$E$10*SCENARIU!$B$5*SCENARIU!$E$14 -> 3110877.7 | J7: =IFERROR((SUMIFS('SIMULARE PE PRODUS'!$L$6:$L$243,'SIMULARE PE PRODUS'!$C$6:$C$243,$A7,'SIMULARE PE PRODUS'!$D$6:$D$243,">0")*SCENARIU!$E$10*SCENARIU!$B$5*SCENARIU!$E$14)/I7,"") -> 0.67700973 | K7: =SUMIFS('SIMULARE PE PRODUS'!AZ$6:AZ$243,'SIMULARE PE PRODUS'!$C$6:$C$243,$A7,'SIMULARE PE PRODUS'!$D$6:$D$243,">0")*SCENARIU!$F$10*SCENARIU!$B$5*SCENARIU!$F$14 -> 4012841.2 | L7: =IFERROR((SUMIFS('SIMULARE PE PRODUS'!$L$6:$L$243,'SIMULARE PE PRODUS'!$C$6:$C$243,$A7,'SIMULARE PE PRODUS'!$D$6:$D$243,">0")*SCENARIU!$F$10*SCENARIU!$B$5*SCENARIU!$F$14)/K7,"") -> 0.65641749 | M7: =IFERROR(L7-D7,"") -> -0.044313866 | N7: =IFERROR($C7/$C$27,"") -> 0.16649228 | O7: =K7-C7 -> 712746.98 | P7: =(E7-C7)+(G7-C7)+(I7-C7)+(K7-C7) -> 204847.12 | Q7: =IFERROR(K7/C7-1,"") -> 0.21597777
A8: BURGERI CORE PUI | B8: =SUMIFS('SIMULARE PE PRODUS'!$F$6:$F$243,'SIMULARE PE PRODUS'!$C$6:$C$243,$A8,'SIMULARE PE PRODUS'!$D$6:$D$243,">0")*SCENARIU!$B$10*SCENARIU!$B$5+SUMIFS('SIMULARE PE PRODUS'!$G$6:$G$243,'SIMULARE PE PRODUS'!$C$6:$C$243,$A8,'SIMULARE PE PRODUS'!$D$6:$D$243,">0")*SCENARIU!$B$10*SCENARIU!$B$5+SUMIFS('SIMULARE PE PRODUS'!$F$6:$F$243,'SIMULARE PE PRODUS'!$C$6:$C$243,$A8,'SIMULARE PE PRODUS'!$D$6:$D$243,0)+SUMIFS('SIMULARE PE PRODUS'!$G$6:$G$243,'SIMULARE PE PRODUS'!$C$6:$C$243,$A8,'SIMULARE PE PRODUS'!$D$6:$D$243,0) -> 51865.907 | C8: =SUMIFS('SIMULARE PE PRODUS'!T$6:T$243,'SIMULARE PE PRODUS'!$C$6:$C$243,$A8,'SIMULARE PE PRODUS'!$D$6:$D$243,">0")*SCENARIU!$B$10*SCENARIU!$B$5*SCENARIU!$B$14+SUMIFS('SIMULARE PE PRODUS'!T$6:T$243,'SIMULARE PE PRODUS'!$C$6:$C$243,$A8,'SIMULARE PE PRODUS'!$D$6:$D$243,0) -> 421704.04 | D8: =IFERROR((SUMIFS('SIMULARE PE PRODUS'!$L$6:$L$243,'SIMULARE PE PRODUS'!$C$6:$C$243,$A8,'SIMULARE PE PRODUS'!$D$6:$D$243,">0")*SCENARIU!$B$10*SCENARIU!$B$5*SCENARIU!$B$14+SUMIFS('SIMULARE PE PRODUS'!$L$6:$L$243,'SIMULARE PE PRODUS'!$C$6:$C$243,$A8,'SIMULARE PE PRODUS'!$D$6:$D$243,0))/C8,"") -> 0.56580541 | E8: =SUMIFS('SIMULARE PE PRODUS'!AB$6:AB$243,'SIMULARE PE PRODUS'!$C$6:$C$243,$A8,'SIMULARE PE PRODUS'!$D$6:$D$243,">0")*SCENARIU!$C$10*SCENARIU!$B$5*SCENARIU!$C$14 -> 391723.3 | F8: =IFERROR((SUMIFS('SIMULARE PE PRODUS'!$L$6:$L$243,'SIMULARE PE PRODUS'!$C$6:$C$243,$A8,'SIMULARE PE PRODUS'!$D$6:$D$243,">0")*SCENARIU!$C$10*SCENARIU!$B$5*SCENARIU!$C$14)/E8,"") -> 0.53658038 | G8: =SUMIFS('SIMULARE PE PRODUS'!AJ$6:AJ$243,'SIMULARE PE PRODUS'!$C$6:$C$243,$A8,'SIMULARE PE PRODUS'!$D$6:$D$243,">0")*SCENARIU!$D$10*SCENARIU!$B$5*SCENARIU!$D$14 -> 426027.18 | H8: =IFERROR((SUMIFS('SIMULARE PE PRODUS'!$L$6:$L$243,'SIMULARE PE PRODUS'!$C$6:$C$243,$A8,'SIMULARE PE PRODUS'!$D$6:$D$243,">0")*SCENARIU!$D$10*SCENARIU!$B$5*SCENARIU!$D$14)/G8,"") -> 0.53658038 | I8: =SUMIFS('SIMULARE PE PRODUS'!AR$6:AR$243,'SIMULARE PE PRODUS'!$C$6:$C$243,$A8,'SIMULARE PE PRODUS'!$D$6:$D$243,">0")*SCENARIU!$E$10*SCENARIU!$B$5*SCENARIU!$E$14 -> 404986 | J8: =IFERROR((SUMIFS('SIMULARE PE PRODUS'!$L$6:$L$243,'SIMULARE PE PRODUS'!$C$6:$C$243,$A8,'SIMULARE PE PRODUS'!$D$6:$D$243,">0")*SCENARIU!$E$10*SCENARIU!$B$5*SCENARIU!$E$14)/I8,"") -> 0.53658038 | K8: =SUMIFS('SIMULARE PE PRODUS'!AZ$6:AZ$243,'SIMULARE PE PRODUS'!$C$6:$C$243,$A8,'SIMULARE PE PRODUS'!$D$6:$D$243,">0")*SCENARIU!$F$10*SCENARIU!$B$5*SCENARIU!$F$14 -> 533129.66 | L8: =IFERROR((SUMIFS('SIMULARE PE PRODUS'!$L$6:$L$243,'SIMULARE PE PRODUS'!$C$6:$C$243,$A8,'SIMULARE PE PRODUS'!$D$6:$D$243,">0")*SCENARIU!$F$10*SCENARIU!$B$5*SCENARIU!$F$14)/K8,"") -> 0.50979578 | M8: =IFERROR(L8-D8,"") -> -0.056009629 | N8: =IFERROR($C8/$C$27,"") -> 0.021275292 | O8: =K8-C8 -> 111425.62 | P8: =(E8-C8)+(G8-C8)+(I8-C8)+(K8-C8) -> 69049.987 | Q8: =IFERROR(K8/C8-1,"") -> 0.26422707
A9: BURGERI NON-CORE VITĂ | B9: =SUMIFS('SIMULARE PE PRODUS'!$F$6:$F$243,'SIMULARE PE PRODUS'!$C$6:$C$243,$A9,'SIMULARE PE PRODUS'!$D$6:$D$243,">0")*SCENARIU!$B$10*SCENARIU!$B$5+SUMIFS('SIMULARE PE PRODUS'!$G$6:$G$243,'SIMULARE PE PRODUS'!$C$6:$C$243,$A9,'SIMULARE PE PRODUS'!$D$6:$D$243,">0")*SCENARIU!$B$10*SCENARIU!$B$5+SUMIFS('SIMULARE PE PRODUS'!$F$6:$F$243,'SIMULARE PE PRODUS'!$C$6:$C$243,$A9,'SIMULARE PE PRODUS'!$D$6:$D$243,0)+SUMIFS('SIMULARE PE PRODUS'!$G$6:$G$243,'SIMULARE PE PRODUS'!$C$6:$C$243,$A9,'SIMULARE PE PRODUS'!$D$6:$D$243,0) -> 155312.74 | C9: =SUMIFS('SIMULARE PE PRODUS'!T$6:T$243,'SIMULARE PE PRODUS'!$C$6:$C$243,$A9,'SIMULARE PE PRODUS'!$D$6:$D$243,">0")*SCENARIU!$B$10*SCENARIU!$B$5*SCENARIU!$B$14+SUMIFS('SIMULARE PE PRODUS'!T$6:T$243,'SIMULARE PE PRODUS'!$C$6:$C$243,$A9,'SIMULARE PE PRODUS'!$D$6:$D$243,0) -> 3874621.5 | D9: =IFERROR((SUMIFS('SIMULARE PE PRODUS'!$L$6:$L$243,'SIMULARE PE PRODUS'!$C$6:$C$243,$A9,'SIMULARE PE PRODUS'!$D$6:$D$243,">0")*SCENARIU!$B$10*SCENARIU!$B$5*SCENARIU!$B$14+SUMIFS('SIMULARE PE PRODUS'!$L$6:$L$243,'SIMULARE PE PRODUS'!$C$6:$C$243,$A9,'SIMULARE PE PRODUS'!$D$6:$D$243,0))/C9,"") -> 0.46895225 | E9: =SUMIFS('SIMULARE PE PRODUS'!AB$6:AB$243,'SIMULARE PE PRODUS'!$C$6:$C$243,$A9,'SIMULARE PE PRODUS'!$D$6:$D$243,">0")*SCENARIU!$C$10*SCENARIU!$B$5*SCENARIU!$C$14 -> 3474884.2 | F9: =IFERROR((SUMIFS('SIMULARE PE PRODUS'!$L$6:$L$243,'SIMULARE PE PRODUS'!$C$6:$C$243,$A9,'SIMULARE PE PRODUS'!$D$6:$D$243,">0")*SCENARIU!$C$10*SCENARIU!$B$5*SCENARIU!$C$14)/E9,"") -> 0.46063496 | G9: =SUMIFS('SIMULARE PE PRODUS'!AJ$6:AJ$243,'SIMULARE PE PRODUS'!$C$6:$C$243,$A9,'SIMULARE PE PRODUS'!$D$6:$D$243,">0")*SCENARIU!$D$10*SCENARIU!$B$5*SCENARIU!$D$14 -> 3779185.9 | H9: =IFERROR((SUMIFS('SIMULARE PE PRODUS'!$L$6:$L$243,'SIMULARE PE PRODUS'!$C$6:$C$243,$A9,'SIMULARE PE PRODUS'!$D$6:$D$243,">0")*SCENARIU!$D$10*SCENARIU!$B$5*SCENARIU!$D$14)/G9,"") -> 0.46063496 | I9: =SUMIFS('SIMULARE PE PRODUS'!AR$6:AR$243,'SIMULARE PE PRODUS'!$C$6:$C$243,$A9,'SIMULARE PE PRODUS'!$D$6:$D$243,">0")*SCENARIU!$E$10*SCENARIU!$B$5*SCENARIU!$E$14 -> 3654234.7 | J9: =IFERROR((SUMIFS('SIMULARE PE PRODUS'!$L$6:$L$243,'SIMULARE PE PRODUS'!$C$6:$C$243,$A9,'SIMULARE PE PRODUS'!$D$6:$D$243,">0")*SCENARIU!$E$10*SCENARIU!$B$5*SCENARIU!$E$14)/I9,"") -> 0.45285735 | K9: =SUMIFS('SIMULARE PE PRODUS'!AZ$6:AZ$243,'SIMULARE PE PRODUS'!$C$6:$C$243,$A9,'SIMULARE PE PRODUS'!$D$6:$D$243,">0")*SCENARIU!$F$10*SCENARIU!$B$5*SCENARIU!$F$14 -> 4572885.5 | L9: =IFERROR((SUMIFS('SIMULARE PE PRODUS'!$L$6:$L$243,'SIMULARE PE PRODUS'!$C$6:$C$243,$A9,'SIMULARE PE PRODUS'!$D$6:$D$243,">0")*SCENARIU!$F$10*SCENARIU!$B$5*SCENARIU!$F$14)/K9,"") -> 0.45260756 | M9: =IFERROR(L9-D9,"") -> -0.016344688 | N9: =IFERROR($C9/$C$27,"") -> 0.19547762 | O9: =K9-C9 -> 698264.01 | P9: =(E9-C9)+(G9-C9)+(I9-C9)+(K9-C9) -> -17295.683 | Q9: =IFERROR(K9/C9-1,"") -> 0.18021477
A10: BURGERI NON-CORE PUI | B10: =SUMIFS('SIMULARE PE PRODUS'!$F$6:$F$243,'SIMULARE PE PRODUS'!$C$6:$C$243,$A10,'SIMULARE PE PRODUS'!$D$6:$D$243,">0")*SCENARIU!$B$10*SCENARIU!$B$5+SUMIFS('SIMULARE PE PRODUS'!$G$6:$G$243,'SIMULARE PE PRODUS'!$C$6:$C$243,$A10,'SIMULARE PE PRODUS'!$D$6:$D$243,">0")*SCENARIU!$B$10*SCENARIU!$B$5+SUMIFS('SIMULARE PE PRODUS'!$F$6:$F$243,'SIMULARE PE PRODUS'!$C$6:$C$243,$A10,'SIMULARE PE PRODUS'!$D$6:$D$243,0)+SUMIFS('SIMULARE PE PRODUS'!$G$6:$G$243,'SIMULARE PE PRODUS'!$C$6:$C$243,$A10,'SIMULARE PE PRODUS'!$D$6:$D$243,0) -> 77036.126 | C10: =SUMIFS('SIMULARE PE PRODUS'!T$6:T$243,'SIMULARE PE PRODUS'!$C$6:$C$243,$A10,'SIMULARE PE PRODUS'!$D$6:$D$243,">0")*SCENARIU!$B$10*SCENARIU!$B$5*SCENARIU!$B$14+SUMIFS('SIMULARE PE PRODUS'!T$6:T$243,'SIMULARE PE PRODUS'!$C$6:$C$243,$A10,'SIMULARE PE PRODUS'!$D$6:$D$243,0) -> 1395551.2 | D10: =IFERROR((SUMIFS('SIMULARE PE PRODUS'!$L$6:$L$243,'SIMULARE PE PRODUS'!$C$6:$C$243,$A10,'SIMULARE PE PRODUS'!$D$6:$D$243,">0")*SCENARIU!$B$10*SCENARIU!$B$5*SCENARIU!$B$14+SUMIFS('SIMULARE PE PRODUS'!$L$6:$L$243,'SIMULARE PE PRODUS'!$C$6:$C$243,$A10,'SIMULARE PE PRODUS'!$D$6:$D$243,0))/C10,"") -> 0.38072352 | E10: =SUMIFS('SIMULARE PE PRODUS'!AB$6:AB$243,'SIMULARE PE PRODUS'!$C$6:$C$243,$A10,'SIMULARE PE PRODUS'!$D$6:$D$243,">0")*SCENARIU!$C$10*SCENARIU!$B$5*SCENARIU!$C$14 -> 1259946 | F10: =IFERROR((SUMIFS('SIMULARE PE PRODUS'!$L$6:$L$243,'SIMULARE PE PRODUS'!$C$6:$C$243,$A10,'SIMULARE PE PRODUS'!$D$6:$D$243,">0")*SCENARIU!$C$10*SCENARIU!$B$5*SCENARIU!$C$14)/E10,"") -> 0.37148636 | G10: =SUMIFS('SIMULARE PE PRODUS'!AJ$6:AJ$243,'SIMULARE PE PRODUS'!$C$6:$C$243,$A10,'SIMULARE PE PRODUS'!$D$6:$D$243,">0")*SCENARIU!$D$10*SCENARIU!$B$5*SCENARIU!$D$14 -> 1370281.7 | H10: =IFERROR((SUMIFS('SIMULARE PE PRODUS'!$L$6:$L$243,'SIMULARE PE PRODUS'!$C$6:$C$243,$A10,'SIMULARE PE PRODUS'!$D$6:$D$243,">0")*SCENARIU!$D$10*SCENARIU!$B$5*SCENARIU!$D$14)/G10,"") -> 0.37148636 | I10: =SUMIFS('SIMULARE PE PRODUS'!AR$6:AR$243,'SIMULARE PE PRODUS'!$C$6:$C$243,$A10,'SIMULARE PE PRODUS'!$D$6:$D$243,">0")*SCENARIU!$E$10*SCENARIU!$B$5*SCENARIU!$E$14 -> 1334208.4 | J10: =IFERROR((SUMIFS('SIMULARE PE PRODUS'!$L$6:$L$243,'SIMULARE PE PRODUS'!$C$6:$C$243,$A10,'SIMULARE PE PRODUS'!$D$6:$D$243,">0")*SCENARIU!$E$10*SCENARIU!$B$5*SCENARIU!$E$14)/I10,"") -> 0.3626868 | K10: =SUMIFS('SIMULARE PE PRODUS'!AZ$6:AZ$243,'SIMULARE PE PRODUS'!$C$6:$C$243,$A10,'SIMULARE PE PRODUS'!$D$6:$D$243,">0")*SCENARIU!$F$10*SCENARIU!$B$5*SCENARIU!$F$14 -> 1708226 | L10: =IFERROR((SUMIFS('SIMULARE PE PRODUS'!$L$6:$L$243,'SIMULARE PE PRODUS'!$C$6:$C$243,$A10,'SIMULARE PE PRODUS'!$D$6:$D$243,">0")*SCENARIU!$F$10*SCENARIU!$B$5*SCENARIU!$F$14)/K10,"") -> 0.35429448 | M10: =IFERROR(L10-D10,"") -> -0.026429036 | N10: =IFERROR($C10/$C$27,"") -> 0.070406628 | O10: =K10-C10 -> 312674.76 | P10: =(E10-C10)+(G10-C10)+(I10-C10)+(K10-C10) -> 90457.293 | Q10: =IFERROR(K10/C10-1,"") -> 0.22405109
A11: CREVEȚI | B11: =SUMIFS('SIMULARE PE PRODUS'!$F$6:$F$243,'SIMULARE PE PRODUS'!$C$6:$C$243,$A11,'SIMULARE PE PRODUS'!$D$6:$D$243,">0")*SCENARIU!$B$10*SCENARIU!$B$5+SUMIFS('SIMULARE PE PRODUS'!$G$6:$G$243,'SIMULARE PE PRODUS'!$C$6:$C$243,$A11,'SIMULARE PE PRODUS'!$D$6:$D$243,">0")*SCENARIU!$B$10*SCENARIU!$B$5+SUMIFS('SIMULARE PE PRODUS'!$F$6:$F$243,'SIMULARE PE PRODUS'!$C$6:$C$243,$A11,'SIMULARE PE PRODUS'!$D$6:$D$243,0)+SUMIFS('SIMULARE PE PRODUS'!$G$6:$G$243,'SIMULARE PE PRODUS'!$C$6:$C$243,$A11,'SIMULARE PE PRODUS'!$D$6:$D$243,0) -> 3092.8441 | C11: =SUMIFS('SIMULARE PE PRODUS'!T$6:T$243,'SIMULARE PE PRODUS'!$C$6:$C$243,$A11,'SIMULARE PE PRODUS'!$D$6:$D$243,">0")*SCENARIU!$B$10*SCENARIU!$B$5*SCENARIU!$B$14+SUMIFS('SIMULARE PE PRODUS'!T$6:T$243,'SIMULARE PE PRODUS'!$C$6:$C$243,$A11,'SIMULARE PE PRODUS'!$D$6:$D$243,0) -> 75452.666 | D11: =IFERROR((SUMIFS('SIMULARE PE PRODUS'!$L$6:$L$243,'SIMULARE PE PRODUS'!$C$6:$C$243,$A11,'SIMULARE PE PRODUS'!$D$6:$D$243,">0")*SCENARIU!$B$10*SCENARIU!$B$5*SCENARIU!$B$14+SUMIFS('SIMULARE PE PRODUS'!$L$6:$L$243,'SIMULARE PE PRODUS'!$C$6:$C$243,$A11,'SIMULARE PE PRODUS'!$D$6:$D$243,0))/C11,"") -> 0.44168801 | E11: =SUMIFS('SIMULARE PE PRODUS'!AB$6:AB$243,'SIMULARE PE PRODUS'!$C$6:$C$243,$A11,'SIMULARE PE PRODUS'!$D$6:$D$243,">0")*SCENARIU!$C$10*SCENARIU!$B$5*SCENARIU!$C$14 -> 66468.201 | F11: =IFERROR((SUMIFS('SIMULARE PE PRODUS'!$L$6:$L$243,'SIMULARE PE PRODUS'!$C$6:$C$243,$A11,'SIMULARE PE PRODUS'!$D$6:$D$243,">0")*SCENARIU!$C$10*SCENARIU!$B$5*SCENARIU!$C$14)/E11,"") -> 0.44168801 | G11: =SUMIFS('SIMULARE PE PRODUS'!AJ$6:AJ$243,'SIMULARE PE PRODUS'!$C$6:$C$243,$A11,'SIMULARE PE PRODUS'!$D$6:$D$243,">0")*SCENARIU!$D$10*SCENARIU!$B$5*SCENARIU!$D$14 -> 73623.693 | H11: =IFERROR((SUMIFS('SIMULARE PE PRODUS'!$L$6:$L$243,'SIMULARE PE PRODUS'!$C$6:$C$243,$A11,'SIMULARE PE PRODUS'!$D$6:$D$243,">0")*SCENARIU!$D$10*SCENARIU!$B$5*SCENARIU!$D$14)/G11,"") -> 0.43368044 | I11: =SUMIFS('SIMULARE PE PRODUS'!AR$6:AR$243,'SIMULARE PE PRODUS'!$C$6:$C$243,$A11,'SIMULARE PE PRODUS'!$D$6:$D$243,">0")*SCENARIU!$E$10*SCENARIU!$B$5*SCENARIU!$E$14 -> 69987.472 | J11: =IFERROR((SUMIFS('SIMULARE PE PRODUS'!$L$6:$L$243,'SIMULARE PE PRODUS'!$C$6:$C$243,$A11,'SIMULARE PE PRODUS'!$D$6:$D$243,">0")*SCENARIU!$E$10*SCENARIU!$B$5*SCENARIU!$E$14)/I11,"") -> 0.43368044 | K11: =SUMIFS('SIMULARE PE PRODUS'!AZ$6:AZ$243,'SIMULARE PE PRODUS'!$C$6:$C$243,$A11,'SIMULARE PE PRODUS'!$D$6:$D$243,">0")*SCENARIU!$F$10*SCENARIU!$B$5*SCENARIU!$F$14 -> 92294.365 | L11: =IFERROR((SUMIFS('SIMULARE PE PRODUS'!$L$6:$L$243,'SIMULARE PE PRODUS'!$C$6:$C$243,$A11,'SIMULARE PE PRODUS'!$D$6:$D$243,">0")*SCENARIU!$F$10*SCENARIU!$B$5*SCENARIU!$F$14)/K11,"") -> 0.41130997 | M11: =IFERROR(L11-D11,"") -> -0.030378036 | N11: =IFERROR($C11/$C$27,"") -> 0.0038066448 | O11: =K11-C11 -> 16841.699 | P11: =(E11-C11)+(G11-C11)+(I11-C11)+(K11-C11) -> 563.06646 | Q11: =IFERROR(K11/C11-1,"") -> 0.2232088
A12: VEGETARIAN | B12: =SUMIFS('SIMULARE PE PRODUS'!$F$6:$F$243,'SIMULARE PE PRODUS'!$C$6:$C$243,$A12,'SIMULARE PE PRODUS'!$D$6:$D$243,">0")*SCENARIU!$B$10*SCENARIU!$B$5+SUMIFS('SIMULARE PE PRODUS'!$G$6:$G$243,'SIMULARE PE PRODUS'!$C$6:$C$243,$A12,'SIMULARE PE PRODUS'!$D$6:$D$243,">0")*SCENARIU!$B$10*SCENARIU!$B$5+SUMIFS('SIMULARE PE PRODUS'!$F$6:$F$243,'SIMULARE PE PRODUS'!$C$6:$C$243,$A12,'SIMULARE PE PRODUS'!$D$6:$D$243,0)+SUMIFS('SIMULARE PE PRODUS'!$G$6:$G$243,'SIMULARE PE PRODUS'!$C$6:$C$243,$A12,'SIMULARE PE PRODUS'!$D$6:$D$243,0) -> 4157.3189 | C12: =SUMIFS('SIMULARE PE PRODUS'!T$6:T$243,'SIMULARE PE PRODUS'!$C$6:$C$243,$A12,'SIMULARE PE PRODUS'!$D$6:$D$243,">0")*SCENARIU!$B$10*SCENARIU!$B$5*SCENARIU!$B$14+SUMIFS('SIMULARE PE PRODUS'!T$6:T$243,'SIMULARE PE PRODUS'!$C$6:$C$243,$A12,'SIMULARE PE PRODUS'!$D$6:$D$243,0) -> 81480.159 | D12: =IFERROR((SUMIFS('SIMULARE PE PRODUS'!$L$6:$L$243,'SIMULARE PE PRODUS'!$C$6:$C$243,$A12,'SIMULARE PE PRODUS'!$D$6:$D$243,">0")*SCENARIU!$B$10*SCENARIU!$B$5*SCENARIU!$B$14+SUMIFS('SIMULARE PE PRODUS'!$L$6:$L$243,'SIMULARE PE PRODUS'!$C$6:$C$243,$A12,'SIMULARE PE PRODUS'!$D$6:$D$243,0))/C12,"") -> 0.36692035 | E12: =SUMIFS('SIMULARE PE PRODUS'!AB$6:AB$243,'SIMULARE PE PRODUS'!$C$6:$C$243,$A12,'SIMULARE PE PRODUS'!$D$6:$D$243,">0")*SCENARIU!$C$10*SCENARIU!$B$5*SCENARIU!$C$14 -> 71777.975 | F12: =IFERROR((SUMIFS('SIMULARE PE PRODUS'!$L$6:$L$243,'SIMULARE PE PRODUS'!$C$6:$C$243,$A12,'SIMULARE PE PRODUS'!$D$6:$D$243,">0")*SCENARIU!$C$10*SCENARIU!$B$5*SCENARIU!$C$14)/E12,"") -> 0.36692035 | G12: =SUMIFS('SIMULARE PE PRODUS'!AJ$6:AJ$243,'SIMULARE PE PRODUS'!$C$6:$C$243,$A12,'SIMULARE PE PRODUS'!$D$6:$D$243,">0")*SCENARIU!$D$10*SCENARIU!$B$5*SCENARIU!$D$14 -> 79857.841 | H12: =IFERROR((SUMIFS('SIMULARE PE PRODUS'!$L$6:$L$243,'SIMULARE PE PRODUS'!$C$6:$C$243,$A12,'SIMULARE PE PRODUS'!$D$6:$D$243,">0")*SCENARIU!$D$10*SCENARIU!$B$5*SCENARIU!$D$14)/G12,"") -> 0.35867684 | I12: =SUMIFS('SIMULARE PE PRODUS'!AR$6:AR$243,'SIMULARE PE PRODUS'!$C$6:$C$243,$A12,'SIMULARE PE PRODUS'!$D$6:$D$243,">0")*SCENARIU!$E$10*SCENARIU!$B$5*SCENARIU!$E$14 -> 77619.254 | J12: =IFERROR((SUMIFS('SIMULARE PE PRODUS'!$L$6:$L$243,'SIMULARE PE PRODUS'!$C$6:$C$243,$A12,'SIMULARE PE PRODUS'!$D$6:$D$243,">0")*SCENARIU!$E$10*SCENARIU!$B$5*SCENARIU!$E$14)/I12,"") -> 0.35079561 | K12: =SUMIFS('SIMULARE PE PRODUS'!AZ$6:AZ$243,'SIMULARE PE PRODUS'!$C$6:$C$243,$A12,'SIMULARE PE PRODUS'!$D$6:$D$243,">0")*SCENARIU!$F$10*SCENARIU!$B$5*SCENARIU!$F$14 -> 97078.653 | L12: =IFERROR((SUMIFS('SIMULARE PE PRODUS'!$L$6:$L$243,'SIMULARE PE PRODUS'!$C$6:$C$243,$A12,'SIMULARE PE PRODUS'!$D$6:$D$243,">0")*SCENARIU!$F$10*SCENARIU!$B$5*SCENARIU!$F$14)/K12,"") -> 0.35079561 | M12: =IFERROR(L12-D12,"") -> -0.016124737 | N12: =IFERROR($C12/$C$27,"") -> 0.0041107365 | O12: =K12-C12 -> 15598.494 | P12: =(E12-C12)+(G12-C12)+(I12-C12)+(K12-C12) -> 413.08646 | Q12: =IFERROR(K12/C12-1,"") -> 0.19143917
A13: FRIED CHICKEN | B13: =SUMIFS('SIMULARE PE PRODUS'!$F$6:$F$243,'SIMULARE PE PRODUS'!$C$6:$C$243,$A13,'SIMULARE PE PRODUS'!$D$6:$D$243,">0")*SCENARIU!$B$10*SCENARIU!$B$5+SUMIFS('SIMULARE PE PRODUS'!$G$6:$G$243,'SIMULARE PE PRODUS'!$C$6:$C$243,$A13,'SIMULARE PE PRODUS'!$D$6:$D$243,">0")*SCENARIU!$B$10*SCENARIU!$B$5+SUMIFS('SIMULARE PE PRODUS'!$F$6:$F$243,'SIMULARE PE PRODUS'!$C$6:$C$243,$A13,'SIMULARE PE PRODUS'!$D$6:$D$243,0)+SUMIFS('SIMULARE PE PRODUS'!$G$6:$G$243,'SIMULARE PE PRODUS'!$C$6:$C$243,$A13,'SIMULARE PE PRODUS'!$D$6:$D$243,0) -> 76348.827 | C13: =SUMIFS('SIMULARE PE PRODUS'!T$6:T$243,'SIMULARE PE PRODUS'!$C$6:$C$243,$A13,'SIMULARE PE PRODUS'!$D$6:$D$243,">0")*SCENARIU!$B$10*SCENARIU!$B$5*SCENARIU!$B$14+SUMIFS('SIMULARE PE PRODUS'!T$6:T$243,'SIMULARE PE PRODUS'!$C$6:$C$243,$A13,'SIMULARE PE PRODUS'!$D$6:$D$243,0) -> 1780871.6 | D13: =IFERROR((SUMIFS('SIMULARE PE PRODUS'!$L$6:$L$243,'SIMULARE PE PRODUS'!$C$6:$C$243,$A13,'SIMULARE PE PRODUS'!$D$6:$D$243,">0")*SCENARIU!$B$10*SCENARIU!$B$5*SCENARIU!$B$14+SUMIFS('SIMULARE PE PRODUS'!$L$6:$L$243,'SIMULARE PE PRODUS'!$C$6:$C$243,$A13,'SIMULARE PE PRODUS'!$D$6:$D$243,0))/C13,"") -> 0.45861062 | E13: =SUMIFS('SIMULARE PE PRODUS'!AB$6:AB$243,'SIMULARE PE PRODUS'!$C$6:$C$243,$A13,'SIMULARE PE PRODUS'!$D$6:$D$243,">0")*SCENARIU!$C$10*SCENARIU!$B$5*SCENARIU!$C$14 -> 1604132.5 | F13: =IFERROR((SUMIFS('SIMULARE PE PRODUS'!$L$6:$L$243,'SIMULARE PE PRODUS'!$C$6:$C$243,$A13,'SIMULARE PE PRODUS'!$D$6:$D$243,">0")*SCENARIU!$C$10*SCENARIU!$B$5*SCENARIU!$C$14)/E13,"") -> 0.44851379 | G13: =SUMIFS('SIMULARE PE PRODUS'!AJ$6:AJ$243,'SIMULARE PE PRODUS'!$C$6:$C$243,$A13,'SIMULARE PE PRODUS'!$D$6:$D$243,">0")*SCENARIU!$D$10*SCENARIU!$B$5*SCENARIU!$D$14 -> 1744609.2 | H13: =IFERROR((SUMIFS('SIMULARE PE PRODUS'!$L$6:$L$243,'SIMULARE PE PRODUS'!$C$6:$C$243,$A13,'SIMULARE PE PRODUS'!$D$6:$D$243,">0")*SCENARIU!$D$10*SCENARIU!$B$5*SCENARIU!$D$14)/G13,"") -> 0.44851379 | I13: =SUMIFS('SIMULARE PE PRODUS'!AR$6:AR$243,'SIMULARE PE PRODUS'!$C$6:$C$243,$A13,'SIMULARE PE PRODUS'!$D$6:$D$243,">0")*SCENARIU!$E$10*SCENARIU!$B$5*SCENARIU!$E$14 -> 1689766.2 | J13: =IFERROR((SUMIFS('SIMULARE PE PRODUS'!$L$6:$L$243,'SIMULARE PE PRODUS'!$C$6:$C$243,$A13,'SIMULARE PE PRODUS'!$D$6:$D$243,">0")*SCENARIU!$E$10*SCENARIU!$B$5*SCENARIU!$E$14)/I13,"") -> 0.44020001 | K13: =SUMIFS('SIMULARE PE PRODUS'!AZ$6:AZ$243,'SIMULARE PE PRODUS'!$C$6:$C$243,$A13,'SIMULARE PE PRODUS'!$D$6:$D$243,">0")*SCENARIU!$F$10*SCENARIU!$B$5*SCENARIU!$F$14 -> 2159771.2 | L13: =IFERROR((SUMIFS('SIMULARE PE PRODUS'!$L$6:$L$243,'SIMULARE PE PRODUS'!$C$6:$C$243,$A13,'SIMULARE PE PRODUS'!$D$6:$D$243,">0")*SCENARIU!$F$10*SCENARIU!$B$5*SCENARIU!$F$14)/K13,"") -> 0.43074792 | M13: =IFERROR(L13-D13,"") -> -0.027862698 | N13: =IFERROR($C13/$C$27,"") -> 0.089846336 | O13: =K13-C13 -> 378899.62 | P13: =(E13-C13)+(G13-C13)+(I13-C13)+(K13-C13) -> 74792.752 | Q13: =IFERROR(K13/C13-1,"") -> 0.21276078
A14: CARTOFI | B14: =SUMIFS('SIMULARE PE PRODUS'!$F$6:$F$243,'SIMULARE PE PRODUS'!$C$6:$C$243,$A14,'SIMULARE PE PRODUS'!$D$6:$D$243,">0")*SCENARIU!$B$10*SCENARIU!$B$5+SUMIFS('SIMULARE PE PRODUS'!$G$6:$G$243,'SIMULARE PE PRODUS'!$C$6:$C$243,$A14,'SIMULARE PE PRODUS'!$D$6:$D$243,">0")*SCENARIU!$B$10*SCENARIU!$B$5+SUMIFS('SIMULARE PE PRODUS'!$F$6:$F$243,'SIMULARE PE PRODUS'!$C$6:$C$243,$A14,'SIMULARE PE PRODUS'!$D$6:$D$243,0)+SUMIFS('SIMULARE PE PRODUS'!$G$6:$G$243,'SIMULARE PE PRODUS'!$C$6:$C$243,$A14,'SIMULARE PE PRODUS'!$D$6:$D$243,0) -> 304507.69 | C14: =SUMIFS('SIMULARE PE PRODUS'!T$6:T$243,'SIMULARE PE PRODUS'!$C$6:$C$243,$A14,'SIMULARE PE PRODUS'!$D$6:$D$243,">0")*SCENARIU!$B$10*SCENARIU!$B$5*SCENARIU!$B$14+SUMIFS('SIMULARE PE PRODUS'!T$6:T$243,'SIMULARE PE PRODUS'!$C$6:$C$243,$A14,'SIMULARE PE PRODUS'!$D$6:$D$243,0) -> 3694922.4 | D14: =IFERROR((SUMIFS('SIMULARE PE PRODUS'!$L$6:$L$243,'SIMULARE PE PRODUS'!$C$6:$C$243,$A14,'SIMULARE PE PRODUS'!$D$6:$D$243,">0")*SCENARIU!$B$10*SCENARIU!$B$5*SCENARIU!$B$14+SUMIFS('SIMULARE PE PRODUS'!$L$6:$L$243,'SIMULARE PE PRODUS'!$C$6:$C$243,$A14,'SIMULARE PE PRODUS'!$D$6:$D$243,0))/C14,"") -> 0.3008901 | E14: =SUMIFS('SIMULARE PE PRODUS'!AB$6:AB$243,'SIMULARE PE PRODUS'!$C$6:$C$243,$A14,'SIMULARE PE PRODUS'!$D$6:$D$243,">0")*SCENARIU!$C$10*SCENARIU!$B$5*SCENARIU!$C$14 -> 3263244 | F14: =IFERROR((SUMIFS('SIMULARE PE PRODUS'!$L$6:$L$243,'SIMULARE PE PRODUS'!$C$6:$C$243,$A14,'SIMULARE PE PRODUS'!$D$6:$D$243,">0")*SCENARIU!$C$10*SCENARIU!$B$5*SCENARIU!$C$14)/E14,"") -> 0.29227739 | G14: =SUMIFS('SIMULARE PE PRODUS'!AJ$6:AJ$243,'SIMULARE PE PRODUS'!$C$6:$C$243,$A14,'SIMULARE PE PRODUS'!$D$6:$D$243,">0")*SCENARIU!$D$10*SCENARIU!$B$5*SCENARIU!$D$14 -> 3549011.9 | H14: =IFERROR((SUMIFS('SIMULARE PE PRODUS'!$L$6:$L$243,'SIMULARE PE PRODUS'!$C$6:$C$243,$A14,'SIMULARE PE PRODUS'!$D$6:$D$243,">0")*SCENARIU!$D$10*SCENARIU!$B$5*SCENARIU!$D$14)/G14,"") -> 0.29227739 | I14: =SUMIFS('SIMULARE PE PRODUS'!AR$6:AR$243,'SIMULARE PE PRODUS'!$C$6:$C$243,$A14,'SIMULARE PE PRODUS'!$D$6:$D$243,">0")*SCENARIU!$E$10*SCENARIU!$B$5*SCENARIU!$E$14 -> 3422335.3 | J14: =IFERROR((SUMIFS('SIMULARE PE PRODUS'!$L$6:$L$243,'SIMULARE PE PRODUS'!$C$6:$C$243,$A14,'SIMULARE PE PRODUS'!$D$6:$D$243,">0")*SCENARIU!$E$10*SCENARIU!$B$5*SCENARIU!$E$14)/I14,"") -> 0.28812624 | K14: =SUMIFS('SIMULARE PE PRODUS'!AZ$6:AZ$243,'SIMULARE PE PRODUS'!$C$6:$C$243,$A14,'SIMULARE PE PRODUS'!$D$6:$D$243,">0")*SCENARIU!$F$10*SCENARIU!$B$5*SCENARIU!$F$14 -> 4583740.8 | L14: =IFERROR((SUMIFS('SIMULARE PE PRODUS'!$L$6:$L$243,'SIMULARE PE PRODUS'!$C$6:$C$243,$A14,'SIMULARE PE PRODUS'!$D$6:$D$243,">0")*SCENARIU!$F$10*SCENARIU!$B$5*SCENARIU!$F$14)/K14,"") -> 0.26905409 | M14: =IFERROR(L14-D14,"") -> -0.031836004 | N14: =IFERROR($C14/$C$27,"") -> 0.18641167 | O14: =K14-C14 -> 888818.34 | P14: =(E14-C14)+(G14-C14)+(I14-C14)+(K14-C14) -> 38642.204 | Q14: =IFERROR(K14/C14-1,"") -> 0.24055128
A15: SOSURI | B15: =SUMIFS('SIMULARE PE PRODUS'!$F$6:$F$243,'SIMULARE PE PRODUS'!$C$6:$C$243,$A15,'SIMULARE PE PRODUS'!$D$6:$D$243,">0")*SCENARIU!$B$10*SCENARIU!$B$5+SUMIFS('SIMULARE PE PRODUS'!$G$6:$G$243,'SIMULARE PE PRODUS'!$C$6:$C$243,$A15,'SIMULARE PE PRODUS'!$D$6:$D$243,">0")*SCENARIU!$B$10*SCENARIU!$B$5+SUMIFS('SIMULARE PE PRODUS'!$F$6:$F$243,'SIMULARE PE PRODUS'!$C$6:$C$243,$A15,'SIMULARE PE PRODUS'!$D$6:$D$243,0)+SUMIFS('SIMULARE PE PRODUS'!$G$6:$G$243,'SIMULARE PE PRODUS'!$C$6:$C$243,$A15,'SIMULARE PE PRODUS'!$D$6:$D$243,0) -> 240935.91 | C15: =SUMIFS('SIMULARE PE PRODUS'!T$6:T$243,'SIMULARE PE PRODUS'!$C$6:$C$243,$A15,'SIMULARE PE PRODUS'!$D$6:$D$243,">0")*SCENARIU!$B$10*SCENARIU!$B$5*SCENARIU!$B$14+SUMIFS('SIMULARE PE PRODUS'!T$6:T$243,'SIMULARE PE PRODUS'!$C$6:$C$243,$A15,'SIMULARE PE PRODUS'!$D$6:$D$243,0) -> 1978107.3 | D15: =IFERROR((SUMIFS('SIMULARE PE PRODUS'!$L$6:$L$243,'SIMULARE PE PRODUS'!$C$6:$C$243,$A15,'SIMULARE PE PRODUS'!$D$6:$D$243,">0")*SCENARIU!$B$10*SCENARIU!$B$5*SCENARIU!$B$14+SUMIFS('SIMULARE PE PRODUS'!$L$6:$L$243,'SIMULARE PE PRODUS'!$C$6:$C$243,$A15,'SIMULARE PE PRODUS'!$D$6:$D$243,0))/C15,"") -> 0.31183446 | E15: =SUMIFS('SIMULARE PE PRODUS'!AB$6:AB$243,'SIMULARE PE PRODUS'!$C$6:$C$243,$A15,'SIMULARE PE PRODUS'!$D$6:$D$243,">0")*SCENARIU!$C$10*SCENARIU!$B$5*SCENARIU!$C$14 -> 1780808.4 | F15: =IFERROR((SUMIFS('SIMULARE PE PRODUS'!$L$6:$L$243,'SIMULARE PE PRODUS'!$C$6:$C$243,$A15,'SIMULARE PE PRODUS'!$D$6:$D$243,">0")*SCENARIU!$C$10*SCENARIU!$B$5*SCENARIU!$C$14)/E15,"") -> 0.30513785 | G15: =SUMIFS('SIMULARE PE PRODUS'!AJ$6:AJ$243,'SIMULARE PE PRODUS'!$C$6:$C$243,$A15,'SIMULARE PE PRODUS'!$D$6:$D$243,">0")*SCENARIU!$D$10*SCENARIU!$B$5*SCENARIU!$D$14 -> 1936756.8 | H15: =IFERROR((SUMIFS('SIMULARE PE PRODUS'!$L$6:$L$243,'SIMULARE PE PRODUS'!$C$6:$C$243,$A15,'SIMULARE PE PRODUS'!$D$6:$D$243,">0")*SCENARIU!$D$10*SCENARIU!$B$5*SCENARIU!$D$14)/G15,"") -> 0.30513785 | I15: =SUMIFS('SIMULARE PE PRODUS'!AR$6:AR$243,'SIMULARE PE PRODUS'!$C$6:$C$243,$A15,'SIMULARE PE PRODUS'!$D$6:$D$243,">0")*SCENARIU!$E$10*SCENARIU!$B$5*SCENARIU!$E$14 -> 1841101.8 | J15: =IFERROR((SUMIFS('SIMULARE PE PRODUS'!$L$6:$L$243,'SIMULARE PE PRODUS'!$C$6:$C$243,$A15,'SIMULARE PE PRODUS'!$D$6:$D$243,">0")*SCENARIU!$E$10*SCENARIU!$B$5*SCENARIU!$E$14)/I15,"") -> 0.30513785 | K15: =SUMIFS('SIMULARE PE PRODUS'!AZ$6:AZ$243,'SIMULARE PE PRODUS'!$C$6:$C$243,$A15,'SIMULARE PE PRODUS'!$D$6:$D$243,">0")*SCENARIU!$F$10*SCENARIU!$B$5*SCENARIU!$F$14 -> 2351415.1 | L15: =IFERROR((SUMIFS('SIMULARE PE PRODUS'!$L$6:$L$243,'SIMULARE PE PRODUS'!$C$6:$C$243,$A15,'SIMULARE PE PRODUS'!$D$6:$D$243,">0")*SCENARIU!$F$10*SCENARIU!$B$5*SCENARIU!$F$14)/K15,"") -> 0.29881257 | M15: =IFERROR(L15-D15,"") -> -0.013021888 | N15: =IFERROR($C15/$C$27,"") -> 0.099797028 | O15: =K15-C15 -> 373307.85 | P15: =(E15-C15)+(G15-C15)+(I15-C15)+(K15-C15) -> -2346.9059 | Q15: =IFERROR(K15/C15-1,"") -> 0.18871972
A16: DRINKS | B16: =SUMIFS('SIMULARE PE PRODUS'!$F$6:$F$243,'SIMULARE PE PRODUS'!$C$6:$C$243,$A16,'SIMULARE PE PRODUS'!$D$6:$D$243,">0")*SCENARIU!$B$10*SCENARIU!$B$5+SUMIFS('SIMULARE PE PRODUS'!$G$6:$G$243,'SIMULARE PE PRODUS'!$C$6:$C$243,$A16,'SIMULARE PE PRODUS'!$D$6:$D$243,">0")*SCENARIU!$B$10*SCENARIU!$B$5+SUMIFS('SIMULARE PE PRODUS'!$F$6:$F$243,'SIMULARE PE PRODUS'!$C$6:$C$243,$A16,'SIMULARE PE PRODUS'!$D$6:$D$243,0)+SUMIFS('SIMULARE PE PRODUS'!$G$6:$G$243,'SIMULARE PE PRODUS'!$C$6:$C$243,$A16,'SIMULARE PE PRODUS'!$D$6:$D$243,0) -> 196672.2 | C16: =SUMIFS('SIMULARE PE PRODUS'!T$6:T$243,'SIMULARE PE PRODUS'!$C$6:$C$243,$A16,'SIMULARE PE PRODUS'!$D$6:$D$243,">0")*SCENARIU!$B$10*SCENARIU!$B$5*SCENARIU!$B$14+SUMIFS('SIMULARE PE PRODUS'!T$6:T$243,'SIMULARE PE PRODUS'!$C$6:$C$243,$A16,'SIMULARE PE PRODUS'!$D$6:$D$243,0) -> 1601597 | D16: =IFERROR((SUMIFS('SIMULARE PE PRODUS'!$L$6:$L$243,'SIMULARE PE PRODUS'!$C$6:$C$243,$A16,'SIMULARE PE PRODUS'!$D$6:$D$243,">0")*SCENARIU!$B$10*SCENARIU!$B$5*SCENARIU!$B$14+SUMIFS('SIMULARE PE PRODUS'!$L$6:$L$243,'SIMULARE PE PRODUS'!$C$6:$C$243,$A16,'SIMULARE PE PRODUS'!$D$6:$D$243,0))/C16,"") -> 0.48832119 | E16: =SUMIFS('SIMULARE PE PRODUS'!AB$6:AB$243,'SIMULARE PE PRODUS'!$C$6:$C$243,$A16,'SIMULARE PE PRODUS'!$D$6:$D$243,">0")*SCENARIU!$C$10*SCENARIU!$B$5*SCENARIU!$C$14 -> 1469006.9 | F16: =IFERROR((SUMIFS('SIMULARE PE PRODUS'!$L$6:$L$243,'SIMULARE PE PRODUS'!$C$6:$C$243,$A16,'SIMULARE PE PRODUS'!$D$6:$D$243,">0")*SCENARIU!$C$10*SCENARIU!$B$5*SCENARIU!$C$14)/E16,"") -> 0.46900159 | G16: =SUMIFS('SIMULARE PE PRODUS'!AJ$6:AJ$243,'SIMULARE PE PRODUS'!$C$6:$C$243,$A16,'SIMULARE PE PRODUS'!$D$6:$D$243,">0")*SCENARIU!$D$10*SCENARIU!$B$5*SCENARIU!$D$14 -> 1748725.2 | H16: =IFERROR((SUMIFS('SIMULARE PE PRODUS'!$L$6:$L$243,'SIMULARE PE PRODUS'!$C$6:$C$243,$A16,'SIMULARE PE PRODUS'!$D$6:$D$243,">0")*SCENARIU!$D$10*SCENARIU!$B$5*SCENARIU!$D$14)/G16,"") -> 0.42848388 | I16: =SUMIFS('SIMULARE PE PRODUS'!AR$6:AR$243,'SIMULARE PE PRODUS'!$C$6:$C$243,$A16,'SIMULARE PE PRODUS'!$D$6:$D$243,">0")*SCENARIU!$E$10*SCENARIU!$B$5*SCENARIU!$E$14 -> 1734163.6 | J16: =IFERROR((SUMIFS('SIMULARE PE PRODUS'!$L$6:$L$243,'SIMULARE PE PRODUS'!$C$6:$C$243,$A16,'SIMULARE PE PRODUS'!$D$6:$D$243,">0")*SCENARIU!$E$10*SCENARIU!$B$5*SCENARIU!$E$14)/I16,"") -> 0.41074161 | K16: =SUMIFS('SIMULARE PE PRODUS'!AZ$6:AZ$243,'SIMULARE PE PRODUS'!$C$6:$C$243,$A16,'SIMULARE PE PRODUS'!$D$6:$D$243,">0")*SCENARIU!$F$10*SCENARIU!$B$5*SCENARIU!$F$14 -> 2258732.9 | L16: =IFERROR((SUMIFS('SIMULARE PE PRODUS'!$L$6:$L$243,'SIMULARE PE PRODUS'!$C$6:$C$243,$A16,'SIMULARE PE PRODUS'!$D$6:$D$243,">0")*SCENARIU!$F$10*SCENARIU!$B$5*SCENARIU!$F$14)/K16,"") -> 0.39441023 | M16: =IFERROR(L16-D16,"") -> -0.09391096 | N16: =IFERROR($C16/$C$27,"") -> 0.080801799 | O16: =K16-C16 -> 657135.9 | P16: =(E16-C16)+(G16-C16)+(I16-C16)+(K16-C16) -> 804240.58 | Q16: =IFERROR(K16/C16-1,"") -> 0.41030039
A17: FRYCAFE | B17: =SUMIFS('SIMULARE PE PRODUS'!$F$6:$F$243,'SIMULARE PE PRODUS'!$C$6:$C$243,$A17,'SIMULARE PE PRODUS'!$D$6:$D$243,">0")*SCENARIU!$B$10*SCENARIU!$B$5+SUMIFS('SIMULARE PE PRODUS'!$G$6:$G$243,'SIMULARE PE PRODUS'!$C$6:$C$243,$A17,'SIMULARE PE PRODUS'!$D$6:$D$243,">0")*SCENARIU!$B$10*SCENARIU!$B$5+SUMIFS('SIMULARE PE PRODUS'!$F$6:$F$243,'SIMULARE PE PRODUS'!$C$6:$C$243,$A17,'SIMULARE PE PRODUS'!$D$6:$D$243,0)+SUMIFS('SIMULARE PE PRODUS'!$G$6:$G$243,'SIMULARE PE PRODUS'!$C$6:$C$243,$A17,'SIMULARE PE PRODUS'!$D$6:$D$243,0) -> 19395.234 | C17: =SUMIFS('SIMULARE PE PRODUS'!T$6:T$243,'SIMULARE PE PRODUS'!$C$6:$C$243,$A17,'SIMULARE PE PRODUS'!$D$6:$D$243,">0")*SCENARIU!$B$10*SCENARIU!$B$5*SCENARIU!$B$14+SUMIFS('SIMULARE PE PRODUS'!T$6:T$243,'SIMULARE PE PRODUS'!$C$6:$C$243,$A17,'SIMULARE PE PRODUS'!$D$6:$D$243,0) -> 234693.34 | D17: =IFERROR((SUMIFS('SIMULARE PE PRODUS'!$L$6:$L$243,'SIMULARE PE PRODUS'!$C$6:$C$243,$A17,'SIMULARE PE PRODUS'!$D$6:$D$243,">0")*SCENARIU!$B$10*SCENARIU!$B$5*SCENARIU!$B$14+SUMIFS('SIMULARE PE PRODUS'!$L$6:$L$243,'SIMULARE PE PRODUS'!$C$6:$C$243,$A17,'SIMULARE PE PRODUS'!$D$6:$D$243,0))/C17,"") -> 0.42072833 | E17: =SUMIFS('SIMULARE PE PRODUS'!AB$6:AB$243,'SIMULARE PE PRODUS'!$C$6:$C$243,$A17,'SIMULARE PE PRODUS'!$D$6:$D$243,">0")*SCENARIU!$C$10*SCENARIU!$B$5*SCENARIU!$C$14 -> 206747.42 | F17: =IFERROR((SUMIFS('SIMULARE PE PRODUS'!$L$6:$L$243,'SIMULARE PE PRODUS'!$C$6:$C$243,$A17,'SIMULARE PE PRODUS'!$D$6:$D$243,">0")*SCENARIU!$C$10*SCENARIU!$B$5*SCENARIU!$C$14)/E17,"") -> 0.42072833 | G17: =SUMIFS('SIMULARE PE PRODUS'!AJ$6:AJ$243,'SIMULARE PE PRODUS'!$C$6:$C$243,$A17,'SIMULARE PE PRODUS'!$D$6:$D$243,">0")*SCENARIU!$D$10*SCENARIU!$B$5*SCENARIU!$D$14 -> 225934.2 | H17: =IFERROR((SUMIFS('SIMULARE PE PRODUS'!$L$6:$L$243,'SIMULARE PE PRODUS'!$C$6:$C$243,$A17,'SIMULARE PE PRODUS'!$D$6:$D$243,">0")*SCENARIU!$D$10*SCENARIU!$B$5*SCENARIU!$D$14)/G17,"") -> 0.41871429 | I17: =SUMIFS('SIMULARE PE PRODUS'!AR$6:AR$243,'SIMULARE PE PRODUS'!$C$6:$C$243,$A17,'SIMULARE PE PRODUS'!$D$6:$D$243,">0")*SCENARIU!$E$10*SCENARIU!$B$5*SCENARIU!$E$14 -> 215803.6 | J17: =IFERROR((SUMIFS('SIMULARE PE PRODUS'!$L$6:$L$243,'SIMULARE PE PRODUS'!$C$6:$C$243,$A17,'SIMULARE PE PRODUS'!$D$6:$D$243,">0")*SCENARIU!$E$10*SCENARIU!$B$5*SCENARIU!$E$14)/I17,"") -> 0.41671945 | K17: =SUMIFS('SIMULARE PE PRODUS'!AZ$6:AZ$243,'SIMULARE PE PRODUS'!$C$6:$C$243,$A17,'SIMULARE PE PRODUS'!$D$6:$D$243,">0")*SCENARIU!$F$10*SCENARIU!$B$5*SCENARIU!$F$14 -> 269906.27 | L17: =IFERROR((SUMIFS('SIMULARE PE PRODUS'!$L$6:$L$243,'SIMULARE PE PRODUS'!$C$6:$C$243,$A17,'SIMULARE PE PRODUS'!$D$6:$D$243,">0")*SCENARIU!$F$10*SCENARIU!$B$5*SCENARIU!$F$14)/K17,"") -> 0.41671945 | M17: =IFERROR(L17-D17,"") -> -0.0040088784 | N17: =IFERROR($C17/$C$27,"") -> 0.011840459 | O17: =K17-C17 -> 35212.931 | P17: =(E17-C17)+(G17-C17)+(I17-C17)+(K17-C17) -> -20381.862 | Q17: =IFERROR(K17/C17-1,"") -> 0.15003805
A18: MILKSHAKE & DESERT | B18: =SUMIFS('SIMULARE PE PRODUS'!$F$6:$F$243,'SIMULARE PE PRODUS'!$C$6:$C$243,$A18,'SIMULARE PE PRODUS'!$D$6:$D$243,">0")*SCENARIU!$B$10*SCENARIU!$B$5+SUMIFS('SIMULARE PE PRODUS'!$G$6:$G$243,'SIMULARE PE PRODUS'!$C$6:$C$243,$A18,'SIMULARE PE PRODUS'!$D$6:$D$243,">0")*SCENARIU!$B$10*SCENARIU!$B$5+SUMIFS('SIMULARE PE PRODUS'!$F$6:$F$243,'SIMULARE PE PRODUS'!$C$6:$C$243,$A18,'SIMULARE PE PRODUS'!$D$6:$D$243,0)+SUMIFS('SIMULARE PE PRODUS'!$G$6:$G$243,'SIMULARE PE PRODUS'!$C$6:$C$243,$A18,'SIMULARE PE PRODUS'!$D$6:$D$243,0) -> 45948.432 | C18: =SUMIFS('SIMULARE PE PRODUS'!T$6:T$243,'SIMULARE PE PRODUS'!$C$6:$C$243,$A18,'SIMULARE PE PRODUS'!$D$6:$D$243,">0")*SCENARIU!$B$10*SCENARIU!$B$5*SCENARIU!$B$14+SUMIFS('SIMULARE PE PRODUS'!T$6:T$243,'SIMULARE PE PRODUS'!$C$6:$C$243,$A18,'SIMULARE PE PRODUS'!$D$6:$D$243,0) -> 566672.19 | D18: =IFERROR((SUMIFS('SIMULARE PE PRODUS'!$L$6:$L$243,'SIMULARE PE PRODUS'!$C$6:$C$243,$A18,'SIMULARE PE PRODUS'!$D$6:$D$243,">0")*SCENARIU!$B$10*SCENARIU!$B$5*SCENARIU!$B$14+SUMIFS('SIMULARE PE PRODUS'!$L$6:$L$243,'SIMULARE PE PRODUS'!$C$6:$C$243,$A18,'SIMULARE PE PRODUS'!$D$6:$D$243,0))/C18,"") -> 0.39175729 | E18: =SUMIFS('SIMULARE PE PRODUS'!AB$6:AB$243,'SIMULARE PE PRODUS'!$C$6:$C$243,$A18,'SIMULARE PE PRODUS'!$D$6:$D$243,">0")*SCENARIU!$C$10*SCENARIU!$B$5*SCENARIU!$C$14 -> 499196.15 | F18: =IFERROR((SUMIFS('SIMULARE PE PRODUS'!$L$6:$L$243,'SIMULARE PE PRODUS'!$C$6:$C$243,$A18,'SIMULARE PE PRODUS'!$D$6:$D$243,">0")*SCENARIU!$C$10*SCENARIU!$B$5*SCENARIU!$C$14)/E18,"") -> 0.39175729 | G18: =SUMIFS('SIMULARE PE PRODUS'!AJ$6:AJ$243,'SIMULARE PE PRODUS'!$C$6:$C$243,$A18,'SIMULARE PE PRODUS'!$D$6:$D$243,">0")*SCENARIU!$D$10*SCENARIU!$B$5*SCENARIU!$D$14 -> 563489.53 | H18: =IFERROR((SUMIFS('SIMULARE PE PRODUS'!$L$6:$L$243,'SIMULARE PE PRODUS'!$C$6:$C$243,$A18,'SIMULARE PE PRODUS'!$D$6:$D$243,">0")*SCENARIU!$D$10*SCENARIU!$B$5*SCENARIU!$D$14)/G18,"") -> 0.37745082 | I18: =SUMIFS('SIMULARE PE PRODUS'!AR$6:AR$243,'SIMULARE PE PRODUS'!$C$6:$C$243,$A18,'SIMULARE PE PRODUS'!$D$6:$D$243,">0")*SCENARIU!$E$10*SCENARIU!$B$5*SCENARIU!$E$14 -> 554480.23 | J18: =IFERROR((SUMIFS('SIMULARE PE PRODUS'!$L$6:$L$243,'SIMULARE PE PRODUS'!$C$6:$C$243,$A18,'SIMULARE PE PRODUS'!$D$6:$D$243,">0")*SCENARIU!$E$10*SCENARIU!$B$5*SCENARIU!$E$14)/I18,"") -> 0.36463879 | K18: =SUMIFS('SIMULARE PE PRODUS'!AZ$6:AZ$243,'SIMULARE PE PRODUS'!$C$6:$C$243,$A18,'SIMULARE PE PRODUS'!$D$6:$D$243,">0")*SCENARIU!$F$10*SCENARIU!$B$5*SCENARIU!$F$14 -> 693490.23 | L18: =IFERROR((SUMIFS('SIMULARE PE PRODUS'!$L$6:$L$243,'SIMULARE PE PRODUS'!$C$6:$C$243,$A18,'SIMULARE PE PRODUS'!$D$6:$D$243,">0")*SCENARIU!$F$10*SCENARIU!$B$5*SCENARIU!$F$14)/K18,"") -> 0.36463879 | M18: =IFERROR(L18-D18,"") -> -0.027118501 | N18: =IFERROR($C18/$C$27,"") -> 0.028589046 | O18: =K18-C18 -> 126818.04 | P18: =(E18-C18)+(G18-C18)+(I18-C18)+(K18-C18) -> 43967.394 | Q18: =IFERROR(K18/C18-1,"") -> 0.22379436
... A26: GARANTII SGR | B26: =SUMIFS('SIMULARE PE PRODUS'!$F$6:$F$243,'SIMULARE PE PRODUS'!$C$6:$C$243,$A26,'SIMULARE PE PRODUS'!$D$6:$D$243,">0")*SCENARIU!$B$10*SCENARIU!$B$5+SUMIFS('SIMULARE PE PRODUS'!$G$6:$G$243,'SIMULARE PE PRODUS'!$C$6:$C$243,$A26,'SIMULARE PE PRODUS'!$D$6:$D$243,">0")*SCENARIU!$B$10*SCENARIU!$B$5+SUMIFS('SIMULARE PE PRODUS'!$F$6:$F$243,'SIMULARE PE PRODUS'!$C$6:$C$243,$A26,'SIMULARE PE PRODUS'!$D$6:$D$243,0)+SUMIFS('SIMULARE PE PRODUS'!$G$6:$G$243,'SIMULARE PE PRODUS'!$C$6:$C$243,$A26,'SIMULARE PE PRODUS'!$D$6:$D$243,0) -> 25664.739 | C26: =SUMIFS('SIMULARE PE PRODUS'!T$6:T$243,'SIMULARE PE PRODUS'!$C$6:$C$243,$A26,'SIMULARE PE PRODUS'!$D$6:$D$243,">0")*SCENARIU!$B$10*SCENARIU!$B$5*SCENARIU!$B$14+SUMIFS('SIMULARE PE PRODUS'!T$6:T$243,'SIMULARE PE PRODUS'!$C$6:$C$243,$A26,'SIMULARE PE PRODUS'!$D$6:$D$243,0) -> 10605.264 | D26: =IFERROR((SUMIFS('SIMULARE PE PRODUS'!$L$6:$L$243,'SIMULARE PE PRODUS'!$C$6:$C$243,$A26,'SIMULARE PE PRODUS'!$D$6:$D$243,">0")*SCENARIU!$B$10*SCENARIU!$B$5*SCENARIU!$B$14+SUMIFS('SIMULARE PE PRODUS'!$L$6:$L$243,'SIMULARE PE PRODUS'!$C$6:$C$243,$A26,'SIMULARE PE PRODUS'!$D$6:$D$243,0))/C26,"") -> 1.21 | E26: =SUMIFS('SIMULARE PE PRODUS'!AB$6:AB$243,'SIMULARE PE PRODUS'!$C$6:$C$243,$A26,'SIMULARE PE PRODUS'!$D$6:$D$243,">0")*SCENARIU!$C$10*SCENARIU!$B$5*SCENARIU!$C$14 -> 9342.4508 | F26: =IFERROR((SUMIFS('SIMULARE PE PRODUS'!$L$6:$L$243,'SIMULARE PE PRODUS'!$C$6:$C$243,$A26,'SIMULARE PE PRODUS'!$D$6:$D$243,">0")*SCENARIU!$C$10*SCENARIU!$B$5*SCENARIU!$C$14)/E26,"") -> 1.21 | G26: =SUMIFS('SIMULARE PE PRODUS'!AJ$6:AJ$243,'SIMULARE PE PRODUS'!$C$6:$C$243,$A26,'SIMULARE PE PRODUS'!$D$6:$D$243,">0")*SCENARIU!$D$10*SCENARIU!$B$5*SCENARIU!$D$14 -> 10160.585 | H26: =IFERROR((SUMIFS('SIMULARE PE PRODUS'!$L$6:$L$243,'SIMULARE PE PRODUS'!$C$6:$C$243,$A26,'SIMULARE PE PRODUS'!$D$6:$D$243,">0")*SCENARIU!$D$10*SCENARIU!$B$5*SCENARIU!$D$14)/G26,"") -> 1.21 | I26: =SUMIFS('SIMULARE PE PRODUS'!AR$6:AR$243,'SIMULARE PE PRODUS'!$C$6:$C$243,$A26,'SIMULARE PE PRODUS'!$D$6:$D$243,">0")*SCENARIU!$E$10*SCENARIU!$B$5*SCENARIU!$E$14 -> 9658.7614 | J26: =IFERROR((SUMIFS('SIMULARE PE PRODUS'!$L$6:$L$243,'SIMULARE PE PRODUS'!$C$6:$C$243,$A26,'SIMULARE PE PRODUS'!$D$6:$D$243,">0")*SCENARIU!$E$10*SCENARIU!$B$5*SCENARIU!$E$14)/I26,"") -> 1.21 | K26: =SUMIFS('SIMULARE PE PRODUS'!AZ$6:AZ$243,'SIMULARE PE PRODUS'!$C$6:$C$243,$A26,'SIMULARE PE PRODUS'!$D$6:$D$243,">0")*SCENARIU!$F$10*SCENARIU!$B$5*SCENARIU!$F$14 -> 12080.244 | L26: =IFERROR((SUMIFS('SIMULARE PE PRODUS'!$L$6:$L$243,'SIMULARE PE PRODUS'!$C$6:$C$243,$A26,'SIMULARE PE PRODUS'!$D$6:$D$243,">0")*SCENARIU!$F$10*SCENARIU!$B$5*SCENARIU!$F$14)/K26,"") -> 1.21 | M26: =IFERROR(L26-D26,"") -> -2.220446e-16 | N26: =IFERROR($C26/$C$27,"") -> 0.0005350437 | O26: =K26-C26 -> 1474.9801 | P26: =(E26-C26)+(G26-C26)+(I26-C26)+(K26-C26) -> -1179.0146 | Q26: =IFERROR(K26/C26-1,"") -> 0.13908
A27: TOTAL | B27: =SUM(B7:B26) -> 1829382.8 | C27: =SUM(C7:C26) -> 19821304 | D27: =IFERROR((SUMPRODUCT(ISNUMBER('SIMULARE PE PRODUS'!$A$6:$A$243)*('SIMULARE PE PRODUS'!$D$6:$D$243>0)*'SIMULARE PE PRODUS'!$L$6:$L$243)*SCENARIU!$B$10*SCENARIU!$B$5*SCENARIU!$B$14+SUMPRODUCT(ISNUMBER('SIMULARE PE PRODUS'!$A$6:$A$243)*('SIMULARE PE PRODUS'!$D$6:$D$243=0)*'SIMULARE PE PRODUS'!$L$6:$L$243))/C27,"") -> 0.45791945 | E27: =SUM(E7:E26) -> 17851023 | F27: =IFERROR((SUMPRODUCT(ISNUMBER('SIMULARE PE PRODUS'!$A$6:$A$243)*('SIMULARE PE PRODUS'!$D$6:$D$243>0)*'SIMULARE PE PRODUS'!$L$6:$L$243)*SCENARIU!$C$10*SCENARIU!$B$5*SCENARIU!$C$14)/E27,"") -> 0.44581832 | G27: =SUM(G7:G26) -> 19590131 | H27: =IFERROR((SUMPRODUCT(ISNUMBER('SIMULARE PE PRODUS'!$A$6:$A$243)*('SIMULARE PE PRODUS'!$D$6:$D$243>0)*'SIMULARE PE PRODUS'!$L$6:$L$243)*SCENARIU!$D$10*SCENARIU!$B$5*SCENARIU!$D$14)/G27,"") -> 0.44181615 | I27: =SUM(I7:I26) -> 18889183 | J27: =IFERROR((SUMPRODUCT(ISNUMBER('SIMULARE PE PRODUS'!$A$6:$A$243)*('SIMULARE PE PRODUS'!$D$6:$D$243>0)*'SIMULARE PE PRODUS'!$L$6:$L$243)*SCENARIU!$E$10*SCENARIU!$B$5*SCENARIU!$E$14)/I27,"") -> 0.43558054 | K27: =SUM(K7:K26) -> 24310694 | L27: =IFERROR((SUMPRODUCT(ISNUMBER('SIMULARE PE PRODUS'!$A$6:$A$243)*('SIMULARE PE PRODUS'!$D$6:$D$243>0)*'SIMULARE PE PRODUS'!$L$6:$L$243)*SCENARIU!$F$10*SCENARIU!$B$5*SCENARIU!$F$14)/K27,"") -> 0.42329054 | M27: =IFERROR(L27-D27,"") -> -0.034628913 | N27: =SUM(N7:N26) -> 1 | O27: =K27-C27 -> 4489389.7 | P27: =(E27-C27)+(G27-C27)+(I27-C27)+(K27-C27) -> 1355813.5 | Q27: =IFERROR(K27/C27-1,"") -> 0.22649315

Sheet TOP SALES
A1: TOP SALES — produsele după vânzări nete, descrescător
A2: August, săptămâna 03–09.08. Se actualizează automat la orice modificare de preț sau rețetă.
A4: # | B4: Produs | C4: Categorie | D4: Buc InStore | E4: Buc Delivery | F4: Buc TOTAL | G4: Vânzări nete | H4: % din total | I4: Cost material | J4: FOOD COST | K4: Profit brut
A5: 1 | B5: REALLY CRUNCHY FRIES 170G | C5: CARTOFI | D5: ='SIMULARE PE PRODUS'!$F$69 -> 42662 | E5: ='SIMULARE PE PRODUS'!$G$69 -> 6061 | F5: =$D5+$E5 -> 48723 | G5: ='SIMULARE PE PRODUS'!T$69 -> 558435.31 | H5: =IFERROR($G5/'SIMULARE PE PRODUS'!T$4,"") -> 0.11762269 | I5: ='SIMULARE PE PRODUS'!$L$69 -> 181601.43 | J5: =IFERROR($I5/$G5,"") -> 0.3251969 | K5: =$G5-$I5 -> 376833.88
A6: 2 | B6: DUBLU SMASHED BURGER | C6: BURGERI NON-CORE VITĂ | D6: ='SIMULARE PE PRODUS'!$F$21 -> 6175 | E6: ='SIMULARE PE PRODUS'!$G$21 -> 3718 | F6: =$D6+$E6 -> 9893 | G6: ='SIMULARE PE PRODUS'!T$21 -> 270100.06 | H6: =IFERROR($G6/'SIMULARE PE PRODUS'!T$4,"") -> 0.056890915 | I6: ='SIMULARE PE PRODUS'!$L$21 -> 125521.3 | J6: =IFERROR($I6/$G6,"") -> 0.46472148 | K6: =$G6-$I6 -> 144578.76
A7: 3 | B7: CARTOFI CRISS CUT 140G | C7: CARTOFI | D7: ='SIMULARE PE PRODUS'!$F$70 -> 9978 | E7: ='SIMULARE PE PRODUS'!$G$70 -> 6098 | F7: =$D7+$E7 -> 16076 | G7: ='SIMULARE PE PRODUS'!T$70 -> 217068.2 | H7: =IFERROR($G7/'SIMULARE PE PRODUS'!T$4,"") -> 0.045720864 | I7: ='SIMULARE PE PRODUS'!$L$70 -> 54382.438 | J7: =IFERROR($I7/$G7,"") -> 0.25053158 | K7: =$G7-$I7 -> 162685.76
A8: 4 | B8: DUBLU BLACK TRUFFLE SMASHED | C8: BURGERI NON-CORE VITĂ | D8: ='SIMULARE PE PRODUS'!$F$22 -> 5163 | E8: ='SIMULARE PE PRODUS'!$G$22 -> 2418 | F8: =$D8+$E8 -> 7581 | G8: ='SIMULARE PE PRODUS'!T$22 -> 211358.73 | H8: =IFERROR($G8/'SIMULARE PE PRODUS'!T$4,"") -> 0.044518285 | I8: ='SIMULARE PE PRODUS'!$L$22 -> 101328.14 | J8: =IFERROR($I8/$G8,"") -> 0.47941308 | K8: =$G8-$I8 -> 110030.59
A9: 5 | B9: DUBLU CHEESEBURGER | C9: BURGERI CORE VITĂ | D9: ='SIMULARE PE PRODUS'!$F$7 -> 5150 | E9: ='SIMULARE PE PRODUS'!$G$7 -> 6698 | F9: =$D9+$E9 -> 11848 | G9: ='SIMULARE PE PRODUS'!T$7 -> 204091.46 | H9: =IFERROR($G9/'SIMULARE PE PRODUS'!T$4,"") -> 0.042987587 | I9: ='SIMULARE PE PRODUS'!$L$7 -> 133784.26 | J9: =IFERROR($I9/$G9,"") -> 0.65551133 | K9: =$G9-$I9 -> 70307.195
A10: 6 | B10: AMERICAN TRIPLU CHEESEBURGER | C10: BURGERI CORE VITĂ | D10: ='SIMULARE PE PRODUS'!$F$8 -> 4896 | E10: ='SIMULARE PE PRODUS'!$G$8 -> 4666 | F10: =$D10+$E10 -> 9562 | G10: ='SIMULARE PE PRODUS'!T$8 -> 202127.93 | H10: =IFERROR($G10/'SIMULARE PE PRODUS'!T$4,"") -> 0.04257401 | I10: ='SIMULARE PE PRODUS'!$L$8 -> 144070.65 | J10: =IFERROR($I10/$G10,"") -> 0.71276966 | K10: =$G10-$I10 -> 58057.274
A11: 7 | B11: BLACK TRUFFLE SMASHED | C11: BURGERI NON-CORE VITĂ | D11: ='SIMULARE PE PRODUS'!$F$23 -> 4157 | E11: ='SIMULARE PE PRODUS'!$G$23 -> 2680 | F11: =$D11+$E11 -> 6837 | G11: ='SIMULARE PE PRODUS'!T$23 -> 148849.22 | H11: =IFERROR($G11/'SIMULARE PE PRODUS'!T$4,"") -> 0.031351966 | I11: ='SIMULARE PE PRODUS'!$L$23 -> 60267.897 | J11: =IFERROR($I11/$G11,"") -> 0.40489227 | K11: =$G11-$I11 -> 88581.32
A12: 8 | B12: SMASHED BURGER | C12: BURGERI NON-CORE VITĂ | D12: ='SIMULARE PE PRODUS'!$F$24 -> 4656 | E12: ='SIMULARE PE PRODUS'!$G$24 -> 1173 | F12: =$D12+$E12 -> 5829 | G12: ='SIMULARE PE PRODUS'!T$24 -> 119175.86 | H12: =IFERROR($G12/'SIMULARE PE PRODUS'!T$4,"") -> 0.025101897 | I12: ='SIMULARE PE PRODUS'!$L$24 -> 47900.446 | J12: =IFERROR($I12/$G12,"") -> 0.40193076 | K12: =$G12-$I12 -> 71275.419
A13: 9 | B13: AMERICAN DUBLU CHEESEBURGER | C13: BURGERI CORE VITĂ | D13: ='SIMULARE PE PRODUS'!$F$9 -> 6649 | E13: ='SIMULARE PE PRODUS'!$G$9 -> 1326 | F13: =$D13+$E13 -> 7975 | G13: ='SIMULARE PE PRODUS'!T$9 -> 118538.74 | H13: =IFERROR($G13/'SIMULARE PE PRODUS'!T$4,"") -> 0.0249677 | I13: ='SIMULARE PE PRODUS'!$L$9 -> 86664.325 | J13: =IFERROR($I13/$G13,"") -> 0.73110551 | K13: =$G13-$I13 -> 31874.414
A14: 10 | B14: DIP N Cheddar 100 ML | C14: SOSURI | D14: ='SIMULARE PE PRODUS'!$F$75 -> 6426 | E14: ='SIMULARE PE PRODUS'!$G$75 -> 2882 | F14: =$D14+$E14 -> 9308 | G14: ='SIMULARE PE PRODUS'!T$75 -> 118069.05 | H14: =IFERROR($G14/'SIMULARE PE PRODUS'!T$4,"") -> 0.024868769 | I14: ='SIMULARE PE PRODUS'!$L$75 -> 45536.691 | J14: =IFERROR($I14/$G14,"") -> 0.38567849 | K14: =$G14-$I14 -> 72532.354
A15: 11 | B15: DIP N FRYRANCH 100G | C15: SOSURI | D15: ='SIMULARE PE PRODUS'!$F$76 -> 6337 | E15: ='SIMULARE PE PRODUS'!$G$76 -> 2549 | F15: =$D15+$E15 -> 8886 | G15: ='SIMULARE PE PRODUS'!T$76 -> 112716.11 | H15: =IFERROR($G15/'SIMULARE PE PRODUS'!T$4,"") -> 0.023741285 | I15: ='SIMULARE PE PRODUS'!$L$76 -> 26643.605 | J15: =IFERROR($I15/$G15,"") -> 0.23637797 | K15: =$G15-$I15 -> 86072.503
A16: 12 | B16: REALLY CRUNCHY FRIES 170G — transfer 03–09.08 | C16: CARTOFI | D16: ='SIMULARE PE PRODUS'!$F$71 -> 0 | E16: ='SIMULARE PE PRODUS'!$G$71 -> 7800 | F16: =$D16+$E16 -> 7800 | G16: ='SIMULARE PE PRODUS'!T$71 -> 105335.14 | H16: =IFERROR($G16/'SIMULARE PE PRODUS'!T$4,"") -> 0.022186638 | I16: ='SIMULARE PE PRODUS'!$L$71 -> 29072.33 | J16: =IFERROR($I16/$G16,"") -> 0.27599841 | K16: =$G16-$I16 -> 76262.805
A17: 13 | B17: AMERICAN TRIPLU CHEESEBURGER LETTUCE WRAP | C17: BURGERI NON-CORE VITĂ | D17: ='SIMULARE PE PRODUS'!$F$25 -> 2652 | E17: ='SIMULARE PE PRODUS'!$G$25 -> 1759 | F17: =$D17+$E17 -> 4411 | G17: ='SIMULARE PE PRODUS'!T$25 -> 104061.16 | H17: =IFERROR($G17/'SIMULARE PE PRODUS'!T$4,"") -> 0.021918302 | I17: ='SIMULARE PE PRODUS'!$L$25 -> 66956.797 | J17: =IFERROR($I17/$G17,"") -> 0.64343696 | K17: =$G17-$I17 -> 37104.365
A18: 14 | B18: AMERICAN CHEESEBURGER | C18: BURGERI CORE VITĂ | D18: ='SIMULARE PE PRODUS'!$F$10 -> 9314 | E18: ='SIMULARE PE PRODUS'!$G$10 -> 1557 | F18: =$D18+$E18 -> 10871 | G18: ='SIMULARE PE PRODUS'!T$10 -> 102145.05 | H18: =IFERROR($G18/'SIMULARE PE PRODUS'!T$4,"") -> 0.021514712 | I18: ='SIMULARE PE PRODUS'!$L$10 -> 72476.957 | J18: =IFERROR($I18/$G18,"") -> 0.70954942 | K18: =$G18-$I18 -> 29668.088
A19: 15 | B19: HOMESTYLE CRISPY 5 (300G) | C19: FRIED CHICKEN | D19: ='SIMULARE PE PRODUS'!$F$50 -> 2302 | E19: ='SIMULARE PE PRODUS'!$G$50 -> 1136 | F19: =$D19+$E19 -> 3438 | G19: ='SIMULARE PE PRODUS'!T$50 -> 98561.261 | H19: =IFERROR($G19/'SIMULARE PE PRODUS'!T$4,"") -> 0.020759863 | I19: ='SIMULARE PE PRODUS'!$L$50 -> 49451.889 | J19: =IFERROR($I19/$G19,"") -> 0.50173758 | K19: =$G19-$I19 -> 49109.372
A20: 16 | B20: CHEESEBURGER | C20: BURGERI CORE VITĂ | D20: ='SIMULARE PE PRODUS'!$F$11 -> 6953 | E20: ='SIMULARE PE PRODUS'!$G$11 -> 1987 | F20: =$D20+$E20 -> 8940 | G20: ='SIMULARE PE PRODUS'!T$11 -> 96121.261 | H20: =IFERROR($G20/'SIMULARE PE PRODUS'!T$4,"") -> 0.020245928 | I20: ='SIMULARE PE PRODUS'!$L$11 -> 62527.3 | J20: =IFERROR($I20/$G20,"") -> 0.65050436 | K20: =$G20-$I20 -> 33593.962
A21: 17 | B21: Pepsi-Cola 500ml | C21: DRINKS | D21: ='SIMULARE PE PRODUS'!$F$93 -> 8964 | E21: ='SIMULARE PE PRODUS'!$G$93 -> 0 | F21: =$D21+$E21 -> 8964 | G21: ='SIMULARE PE PRODUS'!T$93 -> 81416.826 | H21: =IFERROR($G21/'SIMULARE PE PRODUS'!T$4,"") -> 0.017148747 | I21: ='SIMULARE PE PRODUS'!$L$93 -> 42945.367 | J21: =IFERROR($I21/$G21,"") -> 0.52747532 | K21: =$G21-$I21 -> 38471.46
A22: 18 | B22: REALLY CRUNCHY FRIES 170G — transfer forecast | C22: CARTOFI | D22: ='SIMULARE PE PRODUS'!$F$72 -> 0 | E22: ='SIMULARE PE PRODUS'!$G$72 -> 6000 | F22: =$D22+$E22 -> 6000 | G22: ='SIMULARE PE PRODUS'!T$72 -> 81027.027 | H22: =IFERROR($G22/'SIMULARE PE PRODUS'!T$4,"") -> 0.017066644 | I22: ='SIMULARE PE PRODUS'!$L$72 -> 22363.331 | J22: =IFERROR($I22/$G22,"") -> 0.27599841 | K22: =$G22-$I22 -> 58663.696
A23: 19 | B23: PUI BURGER | C23: BURGERI CORE PUI | D23: ='SIMULARE PE PRODUS'!$F$16 -> 8484 | E23: ='SIMULARE PE PRODUS'!$G$16 -> 1972 | F23: =$D23+$E23 -> 10456 | G23: ='SIMULARE PE PRODUS'!T$16 -> 71268.468 | H23: =IFERROR($G23/'SIMULARE PE PRODUS'!T$4,"") -> 0.015011209 | I23: ='SIMULARE PE PRODUS'!$L$16 -> 44709.473 | J23: =IFERROR($I23/$G23,"") -> 0.62733877 | K23: =$G23-$I23 -> 26558.995
A24: 20 | B24: Pepsi -Cola 350ML new2026 | C24: DRINKS | D24: ='SIMULARE PE PRODUS'!$F$94 -> 9763 | E24: ='SIMULARE PE PRODUS'!$G$94 -> 0 | F24: =$D24+$E24 -> 9763 | G24: ='SIMULARE PE PRODUS'!T$94 -> 64468.074 | H24: =IFERROR($G24/'SIMULARE PE PRODUS'!T$4,"") -> 0.013578848 | I24: ='SIMULARE PE PRODUS'!$L$94 -> 34282.248 | J24: =IFERROR($I24/$G24,"") -> 0.53177093 | K24: =$G24-$I24 -> 30185.827
A25: 21 | B25: SAMURAI CHICKEN | C25: BURGERI NON-CORE PUI | D25: ='SIMULARE PE PRODUS'!$F$30 -> 2828 | E25: ='SIMULARE PE PRODUS'!$G$30 -> 1452 | F25: =$D25+$E25 -> 4280 | G25: ='SIMULARE PE PRODUS'!T$30 -> 64271.351 | H25: =IFERROR($G25/'SIMULARE PE PRODUS'!T$4,"") -> 0.013537413 | I25: ='SIMULARE PE PRODUS'!$L$30 -> 20969.513 | J25: =IFERROR($I25/$G25,"") -> 0.32626531 | K25: =$G25-$I25 -> 43301.839
A26: 22 | B26: HOMESTYLE CHICKEN RANCH | C26: BURGERI NON-CORE PUI | D26: ='SIMULARE PE PRODUS'!$F$31 -> 1779 | E26: ='SIMULARE PE PRODUS'!$G$31 -> 751 | F26: =$D26+$E26 -> 2530 | G26: ='SIMULARE PE PRODUS'!T$31 -> 62870.901 | H26: =IFERROR($G26/'SIMULARE PE PRODUS'!T$4,"") -> 0.013242437 | I26: ='SIMULARE PE PRODUS'!$L$31 -> 25669.388 | J26: =IFERROR($I26/$G26,"") -> 0.40828726 | K26: =$G26-$I26 -> 37201.513
A27: 23 | B27: HOMESTYLE CRISPY 3 (180G) | C27: FRIED CHICKEN | D27: ='SIMULARE PE PRODUS'!$F$51 -> 2205 | E27: ='SIMULARE PE PRODUS'!$G$51 -> 628 | F27: =$D27+$E27 -> 2833 | G27: ='SIMULARE PE PRODUS'!T$51 -> 48631.081 | H27: =IFERROR($G27/'SIMULARE PE PRODUS'!T$4,"") -> 0.010243118 | I27: ='SIMULARE PE PRODUS'!$L$51 -> 24593.69 | J27: =IFERROR($I27/$G27,"") -> 0.50571958 | K27: =$G27-$I27 -> 24037.391
A28: 24 | B28: HAMBURGER | C28: BURGERI CORE VITĂ | D28: ='SIMULARE PE PRODUS'!$F$12 -> 5302 | E28: ='SIMULARE PE PRODUS'!$G$12 -> 1141 | F28: =$D28+$E28 -> 6443 | G28: ='SIMULARE PE PRODUS'!T$12 -> 48491.892 | H28: =IFERROR($G28/'SIMULARE PE PRODUS'!T$4,"") -> 0.0102138 | I28: ='SIMULARE PE PRODUS'!$L$12 -> 41003.929 | J28: =IFERROR($I28/$G28,"") -> 0.8455832 | K28: =$G28-$I28 -> 7487.9627
A29: 25 | B29: Punga Mica | C29: AMBALAJE VÂNDUTE | D29: ='SIMULARE PE PRODUS'!$F$234 -> 3077 | E29: ='SIMULARE PE PRODUS'!$G$234 -> 67784 | F29: =$D29+$E29 -> 70861 | G29: ='SIMULARE PE PRODUS'!T$234 -> 47879.054 | H29: =IFERROR($G29/'SIMULARE PE PRODUS'!T$4,"") -> 0.010084719 | I29: ='SIMULARE PE PRODUS'!$L$234 -> 37485.469 | J29: =IFERROR($I29/$G29,"") -> 0.78292 | K29: =$G29-$I29 -> 10393.585
A30: 26 | B30: HOMESTYLE CRISPY 4 (240G) | C30: FRIED CHICKEN | D30: ='SIMULARE PE PRODUS'!$F$52 -> 1543 | E30: ='SIMULARE PE PRODUS'!$G$52 -> 498 | F30: =$D30+$E30 -> 2041 | G30: ='SIMULARE PE PRODUS'!T$52 -> 46843.694 | H30: =IFERROR($G30/'SIMULARE PE PRODUS'!T$4,"") -> 0.0098666419 | I30: ='SIMULARE PE PRODUS'!$L$52 -> 23537.893 | J30: =IFERROR($I30/$G30,"") -> 0.5024773 | K30: =$G30-$I30 -> 23305.801
A31: 27 | B31: Side Cheddar 40ml | C31: SOSURI | D31: ='SIMULARE PE PRODUS'!$F$77 -> 5108 | E31: ='SIMULARE PE PRODUS'!$G$77 -> 2497 | F31: =$D31+$E31 -> 7605 | G31: ='SIMULARE PE PRODUS'!T$77 -> 42918.018 | H31: =IFERROR($G31/'SIMULARE PE PRODUS'!T$4,"") -> 0.0090397806 | I31: ='SIMULARE PE PRODUS'!$L$77 -> 15429.663 | J31: =IFERROR($I31/$G31,"") -> 0.3595148 | K31: =$G31-$I31 -> 27488.355
A32: 28 | B32: DUBLU RED PEPPER SMASHED | C32: BURGERI NON-CORE VITĂ | D32: ='SIMULARE PE PRODUS'!$F$26 -> 919 | E32: ='SIMULARE PE PRODUS'!$G$26 -> 398 | F32: =$D32+$E32 -> 1317 | G32: ='SIMULARE PE PRODUS'!T$26 -> 41404.351 | H32: =IFERROR($G32/'SIMULARE PE PRODUS'!T$4,"") -> 0.0087209584 | I32: ='SIMULARE PE PRODUS'!$L$26 -> 19582.961 | J32: =IFERROR($I32/$G32,"") -> 0.47296866 | K32: =$G32-$I32 -> 21821.391
A33: 29 | B33: Pepsi Zero 500ml | C33: DRINKS | D33: ='SIMULARE PE PRODUS'!$F$95 -> 4497 | E33: ='SIMULARE PE PRODUS'!$G$95 -> 0 | F33: =$D33+$E33 -> 4497 | G33: ='SIMULARE PE PRODUS'!T$95 -> 40844.653 | H33: =IFERROR($G33/'SIMULARE PE PRODUS'!T$4,"") -> 0.0086030697 | I33: ='SIMULARE PE PRODUS'!$L$95 -> 21545.131 | J33: =IFERROR($I33/$G33,"") -> 0.52748963 | K33: =$G33-$I33 -> 19299.522
A34: 30 | B34: Sos Usturoi | C34: SOSURI | D34: ='SIMULARE PE PRODUS'!$F$78 -> 5449 | E34: ='SIMULARE PE PRODUS'!$G$78 -> 1627 | F34: =$D34+$E34 -> 7076 | G34: ='SIMULARE PE PRODUS'!T$78 -> 38886.126 | H34: =IFERROR($G34/'SIMULARE PE PRODUS'!T$4,"") -> 0.0081905471 | I34: ='SIMULARE PE PRODUS'!$L$78 -> 14038.784 | J34: =IFERROR($I34/$G34,"") -> 0.36102295 | K34: =$G34-$I34 -> 24847.342
A35: 31 | B35: Pepsi Zero 350ML new2026 | C35: DRINKS | D35: ='SIMULARE PE PRODUS'!$F$96 -> 5796 | E35: ='SIMULARE PE PRODUS'!$G$96 -> 0 | F35: =$D35+$E35 -> 5796 | G35: ='SIMULARE PE PRODUS'!T$96 -> 38272.76 | H35: =IFERROR($G35/'SIMULARE PE PRODUS'!T$4,"") -> 0.0080613545 | I35: ='SIMULARE PE PRODUS'!$L$96 -> 20352.873 | J35: =IFERROR($I35/$G35,"") -> 0.53178483 | K35: =$G35-$I35 -> 17919.887
A36: 32 | B36: PACK HOMESTYLE CRISPY 20 (1200G) | C36: FRIED CHICKEN | D36: ='SIMULARE PE PRODUS'!$F$53 -> 259 | E36: ='SIMULARE PE PRODUS'!$G$53 -> 116 | F36: =$D36+$E36 -> 375 | G36: ='SIMULARE PE PRODUS'!T$53 -> 36292.793 | H36: =IFERROR($G36/'SIMULARE PE PRODUS'!T$4,"") -> 0.0076443158 | I36: ='SIMULARE PE PRODUS'!$L$53 -> 22232.118 | J36: =IFERROR($I36/$G36,"") -> 0.61257666 | K36: =$G36-$I36 -> 14060.675
A37: 33 | B37: CHICKEN LEMON | C37: BURGERI NON-CORE PUI | D37: ='SIMULARE PE PRODUS'!$F$32 -> 1599 | E37: ='SIMULARE PE PRODUS'!$G$32 -> 799 | F37: =$D37+$E37 -> 2398 | G37: ='SIMULARE PE PRODUS'!T$32 -> 35983.802 | H37: =IFERROR($G37/'SIMULARE PE PRODUS'!T$4,"") -> 0.0075792333 | I37: ='SIMULARE PE PRODUS'!$L$32 -> 12030.9 | J37: =IFERROR($I37/$G37,"") -> 0.3343421 | K37: =$G37-$I37 -> 23952.902
A38: 34 | B38: SIDE FRYRANCH 40G | C38: SOSURI | D38: ='SIMULARE PE PRODUS'!$F$79 -> 4095 | E38: ='SIMULARE PE PRODUS'!$G$79 -> 2349 | F38: =$D38+$E38 -> 6444 | G38: ='SIMULARE PE PRODUS'!T$79 -> 35412.973 | H38: =IFERROR($G38/'SIMULARE PE PRODUS'!T$4,"") -> 0.0074590002 | I38: ='SIMULARE PE PRODUS'!$L$79 -> 8192.5923 | J38: =IFERROR($I38/$G38,"") -> 0.23134438 | K38: =$G38-$I38 -> 27220.381
A39: 35 | B39: CHICKEN TRUFFLE | C39: BURGERI NON-CORE PUI | D39: ='SIMULARE PE PRODUS'!$F$33 -> 1943 | E39: ='SIMULARE PE PRODUS'!$G$33 -> 626 | F39: =$D39+$E39 -> 2569 | G39: ='SIMULARE PE PRODUS'!T$33 -> 34663.793 | H39: =IFERROR($G39/'SIMULARE PE PRODUS'!T$4,"") -> 0.0073012011 | I39: ='SIMULARE PE PRODUS'!$L$33 -> 14377.403 | J39: =IFERROR($I39/$G39,"") -> 0.41476716 | K39: =$G39-$I39 -> 20286.39
A40: 36 | B40: DIP N FRYRANCH 250G | C40: SOSURI | D40: ='SIMULARE PE PRODUS'!$F$80 -> 674 | E40: ='SIMULARE PE PRODUS'!$G$80 -> 828 | F40: =$D40+$E40 -> 1502 | G40: ='SIMULARE PE PRODUS'!T$80 -> 33964.144 | H40: =IFERROR($G40/'SIMULARE PE PRODUS'!T$4,"") -> 0.0071538348 | I40: ='SIMULARE PE PRODUS'!$L$80 -> 10406.532 | J40: =IFERROR($I40/$G40,"") -> 0.30639759 | K40: =$G40-$I40 -> 23557.612
A41: 37 | B41: DUBLU CHICKEN TRUFFLE | C41: BURGERI NON-CORE PUI | D41: ='SIMULARE PE PRODUS'!$F$34 -> 725 | E41: ='SIMULARE PE PRODUS'!$G$34 -> 936 | F41: =$D41+$E41 -> 1661 | G41: ='SIMULARE PE PRODUS'!T$34 -> 31599.45 | H41: =IFERROR($G41/'SIMULARE PE PRODUS'!T$4,"") -> 0.0066557617 | I41: ='SIMULARE PE PRODUS'!$L$34 -> 12826.064 | J41: =IFERROR($I41/$G41,"") -> 0.40589515 | K41: =$G41-$I41 -> 18773.387
A42: 38 | B42: RED PEPPER SMASHED | C42: BURGERI NON-CORE VITĂ | D42: ='SIMULARE PE PRODUS'!$F$27 -> 966 | E42: ='SIMULARE PE PRODUS'!$G$27 -> 226 | F42: =$D42+$E42 -> 1192 | G42: ='SIMULARE PE PRODUS'!T$27 -> 29594.667 | H42: =IFERROR($G42/'SIMULARE PE PRODUS'!T$4,"") -> 0.006233496 | I42: ='SIMULARE PE PRODUS'!$L$27 -> 12009.47 | J42: =IFERROR($I42/$G42,"") -> 0.40579845 | K42: =$G42-$I42 -> 17585.197
A43: 39 | B43: DUBLU PUI BURGER | C43: BURGERI CORE PUI | D43: ='SIMULARE PE PRODUS'!$F$17 -> 1030 | E43: ='SIMULARE PE PRODUS'!$G$17 -> 820 | F43: =$D43+$E43 -> 1850 | G43: ='SIMULARE PE PRODUS'!T$17 -> 28032.883 | H43: =IFERROR($G43/'SIMULARE PE PRODUS'!T$4,"") -> 0.005904539 | I43: ='SIMULARE PE PRODUS'!$L$17 -> 11678.67 | J43: =IFERROR($I43/$G43,"") -> 0.41660609 | K43: =$G43-$I43 -> 16354.213
A44: 40 | B44: MAC & CHEESY BITES | C44: SNACK | D44: ='SIMULARE PE PRODUS'!$F$207 -> 971 | E44: ='SIMULARE PE PRODUS'!$G$207 -> 865 | F44: =$D44+$E44 -> 1836 | G44: ='SIMULARE PE PRODUS'!T$207 -> 27291.892 | H44: =IFERROR($G44/'SIMULARE PE PRODUS'!T$4,"") -> 0.0057484648 | I44: ='SIMULARE PE PRODUS'!$L$207 -> 10688.932 | J44: =IFERROR($I44/$G44,"") -> 0.39165228 | K44: =$G44-$I44 -> 16602.96
A45: 41 | B45: 9 NUGGETS | C45: FRIED CHICKEN | D45: ='SIMULARE PE PRODUS'!$F$54 -> 549 | E45: ='SIMULARE PE PRODUS'!$G$54 -> 639 | F45: =$D45+$E45 -> 1188 | G45: ='SIMULARE PE PRODUS'!T$54 -> 26383.784 | H45: =IFERROR($G45/'SIMULARE PE PRODUS'!T$4,"") -> 0.0055571908 | I45: ='SIMULARE PE PRODUS'!$L$54 -> 8088.8118 | J45: =IFERROR($I45/$G45,"") -> 0.30658271 | K45: =$G45-$I45 -> 18294.972
A46: 42 | B46: CHICKEN PESTO | C46: BURGERI NON-CORE PUI | D46: ='SIMULARE PE PRODUS'!$F$35 -> 1219 | E46: ='SIMULARE PE PRODUS'!$G$35 -> 518 | F46: =$D46+$E46 -> 1737 | G46: ='SIMULARE PE PRODUS'!T$35 -> 25955.523 | H46: =IFERROR($G46/'SIMULARE PE PRODUS'!T$4,"") -> 0.0054669866 | I46: ='SIMULARE PE PRODUS'!$L$35 -> 8877.7275 | J46: =IFERROR($I46/$G46,"") -> 0.34203617 | K46: =$G46-$I46 -> 17077.795
A47: 43 | B47: DIP N TRUFFLE 100G | C47: SOSURI | D47: ='SIMULARE PE PRODUS'!$F$81 -> 1080 | E47: ='SIMULARE PE PRODUS'!$G$81 -> 929 | F47: =$D47+$E47 -> 2009 | G47: ='SIMULARE PE PRODUS'!T$81 -> 25483.532 | H47: =IFERROR($G47/'SIMULARE PE PRODUS'!T$4,"") -> 0.0053675716 | I47: ='SIMULARE PE PRODUS'!$L$81 -> 7827.1243 | J47: =IFERROR($I47/$G47,"") -> 0.30714441 | K47: =$G47-$I47 -> 17656.407
A48: 44 | B48: 6 NUGGETS | C48: FRIED CHICKEN | D48: ='SIMULARE PE PRODUS'!$F$55 -> 909 | E48: ='SIMULARE PE PRODUS'!$G$55 -> 662 | F48: =$D48+$E48 -> 1571 | G48: ='SIMULARE PE PRODUS'!T$55 -> 25141.892 | H48: =IFERROR($G48/'SIMULARE PE PRODUS'!T$4,"") -> 0.0052956124 | I48: ='SIMULARE PE PRODUS'!$L$55 -> 7197.5513 | J48: =IFERROR($I48/$G48,"") -> 0.28627724 | K48: =$G48-$I48 -> 17944.341
A49: 45 | B49: HOMESTYLE CHICKEN FRYRANCH LETTUCE WRAP | C49: BURGERI NON-CORE PUI | D49: ='SIMULARE PE PRODUS'!$F$36 -> 490 | E49: ='SIMULARE PE PRODUS'!$G$36 -> 462 | F49: =$D49+$E49 -> 952 | G49: ='SIMULARE PE PRODUS'!T$36 -> 23980.613 | H49: =IFERROR($G49/'SIMULARE PE PRODUS'!T$4,"") -> 0.0050510132 | I49: ='SIMULARE PE PRODUS'!$L$36 -> 9766.1 | J49: =IFERROR($I49/$G49,"") -> 0.40724981 | K49: =$G49-$I49 -> 14214.513
A50: 46 | B50: APPLE PIE TOFFIE 2X | C50: MILKSHAKE & DESERT | D50: ='SIMULARE PE PRODUS'!$F$164 -> 1104 | E50: ='SIMULARE PE PRODUS'!$G$164 -> 643 | F50: =$D50+$E50 -> 1747 | G50: ='SIMULARE PE PRODUS'!T$164 -> 23608.108 | H50: =IFERROR($G50/'SIMULARE PE PRODUS'!T$4,"") -> 0.004972553 | I50: ='SIMULARE PE PRODUS'!$L$164 -> 10397.63 | J50: =IFERROR($I50/$G50,"") -> 0.44042624 | K50: =$G50-$I50 -> 13210.478
A51: 47 | B51: Apa Plata AQUA CARPATICA | C51: DRINKS | D51: ='SIMULARE PE PRODUS'!$F$97 -> 2416 | E51: ='SIMULARE PE PRODUS'!$G$97 -> 109 | F51: =$D51+$E51 -> 2525 | G51: ='SIMULARE PE PRODUS'!T$97 -> 23023.76 | H51: =IFERROR($G51/'SIMULARE PE PRODUS'!T$4,"") -> 0.0048494724 | I51: ='SIMULARE PE PRODUS'!$L$97 -> 7049.8 | J51: =IFERROR($I51/$G51,"") -> 0.30619672 | K51: =$G51-$I51 -> 15973.96
A52: 48 | B52: 9 HOT COUNTRY WINGS | C52: FRIED CHICKEN | D52: ='SIMULARE PE PRODUS'!$F$56 -> 345 | E52: ='SIMULARE PE PRODUS'!$G$56 -> 356 | F52: =$D52+$E52 -> 701 | G52: ='SIMULARE PE PRODUS'!T$56 -> 21652.252 | H52: =IFERROR($G52/'SIMULARE PE PRODUS'!T$4,"") -> 0.0045605929 | I52: ='SIMULARE PE PRODUS'!$L$56 -> 10295.001 | J52: =IFERROR($I52/$G52,"") -> 0.47547022 | K52: =$G52-$I52 -> 11357.251
A53: 49 | B53: M Festival Combo Db Chee* | C53: COMBO | D53: ='SIMULARE PE PRODUS'!$F$223 -> 737 | E53: ='SIMULARE PE PRODUS'!$G$223 -> 0 | F53: =$D53+$E53 -> 737 | G53: ='SIMULARE PE PRODUS'!T$223 -> 19912.279 | H53: =IFERROR($G53/'SIMULARE PE PRODUS'!T$4,"") -> 0.0041941041 | I53: ='SIMULARE PE PRODUS'!$L$223 -> 11542.82 | J53: =IFERROR($I53/$G53,"") -> 0.57968353 | K53: =$G53-$I53 -> 8369.459
A54: 50 | B54: Nutella Burger Capsuni | C54: MILKSHAKE & DESERT | D54: ='SIMULARE PE PRODUS'!$F$165 -> 1282 | E54: ='SIMULARE PE PRODUS'!$G$165 -> 478 | F54: =$D54+$E54 -> 1760 | G54: ='SIMULARE PE PRODUS'!T$165 -> 19888.288 | H54: =IFERROR($G54/'SIMULARE PE PRODUS'!T$4,"") -> 0.0041890509 | I54: ='SIMULARE PE PRODUS'!$L$165 -> 8220.2706 | J54: =IFERROR($I54/$G54,"") -> 0.41332218 | K54: =$G54-$I54 -> 11668.018
A55: 51 | B55: HOMESTYLE CHICKEN LEMON | C55: BURGERI NON-CORE PUI | D55: ='SIMULARE PE PRODUS'!$F$37 -> 609 | E55: ='SIMULARE PE PRODUS'!$G$37 -> 193 | F55: =$D55+$E55 -> 802 | G55: ='SIMULARE PE PRODUS'!T$37 -> 19848.631 | H55: =IFERROR($G55/'SIMULARE PE PRODUS'!T$4,"") -> 0.0041806979 | I55: ='SIMULARE PE PRODUS'!$L$37 -> 8306.4506 | J55: =IFERROR($I55/$G55,"") -> 0.41848986 | K55: =$G55-$I55 -> 11542.18
A56: 52 | B56: 5 HOT COUNTRY WINGS | C56: FRIED CHICKEN | D56: ='SIMULARE PE PRODUS'!$F$57 -> 711 | E56: ='SIMULARE PE PRODUS'!$G$57 -> 239 | F56: =$D56+$E56 -> 950 | G56: ='SIMULARE PE PRODUS'!T$57 -> 19800.45 | H56: =IFERROR($G56/'SIMULARE PE PRODUS'!T$4,"") -> 0.0041705497 | I56: ='SIMULARE PE PRODUS'!$L$57 -> 7978.1866 | J56: =IFERROR($I56/$G56,"") -> 0.40292955 | K56: =$G56-$I56 -> 11822.264
A57: 53 | B57: Junior Meal Pui Burger | C57: JUNIOR | D57: ='SIMULARE PE PRODUS'!$F$218 -> 448 | E57: ='SIMULARE PE PRODUS'!$G$218 -> 114 | F57: =$D57+$E57 -> 562 | G57: ='SIMULARE PE PRODUS'!T$218 -> 19745.946 | H57: =IFERROR($G57/'SIMULARE PE PRODUS'!T$4,"") -> 0.0041590695 | I57: ='SIMULARE PE PRODUS'!$L$218 -> 12250.02 | J57: =IFERROR($I57/$G57,"") -> 0.62038151 | K57: =$G57-$I57 -> 7495.9261
A58: 54 | B58: Junior Meal 4 Nuggets | C58: JUNIOR | D58: ='SIMULARE PE PRODUS'!$F$219 -> 455 | E58: ='SIMULARE PE PRODUS'!$G$219 -> 106 | F58: =$D58+$E58 -> 561 | G58: ='SIMULARE PE PRODUS'!T$219 -> 19710.811 | H58: =IFERROR($G58/'SIMULARE PE PRODUS'!T$4,"") -> 0.004151669 | I58: ='SIMULARE PE PRODUS'!$L$219 -> 11554.569 | J58: =IFERROR($I58/$G58,"") -> 0.58620467 | K58: =$G58-$I58 -> 8156.2414
A59: 55 | B59: BURGER VEGETARIAN | C59: VEGETARIAN | D59: ='SIMULARE PE PRODUS'!$F$47 -> 739 | E59: ='SIMULARE PE PRODUS'!$G$47 -> 253 | F59: =$D59+$E59 -> 992 | G59: ='SIMULARE PE PRODUS'!T$47 -> 19442.414 | H59: =IFERROR($G59/'SIMULARE PE PRODUS'!T$4,"") -> 0.0040951369 | I59: ='SIMULARE PE PRODUS'!$L$47 -> 7133.8174 | J59: =IFERROR($I59/$G59,"") -> 0.36692035 | K59: =$G59-$I59 -> 12308.597
A60: 56 | B60: Sos Truffle Mayo | C60: SOSURI | D60: ='SIMULARE PE PRODUS'!$F$82 -> 2385 | E60: ='SIMULARE PE PRODUS'!$G$82 -> 1081 | F60: =$D60+$E60 -> 3466 | G60: ='SIMULARE PE PRODUS'!T$82 -> 19047.387 | H60: =IFERROR($G60/'SIMULARE PE PRODUS'!T$4,"") -> 0.0040119328 | I60: ='SIMULARE PE PRODUS'!$L$82 -> 7874.752 | J60: =IFERROR($I60/$G60,"") -> 0.41342951 | K60: =$G60-$I60 -> 11172.635
A61: 57 | B61: SHRIMP BURGER | C61: CREVEȚI | D61: ='SIMULARE PE PRODUS'!$F$44 -> 470 | E61: ='SIMULARE PE PRODUS'!$G$44 -> 268 | F61: =$D61+$E61 -> 738 | G61: ='SIMULARE PE PRODUS'!T$44 -> 18004.162 | H61: =IFERROR($G61/'SIMULARE PE PRODUS'!T$4,"") -> 0.0037921992 | I61: ='SIMULARE PE PRODUS'!$L$44 -> 7952.2225 | J61: =IFERROR($I61/$G61,"") -> 0.44168801 | K61: =$G61-$I61 -> 10051.94
A62: 58 | B62: 9 COUNTRY WINGS | C62: FRIED CHICKEN | D62: ='SIMULARE PE PRODUS'!$F$58 -> 320 | E62: ='SIMULARE PE PRODUS'!$G$58 -> 255 | F62: =$D62+$E62 -> 575 | G62: ='SIMULARE PE PRODUS'!T$58 -> 17610.36 | H62: =IFERROR($G62/'SIMULARE PE PRODUS'!T$4,"") -> 0.0037092532 | I62: ='SIMULARE PE PRODUS'!$L$58 -> 7832.2844 | J62: =IFERROR($I62/$G62,"") -> 0.44475435 | K62: =$G62-$I62 -> 9778.076
A63: 59 | B63: DUBLU HAMBURGER | C63: BURGERI CORE VITĂ | D63: ='SIMULARE PE PRODUS'!$F$13 -> 695 | E63: ='SIMULARE PE PRODUS'!$G$13 -> 428 | F63: =$D63+$E63 -> 1123 | G63: ='SIMULARE PE PRODUS'!T$13 -> 15936.73 | H63: =IFERROR($G63/'SIMULARE PE PRODUS'!T$4,"") -> 0.003356738 | I63: ='SIMULARE PE PRODUS'!$L$13 -> 11265.618 | J63: =IFERROR($I63/$G63,"") -> 0.70689649 | K63: =$G63-$I63 -> 4671.1114
A64: 60 | B64: 4 NUGGETS | C64: FRIED CHICKEN | D64: ='SIMULARE PE PRODUS'!$F$59 -> 1059 | E64: ='SIMULARE PE PRODUS'!$G$59 -> 573 | F64: =$D64+$E64 -> 1632 | G64: ='SIMULARE PE PRODUS'!T$59 -> 15516.216 | H64: =IFERROR($G64/'SIMULARE PE PRODUS'!T$4,"") -> 0.0032681656 | I64: ='SIMULARE PE PRODUS'!$L$59 -> 5053.7703 | J64: =IFERROR($I64/$G64,"") -> 0.32570894 | K64: =$G64-$I64 -> 10462.446
A65: 61 | B65: 5 COUNTRY WINGS | C65: FRIED CHICKEN | D65: ='SIMULARE PE PRODUS'!$F$60 -> 597 | E65: ='SIMULARE PE PRODUS'!$G$60 -> 143 | F65: =$D65+$E65 -> 740 | G65: ='SIMULARE PE PRODUS'!T$60 -> 15170.721 | H65: =IFERROR($G65/'SIMULARE PE PRODUS'!T$4,"") -> 0.0031953942 | I65: ='SIMULARE PE PRODUS'!$L$60 -> 5761.7075 | J65: =IFERROR($I65/$G65,"") -> 0.37979128 | K65: =$G65-$I65 -> 9409.0132
A66: 62 | B66: 7 HOT COUNTRY WINGS | C66: FRIED CHICKEN | D66: ='SIMULARE PE PRODUS'!$F$61 -> 331 | E66: ='SIMULARE PE PRODUS'!$G$61 -> 251 | F66: =$D66+$E66 -> 582 | G66: ='SIMULARE PE PRODUS'!T$61 -> 15061.261 | H66: =IFERROR($G66/'SIMULARE PE PRODUS'!T$4,"") -> 0.0031723389 | I66: ='SIMULARE PE PRODUS'!$L$61 -> 6717.5183 | J66: =IFERROR($I66/$G66,"") -> 0.446013 | K66: =$G66-$I66 -> 8343.743
A67: 63 | B67: Nutella Burger Banane | C67: MILKSHAKE & DESERT | D67: ='SIMULARE PE PRODUS'!$F$166 -> 982 | E67: ='SIMULARE PE PRODUS'!$G$166 -> 351 | F67: =$D67+$E67 -> 1333 | G67: ='SIMULARE PE PRODUS'!T$166 -> 15043.243 | H67: =IFERROR($G67/'SIMULARE PE PRODUS'!T$4,"") -> 0.0031685438 | I67: ='SIMULARE PE PRODUS'!$L$166 -> 5450.0891 | J67: =IFERROR($I67/$G67,"") -> 0.36229482 | K67: =$G67-$I67 -> 9593.1541
A68: 64 | B68: HOMESTYLE CHICKEN PESTO | C68: BURGERI NON-CORE PUI | D68: ='SIMULARE PE PRODUS'!$F$38 -> 465 | E68: ='SIMULARE PE PRODUS'!$G$38 -> 134 | F68: =$D68+$E68 -> 599 | G68: ='SIMULARE PE PRODUS'!T$38 -> 14806.315 | H68: =IFERROR($G68/'SIMULARE PE PRODUS'!T$4,"") -> 0.0031186399 | I68: ='SIMULARE PE PRODUS'!$L$38 -> 6316.4354 | J68: =IFERROR($I68/$G68,"") -> 0.42660414 | K68: =$G68-$I68 -> 8489.8799
A69: 65 | B69: Punga | C69: AMBALAJE VÂNDUTE | D69: ='SIMULARE PE PRODUS'!$F$235 -> 10831 | E69: ='SIMULARE PE PRODUS'!$G$235 -> 0 | F69: =$D69+$E69 -> 10831 | G69: ='SIMULARE PE PRODUS'!T$235 -> 14636.486 | H69: =IFERROR($G69/'SIMULARE PE PRODUS'!T$4,"") -> 0.003082869 | I69: ='SIMULARE PE PRODUS'!$L$235 -> 10170.309 | J69: =IFERROR($I69/$G69,"") -> 0.69486 | K69: =$G69-$I69 -> 4466.1775
A70: 66 | B70: LIPTON 350ML NEW2026 | C70: DRINKS | D70: ='SIMULARE PE PRODUS'!$F$98 -> 2083 | E70: ='SIMULARE PE PRODUS'!$G$98 -> 0 | F70: =$D70+$E70 -> 2083 | G70: ='SIMULARE PE PRODUS'!T$98 -> 13754.686 | H70: =IFERROR($G70/'SIMULARE PE PRODUS'!T$4,"") -> 0.0028971362 | I70: ='SIMULARE PE PRODUS'!$L$98 -> 7091.27 | J70: =IFERROR($I70/$G70,"") -> 0.51555303 | K70: =$G70-$I70 -> 6663.416
A71: 67 | B71: Bautura 7 UP zero 350ml new2026 | C71: DRINKS | D71: ='SIMULARE PE PRODUS'!$F$99 -> 2047 | E71: ='SIMULARE PE PRODUS'!$G$99 -> 0 | F71: =$D71+$E71 -> 2047 | G71: ='SIMULARE PE PRODUS'!T$99 -> 13516.967 | H71: =IFERROR($G71/'SIMULARE PE PRODUS'!T$4,"") -> 0.0028470657 | I71: ='SIMULARE PE PRODUS'!$L$99 -> 7187.9108 | J71: =IFERROR($I71/$G71,"") -> 0.5317695 | K71: =$G71-$I71 -> 6329.0562
A72: 68 | B72: HOMESTYLE CHICKEN LEMON LETTUCE WRAP | C72: BURGERI NON-CORE PUI | D72: ='SIMULARE PE PRODUS'!$F$39 -> 352 | E72: ='SIMULARE PE PRODUS'!$G$39 -> 167 | F72: =$D72+$E72 -> 519 | G72: ='SIMULARE PE PRODUS'!T$39 -> 12920.55 | H72: =IFERROR($G72/'SIMULARE PE PRODUS'!T$4,"") -> 0.0027214428 | I72: ='SIMULARE PE PRODUS'!$L$39 -> 5433.7616 | J72: =IFERROR($I72/$G72,"") -> 0.42055189 | K72: =$G72-$I72 -> 7486.788
A73: 69 | B73: Lipton 500 ml | C73: DRINKS | D73: ='SIMULARE PE PRODUS'!$F$100 -> 1402 | E73: ='SIMULARE PE PRODUS'!$G$100 -> 0 | F73: =$D73+$E73 -> 1402 | G73: ='SIMULARE PE PRODUS'!T$100 -> 12733.868 | H73: =IFERROR($G73/'SIMULARE PE PRODUS'!T$4,"") -> 0.0026821222 | I73: ='SIMULARE PE PRODUS'!$L$100 -> 6547.588 | J73: =IFERROR($I73/$G73,"") -> 0.5141869 | K73: =$G73-$I73 -> 6186.2798
A74: 70 | B74: 7 COUNTRY WINGS | C74: FRIED CHICKEN | D74: ='SIMULARE PE PRODUS'!$F$62 -> 364 | E74: ='SIMULARE PE PRODUS'!$G$62 -> 130 | F74: =$D74+$E74 -> 494 | G74: ='SIMULARE PE PRODUS'!T$62 -> 12484.685 | H74: =IFERROR($G74/'SIMULARE PE PRODUS'!T$4,"") -> 0.002629637 | I74: ='SIMULARE PE PRODUS'!$L$62 -> 5287.6415 | J74: =IFERROR($I74/$G74,"") -> 0.42353024 | K74: =$G74-$I74 -> 7197.0432
A75: 71 | B75: Bautura 7 UP zero 500 ml | C75: DRINKS | D75: ='SIMULARE PE PRODUS'!$F$101 -> 1296 | E75: ='SIMULARE PE PRODUS'!$G$101 -> 0 | F75: =$D75+$E75 -> 1296 | G75: ='SIMULARE PE PRODUS'!T$101 -> 11771.107 | H75: =IFERROR($G75/'SIMULARE PE PRODUS'!T$4,"") -> 0.002479337 | I75: ='SIMULARE PE PRODUS'!$L$101 -> 6208.9514 | J75: =IFERROR($I75/$G75,"") -> 0.52747385 | K75: =$G75-$I75 -> 5562.156
A76: 72 | B76: Sos Mayoneza 10ml | C76: SOSURI | D76: ='SIMULARE PE PRODUS'!$F$83 -> 3109 | E76: ='SIMULARE PE PRODUS'!$G$83 -> 606 | F76: =$D76+$E76 -> 3715 | G76: ='SIMULARE PE PRODUS'!T$83 -> 10648.198 | H76: =IFERROR($G76/'SIMULARE PE PRODUS'!T$4,"") -> 0.0022428197 | I76: ='SIMULARE PE PRODUS'!$L$83 -> 1671.75 | J76: =IFERROR($I76/$G76,"") -> 0.15699839 | K76: =$G76-$I76 -> 8976.4482
A77: 73 | B77: Junior Meal Hamburger | C77: JUNIOR | D77: ='SIMULARE PE PRODUS'!$F$220 -> 247 | E77: ='SIMULARE PE PRODUS'!$G$220 -> 41 | F77: =$D77+$E77 -> 288 | G77: ='SIMULARE PE PRODUS'!T$220 -> 10118.919 | H77: =IFERROR($G77/'SIMULARE PE PRODUS'!T$4,"") -> 0.0021313381 | I77: ='SIMULARE PE PRODUS'!$L$220 -> 6852.006 | J77: =IFERROR($I77/$G77,"") -> 0.67714803 | K77: =$G77-$I77 -> 3266.9129
A78: 74 | B78: Nutella Burger | C78: MILKSHAKE & DESERT | D78: ='SIMULARE PE PRODUS'!$F$167 -> 748 | E78: ='SIMULARE PE PRODUS'!$G$167 -> 284 | F78: =$D78+$E78 -> 1032 | G78: ='SIMULARE PE PRODUS'!T$167 -> 9809.009 | H78: =IFERROR($G78/'SIMULARE PE PRODUS'!T$4,"") -> 0.0020660621 | I78: ='SIMULARE PE PRODUS'!$L$167 -> 3868.5438 | J78: =IFERROR($I78/$G78,"") -> 0.39438682 | K78: =$G78-$I78 -> 5940.4652
A79: 75 | B79: Mirinda Zero Zahar 350ML new2026 | C79: DRINKS | D79: ='SIMULARE PE PRODUS'!$F$102 -> 1456 | E79: ='SIMULARE PE PRODUS'!$G$102 -> 0 | F79: =$D79+$E79 -> 1456 | G79: ='SIMULARE PE PRODUS'!T$102 -> 9614.4132 | H79: =IFERROR($G79/'SIMULARE PE PRODUS'!T$4,"") -> 0.0020250746 | I79: ='SIMULARE PE PRODUS'!$L$102 -> 5112.5498 | J79: =IFERROR($I79/$G79,"") -> 0.5317589 | K79: =$G79-$I79 -> 4501.8634
A80: 76 | B80: Sos Ketchup 10ml | C80: SOSURI | D80: ='SIMULARE PE PRODUS'!$F$84 -> 2993 | E80: ='SIMULARE PE PRODUS'!$G$84 -> 373 | F80: =$D80+$E80 -> 3366 | G80: ='SIMULARE PE PRODUS'!T$84 -> 9568.5586 | H80: =IFERROR($G80/'SIMULARE PE PRODUS'!T$4,"") -> 0.0020154162 | I80: ='SIMULARE PE PRODUS'!$L$84 -> 1521.432 | J80: =IFERROR($I80/$G80,"") -> 0.15900326 | K80: =$G80-$I80 -> 8047.1266
A81: 77 | B81: LIMONADA | C81: FRYCAFE | D81: ='SIMULARE PE PRODUS'!$F$128 -> 1005 | E81: ='SIMULARE PE PRODUS'!$G$128 -> 0 | F81: =$D81+$E81 -> 1005 | G81: ='SIMULARE PE PRODUS'!T$128 -> 9128.0579 | H81: =IFERROR($G81/'SIMULARE PE PRODUS'!T$4,"") -> 0.001922634 | I81: ='SIMULARE PE PRODUS'!$L$128 -> 1589.9096 | J81: =IFERROR($I81/$G81,"") -> 0.1741783 | K81: =$G81-$I81 -> 7538.1482
A82: 78 | B82: APPLE PIE TOFFIE | C82: MILKSHAKE & DESERT | D82: ='SIMULARE PE PRODUS'!$F$168 -> 713 | E82: ='SIMULARE PE PRODUS'!$G$168 -> 296 | F82: =$D82+$E82 -> 1009 | G82: ='SIMULARE PE PRODUS'!T$168 -> 9090.0901 | H82: =IFERROR($G82/'SIMULARE PE PRODUS'!T$4,"") -> 0.0019146369 | I82: ='SIMULARE PE PRODUS'!$L$168 -> 3002.6357 | J82: =IFERROR($I82/$G82,"") -> 0.33031968 | K82: =$G82-$I82 -> 6087.4544
A83: 79 | B83: SALATA COLESLAW | C83: SNACK | D83: ='SIMULARE PE PRODUS'!$F$208 -> 355 | E83: ='SIMULARE PE PRODUS'!$G$208 -> 562 | F83: =$D83+$E83 -> 917 | G83: ='SIMULARE PE PRODUS'!T$208 -> 8467.7928 | H83: =IFERROR($G83/'SIMULARE PE PRODUS'!T$4,"") -> 0.001783563 | I83: ='SIMULARE PE PRODUS'!$L$208 -> 3197.1205 | J83: =IFERROR($I83/$G83,"") -> 0.37756244 | K83: =$G83-$I83 -> 5270.6723
A84: 80 | B84: Sos Samurai | C84: SOSURI | D84: ='SIMULARE PE PRODUS'!$F$85 -> 987 | E84: ='SIMULARE PE PRODUS'!$G$85 -> 455 | F84: =$D84+$E84 -> 1442 | G84: ='SIMULARE PE PRODUS'!T$85 -> 7924.5045 | H84: =IFERROR($G84/'SIMULARE PE PRODUS'!T$4,"") -> 0.0016691307 | I84: ='SIMULARE PE PRODUS'!$L$85 -> 3068.576 | J84: =IFERROR($I84/$G84,"") -> 0.38722623 | K84: =$G84-$I84 -> 4855.9285
A85: 81 | B85: 3 HOT COUNTRY WINGS | C85: FRIED CHICKEN | D85: ='SIMULARE PE PRODUS'!$F$63 -> 364 | E85: ='SIMULARE PE PRODUS'!$G$63 -> 179 | F85: =$D85+$E85 -> 543 | G85: ='SIMULARE PE PRODUS'!T$63 -> 7740.991 | H85: =IFERROR($G85/'SIMULARE PE PRODUS'!T$4,"") -> 0.0016304774 | I85: ='SIMULARE PE PRODUS'!$L$63 -> 2852.9517 | J85: =IFERROR($I85/$G85,"") -> 0.36855123 | K85: =$G85-$I85 -> 4888.0393
A86: 82 | B86: PACK COUNTRY WINGS 30 (1050G) | C86: FRIED CHICKEN | D86: ='SIMULARE PE PRODUS'!$F$64 -> 58 | E86: ='SIMULARE PE PRODUS'!$G$64 -> 21 | F86: =$D86+$E86 -> 79 | G86: ='SIMULARE PE PRODUS'!T$64 -> 7583.7477 | H86: =IFERROR($G86/'SIMULARE PE PRODUS'!T$4,"") -> 0.0015973574 | I86: ='SIMULARE PE PRODUS'!$L$64 -> 3635.7812 | J86: =IFERROR($I86/$G86,"") -> 0.47941748 | K86: =$G86-$I86 -> 3947.9665
A87: 83 | B87: FRYZZZ PEPENE ROSU | C87: DRINKS | D87: ='SIMULARE PE PRODUS'!$F$103 -> 625 | E87: ='SIMULARE PE PRODUS'!$G$103 -> 0 | F87: =$D87+$E87 -> 625 | G87: ='SIMULARE PE PRODUS'!T$103 -> 7226.2397 | H87: =IFERROR($G87/'SIMULARE PE PRODUS'!T$4,"") -> 0.0015220559 | I87: ='SIMULARE PE PRODUS'!$L$103 -> 2105.4683 | J87: =IFERROR($I87/$G87,"") -> 0.29136431 | K87: =$G87-$I87 -> 5120.7714
A88: 84 | B88: Mirinda Zero Zahar 500ml | C88: DRINKS | D88: ='SIMULARE PE PRODUS'!$F$104 -> 793 | E88: ='SIMULARE PE PRODUS'!$G$104 -> 0 | F88: =$D88+$E88 -> 793 | G88: ='SIMULARE PE PRODUS'!T$104 -> 7202.5372 | H88: =IFERROR($G88/'SIMULARE PE PRODUS'!T$4,"") -> 0.0015170634 | I88: ='SIMULARE PE PRODUS'!$L$104 -> 3799.0714 | J88: =IFERROR($I88/$G88,"") -> 0.52746294 | K88: =$G88-$I88 -> 3403.4658
A89: 85 | B89: Milkshake Vanilie MARE | C89: MILKSHAKE & DESERT | D89: ='SIMULARE PE PRODUS'!$F$169 -> 435 | E89: ='SIMULARE PE PRODUS'!$G$169 -> 0 | F89: =$D89+$E89 -> 435 | G89: ='SIMULARE PE PRODUS'!T$169 -> 7054.0541 | H89: =IFERROR($G89/'SIMULARE PE PRODUS'!T$4,"") -> 0.0014857886 | I89: ='SIMULARE PE PRODUS'!$L$169 -> 2240.685 | J89: =IFERROR($I89/$G89,"") -> 0.317645 | K89: =$G89-$I89 -> 4813.3691
A90: 86 | B90: FRYZZZ ORANGE SPRITZ | C90: DRINKS | D90: ='SIMULARE PE PRODUS'!$F$105 -> 569 | E90: ='SIMULARE PE PRODUS'!$G$105 -> 0 | F90: =$D90+$E90 -> 569 | G90: ='SIMULARE PE PRODUS'!T$105 -> 7053.719 | H90: =IFERROR($G90/'SIMULARE PE PRODUS'!T$4,"") -> 0.001485718 | I90: ='SIMULARE PE PRODUS'!$L$105 -> 1915.5718 | J90: =IFERROR($I90/$G90,"") -> 0.27156905 | K90: =$G90-$I90 -> 5138.1472
A91: 87 | B91: ALMETTE FRESH PUI | C91: BREAKFAST | D91: ='SIMULARE PE PRODUS'!$F$211 -> 182 | E91: ='SIMULARE PE PRODUS'!$G$211 -> 233 | F91: =$D91+$E91 -> 415 | G91: ='SIMULARE PE PRODUS'!T$211 -> 6985.5856 | H91: =IFERROR($G91/'SIMULARE PE PRODUS'!T$4,"") -> 0.0014713671 | I91: ='SIMULARE PE PRODUS'!$L$211 -> 2703.0645 | J91: =IFERROR($I91/$G91,"") -> 0.38694888 | K91: =$G91-$I91 -> 4282.5211
A92: 88 | B92: Iced Latte Tiramisu | C92: FRYCAFE | D92: ='SIMULARE PE PRODUS'!$F$129 -> 461 | E92: ='SIMULARE PE PRODUS'!$G$129 -> 0 | F92: =$D92+$E92 -> 461 | G92: ='SIMULARE PE PRODUS'!T$129 -> 6476.8595 | H92: =IFERROR($G92/'SIMULARE PE PRODUS'!T$4,"") -> 0.0013642146 | I92: ='SIMULARE PE PRODUS'!$L$129 -> 2917.5765 | J92: =IFERROR($I92/$G92,"") -> 0.4504616 | K92: =$G92-$I92 -> 3559.283
A93: 89 | B93: Milkshake Ciocolata MIC | C93: MILKSHAKE & DESERT | D93: ='SIMULARE PE PRODUS'!$F$170 -> 239 | E93: ='SIMULARE PE PRODUS'!$G$170 -> 224 | F93: =$D93+$E93 -> 463 | G93: ='SIMULARE PE PRODUS'!T$170 -> 6243.2432 | H93: =IFERROR($G93/'SIMULARE PE PRODUS'!T$4,"") -> 0.0013150083 | I93: ='SIMULARE PE PRODUS'!$L$170 -> 2352.3185 | J93: =IFERROR($I93/$G93,"") -> 0.37677829 | K93: =$G93-$I93 -> 3890.9247
A94: 90 | B94: 3 COUNTRY WINGS | C94: FRIED CHICKEN | D94: ='SIMULARE PE PRODUS'!$F$65 -> 321 | E94: ='SIMULARE PE PRODUS'!$G$65 -> 109 | F94: =$D94+$E94 -> 430 | G94: ='SIMULARE PE PRODUS'!T$65 -> 6056.3063 | H94: =IFERROR($G94/'SIMULARE PE PRODUS'!T$4,"") -> 0.0012756339 | I94: ='SIMULARE PE PRODUS'!$L$65 -> 2093.4355 | J94: =IFERROR($I94/$G94,"") -> 0.3456621 | K94: =$G94-$I94 -> 3962.8708
A95: 91 | B95: ICED COFFEE LATTE | C95: FRYCAFE | D95: ='SIMULARE PE PRODUS'!$F$130 -> 516 | E95: ='SIMULARE PE PRODUS'!$G$130 -> 0 | F95: =$D95+$E95 -> 516 | G95: ='SIMULARE PE PRODUS'!T$130 -> 5965.9835 | H95: =IFERROR($G95/'SIMULARE PE PRODUS'!T$4,"") -> 0.0012566093 | I95: ='SIMULARE PE PRODUS'!$L$130 -> 2592.3806 | J95: =IFERROR($I95/$G95,"") -> 0.43452696 | K95: =$G95-$I95 -> 3373.6028
A96: 92 | B96: DIP N FRYRANCH 400G | C96: SOSURI | D96: ='SIMULARE PE PRODUS'!$F$86 -> 73 | E96: ='SIMULARE PE PRODUS'!$G$86 -> 111 | F96: =$D96+$E96 -> 184 | G96: ='SIMULARE PE PRODUS'!T$86 -> 5818.3784 | H96: =IFERROR($G96/'SIMULARE PE PRODUS'!T$4,"") -> 0.0012255194 | I96: ='SIMULARE PE PRODUS'!$L$86 -> 2005.3277 | J96: =IFERROR($I96/$G96,"") -> 0.34465405 | K96: =$G96-$I96 -> 3813.0507
A97: 93 | B97: Milkshake Ciocolata MARE | C97: MILKSHAKE & DESERT | D97: ='SIMULARE PE PRODUS'!$F$171 -> 353 | E97: ='SIMULARE PE PRODUS'!$G$171 -> 0 | F97: =$D97+$E97 -> 353 | G97: ='SIMULARE PE PRODUS'!T$171 -> 5724.3243 | H97: =IFERROR($G97/'SIMULARE PE PRODUS'!T$4,"") -> 0.0012057089 | I97: ='SIMULARE PE PRODUS'!$L$171 -> 2141.6987 | J97: =IFERROR($I97/$G97,"") -> 0.37413999 | K97: =$G97-$I97 -> 3582.6257
A98: 94 | B98: Apa Minerala AQUA CARPATICA | C98: DRINKS | D98: ='SIMULARE PE PRODUS'!$F$106 -> 585 | E98: ='SIMULARE PE PRODUS'!$G$106 -> 34 | F98: =$D98+$E98 -> 619 | G98: ='SIMULARE PE PRODUS'!T$106 -> 5650.2562 | H98: =IFERROR($G98/'SIMULARE PE PRODUS'!T$4,"") -> 0.001190108 | I98: ='SIMULARE PE PRODUS'!$L$106 -> 1702.25 | J98: =IFERROR($I98/$G98,"") -> 0.30126952 | K98: =$G98-$I98 -> 3948.0062
A99: 95 | B99: Fry Shaker Parmezan & Usturoi | C99: ADD ON | D99: ='SIMULARE PE PRODUS'!$F$199 -> 805 | E99: ='SIMULARE PE PRODUS'!$G$199 -> 397 | F99: =$D99+$E99 -> 1202 | G99: ='SIMULARE PE PRODUS'!T$199 -> 5414.4144 | H99: =IFERROR($G99/'SIMULARE PE PRODUS'!T$4,"") -> 0.0011404329 | I99: ='SIMULARE PE PRODUS'!$L$199 -> 919.53 | J99: =IFERROR($I99/$G99,"") -> 0.16983 | K99: =$G99-$I99 -> 4494.8844
A100: 96 | B100: ADD Bacon | C100: ADD ON | D100: ='SIMULARE PE PRODUS'!$F$200 -> 713 | E100: ='SIMULARE PE PRODUS'!$G$200 -> 483 | F100: =$D100+$E100 -> 1196 | G100: ='SIMULARE PE PRODUS'!T$200 -> 5387.3874 | H100: =IFERROR($G100/'SIMULARE PE PRODUS'!T$4,"") -> 0.0011347402 | I100: ='SIMULARE PE PRODUS'!$L$200 -> 1700.3006 | J100: =IFERROR($I100/$G100,"") -> 0.31560764 | K100: =$G100-$I100 -> 3687.0868
A101: 97 | B101: Milkshake Vanilie MIC | C101: MILKSHAKE & DESERT | D101: ='SIMULARE PE PRODUS'!$F$172 -> 245 | E101: ='SIMULARE PE PRODUS'!$G$172 -> 190 | F101: =$D101+$E101 -> 435 | G101: ='SIMULARE PE PRODUS'!T$172 -> 5045.045 | H101: =IFERROR($G101/'SIMULARE PE PRODUS'!T$4,"") -> 0.001062633 | I101: ='SIMULARE PE PRODUS'!$L$172 -> 1768.57 | J101: =IFERROR($I101/$G101,"") -> 0.35055584 | K101: =$G101-$I101 -> 3276.475
...

Sheet TOP FC
A1: TOP FOOD COST — produsele după food cost, de la mare la mic
A2: Produsele din capul listei sunt cele mai puțin rentabile. Roșu = peste 55%, galben = 45–55%, verde = sub 45%.
A4: # | B4: Produs | C4: Categorie | D4: Buc InStore | E4: Buc Delivery | F4: Buc TOTAL | G4: Vânzări nete | H4: % din total | I4: Cost material | J4: FOOD COST | K4: Profit brut
A5: 1 | B5: Garantie SGR Pet | C5: GARANTII SGR | D5: ='SIMULARE PE PRODUS'!$F$240 -> 0 | E5: ='SIMULARE PE PRODUS'!$G$240 -> 3437 | F5: =$D5+$E5 -> 3437 | G5: ='SIMULARE PE PRODUS'!T$240 -> 1420.2479 | H5: =IFERROR($G5/'SIMULARE PE PRODUS'!T$4,"") -> 0.00029914545 | I5: ='SIMULARE PE PRODUS'!$L$240 -> 1718.5 | J5: =IFERROR($I5/$G5,"") -> 1.21 | K5: =$G5-$I5 -> -298.25207
A6: 2 | B6: Garantie SGR Aluminiu | C6: GARANTII SGR | D6: ='SIMULARE PE PRODUS'!$F$241 -> 0 | E6: ='SIMULARE PE PRODUS'!$G$241 -> 2327 | F6: =$D6+$E6 -> 2327 | G6: ='SIMULARE PE PRODUS'!T$241 -> 961.57025 | H6: =IFERROR($G6/'SIMULARE PE PRODUS'!T$4,"") -> 0.00020253461 | I6: ='SIMULARE PE PRODUS'!$L$241 -> 1163.5 | J6: =IFERROR($I6/$G6,"") -> 1.21 | K6: =$G6-$I6 -> -201.92975
A7: 3 | B7: Garantie SGR Sticla | C7: GARANTII SGR | D7: ='SIMULARE PE PRODUS'!$F$242 -> 0 | E7: ='SIMULARE PE PRODUS'!$G$242 -> 360 | F7: =$D7+$E7 -> 360 | G7: ='SIMULARE PE PRODUS'!T$242 -> 148.76033 | H7: =IFERROR($G7/'SIMULARE PE PRODUS'!T$4,"") -> 3.1333244e-05 | I7: ='SIMULARE PE PRODUS'!$L$242 -> 180 | J7: =IFERROR($I7/$G7,"") -> 1.21 | K7: =$G7-$I7 -> -31.239669
A8: 4 | B8: Prosop Umed FRYDAY | C8: AMBALAJE VÂNDUTE | D8: ='SIMULARE PE PRODUS'!$F$237 -> 83 | E8: ='SIMULARE PE PRODUS'!$G$237 -> 0 | F8: =$D8+$E8 -> 83 | G8: ='SIMULARE PE PRODUS'!T$237 -> 149.54955 | H8: =IFERROR($G8/'SIMULARE PE PRODUS'!T$4,"") -> 3.1499477e-05 | I8: ='SIMULARE PE PRODUS'!$L$237 -> 137.614 | J8: =IFERROR($I8/$G8,"") -> 0.92019 | K8: =$G8-$I8 -> 11.93555
A9: 5 | B9: HAMBURGER | C9: BURGERI CORE VITĂ | D9: ='SIMULARE PE PRODUS'!$F$12 -> 5302 | E9: ='SIMULARE PE PRODUS'!$G$12 -> 1141 | F9: =$D9+$E9 -> 6443 | G9: ='SIMULARE PE PRODUS'!T$12 -> 48491.892 | H9: =IFERROR($G9/'SIMULARE PE PRODUS'!T$4,"") -> 0.0102138 | I9: ='SIMULARE PE PRODUS'!$L$12 -> 41003.929 | J9: =IFERROR($I9/$G9,"") -> 0.8455832 | K9: =$G9-$I9 -> 7487.9627
A10: 6 | B10: Punga Mica | C10: AMBALAJE VÂNDUTE | D10: ='SIMULARE PE PRODUS'!$F$234 -> 3077 | E10: ='SIMULARE PE PRODUS'!$G$234 -> 67784 | F10: =$D10+$E10 -> 70861 | G10: ='SIMULARE PE PRODUS'!T$234 -> 47879.054 | H10: =IFERROR($G10/'SIMULARE PE PRODUS'!T$4,"") -> 0.010084719 | I10: ='SIMULARE PE PRODUS'!$L$234 -> 37485.469 | J10: =IFERROR($I10/$G10,"") -> 0.78292 | K10: =$G10-$I10 -> 10393.585
A11: 7 | B11: Baterie Magsafe Fry | C11: MERCH | D11: ='SIMULARE PE PRODUS'!$F$230 -> 1 | E11: ='SIMULARE PE PRODUS'!$G$230 -> 0 | F11: =$D11+$E11 -> 1 | G11: ='SIMULARE PE PRODUS'!T$230 -> 123.1405 | H11: =IFERROR($G11/'SIMULARE PE PRODUS'!T$4,"") -> 2.5936963e-05 | I11: ='SIMULARE PE PRODUS'!$L$230 -> 92.31 | J11: =IFERROR($I11/$G11,"") -> 0.74963154 | K11: =$G11-$I11 -> 30.830496
A12: 8 | B12: Jucarie | C12: MERCH | D12: ='SIMULARE PE PRODUS'!$F$229 -> 53 | E12: ='SIMULARE PE PRODUS'!$G$229 -> 0 | F12: =$D12+$E12 -> 53 | G12: ='SIMULARE PE PRODUS'!T$229 -> 876.03306 | H12: =IFERROR($G12/'SIMULARE PE PRODUS'!T$4,"") -> 0.00018451799 | I12: ='SIMULARE PE PRODUS'!$L$229 -> 655.451 | J12: =IFERROR($I12/$G12,"") -> 0.7482035 | K12: =$G12-$I12 -> 220.58206
A13: 9 | B13: AMERICAN DUBLU CHEESEBURGER | C13: BURGERI CORE VITĂ | D13: ='SIMULARE PE PRODUS'!$F$9 -> 6649 | E13: ='SIMULARE PE PRODUS'!$G$9 -> 1326 | F13: =$D13+$E13 -> 7975 | G13: ='SIMULARE PE PRODUS'!T$9 -> 118538.74 | H13: =IFERROR($G13/'SIMULARE PE PRODUS'!T$4,"") -> 0.0249677 | I13: ='SIMULARE PE PRODUS'!$L$9 -> 86664.325 | J13: =IFERROR($I13/$G13,"") -> 0.73110551 | K13: =$G13-$I13 -> 31874.414
A14: 10 | B14: AMERICAN TRIPLU CHEESEBURGER | C14: BURGERI CORE VITĂ | D14: ='SIMULARE PE PRODUS'!$F$8 -> 4896 | E14: ='SIMULARE PE PRODUS'!$G$8 -> 4666 | F14: =$D14+$E14 -> 9562 | G14: ='SIMULARE PE PRODUS'!T$8 -> 202127.93 | H14: =IFERROR($G14/'SIMULARE PE PRODUS'!T$4,"") -> 0.04257401 | I14: ='SIMULARE PE PRODUS'!$L$8 -> 144070.65 | J14: =IFERROR($I14/$G14,"") -> 0.71276966 | K14: =$G14-$I14 -> 58057.274
A15: 11 | B15: AMERICAN CHEESEBURGER | C15: BURGERI CORE VITĂ | D15: ='SIMULARE PE PRODUS'!$F$10 -> 9314 | E15: ='SIMULARE PE PRODUS'!$G$10 -> 1557 | F15: =$D15+$E15 -> 10871 | G15: ='SIMULARE PE PRODUS'!T$10 -> 102145.05 | H15: =IFERROR($G15/'SIMULARE PE PRODUS'!T$4,"") -> 0.021514712 | I15: ='SIMULARE PE PRODUS'!$L$10 -> 72476.957 | J15: =IFERROR($I15/$G15,"") -> 0.70954942 | K15: =$G15-$I15 -> 29668.088
A16: 12 | B16: DUBLU HAMBURGER | C16: BURGERI CORE VITĂ | D16: ='SIMULARE PE PRODUS'!$F$13 -> 695 | E16: ='SIMULARE PE PRODUS'!$G$13 -> 428 | F16: =$D16+$E16 -> 1123 | G16: ='SIMULARE PE PRODUS'!T$13 -> 15936.73 | H16: =IFERROR($G16/'SIMULARE PE PRODUS'!T$4,"") -> 0.003356738 | I16: ='SIMULARE PE PRODUS'!$L$13 -> 11265.618 | J16: =IFERROR($I16/$G16,"") -> 0.70689649 | K16: =$G16-$I16 -> 4671.1114
A17: 13 | B17: Punga | C17: AMBALAJE VÂNDUTE | D17: ='SIMULARE PE PRODUS'!$F$235 -> 10831 | E17: ='SIMULARE PE PRODUS'!$G$235 -> 0 | F17: =$D17+$E17 -> 10831 | G17: ='SIMULARE PE PRODUS'!T$235 -> 14636.486 | H17: =IFERROR($G17/'SIMULARE PE PRODUS'!T$4,"") -> 0.003082869 | I17: ='SIMULARE PE PRODUS'!$L$235 -> 10170.309 | J17: =IFERROR($I17/$G17,"") -> 0.69486 | K17: =$G17-$I17 -> 4466.1775
A18: 14 | B18: M Chicken FryRanch + Kendama | C18: COMBO | D18: ='SIMULARE PE PRODUS'!$F$225 -> 2 | E18: ='SIMULARE PE PRODUS'!$G$225 -> 0 | F18: =$D18+$E18 -> 2 | G18: ='SIMULARE PE PRODUS'!T$225 -> 302.7027 | H18: =IFERROR($G18/'SIMULARE PE PRODUS'!T$4,"") -> 6.3757977e-05 | I18: ='SIMULARE PE PRODUS'!$L$225 -> 206.8428 | J18: =IFERROR($I18/$G18,"") -> 0.68331996 | K18: =$G18-$I18 -> 95.859903
A19: 15 | B19: Junior Meal Hamburger | C19: JUNIOR | D19: ='SIMULARE PE PRODUS'!$F$220 -> 247 | E19: ='SIMULARE PE PRODUS'!$G$220 -> 41 | F19: =$D19+$E19 -> 288 | G19: ='SIMULARE PE PRODUS'!T$220 -> 10118.919 | H19: =IFERROR($G19/'SIMULARE PE PRODUS'!T$4,"") -> 0.0021313381 | I19: ='SIMULARE PE PRODUS'!$L$220 -> 6852.006 | J19: =IFERROR($I19/$G19,"") -> 0.67714803 | K19: =$G19-$I19 -> 3266.9129
A20: 16 | B20: DUBLU CHEESEBURGER | C20: BURGERI CORE VITĂ | D20: ='SIMULARE PE PRODUS'!$F$7 -> 5150 | E20: ='SIMULARE PE PRODUS'!$G$7 -> 6698 | F20: =$D20+$E20 -> 11848 | G20: ='SIMULARE PE PRODUS'!T$7 -> 204091.46 | H20: =IFERROR($G20/'SIMULARE PE PRODUS'!T$4,"") -> 0.042987587 | I20: ='SIMULARE PE PRODUS'!$L$7 -> 133784.26 | J20: =IFERROR($I20/$G20,"") -> 0.65551133 | K20: =$G20-$I20 -> 70307.195
A21: 17 | B21: CHEESEBURGER | C21: BURGERI CORE VITĂ | D21: ='SIMULARE PE PRODUS'!$F$11 -> 6953 | E21: ='SIMULARE PE PRODUS'!$G$11 -> 1987 | F21: =$D21+$E21 -> 8940 | G21: ='SIMULARE PE PRODUS'!T$11 -> 96121.261 | H21: =IFERROR($G21/'SIMULARE PE PRODUS'!T$4,"") -> 0.020245928 | I21: ='SIMULARE PE PRODUS'!$L$11 -> 62527.3 | J21: =IFERROR($I21/$G21,"") -> 0.65050436 | K21: =$G21-$I21 -> 33593.962
A22: 18 | B22: AMERICAN TRIPLU CHEESEBURGER LETTUCE WRAP | C22: BURGERI NON-CORE VITĂ | D22: ='SIMULARE PE PRODUS'!$F$25 -> 2652 | E22: ='SIMULARE PE PRODUS'!$G$25 -> 1759 | F22: =$D22+$E22 -> 4411 | G22: ='SIMULARE PE PRODUS'!T$25 -> 104061.16 | H22: =IFERROR($G22/'SIMULARE PE PRODUS'!T$4,"") -> 0.021918302 | I22: ='SIMULARE PE PRODUS'!$L$25 -> 66956.797 | J22: =IFERROR($I22/$G22,"") -> 0.64343696 | K22: =$G22-$I22 -> 37104.365
A23: 19 | B23: FRYZZ APEROL SPRITZ | C23: DRINKS | D23: ='SIMULARE PE PRODUS'!$F$109 -> 167 | E23: ='SIMULARE PE PRODUS'!$G$109 -> 0 | F23: =$D23+$E23 -> 167 | G23: ='SIMULARE PE PRODUS'!T$109 -> 4126.6942 | H23: =IFERROR($G23/'SIMULARE PE PRODUS'!T$4,"") -> 0.00086920161 | I23: ='SIMULARE PE PRODUS'!$L$109 -> 2653.296 | J23: =IFERROR($I23/$G23,"") -> 0.6429592 | K23: =$G23-$I23 -> 1473.3982
A24: 20 | B24: Lipton Lamaie 0.5L | C24: DRINKS | D24: ='SIMULARE PE PRODUS'!$F$120 -> 0 | E24: ='SIMULARE PE PRODUS'!$G$120 -> 123 | F24: =$D24+$E24 -> 123 | G24: ='SIMULARE PE PRODUS'!T$120 -> 1320.4711 | H24: =IFERROR($G24/'SIMULARE PE PRODUS'!T$4,"") -> 0.00027812954 | I24: ='SIMULARE PE PRODUS'!$L$120 -> 829.14423 | J24: =IFERROR($I24/$G24,"") -> 0.62791548 | K24: =$G24-$I24 -> 491.32684
A25: 21 | B25: PUI BURGER | C25: BURGERI CORE PUI | D25: ='SIMULARE PE PRODUS'!$F$16 -> 8484 | E25: ='SIMULARE PE PRODUS'!$G$16 -> 1972 | F25: =$D25+$E25 -> 10456 | G25: ='SIMULARE PE PRODUS'!T$16 -> 71268.468 | H25: =IFERROR($G25/'SIMULARE PE PRODUS'!T$4,"") -> 0.015011209 | I25: ='SIMULARE PE PRODUS'!$L$16 -> 44709.473 | J25: =IFERROR($I25/$G25,"") -> 0.62733877 | K25: =$G25-$I25 -> 26558.995
A26: 22 | B26: Junior Meal Pui Burger | C26: JUNIOR | D26: ='SIMULARE PE PRODUS'!$F$218 -> 448 | E26: ='SIMULARE PE PRODUS'!$G$218 -> 114 | F26: =$D26+$E26 -> 562 | G26: ='SIMULARE PE PRODUS'!T$218 -> 19745.946 | H26: =IFERROR($G26/'SIMULARE PE PRODUS'!T$4,"") -> 0.0041590695 | I26: ='SIMULARE PE PRODUS'!$L$218 -> 12250.02 | J26: =IFERROR($I26/$G26,"") -> 0.62038151 | K26: =$G26-$I26 -> 7495.9261
A27: 23 | B27: PACK HOMESTYLE CRISPY 20 (1200G) | C27: FRIED CHICKEN | D27: ='SIMULARE PE PRODUS'!$F$53 -> 259 | E27: ='SIMULARE PE PRODUS'!$G$53 -> 116 | F27: =$D27+$E27 -> 375 | G27: ='SIMULARE PE PRODUS'!T$53 -> 36292.793 | H27: =IFERROR($G27/'SIMULARE PE PRODUS'!T$4,"") -> 0.0076443158 | I27: ='SIMULARE PE PRODUS'!$L$53 -> 22232.118 | J27: =IFERROR($I27/$G27,"") -> 0.61257666 | K27: =$G27-$I27 -> 14060.675
A28: 24 | B28: Prajitura Maritozzo | C28: FRYCAFE | D28: ='SIMULARE PE PRODUS'!$F$153 -> 20 | E28: ='SIMULARE PE PRODUS'!$G$153 -> 14 | F28: =$D28+$E28 -> 34 | G28: ='SIMULARE PE PRODUS'!T$153 -> 533.33333 | H28: =IFERROR($G28/'SIMULARE PE PRODUS'!T$4,"") -> 0.00011233548 | I28: ='SIMULARE PE PRODUS'!$L$153 -> 323.17068 | J28: =IFERROR($I28/$G28,"") -> 0.60594503 | K28: =$G28-$I28 -> 210.16265
A29: 25 | B29: Prajitura mascarpone capsuni | C29: FRYCAFE | D29: ='SIMULARE PE PRODUS'!$F$137 -> 66 | E29: ='SIMULARE PE PRODUS'!$G$137 -> 40 | F29: =$D29+$E29 -> 106 | G29: ='SIMULARE PE PRODUS'!T$137 -> 1659.4595 | H29: =IFERROR($G29/'SIMULARE PE PRODUS'!T$4,"") -> 0.00034953034 | I29: ='SIMULARE PE PRODUS'!$L$137 -> 998.52 | J29: =IFERROR($I29/$G29,"") -> 0.60171401 | K29: =$G29-$I29 -> 660.93946
A30: 26 | B30: Kendama Fry XRemus | C30: MERCH | D30: ='SIMULARE PE PRODUS'!$F$228 -> 8 | E30: ='SIMULARE PE PRODUS'!$G$228 -> 0 | F30: =$D30+$E30 -> 8 | G30: ='SIMULARE PE PRODUS'!T$228 -> 1322.314 | H30: =IFERROR($G30/'SIMULARE PE PRODUS'!T$4,"") -> 0.00027851773 | I30: ='SIMULARE PE PRODUS'!$L$228 -> 788.08 | J30: =IFERROR($I30/$G30,"") -> 0.5959855 | K30: =$G30-$I30 -> 534.23405
A31: 27 | B31: Caffe Latte | C31: FRYCAFE | D31: ='SIMULARE PE PRODUS'!$F$135 -> 154 | E31: ='SIMULARE PE PRODUS'!$G$135 -> 4 | F31: =$D31+$E31 -> 158 | G31: ='SIMULARE PE PRODUS'!T$135 -> 1702.8264 | H31: =IFERROR($G31/'SIMULARE PE PRODUS'!T$4,"") -> 0.00035866469 | I31: ='SIMULARE PE PRODUS'!$L$135 -> 1010.8042 | J31: =IFERROR($I31/$G31,"") -> 0.59360378 | K31: =$G31-$I31 -> 692.02224
A32: 28 | B32: MANDARINA CU SORBET | C32: FRYCAFE | D32: ='SIMULARE PE PRODUS'!$F$146 -> 53 | E32: ='SIMULARE PE PRODUS'!$G$146 -> 0 | F32: =$D32+$E32 -> 53 | G32: ='SIMULARE PE PRODUS'!T$146 -> 1050.4505 | H32: =IFERROR($G32/'SIMULARE PE PRODUS'!T$4,"") -> 0.00022125536 | I32: ='SIMULARE PE PRODUS'!$L$146 -> 617.87347 | J32: =IFERROR($I32/$G32,"") -> 0.58819859 | K32: =$G32-$I32 -> 432.57698
A33: 29 | B33: Junior Meal 4 Nuggets | C33: JUNIOR | D33: ='SIMULARE PE PRODUS'!$F$219 -> 455 | E33: ='SIMULARE PE PRODUS'!$G$219 -> 106 | F33: =$D33+$E33 -> 561 | G33: ='SIMULARE PE PRODUS'!T$219 -> 19710.811 | H33: =IFERROR($G33/'SIMULARE PE PRODUS'!T$4,"") -> 0.004151669 | I33: ='SIMULARE PE PRODUS'!$L$219 -> 11554.569 | J33: =IFERROR($I33/$G33,"") -> 0.58620467 | K33: =$G33-$I33 -> 8156.2414
A34: 30 | B34: M Festival Combo Db Chee* | C34: COMBO | D34: ='SIMULARE PE PRODUS'!$F$223 -> 737 | E34: ='SIMULARE PE PRODUS'!$G$223 -> 0 | F34: =$D34+$E34 -> 737 | G34: ='SIMULARE PE PRODUS'!T$223 -> 19912.279 | H34: =IFERROR($G34/'SIMULARE PE PRODUS'!T$4,"") -> 0.0041941041 | I34: ='SIMULARE PE PRODUS'!$L$223 -> 11542.82 | J34: =IFERROR($I34/$G34,"") -> 0.57968353 | K34: =$G34-$I34 -> 8369.459
A35: 31 | B35: Tort ciocolata zmeura | C35: FRYCAFE | D35: ='SIMULARE PE PRODUS'!$F$132 -> 84 | E35: ='SIMULARE PE PRODUS'!$G$132 -> 70 | F35: =$D35+$E35 -> 154 | G35: ='SIMULARE PE PRODUS'!T$132 -> 2421.6216 | H35: =IFERROR($G35/'SIMULARE PE PRODUS'!T$4,"") -> 0.00051006382 | I35: ='SIMULARE PE PRODUS'!$L$132 -> 1351.0435 | J35: =IFERROR($I35/$G35,"") -> 0.5579086 | K35: =$G35-$I35 -> 1070.5781
A36: 32 | B36: Millefoglie | C36: FRYCAFE | D36: ='SIMULARE PE PRODUS'!$F$143 -> 41 | E36: ='SIMULARE PE PRODUS'!$G$143 -> 45 | F36: =$D36+$E36 -> 86 | G36: ='SIMULARE PE PRODUS'!T$143 -> 1357.6577 | H36: =IFERROR($G36/'SIMULARE PE PRODUS'!T$4,"") -> 0.00028596212 | I36: ='SIMULARE PE PRODUS'!$L$143 -> 729.88458 | J36: =IFERROR($I36/$G36,"") -> 0.53760576 | K36: =$G36-$I36 -> 627.77308
A37: 33 | B37: Topping Oreo | C37: MILKSHAKE & DESERT | D37: ='SIMULARE PE PRODUS'!$F$186 -> 71 | E37: ='SIMULARE PE PRODUS'!$G$186 -> 0 | F37: =$D37+$E37 -> 71 | G37: ='SIMULARE PE PRODUS'!T$186 -> 255.85586 | H37: =IFERROR($G37/'SIMULARE PE PRODUS'!T$4,"") -> 5.3890671e-05 | I37: ='SIMULARE PE PRODUS'!$L$186 -> 136.75161 | J37: =IFERROR($I37/$G37,"") -> 0.53448692 | K37: =$G37-$I37 -> 119.10425
A38: 34 | B38: Pepsi Zero 350ML new2026 | C38: DRINKS | D38: ='SIMULARE PE PRODUS'!$F$96 -> 5796 | E38: ='SIMULARE PE PRODUS'!$G$96 -> 0 | F38: =$D38+$E38 -> 5796 | G38: ='SIMULARE PE PRODUS'!T$96 -> 38272.76 | H38: =IFERROR($G38/'SIMULARE PE PRODUS'!T$4,"") -> 0.0080613545 | I38: ='SIMULARE PE PRODUS'!$L$96 -> 20352.873 | J38: =IFERROR($I38/$G38,"") -> 0.53178483 | K38: =$G38-$I38 -> 17919.887
A39: 35 | B39: Pepsi -Cola 350ML new2026 | C39: DRINKS | D39: ='SIMULARE PE PRODUS'!$F$94 -> 9763 | E39: ='SIMULARE PE PRODUS'!$G$94 -> 0 | F39: =$D39+$E39 -> 9763 | G39: ='SIMULARE PE PRODUS'!T$94 -> 64468.074 | H39: =IFERROR($G39/'SIMULARE PE PRODUS'!T$4,"") -> 0.013578848 | I39: ='SIMULARE PE PRODUS'!$L$94 -> 34282.248 | J39: =IFERROR($I39/$G39,"") -> 0.53177093 | K39: =$G39-$I39 -> 30185.827
A40: 36 | B40: Bautura 7 UP zero 350ml new2026 | C40: DRINKS | D40: ='SIMULARE PE PRODUS'!$F$99 -> 2047 | E40: ='SIMULARE PE PRODUS'!$G$99 -> 0 | F40: =$D40+$E40 -> 2047 | G40: ='SIMULARE PE PRODUS'!T$99 -> 13516.967 | H40: =IFERROR($G40/'SIMULARE PE PRODUS'!T$4,"") -> 0.0028470657 | I40: ='SIMULARE PE PRODUS'!$L$99 -> 7187.9108 | J40: =IFERROR($I40/$G40,"") -> 0.5317695 | K40: =$G40-$I40 -> 6329.0562
A41: 37 | B41: Mirinda Zero Zahar 350ML new2026 | C41: DRINKS | D41: ='SIMULARE PE PRODUS'!$F$102 -> 1456 | E41: ='SIMULARE PE PRODUS'!$G$102 -> 0 | F41: =$D41+$E41 -> 1456 | G41: ='SIMULARE PE PRODUS'!T$102 -> 9614.4132 | H41: =IFERROR($G41/'SIMULARE PE PRODUS'!T$4,"") -> 0.0020250746 | I41: ='SIMULARE PE PRODUS'!$L$102 -> 5112.5498 | J41: =IFERROR($I41/$G41,"") -> 0.5317589 | K41: =$G41-$I41 -> 4501.8634
A42: 38 | B42: Cioco Cappucino | C42: FRYCAFE | D42: ='SIMULARE PE PRODUS'!$F$158 -> 12 | E42: ='SIMULARE PE PRODUS'!$G$158 -> 5 | F42: =$D42+$E42 -> 17 | G42: ='SIMULARE PE PRODUS'!T$158 -> 200.68595 | H42: =IFERROR($G42/'SIMULARE PE PRODUS'!T$4,"") -> 4.2270287e-05 | I42: ='SIMULARE PE PRODUS'!$L$158 -> 106.22383 | J42: =IFERROR($I42/$G42,"") -> 0.52930376 | K42: =$G42-$I42 -> 94.462122
A43: 39 | B43: Pepsi Zero 500ml | C43: DRINKS | D43: ='SIMULARE PE PRODUS'!$F$95 -> 4497 | E43: ='SIMULARE PE PRODUS'!$G$95 -> 0 | F43: =$D43+$E43 -> 4497 | G43: ='SIMULARE PE PRODUS'!T$95 -> 40844.653 | H43: =IFERROR($G43/'SIMULARE PE PRODUS'!T$4,"") -> 0.0086030697 | I43: ='SIMULARE PE PRODUS'!$L$95 -> 21545.131 | J43: =IFERROR($I43/$G43,"") -> 0.52748963 | K43: =$G43-$I43 -> 19299.522
A44: 40 | B44: Pepsi-Cola 500ml | C44: DRINKS | D44: ='SIMULARE PE PRODUS'!$F$93 -> 8964 | E44: ='SIMULARE PE PRODUS'!$G$93 -> 0 | F44: =$D44+$E44 -> 8964 | G44: ='SIMULARE PE PRODUS'!T$93 -> 81416.826 | H44: =IFERROR($G44/'SIMULARE PE PRODUS'!T$4,"") -> 0.017148747 | I44: ='SIMULARE PE PRODUS'!$L$93 -> 42945.367 | J44: =IFERROR($I44/$G44,"") -> 0.52747532 | K44: =$G44-$I44 -> 38471.46
A45: 41 | B45: Bautura 7 UP zero 500 ml | C45: DRINKS | D45: ='SIMULARE PE PRODUS'!$F$101 -> 1296 | E45: ='SIMULARE PE PRODUS'!$G$101 -> 0 | F45: =$D45+$E45 -> 1296 | G45: ='SIMULARE PE PRODUS'!T$101 -> 11771.107 | H45: =IFERROR($G45/'SIMULARE PE PRODUS'!T$4,"") -> 0.002479337 | I45: ='SIMULARE PE PRODUS'!$L$101 -> 6208.9514 | J45: =IFERROR($I45/$G45,"") -> 0.52747385 | K45: =$G45-$I45 -> 5562.156
A46: 42 | B46: Mirinda Zero Zahar 500ml | C46: DRINKS | D46: ='SIMULARE PE PRODUS'!$F$104 -> 793 | E46: ='SIMULARE PE PRODUS'!$G$104 -> 0 | F46: =$D46+$E46 -> 793 | G46: ='SIMULARE PE PRODUS'!T$104 -> 7202.5372 | H46: =IFERROR($G46/'SIMULARE PE PRODUS'!T$4,"") -> 0.0015170634 | I46: ='SIMULARE PE PRODUS'!$L$104 -> 3799.0714 | J46: =IFERROR($I46/$G46,"") -> 0.52746294 | K46: =$G46-$I46 -> 3403.4658
A47: 43 | B47: CARROT CAKE | C47: FRYCAFE | D47: ='SIMULARE PE PRODUS'!$F$150 -> 24 | E47: ='SIMULARE PE PRODUS'!$G$150 -> 21 | F47: =$D47+$E47 -> 45 | G47: ='SIMULARE PE PRODUS'!T$150 -> 708.10811 | H47: =IFERROR($G47/'SIMULARE PE PRODUS'!T$4,"") -> 0.00014914813 | I47: ='SIMULARE PE PRODUS'!$L$150 -> 368.0541 | J47: =IFERROR($I47/$G47,"") -> 0.51977106 | K47: =$G47-$I47 -> 340.05401
A48: 44 | B48: Caramel Machiato | C48: FRYCAFE | D48: ='SIMULARE PE PRODUS'!$F$145 -> 53 | E48: ='SIMULARE PE PRODUS'!$G$145 -> 31 | F48: =$D48+$E48 -> 84 | G48: ='SIMULARE PE PRODUS'!T$145 -> 1135.6694 | H48: =IFERROR($G48/'SIMULARE PE PRODUS'!T$4,"") -> 0.00023920495 | I48: ='SIMULARE PE PRODUS'!$L$145 -> 589.69032 | J48: =IFERROR($I48/$G48,"") -> 0.51924469 | K48: =$G48-$I48 -> 545.97911
A49: 45 | B49: TIRAMISU CU FISTIC | C49: FRYCAFE | D49: ='SIMULARE PE PRODUS'!$F$134 -> 57 | E49: ='SIMULARE PE PRODUS'!$G$134 -> 54 | F49: =$D49+$E49 -> 111 | G49: ='SIMULARE PE PRODUS'!T$134 -> 2048.6486 | H49: =IFERROR($G49/'SIMULARE PE PRODUS'!T$4,"") -> 0.00043150488 | I49: ='SIMULARE PE PRODUS'!$L$134 -> 1062.0502 | J49: =IFERROR($I49/$G49,"") -> 0.51841502 | K49: =$G49-$I49 -> 986.59843
A50: 46 | B50: LIPTON 350ML NEW2026 | C50: DRINKS | D50: ='SIMULARE PE PRODUS'!$F$98 -> 2083 | E50: ='SIMULARE PE PRODUS'!$G$98 -> 0 | F50: =$D50+$E50 -> 2083 | G50: ='SIMULARE PE PRODUS'!T$98 -> 13754.686 | H50: =IFERROR($G50/'SIMULARE PE PRODUS'!T$4,"") -> 0.0028971362 | I50: ='SIMULARE PE PRODUS'!$L$98 -> 7091.27 | J50: =IFERROR($I50/$G50,"") -> 0.51555303 | K50: =$G50-$I50 -> 6663.416
A51: 47 | B51: PACK COUNTRY HOT WINGS 30 (1050G) | C51: FRIED CHICKEN | D51: ='SIMULARE PE PRODUS'!$F$66 -> 34 | E51: ='SIMULARE PE PRODUS'!$G$66 -> 12 | F51: =$D51+$E51 -> 46 | G51: ='SIMULARE PE PRODUS'!T$66 -> 4411.7477 | H51: =IFERROR($G51/'SIMULARE PE PRODUS'!T$4,"") -> 0.00092924216 | I51: ='SIMULARE PE PRODUS'!$L$66 -> 2273.2532 | J51: =IFERROR($I51/$G51,"") -> 0.5152727 | K51: =$G51-$I51 -> 2138.4946
A52: 48 | B52: CHEESECAKE NEWYORK | C52: FRYCAFE | D52: ='SIMULARE PE PRODUS'!$F$133 -> 79 | E52: ='SIMULARE PE PRODUS'!$G$133 -> 52 | F52: =$D52+$E52 -> 131 | G52: ='SIMULARE PE PRODUS'!T$133 -> 2407.2072 | H52: =IFERROR($G52/'SIMULARE PE PRODUS'!T$4,"") -> 0.00050702772 | I52: ='SIMULARE PE PRODUS'!$L$133 -> 1239.1303 | J52: =IFERROR($I52/$G52,"") -> 0.51475847 | K52: =$G52-$I52 -> 1168.0769
A53: 49 | B53: Lipton 500 ml | C53: DRINKS | D53: ='SIMULARE PE PRODUS'!$F$100 -> 1402 | E53: ='SIMULARE PE PRODUS'!$G$100 -> 0 | F53: =$D53+$E53 -> 1402 | G53: ='SIMULARE PE PRODUS'!T$100 -> 12733.868 | H53: =IFERROR($G53/'SIMULARE PE PRODUS'!T$4,"") -> 0.0026821222 | I53: ='SIMULARE PE PRODUS'!$L$100 -> 6547.588 | J53: =IFERROR($I53/$G53,"") -> 0.5141869 | K53: =$G53-$I53 -> 6186.2798
A54: 50 | B54: Corona | C54: DRINKS | D54: ='SIMULARE PE PRODUS'!$F$111 -> 142 | E54: ='SIMULARE PE PRODUS'!$G$111 -> 84 | F54: =$D54+$E54 -> 226 | G54: ='SIMULARE PE PRODUS'!T$111 -> 3264.2479 | H54: =IFERROR($G54/'SIMULARE PE PRODUS'!T$4,"") -> 0.00068754538 | I54: ='SIMULARE PE PRODUS'!$L$111 -> 1677.3765 | J54: =IFERROR($I54/$G54,"") -> 0.51386309 | K54: =$G54-$I54 -> 1586.8714
A55: 51 | B55: HOMESTYLE CRISPY 3 (180G) | C55: FRIED CHICKEN | D55: ='SIMULARE PE PRODUS'!$F$51 -> 2205 | E55: ='SIMULARE PE PRODUS'!$G$51 -> 628 | F55: =$D55+$E55 -> 2833 | G55: ='SIMULARE PE PRODUS'!T$51 -> 48631.081 | H55: =IFERROR($G55/'SIMULARE PE PRODUS'!T$4,"") -> 0.010243118 | I55: ='SIMULARE PE PRODUS'!$L$51 -> 24593.69 | J55: =IFERROR($I55/$G55,"") -> 0.50571958 | K55: =$G55-$I55 -> 24037.391
A56: 52 | B56: HOMESTYLE CRISPY 4 (240G) | C56: FRIED CHICKEN | D56: ='SIMULARE PE PRODUS'!$F$52 -> 1543 | E56: ='SIMULARE PE PRODUS'!$G$52 -> 498 | F56: =$D56+$E56 -> 2041 | G56: ='SIMULARE PE PRODUS'!T$52 -> 46843.694 | H56: =IFERROR($G56/'SIMULARE PE PRODUS'!T$4,"") -> 0.0098666419 | I56: ='SIMULARE PE PRODUS'!$L$52 -> 23537.893 | J56: =IFERROR($I56/$G56,"") -> 0.5024773 | K56: =$G56-$I56 -> 23305.801
A57: 53 | B57: Cioco Cappucino Grande | C57: FRYCAFE | D57: ='SIMULARE PE PRODUS'!$F$157 -> 6 | E57: ='SIMULARE PE PRODUS'!$G$157 -> 9 | F57: =$D57+$E57 -> 15 | G57: ='SIMULARE PE PRODUS'!T$157 -> 205.66116 | H57: =IFERROR($G57/'SIMULARE PE PRODUS'!T$4,"") -> 4.331821e-05 | I57: ='SIMULARE PE PRODUS'!$L$157 -> 103.25693 | J57: =IFERROR($I57/$G57,"") -> 0.50207307 | K57: =$G57-$I57 -> 102.40423
A58: 54 | B58: HOMESTYLE CRISPY 5 (300G) | C58: FRIED CHICKEN | D58: ='SIMULARE PE PRODUS'!$F$50 -> 2302 | E58: ='SIMULARE PE PRODUS'!$G$50 -> 1136 | F58: =$D58+$E58 -> 3438 | G58: ='SIMULARE PE PRODUS'!T$50 -> 98561.261 | H58: =IFERROR($G58/'SIMULARE PE PRODUS'!T$4,"") -> 0.020759863 | I58: ='SIMULARE PE PRODUS'!$L$50 -> 49451.889 | J58: =IFERROR($I58/$G58,"") -> 0.50173758 | K58: =$G58-$I58 -> 49109.372
A59: 55 | B59: Tort pufos capsuni | C59: FRYCAFE | D59: ='SIMULARE PE PRODUS'!$F$148 -> 32 | E59: ='SIMULARE PE PRODUS'!$G$148 -> 26 | F59: =$D59+$E59 -> 58 | G59: ='SIMULARE PE PRODUS'!T$148 -> 911.71171 | H59: =IFERROR($G59/'SIMULARE PE PRODUS'!T$4,"") -> 0.00019203296 | I59: ='SIMULARE PE PRODUS'!$L$148 -> 451.82 | J59: =IFERROR($I59/$G59,"") -> 0.49557332 | K59: =$G59-$I59 -> 459.89171
A60: 56 | B60: Americano | C60: FRYCAFE | D60: ='SIMULARE PE PRODUS'!$F$147 -> 106 | E60: ='SIMULARE PE PRODUS'!$G$147 -> 1 | F60: =$D60+$E60 -> 107 | G60: ='SIMULARE PE PRODUS'!T$147 -> 972.66942 | H60: =IFERROR($G60/'SIMULARE PE PRODUS'!T$4,"") -> 0.00020487242 | I60: ='SIMULARE PE PRODUS'!$L$147 -> 474.80662 | J60: =IFERROR($I60/$G60,"") -> 0.48814798 | K60: =$G60-$I60 -> 497.86281
A61: 57 | B61: Cappucino | C61: FRYCAFE | D61: ='SIMULARE PE PRODUS'!$F$138 -> 143 | E61: ='SIMULARE PE PRODUS'!$G$138 -> 10 | F61: =$D61+$E61 -> 153 | G61: ='SIMULARE PE PRODUS'!T$138 -> 1650.8017 | H61: =IFERROR($G61/'SIMULARE PE PRODUS'!T$4,"") -> 0.00034770675 | I61: ='SIMULARE PE PRODUS'!$L$138 -> 794.52801 | J61: =IFERROR($I61/$G61,"") -> 0.48129829 | K61: =$G61-$I61 -> 856.27365
A62: 58 | B62: PACK COUNTRY WINGS 30 (1050G) | C62: FRIED CHICKEN | D62: ='SIMULARE PE PRODUS'!$F$64 -> 58 | E62: ='SIMULARE PE PRODUS'!$G$64 -> 21 | F62: =$D62+$E62 -> 79 | G62: ='SIMULARE PE PRODUS'!T$64 -> 7583.7477 | H62: =IFERROR($G62/'SIMULARE PE PRODUS'!T$4,"") -> 0.0015973574 | I62: ='SIMULARE PE PRODUS'!$L$64 -> 3635.7812 | J62: =IFERROR($I62/$G62,"") -> 0.47941748 | K62: =$G62-$I62 -> 3947.9665
A63: 59 | B63: DUBLU BLACK TRUFFLE SMASHED | C63: BURGERI NON-CORE VITĂ | D63: ='SIMULARE PE PRODUS'!$F$22 -> 5163 | E63: ='SIMULARE PE PRODUS'!$G$22 -> 2418 | F63: =$D63+$E63 -> 7581 | G63: ='SIMULARE PE PRODUS'!T$22 -> 211358.73 | H63: =IFERROR($G63/'SIMULARE PE PRODUS'!T$4,"") -> 0.044518285 | I63: ='SIMULARE PE PRODUS'!$L$22 -> 101328.14 | J63: =IFERROR($I63/$G63,"") -> 0.47941308 | K63: =$G63-$I63 -> 110030.59
A64: 60 | B64: Vanilla Latte | C64: FRYCAFE | D64: ='SIMULARE PE PRODUS'!$F$156 -> 20 | E64: ='SIMULARE PE PRODUS'!$G$156 -> 5 | F64: =$D64+$E64 -> 25 | G64: ='SIMULARE PE PRODUS'!T$156 -> 293.18182 | H64: =IFERROR($G64/'SIMULARE PE PRODUS'!T$4,"") -> 6.1752603e-05 | I64: ='SIMULARE PE PRODUS'!$L$156 -> 140.26241 | J64: =IFERROR($I64/$G64,"") -> 0.47841443 | K64: =$G64-$I64 -> 152.91941
A65: 61 | B65: TIRAMISU | C65: FRYCAFE | D65: ='SIMULARE PE PRODUS'!$F$131 -> 139 | E65: ='SIMULARE PE PRODUS'!$G$131 -> 66 | F65: =$D65+$E65 -> 205 | G65: ='SIMULARE PE PRODUS'!T$131 -> 3199.0991 | H65: =IFERROR($G65/'SIMULARE PE PRODUS'!T$4,"") -> 0.00067382315 | I65: ='SIMULARE PE PRODUS'!$L$131 -> 1527.047 | J65: =IFERROR($I65/$G65,"") -> 0.47733659 | K65: =$G65-$I65 -> 1672.052
A66: 62 | B66: 9 HOT COUNTRY WINGS | C66: FRIED CHICKEN | D66: ='SIMULARE PE PRODUS'!$F$56 -> 345 | E66: ='SIMULARE PE PRODUS'!$G$56 -> 356 | F66: =$D66+$E66 -> 701 | G66: ='SIMULARE PE PRODUS'!T$56 -> 21652.252 | H66: =IFERROR($G66/'SIMULARE PE PRODUS'!T$4,"") -> 0.0045605929 | I66: ='SIMULARE PE PRODUS'!$L$56 -> 10295.001 | J66: =IFERROR($I66/$G66,"") -> 0.47547022 | K66: =$G66-$I66 -> 11357.251
A67: 63 | B67: Apa Evian | C67: DRINKS | D67: ='SIMULARE PE PRODUS'!$F$124 -> 55 | E67: ='SIMULARE PE PRODUS'!$G$124 -> 19 | F67: =$D67+$E67 -> 74 | G67: ='SIMULARE PE PRODUS'!T$124 -> 1009.3058 | H67: =IFERROR($G67/'SIMULARE PE PRODUS'!T$4,"") -> 0.0002125891 | I67: ='SIMULARE PE PRODUS'!$L$124 -> 477.596 | J67: =IFERROR($I67/$G67,"") -> 0.47319257 | K67: =$G67-$I67 -> 531.70979
A68: 64 | B68: DUBLU RED PEPPER SMASHED | C68: BURGERI NON-CORE VITĂ | D68: ='SIMULARE PE PRODUS'!$F$26 -> 919 | E68: ='SIMULARE PE PRODUS'!$G$26 -> 398 | F68: =$D68+$E68 -> 1317 | G68: ='SIMULARE PE PRODUS'!T$26 -> 41404.351 | H68: =IFERROR($G68/'SIMULARE PE PRODUS'!T$4,"") -> 0.0087209584 | I68: ='SIMULARE PE PRODUS'!$L$26 -> 19582.961 | J68: =IFERROR($I68/$G68,"") -> 0.47296866 | K68: =$G68-$I68 -> 21821.391
A69: 65 | B69: Prigat Capsuni &Banane | C69: DRINKS | D69: ='SIMULARE PE PRODUS'!$F$113 -> 225 | E69: ='SIMULARE PE PRODUS'!$G$113 -> 68 | F69: =$D69+$E69 -> 293 | G69: ='SIMULARE PE PRODUS'!T$113 -> 2773.6116 | H69: =IFERROR($G69/'SIMULARE PE PRODUS'!T$4,"") -> 0.00058420312 | I69: ='SIMULARE PE PRODUS'!$L$113 -> 1291.837 | J69: =IFERROR($I69/$G69,"") -> 0.46575988 | K69: =$G69-$I69 -> 1481.7746
A70: 66 | B70: DUBLU SMASHED BURGER | C70: BURGERI NON-CORE VITĂ | D70: ='SIMULARE PE PRODUS'!$F$21 -> 6175 | E70: ='SIMULARE PE PRODUS'!$G$21 -> 3718 | F70: =$D70+$E70 -> 9893 | G70: ='SIMULARE PE PRODUS'!T$21 -> 270100.06 | H70: =IFERROR($G70/'SIMULARE PE PRODUS'!T$4,"") -> 0.056890915 | I70: ='SIMULARE PE PRODUS'!$L$21 -> 125521.3 | J70: =IFERROR($I70/$G70,"") -> 0.46472148 | K70: =$G70-$I70 -> 144578.76
A71: 67 | B71: Latte Machiato | C71: FRYCAFE | D71: ='SIMULARE PE PRODUS'!$F$149 -> 65 | E71: ='SIMULARE PE PRODUS'!$G$149 -> 7 | F71: =$D71+$E71 -> 72 | G71: ='SIMULARE PE PRODUS'!T$149 -> 838.24793 | H71: =IFERROR($G71/'SIMULARE PE PRODUS'!T$4,"") -> 0.00017655935 | I71: ='SIMULARE PE PRODUS'!$L$149 -> 385.34416 | J71: =IFERROR($I71/$G71,"") -> 0.45970189 | K71: =$G71-$I71 -> 452.90377
A72: 68 | B72: ALMETTE BASIL PORC | C72: BREAKFAST | D72: ='SIMULARE PE PRODUS'!$F$214 -> 35 | E72: ='SIMULARE PE PRODUS'!$G$214 -> 44 | F72: =$D72+$E72 -> 79 | G72: ='SIMULARE PE PRODUS'!T$214 -> 1328.8288 | H72: =IFERROR($G72/'SIMULARE PE PRODUS'!T$4,"") -> 0.00027988993 | I72: ='SIMULARE PE PRODUS'!$L$214 -> 609.63117 | J72: =IFERROR($I72/$G72,"") -> 0.45877328 | K72: =$G72-$I72 -> 719.19766
A73: 69 | B73: Milkshake Fructul Pasiunii CAN (livrare) | C73: MILKSHAKE & DESERT | D73: ='SIMULARE PE PRODUS'!$F$178 -> 182 | E73: ='SIMULARE PE PRODUS'!$G$178 -> 0 | F73: =$D73+$E73 -> 182 | G73: ='SIMULARE PE PRODUS'!T$178 -> 2623.4234 | H73: =IFERROR($G73/'SIMULARE PE PRODUS'!T$4,"") -> 0.00055256914 | I73: ='SIMULARE PE PRODUS'!$L$178 -> 1201.0968 | J73: =IFERROR($I73/$G73,"") -> 0.45783565 | K73: =$G73-$I73 -> 1422.3267
A74: 70 | B74: Milkshake Cirese CAN (livrare) | C74: MILKSHAKE & DESERT | D74: ='SIMULARE PE PRODUS'!$F$177 -> 198 | E74: ='SIMULARE PE PRODUS'!$G$177 -> 0 | F74: =$D74+$E74 -> 198 | G74: ='SIMULARE PE PRODUS'!T$177 -> 2854.0541 | H74: =IFERROR($G74/'SIMULARE PE PRODUS'!T$4,"") -> 0.00060114664 | I74: ='SIMULARE PE PRODUS'!$L$177 -> 1301.8798 | J74: =IFERROR($I74/$G74,"") -> 0.45615105 | K74: =$G74-$I74 -> 1552.1743
A75: 71 | B75: Vanilla Latte Grande | C75: FRYCAFE | D75: ='SIMULARE PE PRODUS'!$F$155 -> 11 | E75: ='SIMULARE PE PRODUS'!$G$155 -> 18 | F75: =$D75+$E75 -> 29 | G75: ='SIMULARE PE PRODUS'!T$155 -> 398.10744 | H75: =IFERROR($G75/'SIMULARE PE PRODUS'!T$4,"") -> 8.3852984e-05 | I75: ='SIMULARE PE PRODUS'!$L$155 -> 181.12911 | J75: =IFERROR($I75/$G75,"") -> 0.45497544 | K75: =$G75-$I75 -> 216.97833
A76: 72 | B76: DOZE PEPSI 330 ML/TWIST ZERO 330 ML/7UP 330 ML/MIRINDA PORTOCALE 330 ML | C76: DRINKS | D76: ='SIMULARE PE PRODUS'!$F$108 -> 0 | E76: ='SIMULARE PE PRODUS'!$G$108 -> 524 | F76: =$D76+$E76 -> 524 | G76: ='SIMULARE PE PRODUS'!T$108 -> 4542.7769 | H76: =IFERROR($G76/'SIMULARE PE PRODUS'!T$4,"") -> 0.00095684069 | I76: ='SIMULARE PE PRODUS'!$L$108 -> 2056.7 | J76: =IFERROR($I76/$G76,"") -> 0.45274071 | K76: =$G76-$I76 -> 2486.0769
A77: 73 | B77: Extra Homestyle Crispy | C77: ADD ON | D77: ='SIMULARE PE PRODUS'!$F$204 -> 30 | E77: ='SIMULARE PE PRODUS'!$G$204 -> 30 | F77: =$D77+$E77 -> 60 | G77: ='SIMULARE PE PRODUS'!T$204 -> 378.37838 | H77: =IFERROR($G77/'SIMULARE PE PRODUS'!T$4,"") -> 7.9697472e-05 | I77: ='SIMULARE PE PRODUS'!$L$204 -> 171.08294 | J77: =IFERROR($I77/$G77,"") -> 0.45214777 | K77: =$G77-$I77 -> 207.29544
A78: 74 | B78: Iced Latte Tiramisu | C78: FRYCAFE | D78: ='SIMULARE PE PRODUS'!$F$129 -> 461 | E78: ='SIMULARE PE PRODUS'!$G$129 -> 0 | F78: =$D78+$E78 -> 461 | G78: ='SIMULARE PE PRODUS'!T$129 -> 6476.8595 | H78: =IFERROR($G78/'SIMULARE PE PRODUS'!T$4,"") -> 0.0013642146 | I78: ='SIMULARE PE PRODUS'!$L$129 -> 2917.5765 | J78: =IFERROR($I78/$G78,"") -> 0.4504616 | K78: =$G78-$I78 -> 3559.283
A79: 75 | B79: Iced Latte Popcorn | C79: FRYCAFE | D79: ='SIMULARE PE PRODUS'!$F$142 -> 101 | E79: ='SIMULARE PE PRODUS'!$G$142 -> 0 | F79: =$D79+$E79 -> 101 | G79: ='SIMULARE PE PRODUS'!T$142 -> 1419.0083 | H79: =IFERROR($G79/'SIMULARE PE PRODUS'!T$4,"") -> 0.00029888434 | I79: ='SIMULARE PE PRODUS'!$L$142 -> 639.08203 | J79: =IFERROR($I79/$G79,"") -> 0.45037231 | K79: =$G79-$I79 -> 779.92623
A80: 76 | B80: Cappucino Grande | C80: FRYCAFE | D80: ='SIMULARE PE PRODUS'!$F$152 -> 38 | E80: ='SIMULARE PE PRODUS'!$G$152 -> 7 | F80: =$D80+$E80 -> 45 | G80: ='SIMULARE PE PRODUS'!T$152 -> 563.26446 | H80: =IFERROR($G80/'SIMULARE PE PRODUS'!T$4,"") -> 0.00011863985 | I80: ='SIMULARE PE PRODUS'!$L$152 -> 253.45455 | J80: =IFERROR($I80/$G80,"") -> 0.44997432 | K80: =$G80-$I80 -> 309.80992
A81: 77 | B81: Prigat Portocale/Capsuni &Banane | C81: DRINKS | D81: ='SIMULARE PE PRODUS'!$F$118 -> 158 | E81: ='SIMULARE PE PRODUS'!$G$118 -> 27 | F81: =$D81+$E81 -> 185 | G81: ='SIMULARE PE PRODUS'!T$118 -> 1724.9174 | H81: =IFERROR($G81/'SIMULARE PE PRODUS'!T$4,"") -> 0.00036331767 | I81: ='SIMULARE PE PRODUS'!$L$118 -> 771.45 | J81: =IFERROR($I81/$G81,"") -> 0.44723882 | K81: =$G81-$I81 -> 953.46736
A82: 78 | B82: ALMETTE FRESH PORC | C82: BREAKFAST | D82: ='SIMULARE PE PRODUS'!$F$215 -> 35 | E82: ='SIMULARE PE PRODUS'!$G$215 -> 37 | F82: =$D82+$E82 -> 72 | G82: ='SIMULARE PE PRODUS'!T$215 -> 1202.7027 | H82: =IFERROR($G82/'SIMULARE PE PRODUS'!T$4,"") -> 0.00025332411 | I82: ='SIMULARE PE PRODUS'!$L$215 -> 537.22564 | J82: =IFERROR($I82/$G82,"") -> 0.44668199 | K82: =$G82-$I82 -> 665.47706
A83: 79 | B83: 7 HOT COUNTRY WINGS | C83: FRIED CHICKEN | D83: ='SIMULARE PE PRODUS'!$F$61 -> 331 | E83: ='SIMULARE PE PRODUS'!$G$61 -> 251 | F83: =$D83+$E83 -> 582 | G83: ='SIMULARE PE PRODUS'!T$61 -> 15061.261 | H83: =IFERROR($G83/'SIMULARE PE PRODUS'!T$4,"") -> 0.0031723389 | I83: ='SIMULARE PE PRODUS'!$L$61 -> 6717.5183 | J83: =IFERROR($I83/$G83,"") -> 0.446013 | K83: =$G83-$I83 -> 8343.743
A84: 80 | B84: TRIPLU CHICKEN TRUFFLE | C84: BURGERI NON-CORE PUI | D84: ='SIMULARE PE PRODUS'!$F$41 -> 114 | E84: ='SIMULARE PE PRODUS'!$G$41 -> 0 | F84: =$D84+$E84 -> 114 | G84: ='SIMULARE PE PRODUS'!T$41 -> 2515.1892 | H84: =IFERROR($G84/'SIMULARE PE PRODUS'!T$4,"") -> 0.00052977186 | I84: ='SIMULARE PE PRODUS'!$L$41 -> 1121.7411 | J84: =IFERROR($I84/$G84,"") -> 0.44598675 | K84: =$G84-$I84 -> 1393.4481
A85: 81 | B85: Caffe Latte Grande | C85: FRYCAFE | D85: ='SIMULARE PE PRODUS'!$F$151 -> 34 | E85: ='SIMULARE PE PRODUS'!$G$151 -> 14 | F85: =$D85+$E85 -> 48 | G85: ='SIMULARE PE PRODUS'!T$151 -> 606.21488 | H85: =IFERROR($G85/'SIMULARE PE PRODUS'!T$4,"") -> 0.00012768645 | I85: ='SIMULARE PE PRODUS'!$L$151 -> 270.35152 | J85: =IFERROR($I85/$G85,"") -> 0.44596648 | K85: =$G85-$I85 -> 335.86336
A86: 82 | B86: 9 COUNTRY WINGS | C86: FRIED CHICKEN | D86: ='SIMULARE PE PRODUS'!$F$58 -> 320 | E86: ='SIMULARE PE PRODUS'!$G$58 -> 255 | F86: =$D86+$E86 -> 575 | G86: ='SIMULARE PE PRODUS'!T$58 -> 17610.36 | H86: =IFERROR($G86/'SIMULARE PE PRODUS'!T$4,"") -> 0.0037092532 | I86: ='SIMULARE PE PRODUS'!$L$58 -> 7832.2844 | J86: =IFERROR($I86/$G86,"") -> 0.44475435 | K86: =$G86-$I86 -> 9778.076
A87: 83 | B87: Budweiser | C87: DRINKS | D87: ='SIMULARE PE PRODUS'!$F$116 -> 105 | E87: ='SIMULARE PE PRODUS'!$G$116 -> 55 | F87: =$D87+$E87 -> 160 | G87: ='SIMULARE PE PRODUS'!T$116 -> 2250.7438 | H87: =IFERROR($G87/'SIMULARE PE PRODUS'!T$4,"") -> 0.00047407199 | I87: ='SIMULARE PE PRODUS'!$L$116 -> 996.8 | J87: =IFERROR($I87/$G87,"") -> 0.44287582 | K87: =$G87-$I87 -> 1253.9438
A88: 84 | B88: SHRIMP BURGER | C88: CREVEȚI | D88: ='SIMULARE PE PRODUS'!$F$44 -> 470 | E88: ='SIMULARE PE PRODUS'!$G$44 -> 268 | F88: =$D88+$E88 -> 738 | G88: ='SIMULARE PE PRODUS'!T$44 -> 18004.162 | H88: =IFERROR($G88/'SIMULARE PE PRODUS'!T$4,"") -> 0.0037921992 | I88: ='SIMULARE PE PRODUS'!$L$44 -> 7952.2225 | J88: =IFERROR($I88/$G88,"") -> 0.44168801 | K88: =$G88-$I88 -> 10051.94
A89: 85 | B89: Espresso | C89: FRYCAFE | D89: ='SIMULARE PE PRODUS'!$F$139 -> 208 | E89: ='SIMULARE PE PRODUS'!$G$139 -> 11 | F89: =$D89+$E89 -> 219 | G89: ='SIMULARE PE PRODUS'!T$139 -> 1636.2066 | H89: =IFERROR($G89/'SIMULARE PE PRODUS'!T$4,"") -> 0.00034463261 | I89: ='SIMULARE PE PRODUS'!$L$139 -> 721.59536 | J89: =IFERROR($I89/$G89,"") -> 0.44101726 | K89: =$G89-$I89 -> 914.61125
A90: 86 | B90: APPLE PIE TOFFIE 2X | C90: MILKSHAKE & DESERT | D90: ='SIMULARE PE PRODUS'!$F$164 -> 1104 | E90: ='SIMULARE PE PRODUS'!$G$164 -> 643 | F90: =$D90+$E90 -> 1747 | G90: ='SIMULARE PE PRODUS'!T$164 -> 23608.108 | H90: =IFERROR($G90/'SIMULARE PE PRODUS'!T$4,"") -> 0.004972553 | I90: ='SIMULARE PE PRODUS'!$L$164 -> 10397.63 | J90: =IFERROR($I90/$G90,"") -> 0.44042624 | K90: =$G90-$I90 -> 13210.478
A91: 87 | B91: MIRINDA PORTOCALE 330 ML | C91: DRINKS | D91: ='SIMULARE PE PRODUS'!$F$125 -> 0 | E91: ='SIMULARE PE PRODUS'!$G$125 -> 91 | F91: =$D91+$E91 -> 91 | G91: ='SIMULARE PE PRODUS'!T$125 -> 788.91736 | H91: =IFERROR($G91/'SIMULARE PE PRODUS'!T$4,"") -> 0.0001661689 | I91: ='SIMULARE PE PRODUS'!$L$125 -> 346.073 | J91: =IFERROR($I91/$G91,"") -> 0.43866826 | K91: =$G91-$I91 -> 442.84436
A92: 88 | B92: ICED COFFEE LATTE | C92: FRYCAFE | D92: ='SIMULARE PE PRODUS'!$F$130 -> 516 | E92: ='SIMULARE PE PRODUS'!$G$130 -> 0 | F92: =$D92+$E92 -> 516 | G92: ='SIMULARE PE PRODUS'!T$130 -> 5965.9835 | H92: =IFERROR($G92/'SIMULARE PE PRODUS'!T$4,"") -> 0.0012566093 | I92: ='SIMULARE PE PRODUS'!$L$130 -> 2592.3806 | J92: =IFERROR($I92/$G92,"") -> 0.43452696 | K92: =$G92-$I92 -> 3373.6028
A93: 89 | B93: Red Bull | C93: DRINKS | D93: ='SIMULARE PE PRODUS'!$F$119 -> 57 | E93: ='SIMULARE PE PRODUS'!$G$119 -> 55 | F93: =$D93+$E93 -> 112 | G93: ='SIMULARE PE PRODUS'!T$119 -> 1570.9752 | H93: =IFERROR($G93/'SIMULARE PE PRODUS'!T$4,"") -> 0.00033089299 | I93: ='SIMULARE PE PRODUS'!$L$119 -> 680.96 | J93: =IFERROR($I93/$G93,"") -> 0.43346324 | K93: =$G93-$I93 -> 890.01521
A94: 90 | B94: Pepsi Twist Zero 330ml | C94: DRINKS | D94: ='SIMULARE PE PRODUS'!$F$117 -> 0 | E94: ='SIMULARE PE PRODUS'!$G$117 -> 235 | F94: =$D94+$E94 -> 235 | G94: ='SIMULARE PE PRODUS'!T$117 -> 2037.314 | H94: =IFERROR($G94/'SIMULARE PE PRODUS'!T$4,"") -> 0.00042911749 | I94: ='SIMULARE PE PRODUS'!$L$117 -> 877.96 | J94: =IFERROR($I94/$G94,"") -> 0.43093994 | K94: =$G94-$I94 -> 1159.354
A95: 91 | B95: Pepsi cu gust de Căpșuni și Frișcă | C95: DRINKS | D95: ='SIMULARE PE PRODUS'!$F$122 -> 53 | E95: ='SIMULARE PE PRODUS'!$G$122 -> 83 | F95: =$D95+$E95 -> 136 | G95: ='SIMULARE PE PRODUS'!T$122 -> 1179.0413 | H95: =IFERROR($G95/'SIMULARE PE PRODUS'!T$4,"") -> 0.00024834033 | I95: ='SIMULARE PE PRODUS'!$L$122 -> 503.88136 | J95: =IFERROR($I95/$G95,"") -> 0.42736531 | K95: =$G95-$I95 -> 675.15996
A96: 92 | B96: Pepsi cu gust de Înghețată de Vanilie | C96: DRINKS | D96: ='SIMULARE PE PRODUS'!$F$123 -> 36 | E96: ='SIMULARE PE PRODUS'!$G$123 -> 81 | F96: =$D96+$E96 -> 117 | G96: ='SIMULARE PE PRODUS'!T$123 -> 1014.3223 | H96: =IFERROR($G96/'SIMULARE PE PRODUS'!T$4,"") -> 0.00021364573 | I96: ='SIMULARE PE PRODUS'!$L$123 -> 433.134 | J96: =IFERROR($I96/$G96,"") -> 0.42701811 | K96: =$G96-$I96 -> 581.18831
A97: 93 | B97: HOMESTYLE CHICKEN PESTO | C97: BURGERI NON-CORE PUI | D97: ='SIMULARE PE PRODUS'!$F$38 -> 465 | E97: ='SIMULARE PE PRODUS'!$G$38 -> 134 | F97: =$D97+$E97 -> 599 | G97: ='SIMULARE PE PRODUS'!T$38 -> 14806.315 | H97: =IFERROR($G97/'SIMULARE PE PRODUS'!T$4,"") -> 0.0031186399 | I97: ='SIMULARE PE PRODUS'!$L$38 -> 6316.4354 | J97: =IFERROR($I97/$G97,"") -> 0.42660414 | K97: =$G97-$I97 -> 8489.8799
A98: 94 | B98: Bautura 7UP 330 ML | C98: DRINKS | D98: ='SIMULARE PE PRODUS'!$F$121 -> 141 | E98: ='SIMULARE PE PRODUS'!$G$121 -> 0 | F98: =$D98+$E98 -> 141 | G98: ='SIMULARE PE PRODUS'!T$121 -> 1222.3884 | H98: =IFERROR($G98/'SIMULARE PE PRODUS'!T$4,"") -> 0.00025747049 | I98: ='SIMULARE PE PRODUS'!$L$121 -> 520.431 | J98: =IFERROR($I98/$G98,"") -> 0.42574929 | K98: =$G98-$I98 -> 701.95743
A99: 95 | B99: 7 COUNTRY WINGS | C99: FRIED CHICKEN | D99: ='SIMULARE PE PRODUS'!$F$62 -> 364 | E99: ='SIMULARE PE PRODUS'!$G$62 -> 130 | F99: =$D99+$E99 -> 494 | G99: ='SIMULARE PE PRODUS'!T$62 -> 12484.685 | H99: =IFERROR($G99/'SIMULARE PE PRODUS'!T$4,"") -> 0.002629637 | I99: ='SIMULARE PE PRODUS'!$L$62 -> 5287.6415 | J99: =IFERROR($I99/$G99,"") -> 0.42353024 | K99: =$G99-$I99 -> 7197.0432
A100: 96 | B100: Sacosa | C100: AMBALAJE VÂNDUTE | D100: ='SIMULARE PE PRODUS'!$F$236 -> 495 | E100: ='SIMULARE PE PRODUS'!$G$236 -> 410 | F100: =$D100+$E100 -> 905 | G100: ='SIMULARE PE PRODUS'!T$236 -> 1630.6306 | H100: =IFERROR($G100/'SIMULARE PE PRODUS'!T$4,"") -> 0.00034345815 | I100: ='SIMULARE PE PRODUS'!$L$236 -> 687.8 | J100: =IFERROR($I100/$G100,"") -> 0.4218 | K100: =$G100-$I100 -> 942.83063
A101: 97 | B101: HOMESTYLE CHICKEN LEMON LETTUCE WRAP | C101: BURGERI NON-CORE PUI | D101: ='SIMULARE PE PRODUS'!$F$39 -> 352 | E101: ='SIMULARE PE PRODUS'!$G$39 -> 167 | F101: =$D101+$E101 -> 519 | G101: ='SIMULARE PE PRODUS'!T$39 -> 12920.55 | H101: =IFERROR($G101/'SIMULARE PE PRODUS'!T$4,"") -> 0.0027214428 | I101: ='SIMULARE PE PRODUS'!$L$39 -> 5433.7616 | J101: =IFERROR($I101/$G101,"") -> 0.42055189 | K101: =$G101-$I101 -> 7486.788
...

Sheet SCENARIU
A1: SCENARIU — panoul de control
A2: Tot ce modifici aici se propagă în întregul fișier: prețuri, food cost pe produs, pe categorie, în cele trei taburi MASTER FC, în TOP SALES și TOP FC. GALBEN = ajustare de preț pe categorie (lei cu TVA, cumulat de la o lună la alta, peste planul deja inclus). ALBASTRU = index de volum și factorul lunar.
A4: PARAMETRI
A5: Corecție volum săptămână (03–09.08) | B5: 0.94632 | C5: ← săptămâna 03–09.08 a fost peste media lunii; aceasta o normalizează
A7: ZILE ȘI SĂPTĂMÂNI PE LUNĂ
B8: August | C8: Septembrie | D8: Octombrie | E8: Noiembrie | F8: Decembrie
A9: Zile calendaristice | B9: 31 | C9: 30 | D9: 31 | E9: 30 | F9: 31
A10: Săptămâni (zile ÷ 7) | B10: =B9/7 -> 4.4285714 | C10: =C9/7 -> 4.2857143 | D10: =D9/7 -> 4.4285714 | E10: =E9/7 -> 4.2857143 | F10: =F9/7 -> 4.4285714
A12: INDEX VOLUM PE LUNĂ
B13: August | C13: Septembrie | D13: Octombrie | E13: Noiembrie | F13: Decembrie
A14: Index volum (1,00 = ca august) | B14: 1 | C14: 0.91029 | D14: 0.95807 | E14: 0.94111 | F14: 1.13908
A15: Bucăți vândute / lună | B15: =SUMPRODUCT(ISNUMBER('SIMULARE PE PRODUS'!$A$6:$A$243)*('SIMULARE PE PRODUS'!$D$6:$D$243>0)*('SIMULARE PE PRODUS'!$F$6:$F$243+'SIMULARE PE PRODUS'!$G$6:$G$243))*B10*$B$5*B14+SUMPRODUCT(ISNUMBER('SIMULARE PE PRODUS'!$A$6:$A$243)*('SIMULARE PE PRODUS'!$D$6:$D$243=0)*('SIMULARE PE PRODUS'!$F$6:$F$243+'SIMULARE PE PRODUS'!$G$6:$G$243)) -> 1829382.8 | C15: =SUMPRODUCT(ISNUMBER('SIMULARE PE PRODUS'!$A$6:$A$243)*('SIMULARE PE PRODUS'!$D$6:$D$243>0)*('SIMULARE PE PRODUS'!$F$6:$F$243+'SIMULARE PE PRODUS'!$G$6:$G$243))*C10*$B$5*C14 -> 1603872.4 | D15: =SUMPRODUCT(ISNUMBER('SIMULARE PE PRODUS'!$A$6:$A$243)*('SIMULARE PE PRODUS'!$D$6:$D$243>0)*('SIMULARE PE PRODUS'!$F$6:$F$243+'SIMULARE PE PRODUS'!$G$6:$G$243))*D10*$B$5*D14 -> 1744326.3 | E15: =SUMPRODUCT(ISNUMBER('SIMULARE PE PRODUS'!$A$6:$A$243)*('SIMULARE PE PRODUS'!$D$6:$D$243>0)*('SIMULARE PE PRODUS'!$F$6:$F$243+'SIMULARE PE PRODUS'!$G$6:$G$243))*E10*$B$5*E14 -> 1658175.2 | F15: =SUMPRODUCT(ISNUMBER('SIMULARE PE PRODUS'!$A$6:$A$243)*('SIMULARE PE PRODUS'!$D$6:$D$243>0)*('SIMULARE PE PRODUS'!$F$6:$F$243+'SIMULARE PE PRODUS'!$G$6:$G$243))*F10*$B$5*F14 -> 2073885.2
A17: AJUSTĂRI DE PREȚ PE CATEGORIE (lei cu TVA, cumulate)
B18: August | C18: Septembrie | D18: Octombrie | E18: Noiembrie | F18: Decembrie | G18: Σ extra | H18: Buc/săpt | I18: Preț mediu
A19: BURGERI CORE VITĂ | B19: 0 | C19: 0 | D19: 0 | E19: 0 | F19: 0 | G19: =SUM(B19:F19) -> 0 | H19: =SUMIFS('SIMULARE PE PRODUS'!$F$6:$F$243,'SIMULARE PE PRODUS'!$C$6:$C$243,$A19)+SUMIFS('SIMULARE PE PRODUS'!$G$6:$G$243,'SIMULARE PE PRODUS'!$C$6:$C$243,$A19) -> 56762 | I19: =IFERROR(SUMIFS('SIMULARE PE PRODUS'!T$6:T$243,'SIMULARE PE PRODUS'!$C$6:$C$243,$A19)/$H19,"") -> 13.872891
A20: BURGERI CORE PUI | B20: 0 | C20: 0 | D20: 0 | E20: 0 | F20: 0 | G20: =SUM(B20:F20) -> 0 | H20: =SUMIFS('SIMULARE PE PRODUS'!$F$6:$F$243,'SIMULARE PE PRODUS'!$C$6:$C$243,$A20)+SUMIFS('SIMULARE PE PRODUS'!$G$6:$G$243,'SIMULARE PE PRODUS'!$C$6:$C$243,$A20) -> 12376 | I20: =IFERROR(SUMIFS('SIMULARE PE PRODUS'!T$6:T$243,'SIMULARE PE PRODUS'!$C$6:$C$243,$A20)/$H20,"") -> 8.1306597
A21: BURGERI NON-CORE VITĂ | B21: 0 | C21: 0 | D21: 0 | E21: 0 | F21: 0 | G21: =SUM(B21:F21) -> 0 | H21: =SUMIFS('SIMULARE PE PRODUS'!$F$6:$F$243,'SIMULARE PE PRODUS'!$C$6:$C$243,$A21)+SUMIFS('SIMULARE PE PRODUS'!$G$6:$G$243,'SIMULARE PE PRODUS'!$C$6:$C$243,$A21) -> 37060 | I21: =IFERROR(SUMIFS('SIMULARE PE PRODUS'!T$6:T$243,'SIMULARE PE PRODUS'!$C$6:$C$243,$A21)/$H21,"") -> 24.947222
A22: BURGERI NON-CORE PUI | B22: 0 | C22: 0 | D22: 0 | E22: 0 | F22: 0 | G22: =SUM(B22:F22) -> 0 | H22: =SUMIFS('SIMULARE PE PRODUS'!$F$6:$F$243,'SIMULARE PE PRODUS'!$C$6:$C$243,$A22)+SUMIFS('SIMULARE PE PRODUS'!$G$6:$G$243,'SIMULARE PE PRODUS'!$C$6:$C$243,$A22) -> 18382 | I22: =IFERROR(SUMIFS('SIMULARE PE PRODUS'!T$6:T$243,'SIMULARE PE PRODUS'!$C$6:$C$243,$A22)/$H22,"") -> 18.115542
A23: CREVEȚI | B23: 0 | C23: 0 | D23: 0 | E23: 0 | F23: 0 | G23: =SUM(B23:F23) -> 0 | H23: =SUMIFS('SIMULARE PE PRODUS'!$F$6:$F$243,'SIMULARE PE PRODUS'!$C$6:$C$243,$A23)+SUMIFS('SIMULARE PE PRODUS'!$G$6:$G$243,'SIMULARE PE PRODUS'!$C$6:$C$243,$A23) -> 738 | I23: =IFERROR(SUMIFS('SIMULARE PE PRODUS'!T$6:T$243,'SIMULARE PE PRODUS'!$C$6:$C$243,$A23)/$H23,"") -> 24.395884
A24: VEGETARIAN | B24: 0 | C24: 0 | D24: 0 | E24: 0 | F24: 0 | G24: =SUM(B24:F24) -> 0 | H24: =SUMIFS('SIMULARE PE PRODUS'!$F$6:$F$243,'SIMULARE PE PRODUS'!$C$6:$C$243,$A24)+SUMIFS('SIMULARE PE PRODUS'!$G$6:$G$243,'SIMULARE PE PRODUS'!$C$6:$C$243,$A24) -> 992 | I24: =IFERROR(SUMIFS('SIMULARE PE PRODUS'!T$6:T$243,'SIMULARE PE PRODUS'!$C$6:$C$243,$A24)/$H24,"") -> 19.599208
A25: FRIED CHICKEN | B25: 0 | C25: 0 | D25: 0 | E25: 0 | F25: 0 | G25: =SUM(B25:F25) -> 0 | H25: =SUMIFS('SIMULARE PE PRODUS'!$F$6:$F$243,'SIMULARE PE PRODUS'!$C$6:$C$243,$A25)+SUMIFS('SIMULARE PE PRODUS'!$G$6:$G$243,'SIMULARE PE PRODUS'!$C$6:$C$243,$A25) -> 18218 | I25: =IFERROR(SUMIFS('SIMULARE PE PRODUS'!T$6:T$243,'SIMULARE PE PRODUS'!$C$6:$C$243,$A25)/$H25,"") -> 23.325461
A26: CARTOFI | B26: 0 | C26: 0 | D26: 0 | E26: 0 | F26: 0 | G26: =SUM(B26:F26) -> 0 | H26: =SUMIFS('SIMULARE PE PRODUS'!$F$6:$F$243,'SIMULARE PE PRODUS'!$C$6:$C$243,$A26)+SUMIFS('SIMULARE PE PRODUS'!$G$6:$G$243,'SIMULARE PE PRODUS'!$C$6:$C$243,$A26) -> 78599 | I26: =IFERROR(SUMIFS('SIMULARE PE PRODUS'!T$6:T$243,'SIMULARE PE PRODUS'!$C$6:$C$243,$A26)/$H26,"") -> 12.237632
A27: SOSURI | B27: 0 | C27: 0 | D27: 0 | E27: 0 | F27: 0 | G27: =SUM(B27:F27) -> 0 | H27: =SUMIFS('SIMULARE PE PRODUS'!$F$6:$F$243,'SIMULARE PE PRODUS'!$C$6:$C$243,$A27)+SUMIFS('SIMULARE PE PRODUS'!$G$6:$G$243,'SIMULARE PE PRODUS'!$C$6:$C$243,$A27) -> 57491 | I27: =IFERROR(SUMIFS('SIMULARE PE PRODUS'!T$6:T$243,'SIMULARE PE PRODUS'!$C$6:$C$243,$A27)/$H27,"") -> 8.2100973
A28: DRINKS | B28: 0 | C28: 0 | D28: 0 | E28: 0 | F28: 0 | G28: =SUM(B28:F28) -> 0 | H28: =SUMIFS('SIMULARE PE PRODUS'!$F$6:$F$243,'SIMULARE PE PRODUS'!$C$6:$C$243,$A28)+SUMIFS('SIMULARE PE PRODUS'!$G$6:$G$243,'SIMULARE PE PRODUS'!$C$6:$C$243,$A28) -> 46929 | I28: =IFERROR(SUMIFS('SIMULARE PE PRODUS'!T$6:T$243,'SIMULARE PE PRODUS'!$C$6:$C$243,$A28)/$H28,"") -> 8.1434847
A29: FRYCAFE | B29: 0 | C29: 0 | D29: 0 | E29: 0 | F29: 0 | G29: =SUM(B29:F29) -> 0 | H29: =SUMIFS('SIMULARE PE PRODUS'!$F$6:$F$243,'SIMULARE PE PRODUS'!$C$6:$C$243,$A29)+SUMIFS('SIMULARE PE PRODUS'!$G$6:$G$243,'SIMULARE PE PRODUS'!$C$6:$C$243,$A29) -> 4628 | I29: =IFERROR(SUMIFS('SIMULARE PE PRODUS'!T$6:T$243,'SIMULARE PE PRODUS'!$C$6:$C$243,$A29)/$H29,"") -> 12.100567
A30: MILKSHAKE & DESERT | B30: 0 | C30: 0 | D30: 0 | E30: 0 | F30: 0 | G30: =SUM(B30:F30) -> 0 | H30: =SUMIFS('SIMULARE PE PRODUS'!$F$6:$F$243,'SIMULARE PE PRODUS'!$C$6:$C$243,$A30)+SUMIFS('SIMULARE PE PRODUS'!$G$6:$G$243,'SIMULARE PE PRODUS'!$C$6:$C$243,$A30) -> 10964 | I30: =IFERROR(SUMIFS('SIMULARE PE PRODUS'!T$6:T$243,'SIMULARE PE PRODUS'!$C$6:$C$243,$A30)/$H30,"") -> 12.332786
... A38: GARANTII SGR | B38: 0 | C38: 0 | D38: 0 | E38: 0 | F38: 0 | G38: =SUM(B38:F38) -> 0 | H38: =SUMIFS('SIMULARE PE PRODUS'!$F$6:$F$243,'SIMULARE PE PRODUS'!$C$6:$C$243,$A38)+SUMIFS('SIMULARE PE PRODUS'!$G$6:$G$243,'SIMULARE PE PRODUS'!$C$6:$C$243,$A38) -> 6124 | I38: =IFERROR(SUMIFS('SIMULARE PE PRODUS'!T$6:T$243,'SIMULARE PE PRODUS'!$C$6:$C$243,$A38)/$H38,"") -> 0.41322314
A40: REZULTAT (pe lună)
B41: August | C41: Septembrie | D41: Octombrie | E41: Noiembrie | F41: Decembrie
A42: Vânzări nete | B42: =SUMPRODUCT(ISNUMBER('SIMULARE PE PRODUS'!$A$6:$A$243)*('SIMULARE PE PRODUS'!$D$6:$D$243>0)*'SIMULARE PE PRODUS'!T$6:T$243)*B10*$B$5*B14+SUMPRODUCT(ISNUMBER('SIMULARE PE PRODUS'!$A$6:$A$243)*('SIMULARE PE PRODUS'!$D$6:$D$243=0)*'SIMULARE PE PRODUS'!T$6:T$243) -> 19821304 | C42: =SUMPRODUCT(ISNUMBER('SIMULARE PE PRODUS'!$A$6:$A$243)*('SIMULARE PE PRODUS'!$D$6:$D$243>0)*'SIMULARE PE PRODUS'!AB$6:AB$243)*C10*$B$5*C14 -> 17851023 | D42: =SUMPRODUCT(ISNUMBER('SIMULARE PE PRODUS'!$A$6:$A$243)*('SIMULARE PE PRODUS'!$D$6:$D$243>0)*'SIMULARE PE PRODUS'!AJ$6:AJ$243)*D10*$B$5*D14 -> 19590131 | E42: =SUMPRODUCT(ISNUMBER('SIMULARE PE PRODUS'!$A$6:$A$243)*('SIMULARE PE PRODUS'!$D$6:$D$243>0)*'SIMULARE PE PRODUS'!AR$6:AR$243)*E10*$B$5*E14 -> 18889183 | F42: =SUMPRODUCT(ISNUMBER('SIMULARE PE PRODUS'!$A$6:$A$243)*('SIMULARE PE PRODUS'!$D$6:$D$243>0)*'SIMULARE PE PRODUS'!AZ$6:AZ$243)*F10*$B$5*F14 -> 24310694
A43: Cost material | B43: =SUMPRODUCT(ISNUMBER('SIMULARE PE PRODUS'!$A$6:$A$243)*('SIMULARE PE PRODUS'!$D$6:$D$243>0)*'SIMULARE PE PRODUS'!$L$6:$L$243)*B10*$B$5*B14+SUMPRODUCT(ISNUMBER('SIMULARE PE PRODUS'!$A$6:$A$243)*('SIMULARE PE PRODUS'!$D$6:$D$243=0)*'SIMULARE PE PRODUS'!$L$6:$L$243) -> 9076560.8 | C43: =SUMPRODUCT(ISNUMBER('SIMULARE PE PRODUS'!$A$6:$A$243)*('SIMULARE PE PRODUS'!$D$6:$D$243>0)*'SIMULARE PE PRODUS'!$L$6:$L$243)*C10*$B$5*C14 -> 7958313.1 | D43: =SUMPRODUCT(ISNUMBER('SIMULARE PE PRODUS'!$A$6:$A$243)*('SIMULARE PE PRODUS'!$D$6:$D$243>0)*'SIMULARE PE PRODUS'!$L$6:$L$243)*D10*$B$5*D14 -> 8655236.4 | E43: =SUMPRODUCT(ISNUMBER('SIMULARE PE PRODUS'!$A$6:$A$243)*('SIMULARE PE PRODUS'!$D$6:$D$243>0)*'SIMULARE PE PRODUS'!$L$6:$L$243)*E10*$B$5*E14 -> 8227760.5 | F43: =SUMPRODUCT(ISNUMBER('SIMULARE PE PRODUS'!$A$6:$A$243)*('SIMULARE PE PRODUS'!$D$6:$D$243>0)*'SIMULARE PE PRODUS'!$L$6:$L$243)*F10*$B$5*F14 -> 10290487
A44: Economii MC (din tabul ECONOMII) | B44: =ECONOMII!E20*B14 -> 0 | C44: =ECONOMII!F20*C14 -> 75236.151 | D44: =ECONOMII!G20*D14 -> 205291.74 | E44: =ECONOMII!H20*E14 -> 201657.62 | F44: =ECONOMII!I20*F14 -> 244077.9
A45: FOOD COST % | B45: =(B43-B44)/B42 -> 0.45791945 | C45: =(C43-C44)/C42 -> 0.44160365 | D45: =(D43-D44)/D42 -> 0.43133681 | E45: =(E43-E44)/E42 -> 0.42490472 | F45: =(F43-F44)/F42 -> 0.4132506
A46: FOOD COST % — fără economii | B46: =B43/B42 -> 0.45791945 | C46: =C43/C42 -> 0.44581832 | D46: =D43/D42 -> 0.44181615 | E46: =E43/E42 -> 0.43558054 | F46: =F43/F42 -> 0.42329054
A47: câștig din economii (pp) | B47: =B46-B45 -> 0 | C47: =C46-C45 -> 0.0042146689 | D47: =D46-D45 -> 0.010479345 | E47: =E46-E45 -> 0.010675825 | F47: =F46-F45 -> 0.01003994
A48: Marjă brută | B48: =B42-(B43-B44) -> 10744744 | C48: =C42-(C43-C44) -> 9967946.1 | D48: =D42-(D43-D44) -> 11140187 | E48: =E42-(E43-E44) -> 10863080 | F48: =F42-(F43-F44) -> 14264285
A50: FC august (săptămână, fără economii) | C50: =B45 -> 0.45791945 | F50: FC decembrie (cu economii) | H50: =F46 -> 0.42329054

Sheet AJUSTĂRI PE PRODUS
A1: AJUSTĂRI DE PREȚ PE PRODUS
B2: Scrii suma în lei (cu TVA) în celulele GALBENE — se adaugă peste plan și peste SCENARIU, cumulat de la o lună la alta. Lângă fiecare pereche de ajustări vezi FC-ul produsului în acea lună: total, InStore și Delivery.
B3: FC GENERAL: | E3: Aug: | F3: =SCENARIU!B45 -> 0.45791945 | J3: Sep: | K3: =SCENARIU!C45 -> 0.44160365 | O3: Oct: | P3: =SCENARIU!D45 -> 0.43133681 | T3: Nov: | U3: =SCENARIU!E45 -> 0.42490472 | Y3: Dec: | Z3: =SCENARIU!F45 -> 0.4132506
D4: AUGUST (realizat) | I4: SEPTEMBRIE | N4: OCTOMBRIE | S4: NOIEMBRIE | X4: DECEMBRIE
A5: # | B5: Produs | C5: Categorie | D5: Preț aug I | E5: Preț aug D | F5: FC aug | G5: FC I aug | H5: FC D aug | I5: Ajust I | J5: Ajust D | K5: FC | L5: FC I | M5: FC D | N5: Ajust I | O5: Ajust D | P5: FC | Q5: FC I | R5: FC D | S5: Ajust I | T5: Ajust D | U5: FC | V5: FC I | W5: FC D | X5: Ajust I | Y5: Ajust D | Z5: FC | AA5: FC I | AB5: FC D
A6: 1 | B6: REALLY CRUNCHY FRIES 170G | C6: CARTOFI | D6: ='SIMULARE PE PRODUS'!P69 -> 12.4 | E6: ='SIMULARE PE PRODUS'!Q69 -> 14.99 | F6: ='SIMULARE PE PRODUS'!U69 -> 0.3251969 | G6: ='SIMULARE PE PRODUS'!V69 -> 0.33364647 | H6: ='SIMULARE PE PRODUS'!W69 -> 0.27599841 | I6: 0 | J6: 0.5 | K6: ='SIMULARE PE PRODUS'!AC69 -> 0.3166523 | L6: ='SIMULARE PE PRODUS'!AD69 -> 0.32705267 | M6: ='SIMULARE PE PRODUS'!AE69 -> 0.25873773 | N6: 0 | O6: 0 | P6: ='SIMULARE PE PRODUS'!AK69 -> 0.3166523 | Q6: ='SIMULARE PE PRODUS'!AL69 -> 0.32705267 | R6: ='SIMULARE PE PRODUS'!AM69 -> 0.25873773 | S6: 0 | T6: 0 | U6: ='SIMULARE PE PRODUS'!AS69 -> 0.31143449 | V6: ='SIMULARE PE PRODUS'!AT69 -> 0.32071444 | W6: ='SIMULARE PE PRODUS'!AU69 -> 0.25873773 | X6: 0 | Y6: -1 | Z6: ='SIMULARE PE PRODUS'!BA69 -> 0.29055945 | AA6: ='SIMULARE PE PRODUS'!BB69 -> 0.29572668 | AB6: ='SIMULARE PE PRODUS'!BC69 -> 0.25873773
A7: 2 | B7: DUBLU SMASHED BURGER | C7: BURGERI NON-CORE VITĂ | D7: ='SIMULARE PE PRODUS'!P21 -> 28.99 | E7: ='SIMULARE PE PRODUS'!Q21 -> 32.49 | F7: ='SIMULARE PE PRODUS'!U21 -> 0.46472148 | G7: ='SIMULARE PE PRODUS'!V21 -> 0.48580746 | H7: ='SIMULARE PE PRODUS'!W21 -> 0.43347363 | I7: 0 | J7: 0 | K7: ='SIMULARE PE PRODUS'!AC21 -> 0.45717861 | L7: ='SIMULARE PE PRODUS'!AD21 -> 0.47757065 | M7: ='SIMULARE PE PRODUS'!AE21 -> 0.42690386 | N7: 0 | O7: 0 | P7: ='SIMULARE PE PRODUS'!AK21 -> 0.45717861 | Q7: ='SIMULARE PE PRODUS'!AL21 -> 0.47757065 | R7: ='SIMULARE PE PRODUS'!AM21 -> 0.42690386 | S7: 0 | T7: 0 | U7: ='SIMULARE PE PRODUS'!AS21 -> 0.44987669 | V7: ='SIMULARE PE PRODUS'!AT21 -> 0.46960848 | W7: ='SIMULARE PE PRODUS'!AU21 -> 0.42053026 | X7: 0 | Y7: 0 | Z7: ='SIMULARE PE PRODUS'!BA21 -> 0.44987669 | AA7: ='SIMULARE PE PRODUS'!BB21 -> 0.46960848 | AB7: ='SIMULARE PE PRODUS'!BC21 -> 0.42053026
A8: 3 | B8: DUBLU CHEESEBURGER | C8: BURGERI CORE VITĂ | D8: ='SIMULARE PE PRODUS'!P7 -> 17.99 | E8: ='SIMULARE PE PRODUS'!Q7 -> 19.99 | F8: ='SIMULARE PE PRODUS'!U7 -> 0.65551133 | G8: ='SIMULARE PE PRODUS'!V7 -> 0.69670962 | H8: ='SIMULARE PE PRODUS'!W7 -> 0.6270038 | I8: 0 | J8: 0 | K8: ='SIMULARE PE PRODUS'!AC7 -> 0.65551133 | L8: ='SIMULARE PE PRODUS'!AD7 -> 0.69670962 | M8: ='SIMULARE PE PRODUS'!AE7 -> 0.6270038 | N8: 0 | O8: 0 | P8: ='SIMULARE PE PRODUS'!AK7 -> 0.65551133 | Q8: ='SIMULARE PE PRODUS'!AL7 -> 0.69670962 | R8: ='SIMULARE PE PRODUS'!AM7 -> 0.6270038 | S8: 0 | T8: 0 | U8: ='SIMULARE PE PRODUS'!AS7 -> 0.65551133 | V8: ='SIMULARE PE PRODUS'!AT7 -> 0.69670962 | W8: ='SIMULARE PE PRODUS'!AU7 -> 0.6270038 | X8: 0 | Y8: 0 | Z8: ='SIMULARE PE PRODUS'!BA7 -> 0.63880671 | AA8: ='SIMULARE PE PRODUS'!BB7 -> 0.67786944 | AB8: ='SIMULARE PE PRODUS'!BC7 -> 0.61170356
A9: 4 | B9: CARTOFI CRISS CUT 140G | C9: CARTOFI | D9: ='SIMULARE PE PRODUS'!P70 -> 15.5 | E9: ='SIMULARE PE PRODUS'!Q70 -> 14.15 | F9: ='SIMULARE PE PRODUS'!U70 -> 0.25053158 | G9: ='SIMULARE PE PRODUS'!V70 -> 0.24225456 | H9: ='SIMULARE PE PRODUS'!W70 -> 0.26536718 | I9: 0 | J9: 1 | K9: ='SIMULARE PE PRODUS'!AC70 -> 0.23991153 | L9: ='SIMULARE PE PRODUS'!AD70 -> 0.23840925 | M9: ='SIMULARE PE PRODUS'!AE70 -> 0.24241095 | N9: 0 | O9: 0 | P9: ='SIMULARE PE PRODUS'!AK70 -> 0.23991153 | Q9: ='SIMULARE PE PRODUS'!AL70 -> 0.23840925 | R9: ='SIMULARE PE PRODUS'!AM70 -> 0.24241095 | S9: 0 | T9: 0 | U9: ='SIMULARE PE PRODUS'!AS70 -> 0.23664773 | V9: ='SIMULARE PE PRODUS'!AT70 -> 0.2346841 | W9: ='SIMULARE PE PRODUS'!AU70 -> 0.23993263 | X9: 0 | Y9: 0.5 | Z9: ='SIMULARE PE PRODUS'!BA70 -> 0.22100916 | AA9: ='SIMULARE PE PRODUS'!BB70 -> 0.22100916 | AB9: ='SIMULARE PE PRODUS'!BC70 -> 0.22100916
A10: 5 | B10: DUBLU BLACK TRUFFLE SMASHED | C10: BURGERI NON-CORE VITĂ | D10: ='SIMULARE PE PRODUS'!P22 -> 29.99 | E10: ='SIMULARE PE PRODUS'!Q22 -> 32.99 | F10: ='SIMULARE PE PRODUS'!U22 -> 0.47941308 | G10: ='SIMULARE PE PRODUS'!V22 -> 0.49470932 | H10: ='SIMULARE PE PRODUS'!W22 -> 0.44972211 | I10: 0 | K10: ='SIMULARE PE PRODUS'!AC22 -> 0.47179049 | L10: ='SIMULARE PE PRODUS'!AD22 -> 0.48659667 | M10: ='SIMULARE PE PRODUS'!AE22 -> 0.44300783 | N10: 0 | O10: 0 | P10: ='SIMULARE PE PRODUS'!AK22 -> 0.47179049 | Q10: ='SIMULARE PE PRODUS'!AL22 -> 0.48659667 | R10: ='SIMULARE PE PRODUS'!AM22 -> 0.44300783 | S10: 0 | T10: 0 | U10: ='SIMULARE PE PRODUS'!AS22 -> 0.46440651 | V10: ='SIMULARE PE PRODUS'!AT22 -> 0.4787458 | W10: ='SIMULARE PE PRODUS'!AU22 -> 0.4364911 | X10: 0 | Y10: 0 | Z10: ='SIMULARE PE PRODUS'!BA22 -> 0.46440651 | AA10: ='SIMULARE PE PRODUS'!BB22 -> 0.4787458 | AB10: ='SIMULARE PE PRODUS'!BC22 -> 0.4364911
A11: 6 | B11: AMERICAN TRIPLU CHEESEBURGER | C11: BURGERI CORE VITĂ | D11: ='SIMULARE PE PRODUS'!P8 -> 22 | E11: ='SIMULARE PE PRODUS'!Q8 -> 25 | F11: ='SIMULARE PE PRODUS'!U8 -> 0.71276966 | G11: ='SIMULARE PE PRODUS'!V8 -> 0.76019864 | H11: ='SIMULARE PE PRODUS'!W8 -> 0.6689748 | I11: 0 | J11: 0 | K11: ='SIMULARE PE PRODUS'!AC8 -> 0.67021014 | L11: ='SIMULARE PE PRODUS'!AD8 -> 0.71197829 | M11: ='SIMULARE PE PRODUS'!AE8 -> 0.63134655 | N11: 0 | O11: 0 | P11: ='SIMULARE PE PRODUS'!AK8 -> 0.67021014 | Q11: ='SIMULARE PE PRODUS'!AL8 -> 0.71197829 | R11: ='SIMULARE PE PRODUS'!AM8 -> 0.63134655 | S11: 0 | T11: 0 | U11: ='SIMULARE PE PRODUS'!AS8 -> 0.67021014 | V11: ='SIMULARE PE PRODUS'!AT8 -> 0.71197829 | W11: ='SIMULARE PE PRODUS'!AU8 -> 0.63134655 | X11: 0 | Y11: 0 | Z11: ='SIMULARE PE PRODUS'!BA8 -> 0.65704497 | AA11: ='SIMULARE PE PRODUS'!BB8 -> 0.69713922 | AB11: ='SIMULARE PE PRODUS'!BC8 -> 0.61965061
A12: 7 | B12: BLACK TRUFFLE SMASHED | C12: BURGERI NON-CORE VITĂ | D12: ='SIMULARE PE PRODUS'!P23 -> 22.99 | E12: ='SIMULARE PE PRODUS'!Q23 -> 25.99 | F12: ='SIMULARE PE PRODUS'!U23 -> 0.40489227 | G12: ='SIMULARE PE PRODUS'!V23 -> 0.42560279 | H12: ='SIMULARE PE PRODUS'!W23 -> 0.37647588 | I12: 0 | J12: 0 | K12: ='SIMULARE PE PRODUS'!AC23 -> 0.39668475 | L12: ='SIMULARE PE PRODUS'!AD23 -> 0.41654355 | M12: ='SIMULARE PE PRODUS'!AE23 -> 0.36936988 | N12: 0 | O12: 0 | P12: ='SIMULARE PE PRODUS'!AK23 -> 0.39668475 | Q12: ='SIMULARE PE PRODUS'!AL23 -> 0.41654355 | R12: ='SIMULARE PE PRODUS'!AM23 -> 0.36936988 | S12: 0 | T12: 0 | U12: ='SIMULARE PE PRODUS'!AS23 -> 0.38880338 | V12: ='SIMULARE PE PRODUS'!AT23 -> 0.40786194 | W12: ='SIMULARE PE PRODUS'!AU23 -> 0.36252716 | X12: 0 | Y12: 0 | Z12: ='SIMULARE PE PRODUS'!BA23 -> 0.38880338 | AA12: ='SIMULARE PE PRODUS'!BB23 -> 0.40786194 | AB12: ='SIMULARE PE PRODUS'!BC23 -> 0.36252716
A13: 8 | B13: SMASHED BURGER | C13: BURGERI NON-CORE VITĂ | D13: ='SIMULARE PE PRODUS'!P24 -> 21.99 | E13: ='SIMULARE PE PRODUS'!Q24 -> 25.49 | F13: ='SIMULARE PE PRODUS'!U24 -> 0.40193076 | G13: ='SIMULARE PE PRODUS'!V24 -> 0.4148043 | H13: ='SIMULARE PE PRODUS'!W24 -> 0.35784804 | I13: 0 | J13: 0 | K13: ='SIMULARE PE PRODUS'!AC24 -> 0.39326634 | L13: ='SIMULARE PE PRODUS'!AD24 -> 0.40558233 | M13: ='SIMULARE PE PRODUS'!AE24 -> 0.3509637 | N13: 0 | O13: 0 | P13: ='SIMULARE PE PRODUS'!AK24 -> 0.39326634 | Q13: ='SIMULARE PE PRODUS'!AL24 -> 0.40558233 | R13: ='SIMULARE PE PRODUS'!AM24 -> 0.3509637 | S13: 0 | T13: 0 | U13: ='SIMULARE PE PRODUS'!AS24 -> 0.38660933 | V13: ='SIMULARE PE PRODUS'!AT24 -> 0.39676149 | W13: ='SIMULARE PE PRODUS'!AU24 -> 0.3509637 | X13: 0 | Y13: 0 | Z13: ='SIMULARE PE PRODUS'!BA24 -> 0.3849676 | AA13: ='SIMULARE PE PRODUS'!BB24 -> 0.39676149 | AB13: ='SIMULARE PE PRODUS'!BC24 -> 0.34433925
A14: 9 | B14: AMERICAN DUBLU CHEESEBURGER | C14: BURGERI CORE VITĂ | D14: ='SIMULARE PE PRODUS'!P9 -> 16 | E14: ='SIMULARE PE PRODUS'!Q9 -> 19 | F14: ='SIMULARE PE PRODUS'!U9 -> 0.73110551 | G14: ='SIMULARE PE PRODUS'!V9 -> 0.75389812 | H14: ='SIMULARE PE PRODUS'!W9 -> 0.63486158 | I14: 0 | J14: 0 | K14: ='SIMULARE PE PRODUS'!AC9 -> 0.68971936 | L14: ='SIMULARE PE PRODUS'!AD9 -> 0.70996881 | M14: ='SIMULARE PE PRODUS'!AE9 -> 0.60342021 | N14: 0 | O14: 0 | P14: ='SIMULARE PE PRODUS'!AK9 -> 0.68971936 | Q14: ='SIMULARE PE PRODUS'!AL9 -> 0.70996881 | R14: ='SIMULARE PE PRODUS'!AM9 -> 0.60342021 | S14: 0 | T14: 0 | U14: ='SIMULARE PE PRODUS'!AS9 -> 0.68971936 | V14: ='SIMULARE PE PRODUS'!AT9 -> 0.70996881 | W14: ='SIMULARE PE PRODUS'!AU9 -> 0.60342021 | X14: 0 | Y14: 0 | Z14: ='SIMULARE PE PRODUS'!BA9 -> 0.67054857 | AA14: ='SIMULARE PE PRODUS'!BB9 -> 0.68967238 | AB14: ='SIMULARE PE PRODUS'!BC9 -> 0.58869546
A15: 10 | B15: DIP N Cheddar 100 ML | C15: SOSURI | D15: ='SIMULARE PE PRODUS'!P75 -> 14.08 | E15: ='SIMULARE PE PRODUS'!Q75 -> 14.08 | F15: ='SIMULARE PE PRODUS'!U75 -> 0.38567849 | G15: ='SIMULARE PE PRODUS'!V75 -> 0.38567849 | H15: ='SIMULARE PE PRODUS'!W75 -> 0.38567849 | I15: 0 | J15: 0 | K15: ='SIMULARE PE PRODUS'!AC75 -> 0.38027683 | L15: ='SIMULARE PE PRODUS'!AD75 -> 0.38027683 | M15: ='SIMULARE PE PRODUS'!AE75 -> 0.38027683 | N15: 0 | O15: 0 | P15: ='SIMULARE PE PRODUS'!AK75 -> 0.38027683 | Q15: ='SIMULARE PE PRODUS'!AL75 -> 0.38027683 | R15: ='SIMULARE PE PRODUS'!AM75 -> 0.38027683 | S15: 0 | T15: 0 | U15: ='SIMULARE PE PRODUS'!AS75 -> 0.38027683 | V15: ='SIMULARE PE PRODUS'!AT75 -> 0.38027683 | W15: ='SIMULARE PE PRODUS'!AU75 -> 0.38027683 | X15: 0 | Y15: 0 | Z15: ='SIMULARE PE PRODUS'!BA75 -> 0.37476557 | AA15: ='SIMULARE PE PRODUS'!BB75 -> 0.37476557 | AB15: ='SIMULARE PE PRODUS'!BC75 -> 0.37476557
A16: 11 | B16: HOMESTYLE CRISPY 5 (300G) | C16: FRIED CHICKEN | D16: ='SIMULARE PE PRODUS'!P50 -> 30.5 | E16: ='SIMULARE PE PRODUS'!Q50 -> 34.5 | F16: ='SIMULARE PE PRODUS'!U50 -> 0.50173758 | G16: ='SIMULARE PE PRODUS'!V50 -> 0.52348007 | H16: ='SIMULARE PE PRODUS'!W50 -> 0.46278673 | I16: 0 | J16: 0 | K16: ='SIMULARE PE PRODUS'!AC50 -> 0.49397596 | L16: ='SIMULARE PE PRODUS'!AD50 -> 0.51503684 | M16: ='SIMULARE PE PRODUS'!AE50 -> 0.45617549 | N16: 0 | O16: 0 | P16: ='SIMULARE PE PRODUS'!AK50 -> 0.49397596 | Q16: ='SIMULARE PE PRODUS'!AL50 -> 0.51503684 | R16: ='SIMULARE PE PRODUS'!AM50 -> 0.45617549 | S16: 0 | T16: 0 | U16: ='SIMULARE PE PRODUS'!AS50 -> 0.48645082 | V16: ='SIMULARE PE PRODUS'!AT50 -> 0.50686165 | W16: ='SIMULARE PE PRODUS'!AU50 -> 0.44975048 | X16: 0 | Y16: 0 | Z16: ='SIMULARE PE PRODUS'!BA50 -> 0.47929534 | AA16: ='SIMULARE PE PRODUS'!BB50 -> 0.49909791 | AB16: ='SIMULARE PE PRODUS'!BC50 -> 0.44362718
A17: 12 | B17: DIP N FRYRANCH 100G | C17: SOSURI | D17: ='SIMULARE PE PRODUS'!P76 -> 14.08 | E17: ='SIMULARE PE PRODUS'!Q76 -> 14.08 | F17: ='SIMULARE PE PRODUS'!U76 -> 0.23637797 | G17: ='SIMULARE PE PRODUS'!V76 -> 0.23637797 | H17: ='SIMULARE PE PRODUS'!W76 -> 0.23637797 | I17: 0 | J17: 0 | K17: ='SIMULARE PE PRODUS'!AC76 -> 0.23306735 | L17: ='SIMULARE PE PRODUS'!AD76 -> 0.23306735 | M17: ='SIMULARE PE PRODUS'!AE76 -> 0.23306735 | N17: 0 | O17: 0 | P17: ='SIMULARE PE PRODUS'!AK76 -> 0.23306735 | Q17: ='SIMULARE PE PRODUS'!AL76 -> 0.23306735 | R17: ='SIMULARE PE PRODUS'!AM76 -> 0.23306735 | S17: 0 | T17: 0 | U17: ='SIMULARE PE PRODUS'!AS76 -> 0.23306735 | V17: ='SIMULARE PE PRODUS'!AT76 -> 0.23306735 | W17: ='SIMULARE PE PRODUS'!AU76 -> 0.23306735 | X17: 0 | Y17: 0 | Z17: ='SIMULARE PE PRODUS'!BA76 -> 0.22968957 | AA17: ='SIMULARE PE PRODUS'!BB76 -> 0.22968957 | AB17: ='SIMULARE PE PRODUS'!BC76 -> 0.22968957
A18: 13 | B18: CHEESEBURGER | C18: BURGERI CORE VITĂ | D18: ='SIMULARE PE PRODUS'!P11 -> 11.49 | E18: ='SIMULARE PE PRODUS'!Q11 -> 13.49 | F18: ='SIMULARE PE PRODUS'!U11 -> 0.65050436 | G18: ='SIMULARE PE PRODUS'!V11 -> 0.67567073 | H18: ='SIMULARE PE PRODUS'!W11 -> 0.57549716 | I18: 0 | J18: 0 | K18: ='SIMULARE PE PRODUS'!AC11 -> 0.65050436 | L18: ='SIMULARE PE PRODUS'!AD11 -> 0.67567073 | M18: ='SIMULARE PE PRODUS'!AE11 -> 0.57549716 | N18: 0 | O18: 0 | P18: ='SIMULARE PE PRODUS'!AK11 -> 0.65050436 | Q18: ='SIMULARE PE PRODUS'!AL11 -> 0.67567073 | R18: ='SIMULARE PE PRODUS'!AM11 -> 0.57549716 | S18: 0 | T18: 0 | U18: ='SIMULARE PE PRODUS'!AS11 -> 0.65050436 | V18: ='SIMULARE PE PRODUS'!AT11 -> 0.67567073 | W18: ='SIMULARE PE PRODUS'!AU11 -> 0.57549716 | X18: 0 | Y18: 0 | Z18: ='SIMULARE PE PRODUS'!BA11 -> 0.62434716 | AA18: ='SIMULARE PE PRODUS'!BB11 -> 0.6474943 | AB18: ='SIMULARE PE PRODUS'!BC11 -> 0.554929
A19: 14 | B19: AMERICAN TRIPLU CHEESEBURGER LETTUCE WRAP | C19: BURGERI NON-CORE VITĂ | D19: ='SIMULARE PE PRODUS'!P25 -> 24.99 | E19: ='SIMULARE PE PRODUS'!Q25 -> 27.99 | F19: ='SIMULARE PE PRODUS'!U25 -> 0.64343696 | G19: ='SIMULARE PE PRODUS'!V25 -> 0.67423973 | H19: ='SIMULARE PE PRODUS'!W25 -> 0.60197395 | I19: 0 | J19: 0 | K19: ='SIMULARE PE PRODUS'!AC25 -> 0.6313814 | L19: ='SIMULARE PE PRODUS'!AD25 -> 0.66101415 | M19: ='SIMULARE PE PRODUS'!AE25 -> 0.59140929 | N19: 0 | O19: 0 | P19: ='SIMULARE PE PRODUS'!AK25 -> 0.6313814 | Q19: ='SIMULARE PE PRODUS'!AL25 -> 0.66101415 | R19: ='SIMULARE PE PRODUS'!AM25 -> 0.59140929 | S19: 0 | T19: 0 | U19: ='SIMULARE PE PRODUS'!AS25 -> 0.61976929 | V19: ='SIMULARE PE PRODUS'!AT25 -> 0.64829745 | W19: ='SIMULARE PE PRODUS'!AU25 -> 0.58120906 | X19: 0 | Y19: 0 | Z19: ='SIMULARE PE PRODUS'!BA25 -> 0.61976929 | AA19: ='SIMULARE PE PRODUS'!BB25 -> 0.64829745 | AB19: ='SIMULARE PE PRODUS'!BC25 -> 0.58120906
A20: 15 | B20: AMERICAN CHEESEBURGER | C20: BURGERI CORE VITĂ | D20: ='SIMULARE PE PRODUS'!P10 -> 10 | E20: ='SIMULARE PE PRODUS'!Q10 -> 13 | F20: ='SIMULARE PE PRODUS'!U10 -> 0.70954942 | G20: ='SIMULARE PE PRODUS'!V10 -> 0.740037 | H20: ='SIMULARE PE PRODUS'!W10 -> 0.56925923 | I20: 0 | J20: 0 | K20: ='SIMULARE PE PRODUS'!AC10 -> 0.67770971 | L20: ='SIMULARE PE PRODUS'!AD10 -> 0.70546902 | M20: ='SIMULARE PE PRODUS'!AE10 -> 0.54858191 | N20: 0 | O20: 0 | P20: ='SIMULARE PE PRODUS'!AK10 -> 0.67770971 | Q20: ='SIMULARE PE PRODUS'!AL10 -> 0.70546902 | R20: ='SIMULARE PE PRODUS'!AM10 -> 0.54858191 | S20: 0 | T20: 0 | U20: ='SIMULARE PE PRODUS'!AS10 -> 0.67770971 | V20: ='SIMULARE PE PRODUS'!AT10 -> 0.70546902 | W20: ='SIMULARE PE PRODUS'!AU10 -> 0.54858191 | X20: 0 | Y20: 0 | Z20: ='SIMULARE PE PRODUS'!BA10 -> 0.64803682 | AA20: ='SIMULARE PE PRODUS'!BB10 -> 0.67337307 | AB20: ='SIMULARE PE PRODUS'!BC10 -> 0.5289757
