Workbook

Sheet NOMENCLATOR
A1: NOMENCLATOR — cost actual + COST NOU (koliber 7000210 = 3.35)
A2: Col D = cost actual. Col E = cost nou (portocaliu). Koliber @ 3.35; restul = cost actual. Modifici cost → curge în MC și MC nou.
A4: Cod MP | B4: Denumire materie primă (NBO) | C4: UM | D4: Cost / UM | E4: Cost NOU / UM
A5: 700977 | B5: 1.000 EA Aqua Carpatica Plata (raw) | C5: EA | D5: 2.75 | E5: =D5 -> 2.75
A6: 702586 | B6: 1.000 EA Aripioare de pui picante | C6: EA | D6: 1.50443 | E6: =D6 -> 1.50443
A7: 702230 | B7: 1.000 EA Barbecue Sauce 100 x 25g | C7: EA | D7: 1.082 | E7: =D7 -> 1.082
A8: 700158 | B8: 1.000 EA BASE - Milkshake 2021 | C8: EA | D8: 5.151 | E8: =D8 -> 5.151
A9: 7000230 | B9: 1.000 EA BASE - Milkshake 2026 | C9: EA | D9: 3.115 | E9: =D9 -> 3.115
A10: 7000235 | B10: 1.000 EA BASE - Milkshake CAN | C10: EA | D10: 5.216 | E10: =D10 -> 5.216
A11: 702176 | B11: 1.000 EA CARROT CAKE | C11: EA | D11: 8.008 | E11: =D11 -> 8.008
A12: 702479 | B12: 1.000 EA MARITOZZO 90 g x 12 | C12: EA | D12: 9.621 | E12: =D12 -> 9.621
A13: 7000014 | B13: 1.000 EA MILLEFOGLIE RAW | C13: EA | D13: 8.228 | E13: =D13 -> 8.228
A14: 4083 | B14: 1.000 EA Nuggets cornflakes (raw) | C14: EA | D14: 0.67483 | E14: =D14 -> 0.67483
A15: 702044 | B15: 1.000 EA Pepsi Max 0.33L PROMO FREE | C15: EA | D15: 0.643 | E15: =D15 -> 0.643
A16: 702548 | B16: 1.000 EA Prep Limonada | C16: ML | D16: 0.03498 | E16: =D16 -> 0.03498
... A117: 702179 | B117: Prajitura de vanilie cu bezea crocanta | C117: EA | D117: 5.056 | E117: =D117 -> 5.056
A118: 7000210 | B118: PREP - smashed koliber 60G | C118: EA | D118: 2.93233 | E118: 3.35
A119: 7000024 | B119: Prep Salata Coleslaw | C119: GM | D119: 0.01894 | E119: =D119 -> 0.01894
A120: 3016 | B120: Prigat Portocale (raw) | C120: EA | D120: 4.17 | E120: =D120 -> 4.17
A121: 702175 | B121: Profiterol cu ciocolata | C121: EA | D121: 4.92 | E121: =D121 -> 4.92
A122: 702507 | B122: PUNGA 11x5x12.5 BURGER MIC | C122: EA | D122: 0.105 | E122: =D122 -> 0.105
A123: 5046 | B123: Punga Alba Pui 15x15 | C123: EA | D123: 0.127 | E123: =D123 -> 0.127
A124: 7000167 | B124: Punga Fry Shaker | C124: EA | D124: 0.319 | E124: =D124 -> 0.319
A125: 702146 | B125: PUNGA FRYDAY PEPSI 23X10X30 | C125: EA | D125: 0.529 | E125: =D125 -> 0.529
A126: 700970 | B126: Punga Pui Nepicant | C126: EA | D126: 0.294 | E126: =D126 -> 0.294
A127: 700971 | B127: Punga Pui Picant | C127: EA | D127: 0.34 | E127: =D127 -> 0.34
A128: 702147 | B128: PUNGA TO GO FRD+PEPSI 26X17X33 | C128: EA | D128: 0.939 | E128: =D128 -> 0.939
A129: 3017 | B129: Redbull (raw) | C129: EA | D129: 6.08 | E129: =D129 -> 6.08
A130: 702514 | B130: Redpeppajam Sauce | C130: ML | D130: 0.03953 | E130: =D130 -> 0.03953
... A155: 702399 | B155: Y-Castraveti felii in saramura | C155: GM | D155: 0.01554 | E155: =D155 -> 0.01554

Sheet RETETAR
A1: REȚETAR — cost actual + COST NOU (koliber 3.35)
A2: COST = cost actual. COST NOU = cu koliber @ 3.35. TOTAL = MC actual, TOTAL NOU = MC nou.
A4: Single HAMBURGER | F4: BURGER VITA
A5: COD | B5: INGREDIENT | C5: QTY | D5: UM | E5: COST/UM | F5: COST | G5: COST/UM NOU | H5: COST NOU
A6: 7000133 | B6: =IFERROR(VLOOKUP(A6,NOMENCLATOR!$A:$E,2,0),"") -> CHIFLA CARTOF 3.5inch 53G x 72 | C6: 1 | D6: =IFERROR(VLOOKUP(A6,NOMENCLATOR!$A:$E,3,0),"") -> EA | E6: =IFERROR(VLOOKUP(A6,NOMENCLATOR!$A:$E,4,0),"") -> 2.4 | F6: =IF(OR(C6="",E6=""),"",C6*E6) -> 2.4 | G6: =IFERROR(VLOOKUP(A6,NOMENCLATOR!$A:$E,5,0),"") -> 2.4 | H6: =IF(OR(C6="",G6=""),"",C6*G6) -> 2.4
A7: 7000210 | B7: =IFERROR(VLOOKUP(A7,NOMENCLATOR!$A:$E,2,0),"") -> PREP - smashed koliber 60G | C7: 1 | D7: =IFERROR(VLOOKUP(A7,NOMENCLATOR!$A:$E,3,0),"") -> EA | E7: =IFERROR(VLOOKUP(A7,NOMENCLATOR!$A:$E,4,0),"") -> 2.93233 | F7: =IF(OR(C7="",E7=""),"",C7*E7) -> 2.93233 | G7: =IFERROR(VLOOKUP(A7,NOMENCLATOR!$A:$E,5,0),"") -> 3.35 | H7: =IF(OR(C7="",G7=""),"",C7*G7) -> 3.35
A8: 700655 | B8: =IFERROR(VLOOKUP(A8,NOMENCLATOR!$A:$E,2,0),"") -> Hartie Little Hamburgers | C8: 1 | D8: =IFERROR(VLOOKUP(A8,NOMENCLATOR!$A:$E,3,0),"") -> EA | E8: =IFERROR(VLOOKUP(A8,NOMENCLATOR!$A:$E,4,0),"") -> 0.111 | F8: =IF(OR(C8="",E8=""),"",C8*E8) -> 0.111 | G8: =IFERROR(VLOOKUP(A8,NOMENCLATOR!$A:$E,5,0),"") -> 0.111 | H8: =IF(OR(C8="",G8=""),"",C8*G8) -> 0.111
A9: 702052 | B9: =IFERROR(VLOOKUP(A9,NOMENCLATOR!$A:$E,2,0),"") -> Ketchup Jerrycan Heinz 10.2L | C9: 10 | D9: =IFERROR(VLOOKUP(A9,NOMENCLATOR!$A:$E,3,0),"") -> ML | E9: =IFERROR(VLOOKUP(A9,NOMENCLATOR!$A:$E,4,0),"") -> 0.0221 | F9: =IF(OR(C9="",E9=""),"",C9*E9) -> 0.221 | G9: =IFERROR(VLOOKUP(A9,NOMENCLATOR!$A:$E,5,0),"") -> 0.0221 | H9: =IF(OR(C9="",G9=""),"",C9*G9) -> 0.221
A10: 702048 | B10: =IFERROR(VLOOKUP(A10,NOMENCLATOR!$A:$E,2,0),"") -> Mustar Heinz 875ml | C10: 0.7 | D10: =IFERROR(VLOOKUP(A10,NOMENCLATOR!$A:$E,3,0),"") -> ML | E10: =IFERROR(VLOOKUP(A10,NOMENCLATOR!$A:$E,4,0),"") -> 0.033 | F10: =IF(OR(C10="",E10=""),"",C10*E10) -> 0.0231 | G10: =IFERROR(VLOOKUP(A10,NOMENCLATOR!$A:$E,5,0),"") -> 0.033 | H10: =IF(OR(C10="",G10=""),"",C10*G10) -> 0.0231
A11: 702399 | B11: =IFERROR(VLOOKUP(A11,NOMENCLATOR!$A:$E,2,0),"") -> Y-Castraveti felii in saramura | C11: 2.8 | D11: =IFERROR(VLOOKUP(A11,NOMENCLATOR!$A:$E,3,0),"") -> GM | E11: =IFERROR(VLOOKUP(A11,NOMENCLATOR!$A:$E,4,0),"") -> 0.01554 | F11: =IF(OR(C11="",E11=""),"",C11*E11) -> 0.043512 | G11: =IFERROR(VLOOKUP(A11,NOMENCLATOR!$A:$E,5,0),"") -> 0.01554 | H11: =IF(OR(C11="",G11=""),"",C11*G11) -> 0.043512
A12: 7000142 | B12: =IFERROR(VLOOKUP(A12,NOMENCLATOR!$A:$E,2,0),"") -> Y - Ceapa Cuburi | C12: 5 | D12: =IFERROR(VLOOKUP(A12,NOMENCLATOR!$A:$E,3,0),"") -> GM | E12: =IFERROR(VLOOKUP(A12,NOMENCLATOR!$A:$E,4,0),"") -> 0.007 | F12: =IF(OR(C12="",E12=""),"",C12*E12) -> 0.035 | G12: =IFERROR(VLOOKUP(A12,NOMENCLATOR!$A:$E,5,0),"") -> 0.007 | H12: =IF(OR(C12="",G12=""),"",C12*G12) -> 0.035
A13: =IF(A4="","",A4) -> Single HAMBURGER | F13: =IF(A4="","",SUM(F6:F12)) -> 5.765942 | H13: =IF(A4="","",SUM(H6:H12)) -> 6.183612
A15: Single HAMBURGER D | F15: BURGER VITA
A16: COD | B16: INGREDIENT | C16: QTY | D16: UM | E16: COST/UM | F16: COST | G16: COST/UM NOU | H16: COST NOU
A17: 7000133 | B17: =IFERROR(VLOOKUP(A17,NOMENCLATOR!$A:$E,2,0),"") -> CHIFLA CARTOF 3.5inch 53G x 72 | C17: 1 | D17: =IFERROR(VLOOKUP(A17,NOMENCLATOR!$A:$E,3,0),"") -> EA | E17: =IFERROR(VLOOKUP(A17,NOMENCLATOR!$A:$E,4,0),"") -> 2.4 | F17: =IF(OR(C17="",E17=""),"",C17*E17) -> 2.4 | G17: =IFERROR(VLOOKUP(A17,NOMENCLATOR!$A:$E,5,0),"") -> 2.4 | H17: =IF(OR(C17="",G17=""),"",C17*G17) -> 2.4
A18: 7000210 | B18: =IFERROR(VLOOKUP(A18,NOMENCLATOR!$A:$E,2,0),"") -> PREP - smashed koliber 60G | C18: 1 | D18: =IFERROR(VLOOKUP(A18,NOMENCLATOR!$A:$E,3,0),"") -> EA | E18: =IFERROR(VLOOKUP(A18,NOMENCLATOR!$A:$E,4,0),"") -> 2.93233 | F18: =IF(OR(C18="",E18=""),"",C18*E18) -> 2.93233 | G18: =IFERROR(VLOOKUP(A18,NOMENCLATOR!$A:$E,5,0),"") -> 3.35 | H18: =IF(OR(C18="",G18=""),"",C18*G18) -> 3.35
A19: 700655 | B19: =IFERROR(VLOOKUP(A19,NOMENCLATOR!$A:$E,2,0),"") -> Hartie Little Hamburgers | C19: 1 | D19: =IFERROR(VLOOKUP(A19,NOMENCLATOR!$A:$E,3,0),"") -> EA | E19: =IFERROR(VLOOKUP(A19,NOMENCLATOR!$A:$E,4,0),"") -> 0.111 | F19: =IF(OR(C19="",E19=""),"",C19*E19) -> 0.111 | G19: =IFERROR(VLOOKUP(A19,NOMENCLATOR!$A:$E,5,0),"") -> 0.111 | H19: =IF(OR(C19="",G19=""),"",C19*G19) -> 0.111
A20: 702052 | B20: =IFERROR(VLOOKUP(A20,NOMENCLATOR!$A:$E,2,0),"") -> Ketchup Jerrycan Heinz 10.2L | C20: 10 | D20: =IFERROR(VLOOKUP(A20,NOMENCLATOR!$A:$E,3,0),"") -> ML | E20: =IFERROR(VLOOKUP(A20,NOMENCLATOR!$A:$E,4,0),"") -> 0.0221 | F20: =IF(OR(C20="",E20=""),"",C20*E20) -> 0.221 | G20: =IFERROR(VLOOKUP(A20,NOMENCLATOR!$A:$E,5,0),"") -> 0.0221 | H20: =IF(OR(C20="",G20=""),"",C20*G20) -> 0.221
A21: 702048 | B21: =IFERROR(VLOOKUP(A21,NOMENCLATOR!$A:$E,2,0),"") -> Mustar Heinz 875ml | C21: 0.7 | D21: =IFERROR(VLOOKUP(A21,NOMENCLATOR!$A:$E,3,0),"") -> ML | E21: =IFERROR(VLOOKUP(A21,NOMENCLATOR!$A:$E,4,0),"") -> 0.033 | F21: =IF(OR(C21="",E21=""),"",C21*E21) -> 0.0231 | G21: =IFERROR(VLOOKUP(A21,NOMENCLATOR!$A:$E,5,0),"") -> 0.033 | H21: =IF(OR(C21="",G21=""),"",C21*G21) -> 0.0231
A22: 702399 | B22: =IFERROR(VLOOKUP(A22,NOMENCLATOR!$A:$E,2,0),"") -> Y-Castraveti felii in saramura | C22: 2.8 | D22: =IFERROR(VLOOKUP(A22,NOMENCLATOR!$A:$E,3,0),"") -> GM | E22: =IFERROR(VLOOKUP(A22,NOMENCLATOR!$A:$E,4,0),"") -> 0.01554 | F22: =IF(OR(C22="",E22=""),"",C22*E22) -> 0.043512 | G22: =IFERROR(VLOOKUP(A22,NOMENCLATOR!$A:$E,5,0),"") -> 0.01554 | H22: =IF(OR(C22="",G22=""),"",C22*G22) -> 0.043512
A23: 7000142 | B23: =IFERROR(VLOOKUP(A23,NOMENCLATOR!$A:$E,2,0),"") -> Y - Ceapa Cuburi | C23: 5 | D23: =IFERROR(VLOOKUP(A23,NOMENCLATOR!$A:$E,3,0),"") -> GM | E23: =IFERROR(VLOOKUP(A23,NOMENCLATOR!$A:$E,4,0),"") -> 0.007 | F23: =IF(OR(C23="",E23=""),"",C23*E23) -> 0.035 | G23: =IFERROR(VLOOKUP(A23,NOMENCLATOR!$A:$E,5,0),"") -> 0.007 | H23: =IF(OR(C23="",G23=""),"",C23*G23) -> 0.035
A24: =IF(A15="","",A15) -> Single HAMBURGER D | F24: =IF(A15="","",SUM(F17:F23)) -> 5.765942 | H24: =IF(A15="","",SUM(H17:H23)) -> 6.183612
A26: DUBLU HAMBURGER new | F26: BURGER VITA
A27: COD | B27: INGREDIENT | C27: QTY | D27: UM | E27: COST/UM | F27: COST | G27: COST/UM NOU | H27: COST NOU
A28: 7000133 | B28: =IFERROR(VLOOKUP(A28,NOMENCLATOR!$A:$E,2,0),"") -> CHIFLA CARTOF 3.5inch 53G x 72 | C28: 1 | D28: =IFERROR(VLOOKUP(A28,NOMENCLATOR!$A:$E,3,0),"") -> EA | E28: =IFERROR(VLOOKUP(A28,NOMENCLATOR!$A:$E,4,0),"") -> 2.4 | F28: =IF(OR(C28="",E28=""),"",C28*E28) -> 2.4 | G28: =IFERROR(VLOOKUP(A28,NOMENCLATOR!$A:$E,5,0),"") -> 2.4 | H28: =IF(OR(C28="",G28=""),"",C28*G28) -> 2.4
A29: 7000210 | B29: =IFERROR(VLOOKUP(A29,NOMENCLATOR!$A:$E,2,0),"") -> PREP - smashed koliber 60G | C29: 2 | D29: =IFERROR(VLOOKUP(A29,NOMENCLATOR!$A:$E,3,0),"") -> EA | E29: =IFERROR(VLOOKUP(A29,NOMENCLATOR!$A:$E,4,0),"") -> 2.93233 | F29: =IF(OR(C29="",E29=""),"",C29*E29) -> 5.86466 | G29: =IFERROR(VLOOKUP(A29,NOMENCLATOR!$A:$E,5,0),"") -> 3.35 | H29: =IF(OR(C29="",G29=""),"",C29*G29) -> 6.7
A30: 7000140 | B30: =IFERROR(VLOOKUP(A30,NOMENCLATOR!$A:$E,2,0),"") -> HARTIE BURGER Doubles 12x12 AA13 | C30: 1 | D30: =IFERROR(VLOOKUP(A30,NOMENCLATOR!$A:$E,3,0),"") -> EA | E30: =IFERROR(VLOOKUP(A30,NOMENCLATOR!$A:$E,4,0),"") -> 0.111 | F30: =IF(OR(C30="",E30=""),"",C30*E30) -> 0.111 | G30: =IFERROR(VLOOKUP(A30,NOMENCLATOR!$A:$E,5,0),"") -> 0.111 | H30: =IF(OR(C30="",G30=""),"",C30*G30) -> 0.111
A31: 702052 | B31: =IFERROR(VLOOKUP(A31,NOMENCLATOR!$A:$E,2,0),"") -> Ketchup Jerrycan Heinz 10.2L | C31: 10 | D31: =IFERROR(VLOOKUP(A31,NOMENCLATOR!$A:$E,3,0),"") -> ML | E31: =IFERROR(VLOOKUP(A31,NOMENCLATOR!$A:$E,4,0),"") -> 0.0221 | F31: =IF(OR(C31="",E31=""),"",C31*E31) -> 0.221 | G31: =IFERROR(VLOOKUP(A31,NOMENCLATOR!$A:$E,5,0),"") -> 0.0221 | H31: =IF(OR(C31="",G31=""),"",C31*G31) -> 0.221
A32: 702048 | B32: =IFERROR(VLOOKUP(A32,NOMENCLATOR!$A:$E,2,0),"") -> Mustar Heinz 875ml | C32: 1.4 | D32: =IFERROR(VLOOKUP(A32,NOMENCLATOR!$A:$E,3,0),"") -> ML | E32: =IFERROR(VLOOKUP(A32,NOMENCLATOR!$A:$E,4,0),"") -> 0.033 | F32: =IF(OR(C32="",E32=""),"",C32*E32) -> 0.0462 | G32: =IFERROR(VLOOKUP(A32,NOMENCLATOR!$A:$E,5,0),"") -> 0.033 | H32: =IF(OR(C32="",G32=""),"",C32*G32) -> 0.0462
A33: 7000142 | B33: =IFERROR(VLOOKUP(A33,NOMENCLATOR!$A:$E,2,0),"") -> Y - Ceapa Cuburi | C33: 10 | D33: =IFERROR(VLOOKUP(A33,NOMENCLATOR!$A:$E,3,0),"") -> GM | E33: =IFERROR(VLOOKUP(A33,NOMENCLATOR!$A:$E,4,0),"") -> 0.007 | F33: =IF(OR(C33="",E33=""),"",C33*E33) -> 0.07 | G33: =IFERROR(VLOOKUP(A33,NOMENCLATOR!$A:$E,5,0),"") -> 0.007 | H33: =IF(OR(C33="",G33=""),"",C33*G33) -> 0.07
A34: 702399 | B34: =IFERROR(VLOOKUP(A34,NOMENCLATOR!$A:$E,2,0),"") -> Y-Castraveti felii in saramura | C34: 5.6 | D34: =IFERROR(VLOOKUP(A34,NOMENCLATOR!$A:$E,3,0),"") -> GM | E34: =IFERROR(VLOOKUP(A34,NOMENCLATOR!$A:$E,4,0),"") -> 0.01554 | F34: =IF(OR(C34="",E34=""),"",C34*E34) -> 0.087024 | G34: =IFERROR(VLOOKUP(A34,NOMENCLATOR!$A:$E,5,0),"") -> 0.01554 | H34: =IF(OR(C34="",G34=""),"",C34*G34) -> 0.087024
A35: =IF(A26="","",A26) -> DUBLU HAMBURGER new | F35: =IF(A26="","",SUM(F28:F34)) -> 8.799884 | H35: =IF(A26="","",SUM(H28:H34)) -> 9.635224
A37: DUBLU HAMBURGER new D | F37: BURGER VITA
A38: COD | B38: INGREDIENT | C38: QTY | D38: UM | E38: COST/UM | F38: COST | G38: COST/UM NOU | H38: COST NOU
A39: 7000133 | B39: =IFERROR(VLOOKUP(A39,NOMENCLATOR!$A:$E,2,0),"") -> CHIFLA CARTOF 3.5inch 53G x 72 | C39: 1 | D39: =IFERROR(VLOOKUP(A39,NOMENCLATOR!$A:$E,3,0),"") -> EA | E39: =IFERROR(VLOOKUP(A39,NOMENCLATOR!$A:$E,4,0),"") -> 2.4 | F39: =IF(OR(C39="",E39=""),"",C39*E39) -> 2.4 | G39: =IFERROR(VLOOKUP(A39,NOMENCLATOR!$A:$E,5,0),"") -> 2.4 | H39: =IF(OR(C39="",G39=""),"",C39*G39) -> 2.4
A40: 7000210 | B40: =IFERROR(VLOOKUP(A40,NOMENCLATOR!$A:$E,2,0),"") -> PREP - smashed koliber 60G | C40: 2 | D40: =IFERROR(VLOOKUP(A40,NOMENCLATOR!$A:$E,3,0),"") -> EA | E40: =IFERROR(VLOOKUP(A40,NOMENCLATOR!$A:$E,4,0),"") -> 2.93233 | F40: =IF(OR(C40="",E40=""),"",C40*E40) -> 5.86466 | G40: =IFERROR(VLOOKUP(A40,NOMENCLATOR!$A:$E,5,0),"") -> 3.35 | H40: =IF(OR(C40="",G40=""),"",C40*G40) -> 6.7
A41: 7000140 | B41: =IFERROR(VLOOKUP(A41,NOMENCLATOR!$A:$E,2,0),"") -> HARTIE BURGER Doubles 12x12 AA13 | C41: 1 | D41: =IFERROR(VLOOKUP(A41,NOMENCLATOR!$A:$E,3,0),"") -> EA | E41: =IFERROR(VLOOKUP(A41,NOMENCLATOR!$A:$E,4,0),"") -> 0.111 | F41: =IF(OR(C41="",E41=""),"",C41*E41) -> 0.111 | G41: =IFERROR(VLOOKUP(A41,NOMENCLATOR!$A:$E,5,0),"") -> 0.111 | H41: =IF(OR(C41="",G41=""),"",C41*G41) -> 0.111
A42: 702052 | B42: =IFERROR(VLOOKUP(A42,NOMENCLATOR!$A:$E,2,0),"") -> Ketchup Jerrycan Heinz 10.2L | C42: 10 | D42: =IFERROR(VLOOKUP(A42,NOMENCLATOR!$A:$E,3,0),"") -> ML | E42: =IFERROR(VLOOKUP(A42,NOMENCLATOR!$A:$E,4,0),"") -> 0.0221 | F42: =IF(OR(C42="",E42=""),"",C42*E42) -> 0.221 | G42: =IFERROR(VLOOKUP(A42,NOMENCLATOR!$A:$E,5,0),"") -> 0.0221 | H42: =IF(OR(C42="",G42=""),"",C42*G42) -> 0.221
A43: 702048 | B43: =IFERROR(VLOOKUP(A43,NOMENCLATOR!$A:$E,2,0),"") -> Mustar Heinz 875ml | C43: 1.4 | D43: =IFERROR(VLOOKUP(A43,NOMENCLATOR!$A:$E,3,0),"") -> ML | E43: =IFERROR(VLOOKUP(A43,NOMENCLATOR!$A:$E,4,0),"") -> 0.033 | F43: =IF(OR(C43="",E43=""),"",C43*E43) -> 0.0462 | G43: =IFERROR(VLOOKUP(A43,NOMENCLATOR!$A:$E,5,0),"") -> 0.033 | H43: =IF(OR(C43="",G43=""),"",C43*G43) -> 0.0462
A44: 7000142 | B44: =IFERROR(VLOOKUP(A44,NOMENCLATOR!$A:$E,2,0),"") -> Y - Ceapa Cuburi | C44: 10 | D44: =IFERROR(VLOOKUP(A44,NOMENCLATOR!$A:$E,3,0),"") -> GM | E44: =IFERROR(VLOOKUP(A44,NOMENCLATOR!$A:$E,4,0),"") -> 0.007 | F44: =IF(OR(C44="",E44=""),"",C44*E44) -> 0.07 | G44: =IFERROR(VLOOKUP(A44,NOMENCLATOR!$A:$E,5,0),"") -> 0.007 | H44: =IF(OR(C44="",G44=""),"",C44*G44) -> 0.07
A45: 702399 | B45: =IFERROR(VLOOKUP(A45,NOMENCLATOR!$A:$E,2,0),"") -> Y-Castraveti felii in saramura | C45: 5.6 | D45: =IFERROR(VLOOKUP(A45,NOMENCLATOR!$A:$E,3,0),"") -> GM | E45: =IFERROR(VLOOKUP(A45,NOMENCLATOR!$A:$E,4,0),"") -> 0.01554 | F45: =IF(OR(C45="",E45=""),"",C45*E45) -> 0.087024 | G45: =IFERROR(VLOOKUP(A45,NOMENCLATOR!$A:$E,5,0),"") -> 0.01554 | H45: =IF(OR(C45="",G45=""),"",C45*G45) -> 0.087024
A46: =IF(A37="","",A37) -> DUBLU HAMBURGER new D | F46: =IF(A37="","",SUM(F39:F45)) -> 8.799884 | H46: =IF(A37="","",SUM(H39:H45)) -> 9.635224
A48: CHEESEBURGER new | F48: BURGER VITA
A49: COD | B49: INGREDIENT | C49: QTY | D49: UM | E49: COST/UM | F49: COST | G49: COST/UM NOU | H49: COST NOU
A50: 7000133 | B50: =IFERROR(VLOOKUP(A50,NOMENCLATOR!$A:$E,2,0),"") -> CHIFLA CARTOF 3.5inch 53G x 72 | C50: 1 | D50: =IFERROR(VLOOKUP(A50,NOMENCLATOR!$A:$E,3,0),"") -> EA | E50: =IFERROR(VLOOKUP(A50,NOMENCLATOR!$A:$E,4,0),"") -> 2.4 | F50: =IF(OR(C50="",E50=""),"",C50*E50) -> 2.4 | G50: =IFERROR(VLOOKUP(A50,NOMENCLATOR!$A:$E,5,0),"") -> 2.4 | H50: =IF(OR(C50="",G50=""),"",C50*G50) -> 2.4
A51: 7000210 | B51: =IFERROR(VLOOKUP(A51,NOMENCLATOR!$A:$E,2,0),"") -> PREP - smashed koliber 60G | C51: 1 | D51: =IFERROR(VLOOKUP(A51,NOMENCLATOR!$A:$E,3,0),"") -> EA | E51: =IFERROR(VLOOKUP(A51,NOMENCLATOR!$A:$E,4,0),"") -> 2.93233 | F51: =IF(OR(C51="",E51=""),"",C51*E51) -> 2.93233 | G51: =IFERROR(VLOOKUP(A51,NOMENCLATOR!$A:$E,5,0),"") -> 3.35 | H51: =IF(OR(C51="",G51=""),"",C51*G51) -> 3.35
A52: 7000123 | B52: =IFERROR(VLOOKUP(A52,NOMENCLATOR!$A:$E,2,0),"") -> Branza cheddar felii 2026 | C52: 1 | D52: =IFERROR(VLOOKUP(A52,NOMENCLATOR!$A:$E,3,0),"") -> EA | E52: =IFERROR(VLOOKUP(A52,NOMENCLATOR!$A:$E,4,0),"") -> 0.61567 | F52: =IF(OR(C52="",E52=""),"",C52*E52) -> 0.61567 | G52: =IFERROR(VLOOKUP(A52,NOMENCLATOR!$A:$E,5,0),"") -> 0.61567 | H52: =IF(OR(C52="",G52=""),"",C52*G52) -> 0.61567
A53: 700655 | B53: =IFERROR(VLOOKUP(A53,NOMENCLATOR!$A:$E,2,0),"") -> Hartie Little Hamburgers | C53: 1 | D53: =IFERROR(VLOOKUP(A53,NOMENCLATOR!$A:$E,3,0),"") -> EA | E53: =IFERROR(VLOOKUP(A53,NOMENCLATOR!$A:$E,4,0),"") -> 0.111 | F53: =IF(OR(C53="",E53=""),"",C53*E53) -> 0.111 | G53: =IFERROR(VLOOKUP(A53,NOMENCLATOR!$A:$E,5,0),"") -> 0.111 | H53: =IF(OR(C53="",G53=""),"",C53*G53) -> 0.111
A54: 702052 | B54: =IFERROR(VLOOKUP(A54,NOMENCLATOR!$A:$E,2,0),"") -> Ketchup Jerrycan Heinz 10.2L | C54: 10 | D54: =IFERROR(VLOOKUP(A54,NOMENCLATOR!$A:$E,3,0),"") -> ML | E54: =IFERROR(VLOOKUP(A54,NOMENCLATOR!$A:$E,4,0),"") -> 0.0221 | F54: =IF(OR(C54="",E54=""),"",C54*E54) -> 0.221 | G54: =IFERROR(VLOOKUP(A54,NOMENCLATOR!$A:$E,5,0),"") -> 0.0221 | H54: =IF(OR(C54="",G54=""),"",C54*G54) -> 0.221
A55: 702048 | B55: =IFERROR(VLOOKUP(A55,NOMENCLATOR!$A:$E,2,0),"") -> Mustar Heinz 875ml | C55: 0.7 | D55: =IFERROR(VLOOKUP(A55,NOMENCLATOR!$A:$E,3,0),"") -> ML | E55: =IFERROR(VLOOKUP(A55,NOMENCLATOR!$A:$E,4,0),"") -> 0.033 | F55: =IF(OR(C55="",E55=""),"",C55*E55) -> 0.0231 | G55: =IFERROR(VLOOKUP(A55,NOMENCLATOR!$A:$E,5,0),"") -> 0.033 | H55: =IF(OR(C55="",G55=""),"",C55*G55) -> 0.0231
A56: 7000142 | B56: =IFERROR(VLOOKUP(A56,NOMENCLATOR!$A:$E,2,0),"") -> Y - Ceapa Cuburi | C56: 5 | D56: =IFERROR(VLOOKUP(A56,NOMENCLATOR!$A:$E,3,0),"") -> GM | E56: =IFERROR(VLOOKUP(A56,NOMENCLATOR!$A:$E,4,0),"") -> 0.007 | F56: =IF(OR(C56="",E56=""),"",C56*E56) -> 0.035 | G56: =IFERROR(VLOOKUP(A56,NOMENCLATOR!$A:$E,5,0),"") -> 0.007 | H56: =IF(OR(C56="",G56=""),"",C56*G56) -> 0.035
A57: 702399 | B57: =IFERROR(VLOOKUP(A57,NOMENCLATOR!$A:$E,2,0),"") -> Y-Castraveti felii in saramura | C57: 2.8 | D57: =IFERROR(VLOOKUP(A57,NOMENCLATOR!$A:$E,3,0),"") -> GM | E57: =IFERROR(VLOOKUP(A57,NOMENCLATOR!$A:$E,4,0),"") -> 0.01554 | F57: =IF(OR(C57="",E57=""),"",C57*E57) -> 0.043512 | G57: =IFERROR(VLOOKUP(A57,NOMENCLATOR!$A:$E,5,0),"") -> 0.01554 | H57: =IF(OR(C57="",G57=""),"",C57*G57) -> 0.043512
A58: =IF(A48="","",A48) -> CHEESEBURGER new | F58: =IF(A48="","",SUM(F50:F57)) -> 6.381612 | H58: =IF(A48="","",SUM(H50:H57)) -> 6.799282
A60: CHEESEBURGER new D | F60: BURGER VITA
A61: COD | B61: INGREDIENT | C61: QTY | D61: UM | E61: COST/UM | F61: COST | G61: COST/UM NOU | H61: COST NOU
A62: 7000133 | B62: =IFERROR(VLOOKUP(A62,NOMENCLATOR!$A:$E,2,0),"") -> CHIFLA CARTOF 3.5inch 53G x 72 | C62: 1 | D62: =IFERROR(VLOOKUP(A62,NOMENCLATOR!$A:$E,3,0),"") -> EA | E62: =IFERROR(VLOOKUP(A62,NOMENCLATOR!$A:$E,4,0),"") -> 2.4 | F62: =IF(OR(C62="",E62=""),"",C62*E62) -> 2.4 | G62: =IFERROR(VLOOKUP(A62,NOMENCLATOR!$A:$E,5,0),"") -> 2.4 | H62: =IF(OR(C62="",G62=""),"",C62*G62) -> 2.4
A63: 7000210 | B63: =IFERROR(VLOOKUP(A63,NOMENCLATOR!$A:$E,2,0),"") -> PREP - smashed koliber 60G | C63: 1 | D63: =IFERROR(VLOOKUP(A63,NOMENCLATOR!$A:$E,3,0),"") -> EA | E63: =IFERROR(VLOOKUP(A63,NOMENCLATOR!$A:$E,4,0),"") -> 2.93233 | F63: =IF(OR(C63="",E63=""),"",C63*E63) -> 2.93233 | G63: =IFERROR(VLOOKUP(A63,NOMENCLATOR!$A:$E,5,0),"") -> 3.35 | H63: =IF(OR(C63="",G63=""),"",C63*G63) -> 3.35
A64: 7000123 | B64: =IFERROR(VLOOKUP(A64,NOMENCLATOR!$A:$E,2,0),"") -> Branza cheddar felii 2026 | C64: 1 | D64: =IFERROR(VLOOKUP(A64,NOMENCLATOR!$A:$E,3,0),"") -> EA | E64: =IFERROR(VLOOKUP(A64,NOMENCLATOR!$A:$E,4,0),"") -> 0.61567 | F64: =IF(OR(C64="",E64=""),"",C64*E64) -> 0.61567 | G64: =IFERROR(VLOOKUP(A64,NOMENCLATOR!$A:$E,5,0),"") -> 0.61567 | H64: =IF(OR(C64="",G64=""),"",C64*G64) -> 0.61567
A65: 700655 | B65: =IFERROR(VLOOKUP(A65,NOMENCLATOR!$A:$E,2,0),"") -> Hartie Little Hamburgers | C65: 1 | D65: =IFERROR(VLOOKUP(A65,NOMENCLATOR!$A:$E,3,0),"") -> EA | E65: =IFERROR(VLOOKUP(A65,NOMENCLATOR!$A:$E,4,0),"") -> 0.111 | F65: =IF(OR(C65="",E65=""),"",C65*E65) -> 0.111 | G65: =IFERROR(VLOOKUP(A65,NOMENCLATOR!$A:$E,5,0),"") -> 0.111 | H65: =IF(OR(C65="",G65=""),"",C65*G65) -> 0.111
A66: 702052 | B66: =IFERROR(VLOOKUP(A66,NOMENCLATOR!$A:$E,2,0),"") -> Ketchup Jerrycan Heinz 10.2L | C66: 10 | D66: =IFERROR(VLOOKUP(A66,NOMENCLATOR!$A:$E,3,0),"") -> ML | E66: =IFERROR(VLOOKUP(A66,NOMENCLATOR!$A:$E,4,0),"") -> 0.0221 | F66: =IF(OR(C66="",E66=""),"",C66*E66) -> 0.221 | G66: =IFERROR(VLOOKUP(A66,NOMENCLATOR!$A:$E,5,0),"") -> 0.0221 | H66: =IF(OR(C66="",G66=""),"",C66*G66) -> 0.221
A67: 702048 | B67: =IFERROR(VLOOKUP(A67,NOMENCLATOR!$A:$E,2,0),"") -> Mustar Heinz 875ml | C67: 0.7 | D67: =IFERROR(VLOOKUP(A67,NOMENCLATOR!$A:$E,3,0),"") -> ML | E67: =IFERROR(VLOOKUP(A67,NOMENCLATOR!$A:$E,4,0),"") -> 0.033 | F67: =IF(OR(C67="",E67=""),"",C67*E67) -> 0.0231 | G67: =IFERROR(VLOOKUP(A67,NOMENCLATOR!$A:$E,5,0),"") -> 0.033 | H67: =IF(OR(C67="",G67=""),"",C67*G67) -> 0.0231
A68: 7000142 | B68: =IFERROR(VLOOKUP(A68,NOMENCLATOR!$A:$E,2,0),"") -> Y - Ceapa Cuburi | C68: 5 | D68: =IFERROR(VLOOKUP(A68,NOMENCLATOR!$A:$E,3,0),"") -> GM | E68: =IFERROR(VLOOKUP(A68,NOMENCLATOR!$A:$E,4,0),"") -> 0.007 | F68: =IF(OR(C68="",E68=""),"",C68*E68) -> 0.035 | G68: =IFERROR(VLOOKUP(A68,NOMENCLATOR!$A:$E,5,0),"") -> 0.007 | H68: =IF(OR(C68="",G68=""),"",C68*G68) -> 0.035
A69: 702399 | B69: =IFERROR(VLOOKUP(A69,NOMENCLATOR!$A:$E,2,0),"") -> Y-Castraveti felii in saramura | C69: 2.8 | D69: =IFERROR(VLOOKUP(A69,NOMENCLATOR!$A:$E,3,0),"") -> GM | E69: =IFERROR(VLOOKUP(A69,NOMENCLATOR!$A:$E,4,0),"") -> 0.01554 | F69: =IF(OR(C69="",E69=""),"",C69*E69) -> 0.043512 | G69: =IFERROR(VLOOKUP(A69,NOMENCLATOR!$A:$E,5,0),"") -> 0.01554 | H69: =IF(OR(C69="",G69=""),"",C69*G69) -> 0.043512
A70: =IF(A60="","",A60) -> CHEESEBURGER new D | F70: =IF(A60="","",SUM(F62:F69)) -> 6.381612 | H70: =IF(A60="","",SUM(H62:H69)) -> 6.799282
A72: DUBLU CHEESEBURGER new | F72: BURGER VITA
A73: COD | B73: INGREDIENT | C73: QTY | D73: UM | E73: COST/UM | F73: COST | G73: COST/UM NOU | H73: COST NOU
A74: 7000133 | B74: =IFERROR(VLOOKUP(A74,NOMENCLATOR!$A:$E,2,0),"") -> CHIFLA CARTOF 3.5inch 53G x 72 | C74: 1 | D74: =IFERROR(VLOOKUP(A74,NOMENCLATOR!$A:$E,3,0),"") -> EA | E74: =IFERROR(VLOOKUP(A74,NOMENCLATOR!$A:$E,4,0),"") -> 2.4 | F74: =IF(OR(C74="",E74=""),"",C74*E74) -> 2.4 | G74: =IFERROR(VLOOKUP(A74,NOMENCLATOR!$A:$E,5,0),"") -> 2.4 | H74: =IF(OR(C74="",G74=""),"",C74*G74) -> 2.4
A75: 7000210 | B75: =IFERROR(VLOOKUP(A75,NOMENCLATOR!$A:$E,2,0),"") -> PREP - smashed koliber 60G | C75: 2 | D75: =IFERROR(VLOOKUP(A75,NOMENCLATOR!$A:$E,3,0),"") -> EA | E75: =IFERROR(VLOOKUP(A75,NOMENCLATOR!$A:$E,4,0),"") -> 2.93233 | F75: =IF(OR(C75="",E75=""),"",C75*E75) -> 5.86466 | G75: =IFERROR(VLOOKUP(A75,NOMENCLATOR!$A:$E,5,0),"") -> 3.35 | H75: =IF(OR(C75="",G75=""),"",C75*G75) -> 6.7
A76: 7000123 | B76: =IFERROR(VLOOKUP(A76,NOMENCLATOR!$A:$E,2,0),"") -> Branza cheddar felii 2026 | C76: 2 | D76: =IFERROR(VLOOKUP(A76,NOMENCLATOR!$A:$E,3,0),"") -> EA | E76: =IFERROR(VLOOKUP(A76,NOMENCLATOR!$A:$E,4,0),"") -> 0.61567 | F76: =IF(OR(C76="",E76=""),"",C76*E76) -> 1.23134 | G76: =IFERROR(VLOOKUP(A76,NOMENCLATOR!$A:$E,5,0),"") -> 0.61567 | H76: =IF(OR(C76="",G76=""),"",C76*G76) -> 1.23134
A77: 7000140 | B77: =IFERROR(VLOOKUP(A77,NOMENCLATOR!$A:$E,2,0),"") -> HARTIE BURGER Doubles 12x12 AA13 | C77: 1 | D77: =IFERROR(VLOOKUP(A77,NOMENCLATOR!$A:$E,3,0),"") -> EA | E77: =IFERROR(VLOOKUP(A77,NOMENCLATOR!$A:$E,4,0),"") -> 0.111 | F77: =IF(OR(C77="",E77=""),"",C77*E77) -> 0.111 | G77: =IFERROR(VLOOKUP(A77,NOMENCLATOR!$A:$E,5,0),"") -> 0.111 | H77: =IF(OR(C77="",G77=""),"",C77*G77) -> 0.111
A78: 702052 | B78: =IFERROR(VLOOKUP(A78,NOMENCLATOR!$A:$E,2,0),"") -> Ketchup Jerrycan Heinz 10.2L | C78: 10 | D78: =IFERROR(VLOOKUP(A78,NOMENCLATOR!$A:$E,3,0),"") -> ML | E78: =IFERROR(VLOOKUP(A78,NOMENCLATOR!$A:$E,4,0),"") -> 0.0221 | F78: =IF(OR(C78="",E78=""),"",C78*E78) -> 0.221 | G78: =IFERROR(VLOOKUP(A78,NOMENCLATOR!$A:$E,5,0),"") -> 0.0221 | H78: =IF(OR(C78="",G78=""),"",C78*G78) -> 0.221
A79: 702048 | B79: =IFERROR(VLOOKUP(A79,NOMENCLATOR!$A:$E,2,0),"") -> Mustar Heinz 875ml | C79: 1.4 | D79: =IFERROR(VLOOKUP(A79,NOMENCLATOR!$A:$E,3,0),"") -> ML | E79: =IFERROR(VLOOKUP(A79,NOMENCLATOR!$A:$E,4,0),"") -> 0.033 | F79: =IF(OR(C79="",E79=""),"",C79*E79) -> 0.0462 | G79: =IFERROR(VLOOKUP(A79,NOMENCLATOR!$A:$E,5,0),"") -> 0.033 | H79: =IF(OR(C79="",G79=""),"",C79*G79) -> 0.0462
A80: 7000142 | B80: =IFERROR(VLOOKUP(A80,NOMENCLATOR!$A:$E,2,0),"") -> Y - Ceapa Cuburi | C80: 10 | D80: =IFERROR(VLOOKUP(A80,NOMENCLATOR!$A:$E,3,0),"") -> GM | E80: =IFERROR(VLOOKUP(A80,NOMENCLATOR!$A:$E,4,0),"") -> 0.007 | F80: =IF(OR(C80="",E80=""),"",C80*E80) -> 0.07 | G80: =IFERROR(VLOOKUP(A80,NOMENCLATOR!$A:$E,5,0),"") -> 0.007 | H80: =IF(OR(C80="",G80=""),"",C80*G80) -> 0.07
A81: 702399 | B81: =IFERROR(VLOOKUP(A81,NOMENCLATOR!$A:$E,2,0),"") -> Y-Castraveti felii in saramura | C81: 5.6 | D81: =IFERROR(VLOOKUP(A81,NOMENCLATOR!$A:$E,3,0),"") -> GM | E81: =IFERROR(VLOOKUP(A81,NOMENCLATOR!$A:$E,4,0),"") -> 0.01554 | F81: =IF(OR(C81="",E81=""),"",C81*E81) -> 0.087024 | G81: =IFERROR(VLOOKUP(A81,NOMENCLATOR!$A:$E,5,0),"") -> 0.01554 | H81: =IF(OR(C81="",G81=""),"",C81*G81) -> 0.087024
A82: =IF(A72="","",A72) -> DUBLU CHEESEBURGER new | F82: =IF(A72="","",SUM(F74:F81)) -> 10.031224 | H82: =IF(A72="","",SUM(H74:H81)) -> 10.866564
A84: DUBLU CHEESEBURGER new D | F84: BURGER VITA
A85: COD | B85: INGREDIENT | C85: QTY | D85: UM | E85: COST/UM | F85: COST | G85: COST/UM NOU | H85: COST NOU
A86: 7000133 | B86: =IFERROR(VLOOKUP(A86,NOMENCLATOR!$A:$E,2,0),"") -> CHIFLA CARTOF 3.5inch 53G x 72 | C86: 1 | D86: =IFERROR(VLOOKUP(A86,NOMENCLATOR!$A:$E,3,0),"") -> EA | E86: =IFERROR(VLOOKUP(A86,NOMENCLATOR!$A:$E,4,0),"") -> 2.4 | F86: =IF(OR(C86="",E86=""),"",C86*E86) -> 2.4 | G86: =IFERROR(VLOOKUP(A86,NOMENCLATOR!$A:$E,5,0),"") -> 2.4 | H86: =IF(OR(C86="",G86=""),"",C86*G86) -> 2.4
A87: 7000210 | B87: =IFERROR(VLOOKUP(A87,NOMENCLATOR!$A:$E,2,0),"") -> PREP - smashed koliber 60G | C87: 2 | D87: =IFERROR(VLOOKUP(A87,NOMENCLATOR!$A:$E,3,0),"") -> EA | E87: =IFERROR(VLOOKUP(A87,NOMENCLATOR!$A:$E,4,0),"") -> 2.93233 | F87: =IF(OR(C87="",E87=""),"",C87*E87) -> 5.86466 | G87: =IFERROR(VLOOKUP(A87,NOMENCLATOR!$A:$E,5,0),"") -> 3.35 | H87: =IF(OR(C87="",G87=""),"",C87*G87) -> 6.7
A88: 7000123 | B88: =IFERROR(VLOOKUP(A88,NOMENCLATOR!$A:$E,2,0),"") -> Branza cheddar felii 2026 | C88: 2 | D88: =IFERROR(VLOOKUP(A88,NOMENCLATOR!$A:$E,3,0),"") -> EA | E88: =IFERROR(VLOOKUP(A88,NOMENCLATOR!$A:$E,4,0),"") -> 0.61567 | F88: =IF(OR(C88="",E88=""),"",C88*E88) -> 1.23134 | G88: =IFERROR(VLOOKUP(A88,NOMENCLATOR!$A:$E,5,0),"") -> 0.61567 | H88: =IF(OR(C88="",G88=""),"",C88*G88) -> 1.23134
A89: 7000140 | B89: =IFERROR(VLOOKUP(A89,NOMENCLATOR!$A:$E,2,0),"") -> HARTIE BURGER Doubles 12x12 AA13 | C89: 1 | D89: =IFERROR(VLOOKUP(A89,NOMENCLATOR!$A:$E,3,0),"") -> EA | E89: =IFERROR(VLOOKUP(A89,NOMENCLATOR!$A:$E,4,0),"") -> 0.111 | F89: =IF(OR(C89="",E89=""),"",C89*E89) -> 0.111 | G89: =IFERROR(VLOOKUP(A89,NOMENCLATOR!$A:$E,5,0),"") -> 0.111 | H89: =IF(OR(C89="",G89=""),"",C89*G89) -> 0.111
A90: 702052 | B90: =IFERROR(VLOOKUP(A90,NOMENCLATOR!$A:$E,2,0),"") -> Ketchup Jerrycan Heinz 10.2L | C90: 10 | D90: =IFERROR(VLOOKUP(A90,NOMENCLATOR!$A:$E,3,0),"") -> ML | E90: =IFERROR(VLOOKUP(A90,NOMENCLATOR!$A:$E,4,0),"") -> 0.0221 | F90: =IF(OR(C90="",E90=""),"",C90*E90) -> 0.221 | G90: =IFERROR(VLOOKUP(A90,NOMENCLATOR!$A:$E,5,0),"") -> 0.0221 | H90: =IF(OR(C90="",G90=""),"",C90*G90) -> 0.221
A91: 702048 | B91: =IFERROR(VLOOKUP(A91,NOMENCLATOR!$A:$E,2,0),"") -> Mustar Heinz 875ml | C91: 1.4 | D91: =IFERROR(VLOOKUP(A91,NOMENCLATOR!$A:$E,3,0),"") -> ML | E91: =IFERROR(VLOOKUP(A91,NOMENCLATOR!$A:$E,4,0),"") -> 0.033 | F91: =IF(OR(C91="",E91=""),"",C91*E91) -> 0.0462 | G91: =IFERROR(VLOOKUP(A91,NOMENCLATOR!$A:$E,5,0),"") -> 0.033 | H91: =IF(OR(C91="",G91=""),"",C91*G91) -> 0.0462
A92: 7000142 | B92: =IFERROR(VLOOKUP(A92,NOMENCLATOR!$A:$E,2,0),"") -> Y - Ceapa Cuburi | C92: 10 | D92: =IFERROR(VLOOKUP(A92,NOMENCLATOR!$A:$E,3,0),"") -> GM | E92: =IFERROR(VLOOKUP(A92,NOMENCLATOR!$A:$E,4,0),"") -> 0.007 | F92: =IF(OR(C92="",E92=""),"",C92*E92) -> 0.07 | G92: =IFERROR(VLOOKUP(A92,NOMENCLATOR!$A:$E,5,0),"") -> 0.007 | H92: =IF(OR(C92="",G92=""),"",C92*G92) -> 0.07
A93: 702399 | B93: =IFERROR(VLOOKUP(A93,NOMENCLATOR!$A:$E,2,0),"") -> Y-Castraveti felii in saramura | C93: 5.6 | D93: =IFERROR(VLOOKUP(A93,NOMENCLATOR!$A:$E,3,0),"") -> GM | E93: =IFERROR(VLOOKUP(A93,NOMENCLATOR!$A:$E,4,0),"") -> 0.01554 | F93: =IF(OR(C93="",E93=""),"",C93*E93) -> 0.087024 | G93: =IFERROR(VLOOKUP(A93,NOMENCLATOR!$A:$E,5,0),"") -> 0.01554 | H93: =IF(OR(C93="",G93=""),"",C93*G93) -> 0.087024
A94: =IF(A84="","",A84) -> DUBLU CHEESEBURGER new D | F94: =IF(A84="","",SUM(F86:F93)) -> 10.031224 | H94: =IF(A84="","",SUM(H86:H93)) -> 10.866564
A96: AMERICAN CHEESEBURGER new | F96: BURGER VITA
A97: COD | B97: INGREDIENT | C97: QTY | D97: UM | E97: COST/UM | F97: COST | G97: COST/UM NOU | H97: COST NOU
A98: 7000133 | B98: =IFERROR(VLOOKUP(A98,NOMENCLATOR!$A:$E,2,0),"") -> CHIFLA CARTOF 3.5inch 53G x 72 | C98: 1 | D98: =IFERROR(VLOOKUP(A98,NOMENCLATOR!$A:$E,3,0),"") -> EA | E98: =IFERROR(VLOOKUP(A98,NOMENCLATOR!$A:$E,4,0),"") -> 2.4 | F98: =IF(OR(C98="",E98=""),"",C98*E98) -> 2.4 | G98: =IFERROR(VLOOKUP(A98,NOMENCLATOR!$A:$E,5,0),"") -> 2.4 | H98: =IF(OR(C98="",G98=""),"",C98*G98) -> 2.4
A99: 7000210 | B99: =IFERROR(VLOOKUP(A99,NOMENCLATOR!$A:$E,2,0),"") -> PREP - smashed koliber 60G | C99: 1 | D99: =IFERROR(VLOOKUP(A99,NOMENCLATOR!$A:$E,3,0),"") -> EA | E99: =IFERROR(VLOOKUP(A99,NOMENCLATOR!$A:$E,4,0),"") -> 2.93233 | F99: =IF(OR(C99="",E99=""),"",C99*E99) -> 2.93233 | G99: =IFERROR(VLOOKUP(A99,NOMENCLATOR!$A:$E,5,0),"") -> 3.35 | H99: =IF(OR(C99="",G99=""),"",C99*G99) -> 3.35
A100: 7000123 | B100: =IFERROR(VLOOKUP(A100,NOMENCLATOR!$A:$E,2,0),"") -> Branza cheddar felii 2026 | C100: 1 | D100: =IFERROR(VLOOKUP(A100,NOMENCLATOR!$A:$E,3,0),"") -> EA | E100: =IFERROR(VLOOKUP(A100,NOMENCLATOR!$A:$E,4,0),"") -> 0.61567 | F100: =IF(OR(C100="",E100=""),"",C100*E100) -> 0.61567 | G100: =IFERROR(VLOOKUP(A100,NOMENCLATOR!$A:$E,5,0),"") -> 0.61567 | H100: =IF(OR(C100="",G100=""),"",C100*G100) -> 0.61567
A101: 7000141 | B101: =IFERROR(VLOOKUP(A101,NOMENCLATOR!$A:$E,2,0),"") -> HARTIE AMERICAN CHEESBURGER 12X12 AA14 | C101: 1 | D101: =IFERROR(VLOOKUP(A101,NOMENCLATOR!$A:$E,3,0),"") -> EA | E101: =IFERROR(VLOOKUP(A101,NOMENCLATOR!$A:$E,4,0),"") -> 0.111 | F101: =IF(OR(C101="",E101=""),"",C101*E101) -> 0.111 | G101: =IFERROR(VLOOKUP(A101,NOMENCLATOR!$A:$E,5,0),"") -> 0.111 | H101: =IF(OR(C101="",G101=""),"",C101*G101) -> 0.111
A102: =IF(A96="","",A96) -> AMERICAN CHEESEBURGER new | F102: =IF(A96="","",SUM(F98:F101)) -> 6.059 | H102: =IF(A96="","",SUM(H98:H101)) -> 6.47667
A104: AMERICAN CHEESEBURGER new D | F104: BURGER VITA
A105: COD | B105: INGREDIENT | C105: QTY | D105: UM | E105: COST/UM | F105: COST | G105: COST/UM NOU | H105: COST NOU
A106: 7000133 | B106: =IFERROR(VLOOKUP(A106,NOMENCLATOR!$A:$E,2,0),"") -> CHIFLA CARTOF 3.5inch 53G x 72 | C106: 1 | D106: =IFERROR(VLOOKUP(A106,NOMENCLATOR!$A:$E,3,0),"") -> EA | E106: =IFERROR(VLOOKUP(A106,NOMENCLATOR!$A:$E,4,0),"") -> 2.4 | F106: =IF(OR(C106="",E106=""),"",C106*E106) -> 2.4 | G106: =IFERROR(VLOOKUP(A106,NOMENCLATOR!$A:$E,5,0),"") -> 2.4 | H106: =IF(OR(C106="",G106=""),"",C106*G106) -> 2.4
A107: 7000210 | B107: =IFERROR(VLOOKUP(A107,NOMENCLATOR!$A:$E,2,0),"") -> PREP - smashed koliber 60G | C107: 1 | D107: =IFERROR(VLOOKUP(A107,NOMENCLATOR!$A:$E,3,0),"") -> EA | E107: =IFERROR(VLOOKUP(A107,NOMENCLATOR!$A:$E,4,0),"") -> 2.93233 | F107: =IF(OR(C107="",E107=""),"",C107*E107) -> 2.93233 | G107: =IFERROR(VLOOKUP(A107,NOMENCLATOR!$A:$E,5,0),"") -> 3.35 | H107: =IF(OR(C107="",G107=""),"",C107*G107) -> 3.35
A108: 7000123 | B108: =IFERROR(VLOOKUP(A108,NOMENCLATOR!$A:$E,2,0),"") -> Branza cheddar felii 2026 | C108: 1 | D108: =IFERROR(VLOOKUP(A108,NOMENCLATOR!$A:$E,3,0),"") -> EA | E108: =IFERROR(VLOOKUP(A108,NOMENCLATOR!$A:$E,4,0),"") -> 0.61567 | F108: =IF(OR(C108="",E108=""),"",C108*E108) -> 0.61567 | G108: =IFERROR(VLOOKUP(A108,NOMENCLATOR!$A:$E,5,0),"") -> 0.61567 | H108: =IF(OR(C108="",G108=""),"",C108*G108) -> 0.61567
A109: 7000141 | B109: =IFERROR(VLOOKUP(A109,NOMENCLATOR!$A:$E,2,0),"") -> HARTIE AMERICAN CHEESBURGER 12X12 AA14 | C109: 1 | D109: =IFERROR(VLOOKUP(A109,NOMENCLATOR!$A:$E,3,0),"") -> EA | E109: =IFERROR(VLOOKUP(A109,NOMENCLATOR!$A:$E,4,0),"") -> 0.111 | F109: =IF(OR(C109="",E109=""),"",C109*E109) -> 0.111 | G109: =IFERROR(VLOOKUP(A109,NOMENCLATOR!$A:$E,5,0),"") -> 0.111 | H109: =IF(OR(C109="",G109=""),"",C109*G109) -> 0.111
A110: =IF(A104="","",A104) -> AMERICAN CHEESEBURGER new D | F110: =IF(A104="","",SUM(F106:F109)) -> 6.059 | H110: =IF(A104="","",SUM(H106:H109)) -> 6.47667
...

Sheet FOOD COST
A1: FOOD COST — MC actual + MC NOU (koliber 3.35) | Instore + Delivery
A2: Δ Aug/Oct/Dec (N-P, albastru) = majorările EDITABILE. Preț lună = I + Δ cumulat. FC NOU = MC nou / preț fără TVA.
A4: Denumire comercială | B4: Rețetă (Recipe Cards) | C4: Categorie | D4: Canal | E4: Tip TVA | F4: TVA % | G4: MC actual | H4: MC NOU | I4: Preț cu TVA | J4: Preț fără TVA | K4: FC actual % | L4: FC NOU % | M4: Note | N4: Δ Aug (major.) | O4: Δ Oct (major.) | P4: Δ Dec (major.) | Q4: Preț Aug cu TVA | R4: Preț Aug fără TVA | S4: FC NOU Aug % | T4: Preț Oct cu TVA | U4: Preț Oct fără TVA | V4: FC NOU Oct % | W4: Preț Dec cu TVA | X4: Preț Dec fără TVA | Y4: FC NOU Dec %
A5: HAMBURGER | B5: Single HAMBURGER | C5: BURGER VITA | D5: Instore | E5: FOOD | F5: =IF(E5="","",IF(E5="DRINKS",0.21,0.11)) -> 0.11 | G5: =IF(B5="","",SUMIF(RETETAR!A:A,B5,RETETAR!F:F)) -> 5.765942 | H5: =IF(B5="","",SUMIF(RETETAR!A:A,B5,RETETAR!H:H)) -> 6.183612 | I5: 8 | J5: =IF(OR(I5="",F5=""),"",I5/(1+F5)) -> 7.2072072 | K5: =IF(OR(G5="",G5=0,J5="",J5=0),"",G5/J5) -> 0.80002445 | L5: =IF(OR(H5="",H5=0,J5="",J5=0),"",H5/J5) -> 0.85797616 | N5: 0 | O5: 0.49 | P5: 0.5 | Q5: =IF(I5="","",I5+N(N5)) -> 8 | R5: =IF(OR(Q5="",F5=""),"",Q5/(1+F5)) -> 7.2072072 | S5: =IF(OR(H5="",H5=0,R5="",R5=0),"",H5/R5) -> 0.85797616 | T5: =IF(I5="","",I5+N(N5+O5)) -> 8.49 | U5: =IF(OR(T5="",F5=""),"",T5/(1+F5)) -> 7.6486486 | V5: =IF(OR(H5="",H5=0,U5="",U5=0),"",H5/U5) -> 0.80845811 | W5: =IF(I5="","",I5+N(N5+O5+P5)) -> 8.99 | X5: =IF(OR(W5="",F5=""),"",W5/(1+F5)) -> 8.0990991 | Y5: =IF(OR(H5="",H5=0,X5="",X5=0),"",H5/X5) -> 0.76349381
A6: HAMBURGER D | B6: Single HAMBURGER D | C6: BURGER VITA | D6: Delivery | E6: FOOD | F6: =IF(E6="","",IF(E6="DRINKS",0.21,0.11)) -> 0.11 | G6: =IF(B6="","",SUMIF(RETETAR!A:A,B6,RETETAR!F:F)) -> 5.765942 | H6: =IF(B6="","",SUMIF(RETETAR!A:A,B6,RETETAR!H:H)) -> 6.183612 | I6: 10 | J6: =IF(OR(I6="",F6=""),"",I6/(1+F6)) -> 9.009009 | K6: =IF(OR(G6="",G6=0,J6="",J6=0),"",G6/J6) -> 0.64001956 | L6: =IF(OR(H6="",H6=0,J6="",J6=0),"",H6/J6) -> 0.68638093 | N6: 0 | O6: 0.49 | P6: 0.5 | Q6: =IF(I6="","",I6+N(N6)) -> 10 | R6: =IF(OR(Q6="",F6=""),"",Q6/(1+F6)) -> 9.009009 | S6: =IF(OR(H6="",H6=0,R6="",R6=0),"",H6/R6) -> 0.68638093 | T6: =IF(I6="","",I6+N(N6+O6)) -> 10.49 | U6: =IF(OR(T6="",F6=""),"",T6/(1+F6)) -> 9.4504505 | V6: =IF(OR(H6="",H6=0,U6="",U6=0),"",H6/U6) -> 0.65431929 | W6: =IF(I6="","",I6+N(N6+O6+P6)) -> 10.99 | X6: =IF(OR(W6="",F6=""),"",W6/(1+F6)) -> 9.9009009 | Y6: =IF(OR(H6="",H6=0,X6="",X6=0),"",H6/X6) -> 0.62455044
A7: DUBLU HAMBURGER | B7: DUBLU HAMBURGER new | C7: BURGER VITA | D7: Instore | E7: FOOD | F7: =IF(E7="","",IF(E7="DRINKS",0.21,0.11)) -> 0.11 | G7: =IF(B7="","",SUMIF(RETETAR!A:A,B7,RETETAR!F:F)) -> 8.799884 | H7: =IF(B7="","",SUMIF(RETETAR!A:A,B7,RETETAR!H:H)) -> 9.635224 | I7: 14 | J7: =IF(OR(I7="",F7=""),"",I7/(1+F7)) -> 12.612613 | K7: =IF(OR(G7="",G7=0,J7="",J7=0),"",G7/J7) -> 0.69770509 | L7: =IF(OR(H7="",H7=0,J7="",J7=0),"",H7/J7) -> 0.76393562 | N7: 0.99 | O7: 0 | P7: 0.5 | Q7: =IF(I7="","",I7+N(N7)) -> 14.99 | R7: =IF(OR(Q7="",F7=""),"",Q7/(1+F7)) -> 13.504505 | S7: =IF(OR(H7="",H7=0,R7="",R7=0),"",H7/R7) -> 0.71348223 | T7: =IF(I7="","",I7+N(N7+O7)) -> 14.99 | U7: =IF(OR(T7="",F7=""),"",T7/(1+F7)) -> 13.504505 | V7: =IF(OR(H7="",H7=0,U7="",U7=0),"",H7/U7) -> 0.71348223 | W7: =IF(I7="","",I7+N(N7+O7+P7)) -> 15.49 | X7: =IF(OR(W7="",F7=""),"",W7/(1+F7)) -> 13.954955 | Y7: =IF(OR(H7="",H7=0,X7="",X7=0),"",H7/X7) -> 0.69045182
A8: DUBLU HAMBURGER D | B8: DUBLU HAMBURGER new D | C8: BURGER VITA | D8: Delivery | E8: FOOD | F8: =IF(E8="","",IF(E8="DRINKS",0.21,0.11)) -> 0.11 | G8: =IF(B8="","",SUMIF(RETETAR!A:A,B8,RETETAR!F:F)) -> 8.799884 | H8: =IF(B8="","",SUMIF(RETETAR!A:A,B8,RETETAR!H:H)) -> 9.635224 | I8: 16 | J8: =IF(OR(I8="",F8=""),"",I8/(1+F8)) -> 14.414414 | K8: =IF(OR(G8="",G8=0,J8="",J8=0),"",G8/J8) -> 0.61049195 | L8: =IF(OR(H8="",H8=0,J8="",J8=0),"",H8/J8) -> 0.66844366 | N8: 0.99 | O8: 0 | P8: 0.5 | Q8: =IF(I8="","",I8+N(N8)) -> 16.99 | R8: =IF(OR(Q8="",F8=""),"",Q8/(1+F8)) -> 15.306306 | S8: =IF(OR(H8="",H8=0,R8="",R8=0),"",H8/R8) -> 0.62949374 | T8: =IF(I8="","",I8+N(N8+O8)) -> 16.99 | U8: =IF(OR(T8="",F8=""),"",T8/(1+F8)) -> 15.306306 | V8: =IF(OR(H8="",H8=0,U8="",U8=0),"",H8/U8) -> 0.62949374 | W8: =IF(I8="","",I8+N(N8+O8+P8)) -> 17.49 | X8: =IF(OR(W8="",F8=""),"",W8/(1+F8)) -> 15.756757 | Y8: =IF(OR(H8="",H8=0,X8="",X8=0),"",H8/X8) -> 0.61149792
A9: CHEESEBURGER | B9: CHEESEBURGER new | C9: BURGER VITA | D9: Instore | E9: FOOD | F9: =IF(E9="","",IF(E9="DRINKS",0.21,0.11)) -> 0.11 | G9: =IF(B9="","",SUMIF(RETETAR!A:A,B9,RETETAR!F:F)) -> 6.381612 | H9: =IF(B9="","",SUMIF(RETETAR!A:A,B9,RETETAR!H:H)) -> 6.799282 | I9: 11 | J9: =IF(OR(I9="",F9=""),"",I9/(1+F9)) -> 9.9099099 | K9: =IF(OR(G9="",G9=0,J9="",J9=0),"",G9/J9) -> 0.64396267 | L9: =IF(OR(H9="",H9=0,J9="",J9=0),"",H9/J9) -> 0.68610937 | N9: 0.49 | O9: 0 | P9: 0.5 | Q9: =IF(I9="","",I9+N(N9)) -> 11.49 | R9: =IF(OR(Q9="",F9=""),"",Q9/(1+F9)) -> 10.351351 | S9: =IF(OR(H9="",H9=0,R9="",R9=0),"",H9/R9) -> 0.6568497 | T9: =IF(I9="","",I9+N(N9+O9)) -> 11.49 | U9: =IF(OR(T9="",F9=""),"",T9/(1+F9)) -> 10.351351 | V9: =IF(OR(H9="",H9=0,U9="",U9=0),"",H9/U9) -> 0.6568497 | W9: =IF(I9="","",I9+N(N9+O9+P9)) -> 11.99 | X9: =IF(OR(W9="",F9=""),"",W9/(1+F9)) -> 10.801802 | Y9: =IF(OR(H9="",H9=0,X9="",X9=0),"",H9/X9) -> 0.62945813
A10: CHEESEBURGER D | B10: CHEESEBURGER new D | C10: BURGER VITA | D10: Delivery | E10: FOOD | F10: =IF(E10="","",IF(E10="DRINKS",0.21,0.11)) -> 0.11 | G10: =IF(B10="","",SUMIF(RETETAR!A:A,B10,RETETAR!F:F)) -> 6.381612 | H10: =IF(B10="","",SUMIF(RETETAR!A:A,B10,RETETAR!H:H)) -> 6.799282 | I10: 13 | J10: =IF(OR(I10="",F10=""),"",I10/(1+F10)) -> 11.711712 | K10: =IF(OR(G10="",G10=0,J10="",J10=0),"",G10/J10) -> 0.54489149 | L10: =IF(OR(H10="",H10=0,J10="",J10=0),"",H10/J10) -> 0.58055408 | N10: 0.49 | O10: 0 | P10: 0.5 | Q10: =IF(I10="","",I10+N(N10)) -> 13.49 | R10: =IF(OR(Q10="",F10=""),"",Q10/(1+F10)) -> 12.153153 | S10: =IF(OR(H10="",H10=0,R10="",R10=0),"",H10/R10) -> 0.5594665 | T10: =IF(I10="","",I10+N(N10+O10)) -> 13.49 | U10: =IF(OR(T10="",F10=""),"",T10/(1+F10)) -> 12.153153 | V10: =IF(OR(H10="",H10=0,U10="",U10=0),"",H10/U10) -> 0.5594665 | W10: =IF(I10="","",I10+N(N10+O10+P10)) -> 13.99 | X10: =IF(OR(W10="",F10=""),"",W10/(1+F10)) -> 12.603604 | Y10: =IF(OR(H10="",H10=0,X10="",X10=0),"",H10/X10) -> 0.53947127
A11: DUBLU CHEESEBURGER | B11: DUBLU CHEESEBURGER new | C11: BURGER VITA | D11: Instore | E11: FOOD | F11: =IF(E11="","",IF(E11="DRINKS",0.21,0.11)) -> 0.11 | G11: =IF(B11="","",SUMIF(RETETAR!A:A,B11,RETETAR!F:F)) -> 10.031224 | H11: =IF(B11="","",SUMIF(RETETAR!A:A,B11,RETETAR!H:H)) -> 10.866564 | I11: 17 | J11: =IF(OR(I11="",F11=""),"",I11/(1+F11)) -> 15.315315 | K11: =IF(OR(G11="",G11=0,J11="",J11=0),"",G11/J11) -> 0.65497992 | L11: =IF(OR(H11="",H11=0,J11="",J11=0),"",H11/J11) -> 0.70952271 | N11: 0.99 | O11: 0 | P11: 0.5 | Q11: =IF(I11="","",I11+N(N11)) -> 17.99 | R11: =IF(OR(Q11="",F11=""),"",Q11/(1+F11)) -> 16.207207 | S11: =IF(OR(H11="",H11=0,R11="",R11=0),"",H11/R11) -> 0.67047727 | T11: =IF(I11="","",I11+N(N11+O11)) -> 17.99 | U11: =IF(OR(T11="",F11=""),"",T11/(1+F11)) -> 16.207207 | V11: =IF(OR(H11="",H11=0,U11="",U11=0),"",H11/U11) -> 0.67047727 | W11: =IF(I11="","",I11+N(N11+O11+P11)) -> 18.49 | X11: =IF(OR(W11="",F11=""),"",W11/(1+F11)) -> 16.657658 | Y11: =IF(OR(H11="",H11=0,X11="",X11=0),"",H11/X11) -> 0.65234646
A12: DUBLU CHEESEBURGER D | B12: DUBLU CHEESEBURGER new D | C12: BURGER VITA | D12: Delivery | E12: FOOD | F12: =IF(E12="","",IF(E12="DRINKS",0.21,0.11)) -> 0.11 | G12: =IF(B12="","",SUMIF(RETETAR!A:A,B12,RETETAR!F:F)) -> 10.031224 | H12: =IF(B12="","",SUMIF(RETETAR!A:A,B12,RETETAR!H:H)) -> 10.866564 | I12: 19 | J12: =IF(OR(I12="",F12=""),"",I12/(1+F12)) -> 17.117117 | K12: =IF(OR(G12="",G12=0,J12="",J12=0),"",G12/J12) -> 0.58603467 | L12: =IF(OR(H12="",H12=0,J12="",J12=0),"",H12/J12) -> 0.63483611 | N12: 0.99 | O12: 0 | P12: 0.5 | Q12: =IF(I12="","",I12+N(N12)) -> 19.99 | R12: =IF(OR(Q12="",F12=""),"",Q12/(1+F12)) -> 18.009009 | S12: =IF(OR(H12="",H12=0,R12="",R12=0),"",H12/R12) -> 0.603396 | T12: =IF(I12="","",I12+N(N12+O12)) -> 19.99 | U12: =IF(OR(T12="",F12=""),"",T12/(1+F12)) -> 18.009009 | V12: =IF(OR(H12="",H12=0,U12="",U12=0),"",H12/U12) -> 0.603396 | W12: =IF(I12="","",I12+N(N12+O12+P12)) -> 20.49 | X12: =IF(OR(W12="",F12=""),"",W12/(1+F12)) -> 18.459459 | Y12: =IF(OR(H12="",H12=0,X12="",X12=0),"",H12/X12) -> 0.58867184
A13: AMERICAN CHEESEBURGER | B13: AMERICAN CHEESEBURGER new | C13: BURGER VITA | D13: Instore | E13: FOOD | F13: =IF(E13="","",IF(E13="DRINKS",0.21,0.11)) -> 0.11 | G13: =IF(B13="","",SUMIF(RETETAR!A:A,B13,RETETAR!F:F)) -> 6.059 | H13: =IF(B13="","",SUMIF(RETETAR!A:A,B13,RETETAR!H:H)) -> 6.47667 | I13: 10 | J13: =IF(OR(I13="",F13=""),"",I13/(1+F13)) -> 9.009009 | K13: =IF(OR(G13="",G13=0,J13="",J13=0),"",G13/J13) -> 0.672549 | L13: =IF(OR(H13="",H13=0,J13="",J13=0),"",H13/J13) -> 0.71891037 | N13: 0 | O13: 0.49 | P13: 0.5 | Q13: =IF(I13="","",I13+N(N13)) -> 10 | R13: =IF(OR(Q13="",F13=""),"",Q13/(1+F13)) -> 9.009009 | S13: =IF(OR(H13="",H13=0,R13="",R13=0),"",H13/R13) -> 0.71891037 | T13: =IF(I13="","",I13+N(N13+O13)) -> 10.49 | U13: =IF(OR(T13="",F13=""),"",T13/(1+F13)) -> 9.4504505 | V13: =IF(OR(H13="",H13=0,U13="",U13=0),"",H13/U13) -> 0.68532924 | W13: =IF(I13="","",I13+N(N13+O13+P13)) -> 10.99 | X13: =IF(OR(W13="",F13=""),"",W13/(1+F13)) -> 9.9009009 | Y13: =IF(OR(H13="",H13=0,X13="",X13=0),"",H13/X13) -> 0.65414956
A14: AMERICAN CHEESEBURGER D | B14: AMERICAN CHEESEBURGER new D | C14: BURGER VITA | D14: Delivery | E14: FOOD | F14: =IF(E14="","",IF(E14="DRINKS",0.21,0.11)) -> 0.11 | G14: =IF(B14="","",SUMIF(RETETAR!A:A,B14,RETETAR!F:F)) -> 6.059 | H14: =IF(B14="","",SUMIF(RETETAR!A:A,B14,RETETAR!H:H)) -> 6.47667 | I14: 13 | J14: =IF(OR(I14="",F14=""),"",I14/(1+F14)) -> 11.711712 | K14: =IF(OR(G14="",G14=0,J14="",J14=0),"",G14/J14) -> 0.51734538 | L14: =IF(OR(H14="",H14=0,J14="",J14=0),"",H14/J14) -> 0.55300798 | N14: 0 | O14: 0.49 | P14: 0.5 | Q14: =IF(I14="","",I14+N(N14)) -> 13 | R14: =IF(OR(Q14="",F14=""),"",Q14/(1+F14)) -> 11.711712 | S14: =IF(OR(H14="",H14=0,R14="",R14=0),"",H14/R14) -> 0.55300798 | T14: =IF(I14="","",I14+N(N14+O14)) -> 13.49 | U14: =IF(OR(T14="",F14=""),"",T14/(1+F14)) -> 12.153153 | V14: =IF(OR(H14="",H14=0,U14="",U14=0),"",H14/U14) -> 0.53292096 | W14: =IF(I14="","",I14+N(N14+O14+P14)) -> 13.99 | X14: =IF(OR(W14="",F14=""),"",W14/(1+F14)) -> 12.603604 | Y14: =IF(OR(H14="",H14=0,X14="",X14=0),"",H14/X14) -> 0.51387446
A15: AMERICAN DUBLU CHEESEBURGER | B15: AMERICAN DUBLU CHEESEBURGER new | C15: BURGER VITA | D15: Instore | E15: FOOD | F15: =IF(E15="","",IF(E15="DRINKS",0.21,0.11)) -> 0.11 | G15: =IF(B15="","",SUMIF(RETETAR!A:A,B15,RETETAR!F:F)) -> 9.607 | H15: =IF(B15="","",SUMIF(RETETAR!A:A,B15,RETETAR!H:H)) -> 10.44234 | I15: 16 | J15: =IF(OR(I15="",F15=""),"",I15/(1+F15)) -> 14.414414 | K15: =IF(OR(G15="",G15=0,J15="",J15=0),"",G15/J15) -> 0.66648562 | L15: =IF(OR(H15="",H15=0,J15="",J15=0),"",H15/J15) -> 0.72443734 | N15: 0 | O15: 0.99 | P15: 0.5 | Q15: =IF(I15="","",I15+N(N15)) -> 16 | R15: =IF(OR(Q15="",F15=""),"",Q15/(1+F15)) -> 14.414414 | S15: =IF(OR(H15="",H15=0,R15="",R15=0),"",H15/R15) -> 0.72443734 | T15: =IF(I15="","",I15+N(N15+O15)) -> 16.99 | U15: =IF(OR(T15="",F15=""),"",T15/(1+F15)) -> 15.306306 | V15: =IF(OR(H15="",H15=0,U15="",U15=0),"",H15/U15) -> 0.68222469 | W15: =IF(I15="","",I15+N(N15+O15+P15)) -> 17.49 | X15: =IF(OR(W15="",F15=""),"",W15/(1+F15)) -> 15.756757 | Y15: =IF(OR(H15="",H15=0,X15="",X15=0),"",H15/X15) -> 0.66272141
A16: AMERICAN DUBLU CHEESEBURGER D | B16: AMERICAN DUBLU CHEESEBURGER new D | C16: BURGER VITA | D16: Delivery | E16: FOOD | F16: =IF(E16="","",IF(E16="DRINKS",0.21,0.11)) -> 0.11 | G16: =IF(B16="","",SUMIF(RETETAR!A:A,B16,RETETAR!F:F)) -> 9.607 | H16: =IF(B16="","",SUMIF(RETETAR!A:A,B16,RETETAR!H:H)) -> 10.44234 | I16: 19 | J16: =IF(OR(I16="",F16=""),"",I16/(1+F16)) -> 17.117117 | K16: =IF(OR(G16="",G16=0,J16="",J16=0),"",G16/J16) -> 0.56125105 | L16: =IF(OR(H16="",H16=0,J16="",J16=0),"",H16/J16) -> 0.61005249 | N16: 0 | O16: 0.99 | P16: 0.5 | Q16: =IF(I16="","",I16+N(N16)) -> 19 | R16: =IF(OR(Q16="",F16=""),"",Q16/(1+F16)) -> 17.117117 | S16: =IF(OR(H16="",H16=0,R16="",R16=0),"",H16/R16) -> 0.61005249 | T16: =IF(I16="","",I16+N(N16+O16)) -> 19.99 | U16: =IF(OR(T16="",F16=""),"",T16/(1+F16)) -> 18.009009 | V16: =IF(OR(H16="",H16=0,U16="",U16=0),"",H16/U16) -> 0.57983979 | W16: =IF(I16="","",I16+N(N16+O16+P16)) -> 20.49 | X16: =IF(OR(W16="",F16=""),"",W16/(1+F16)) -> 18.459459 | Y16: =IF(OR(H16="",H16=0,X16="",X16=0),"",H16/X16) -> 0.56569045
... A101: PACK COUNTRY HOT WINGS 30 (1050G) D | B101: PACK COUNTRY HOT WINGS 30 (990G) new D | C101: FRIED CHICKEN | D101: Delivery | E101: FOOD | F101: =IF(E101="","",IF(E101="DRINKS",0.21,0.11)) -> 0.11 | G101: =IF(B101="","",SUMIF(RETETAR!A:A,B101,RETETAR!F:F)) -> 49.4189 | H101: =IF(B101="","",SUMIF(RETETAR!A:A,B101,RETETAR!H:H)) -> 49.4189 | I101: 120 | J101: =IF(OR(I101="",F101=""),"",I101/(1+F101)) -> 108.10811 | K101: =IF(OR(G101="",G101=0,J101="",J101=0),"",G101/J101) -> 0.45712483 | L101: =IF(OR(H101="",H101=0,J101="",J101=0),"",H101/J101) -> 0.45712483 | N101: 0.99 | O101: 0 | P101: 0 | Q101: =IF(I101="","",I101+N(N101)) -> 120.99 | R101: =IF(OR(Q101="",F101=""),"",Q101/(1+F101)) -> 109 | S101: =IF(OR(H101="",H101=0,R101="",R101=0),"",H101/R101) -> 0.4533844 | T101: =IF(I101="","",I101+N(N101+O101)) -> 120.99 | U101: =IF(OR(T101="",F101=""),"",T101/(1+F101)) -> 109 | V101: =IF(OR(H101="",H101=0,U101="",U101=0),"",H101/U101) -> 0.4533844 | W101: =IF(I101="","",I101+N(N101+O101+P101)) -> 120.99 | X101: =IF(OR(W101="",F101=""),"",W101/(1+F101)) -> 109 | Y101: =IF(OR(H101="",H101=0,X101="",X101=0),"",H101/X101) -> 0.4533844
A102: REALLY CRUNCHY FRIES 170G | B102: REALLY CRUNCHY FRIES 170G | C102: FRIES | D102: Instore | E102: FOOD | F102: =IF(E102="","",IF(E102="DRINKS",0.21,0.11)) -> 0.11 | G102: =IF(B102="","",SUMIF(RETETAR!A:A,B102,RETETAR!F:F)) -> 3.784852 | H102: =IF(B102="","",SUMIF(RETETAR!A:A,B102,RETETAR!H:H)) -> 3.784852 | I102: 11.9 | J102: =IF(OR(I102="",F102=""),"",I102/(1+F102)) -> 10.720721 | K102: =IF(OR(G102="",G102=0,J102="",J102=0),"",G102/J102) -> 0.35304082 | L102: =IF(OR(H102="",H102=0,J102="",J102=0),"",H102/J102) -> 0.35304082 | M102: acesta se va activa pe delivery cand se termina ambalajele 112/150/250-revin cu cr | N102: 0.25 | O102: 0.25 | P102: 0.49 | Q102: =IF(I102="","",I102+N(N102)) -> 12.15 | R102: =IF(OR(Q102="",F102=""),"",Q102/(1+F102)) -> 10.945946 | S102: =IF(OR(H102="",H102=0,R102="",R102=0),"",H102/R102) -> 0.3457766 | T102: =IF(I102="","",I102+N(N102+O102)) -> 12.4 | U102: =IF(OR(T102="",F102=""),"",T102/(1+F102)) -> 11.171171 | V102: =IF(OR(H102="",H102=0,U102="",U102=0),"",H102/U102) -> 0.3388053 | W102: =IF(I102="","",I102+N(N102+O102+P102)) -> 12.89 | X102: =IF(OR(W102="",F102=""),"",W102/(1+F102)) -> 11.612613 | Y102: =IF(OR(H102="",H102=0,X102="",X102=0),"",H102/X102) -> 0.32592597
A103: CARTOFI CRISS CUT 140G | B103: CARTOFI CRISS CUT 140G new | C103: FRIES | D103: Instore | E103: FOOD | F103: =IF(E103="","",IF(E103="DRINKS",0.21,0.11)) -> 0.11 | G103: =IF(B103="","",SUMIF(RETETAR!A:A,B103,RETETAR!F:F)) -> 4.207672 | H103: =IF(B103="","",SUMIF(RETETAR!A:A,B103,RETETAR!H:H)) -> 4.207672 | I103: 15 | J103: =IF(OR(I103="",F103=""),"",I103/(1+F103)) -> 13.513514 | K103: =IF(OR(G103="",G103=0,J103="",J103=0),"",G103/J103) -> 0.31136773 | L103: =IF(OR(H103="",H103=0,J103="",J103=0),"",H103/J103) -> 0.31136773 | M103: acesta se va lansa in 30 mai -revin cu cr de listare | N103: 0.25 | O103: 0.25 | P103: 0.49 | Q103: =IF(I103="","",I103+N(N103)) -> 15.25 | R103: =IF(OR(Q103="",F103=""),"",Q103/(1+F103)) -> 13.738739 | S103: =IF(OR(H103="",H103=0,R103="",R103=0),"",H103/R103) -> 0.30626334 | T103: =IF(I103="","",I103+N(N103+O103)) -> 15.5 | U103: =IF(OR(T103="",F103=""),"",T103/(1+F103)) -> 13.963964 | V103: =IF(OR(H103="",H103=0,U103="",U103=0),"",H103/U103) -> 0.30132361 | W103: =IF(I103="","",I103+N(N103+O103+P103)) -> 15.99 | X103: =IF(OR(W103="",F103=""),"",W103/(1+F103)) -> 14.405405 | Y103: =IF(OR(H103="",H103=0,X103="",X103=0),"",H103/X103) -> 0.2920898
A104: CARTOFI CRISS CUT 140G D | B104: CARTOFI CRISS CUT D | C104: FRIES | D104: Delivery | E104: FOOD | F104: =IF(E104="","",IF(E104="DRINKS",0.21,0.11)) -> 0.11 | G104: =IF(B104="","",SUMIF(RETETAR!A:A,B104,RETETAR!F:F)) -> 4.2076889 | H104: =IF(B104="","",SUMIF(RETETAR!A:A,B104,RETETAR!H:H)) -> 4.2076889 | I104: 13.65 | J104: =IF(OR(I104="",F104=""),"",I104/(1+F104)) -> 12.297297 | K104: =IF(OR(G104="",G104=0,J104="",J104=0),"",G104/J104) -> 0.34216371 | L104: =IF(OR(H104="",H104=0,J104="",J104=0),"",H104/J104) -> 0.34216371 | N104: 0.25 | O104: 0.25 | P104: 0.49 | Q104: =IF(I104="","",I104+N(N104)) -> 13.9 | R104: =IF(OR(Q104="",F104=""),"",Q104/(1+F104)) -> 12.522523 | S104: =IF(OR(H104="",H104=0,R104="",R104=0),"",H104/R104) -> 0.33600969 | T104: =IF(I104="","",I104+N(N104+O104)) -> 14.15 | U104: =IF(OR(T104="",F104=""),"",T104/(1+F104)) -> 12.747748 | V104: =IF(OR(H104="",H104=0,U104="",U104=0),"",H104/U104) -> 0.33007312 | W104: =IF(I104="","",I104+N(N104+O104+P104)) -> 14.64 | X104: =IF(OR(W104="",F104=""),"",W104/(1+F104)) -> 13.189189 | Y104: =IF(OR(H104="",H104=0,X104="",X104=0),"",H104/X104) -> 0.31902559
A105: Cartofi prajiti in ulei de alune 112g D | B105: Cartofi prajiti in ulei de alune 112g D New | C105: FRIES | D105: Delivery | E105: FOOD | F105: =IF(E105="","",IF(E105="DRINKS",0.21,0.11)) -> 0.11 | G105: =IF(B105="","",SUMIF(RETETAR!A:A,B105,RETETAR!F:F)) -> 2.3752 | H105: =IF(B105="","",SUMIF(RETETAR!A:A,B105,RETETAR!H:H)) -> 2.3752 | I105: 13.99 | J105: =IF(OR(I105="",F105=""),"",I105/(1+F105)) -> 12.603604 | K105: =IF(OR(G105="",G105=0,J105="",J105=0),"",G105/J105) -> 0.18845404 | L105: =IF(OR(H105="",H105=0,J105="",J105=0),"",H105/J105) -> 0.18845404 | N105: 0.25 | O105: 0.25 | P105: 0.49 | Q105: =IF(I105="","",I105+N(N105)) -> 14.24 | R105: =IF(OR(Q105="",F105=""),"",Q105/(1+F105)) -> 12.828829 | S105: =IF(OR(H105="",H105=0,R105="",R105=0),"",H105/R105) -> 0.18514551 | T105: =IF(I105="","",I105+N(N105+O105)) -> 14.49 | U105: =IF(OR(T105="",F105=""),"",T105/(1+F105)) -> 13.054054 | V105: =IF(OR(H105="",H105=0,U105="",U105=0),"",H105/U105) -> 0.18195114 | W105: =IF(I105="","",I105+N(N105+O105+P105)) -> 14.98 | X105: =IF(OR(W105="",F105=""),"",W105/(1+F105)) -> 13.495495 | Y105: =IF(OR(H105="",H105=0,X105="",X105=0),"",H105/X105) -> 0.17599947
A106: Cartofi prajiti in ulei de alune 150g D | B106: Cartofi prajiti in ulei de alune 150g D New | C106: FRIES | D106: Delivery | E106: FOOD | F106: =IF(E106="","",IF(E106="DRINKS",0.21,0.11)) -> 0.11 | G106: =IF(B106="","",SUMIF(RETETAR!A:A,B106,RETETAR!F:F)) -> 4.65138 | H106: =IF(B106="","",SUMIF(RETETAR!A:A,B106,RETETAR!H:H)) -> 4.65138 | I106: 15.99 | J106: =IF(OR(I106="",F106=""),"",I106/(1+F106)) -> 14.405405 | K106: =IF(OR(G106="",G106=0,J106="",J106=0),"",G106/J106) -> 0.32289129 | L106: =IF(OR(H106="",H106=0,J106="",J106=0),"",H106/J106) -> 0.32289129 | N106: 0.25 | O106: 0.25 | P106: 0.49 | Q106: =IF(I106="","",I106+N(N106)) -> 16.24 | R106: =IF(OR(Q106="",F106=""),"",Q106/(1+F106)) -> 14.630631 | S106: =IF(OR(H106="",H106=0,R106="",R106=0),"",H106/R106) -> 0.31792068 | T106: =IF(I106="","",I106+N(N106+O106)) -> 16.49 | U106: =IF(OR(T106="",F106=""),"",T106/(1+F106)) -> 14.855856 | V106: =IF(OR(H106="",H106=0,U106="",U106=0),"",H106/U106) -> 0.31310078 | W106: =IF(I106="","",I106+N(N106+O106+P106)) -> 16.98 | X106: =IF(OR(W106="",F106=""),"",W106/(1+F106)) -> 15.297297 | Y106: =IF(OR(H106="",H106=0,X106="",X106=0),"",H106/X106) -> 0.30406548
A107: Cartofi prajiti in ulei de alune SuperSize 250g D | B107: Cartofi prajiti in ulei de alune SuperSize 250g D New | C107: FRIES | D107: Delivery | E107: FOOD | F107: =IF(E107="","",IF(E107="DRINKS",0.21,0.11)) -> 0.11 | G107: =IF(B107="","",SUMIF(RETETAR!A:A,B107,RETETAR!F:F)) -> 5.25982 | H107: =IF(B107="","",SUMIF(RETETAR!A:A,B107,RETETAR!H:H)) -> 5.25982 | I107: 22.99 | J107: =IF(OR(I107="",F107=""),"",I107/(1+F107)) -> 20.711712 | K107: =IF(OR(G107="",G107=0,J107="",J107=0),"",G107/J107) -> 0.2539539 | L107: =IF(OR(H107="",H107=0,J107="",J107=0),"",H107/J107) -> 0.2539539 | N107: 0.25 | O107: 0.25 | P107: 0.49 | Q107: =IF(I107="","",I107+N(N107)) -> 23.24 | R107: =IF(OR(Q107="",F107=""),"",Q107/(1+F107)) -> 20.936937 | S107: =IF(OR(H107="",H107=0,R107="",R107=0),"",H107/R107) -> 0.25122204 | T107: =IF(I107="","",I107+N(N107+O107)) -> 23.49 | U107: =IF(OR(T107="",F107=""),"",T107/(1+F107)) -> 21.162162 | V107: =IF(OR(H107="",H107=0,U107="",U107=0),"",H107/U107) -> 0.24854833 | W107: =IF(I107="","",I107+N(N107+O107+P107)) -> 23.98 | X107: =IF(OR(W107="",F107=""),"",W107/(1+F107)) -> 21.603604 | Y107: =IF(OR(H107="",H107=0,X107="",X107=0),"",H107/X107) -> 0.24346957
A108: MAC & CHEESY BITES | B108: MAC & CHEESY BITES NEW | C108: SNACK | D108: Instore | E108: FOOD | F108: =IF(E108="","",IF(E108="DRINKS",0.21,0.11)) -> 0.11 | G108: =IF(B108="","",SUMIF(RETETAR!A:A,B108,RETETAR!F:F)) -> 5.82192 | H108: =IF(B108="","",SUMIF(RETETAR!A:A,B108,RETETAR!H:H)) -> 5.82192 | I108: 16.5 | J108: =IF(OR(I108="",F108=""),"",I108/(1+F108)) -> 14.864865 | K108: =IF(OR(G108="",G108=0,J108="",J108=0),"",G108/J108) -> 0.39165644 | L108: =IF(OR(H108="",H108=0,J108="",J108=0),"",H108/J108) -> 0.39165644 | N108: 0 | O108: 0 | P108: 0 | Q108: =IF(I108="","",I108+N(N108)) -> 16.5 | R108: =IF(OR(Q108="",F108=""),"",Q108/(1+F108)) -> 14.864865 | S108: =IF(OR(H108="",H108=0,R108="",R108=0),"",H108/R108) -> 0.39165644 | T108: =IF(I108="","",I108+N(N108+O108)) -> 16.5 | U108: =IF(OR(T108="",F108=""),"",T108/(1+F108)) -> 14.864865 | V108: =IF(OR(H108="",H108=0,U108="",U108=0),"",H108/U108) -> 0.39165644 | W108: =IF(I108="","",I108+N(N108+O108+P108)) -> 16.5 | X108: =IF(OR(W108="",F108=""),"",W108/(1+F108)) -> 14.864865 | Y108: =IF(OR(H108="",H108=0,X108="",X108=0),"",H108/X108) -> 0.39165644
A109: MAC & CHEESY BITES D | B109: MAC & CHEESY BITES NEW D | C109: SNACK | D109: Delivery | E109: FOOD | F109: =IF(E109="","",IF(E109="DRINKS",0.21,0.11)) -> 0.11 | G109: =IF(B109="","",SUMIF(RETETAR!A:A,B109,RETETAR!F:F)) -> 5.82192 | H109: =IF(B109="","",SUMIF(RETETAR!A:A,B109,RETETAR!H:H)) -> 5.82192 | I109: 16.5 | J109: =IF(OR(I109="",F109=""),"",I109/(1+F109)) -> 14.864865 | K109: =IF(OR(G109="",G109=0,J109="",J109=0),"",G109/J109) -> 0.39165644 | L109: =IF(OR(H109="",H109=0,J109="",J109=0),"",H109/J109) -> 0.39165644 | N109: 0 | O109: 0 | P109: 0 | Q109: =IF(I109="","",I109+N(N109)) -> 16.5 | R109: =IF(OR(Q109="",F109=""),"",Q109/(1+F109)) -> 14.864865 | S109: =IF(OR(H109="",H109=0,R109="",R109=0),"",H109/R109) -> 0.39165644 | T109: =IF(I109="","",I109+N(N109+O109)) -> 16.5 | U109: =IF(OR(T109="",F109=""),"",T109/(1+F109)) -> 14.864865 | V109: =IF(OR(H109="",H109=0,U109="",U109=0),"",H109/U109) -> 0.39165644 | W109: =IF(I109="","",I109+N(N109+O109+P109)) -> 16.5 | X109: =IF(OR(W109="",F109=""),"",W109/(1+F109)) -> 14.864865 | Y109: =IF(OR(H109="",H109=0,X109="",X109=0),"",H109/X109) -> 0.39165644
A110: SALATA COLESLAW | B110: SALATA COLESLAW NEW | C110: SNACK | D110: Instore | E110: FOOD | F110: =IF(E110="","",IF(E110="DRINKS",0.21,0.11)) -> 0.11 | G110: =IF(B110="","",SUMIF(RETETAR!A:A,B110,RETETAR!F:F)) -> 3.5025 | H110: =IF(B110="","",SUMIF(RETETAR!A:A,B110,RETETAR!H:H)) -> 3.5025 | I110: 10 | J110: =IF(OR(I110="",F110=""),"",I110/(1+F110)) -> 9.009009 | K110: =IF(OR(G110="",G110=0,J110="",J110=0),"",G110/J110) -> 0.3887775 | L110: =IF(OR(H110="",H110=0,J110="",J110=0),"",H110/J110) -> 0.3887775 | N110: 0.25 | O110: 0.25 | P110: 0.49 | Q110: =IF(I110="","",I110+N(N110)) -> 10.25 | R110: =IF(OR(Q110="",F110=""),"",Q110/(1+F110)) -> 9.2342342 | S110: =IF(OR(H110="",H110=0,R110="",R110=0),"",H110/R110) -> 0.37929512 | T110: =IF(I110="","",I110+N(N110+O110)) -> 10.5 | U110: =IF(OR(T110="",F110=""),"",T110/(1+F110)) -> 9.4594595 | V110: =IF(OR(H110="",H110=0,U110="",U110=0),"",H110/U110) -> 0.37026429 | W110: =IF(I110="","",I110+N(N110+O110+P110)) -> 10.99 | X110: =IF(OR(W110="",F110=""),"",W110/(1+F110)) -> 9.9009009 | Y110: =IF(OR(H110="",H110=0,X110="",X110=0),"",H110/X110) -> 0.35375569
A111: SALATA COLESLAW D | B111: SALATA COLESLAW NEW D | C111: SNACK | D111: Delivery | E111: FOOD | F111: =IF(E111="","",IF(E111="DRINKS",0.21,0.11)) -> 0.11 | G111: =IF(B111="","",SUMIF(RETETAR!A:A,B111,RETETAR!F:F)) -> 3.5025 | H111: =IF(B111="","",SUMIF(RETETAR!A:A,B111,RETETAR!H:H)) -> 3.5025 | I111: 10 | J111: =IF(OR(I111="",F111=""),"",I111/(1+F111)) -> 9.009009 | K111: =IF(OR(G111="",G111=0,J111="",J111=0),"",G111/J111) -> 0.3887775 | L111: =IF(OR(H111="",H111=0,J111="",J111=0),"",H111/J111) -> 0.3887775 | N111: 0.25 | O111: 0.25 | P111: 0.49 | Q111: =IF(I111="","",I111+N(N111)) -> 10.25 | R111: =IF(OR(Q111="",F111=""),"",Q111/(1+F111)) -> 9.2342342 | S111: =IF(OR(H111="",H111=0,R111="",R111=0),"",H111/R111) -> 0.37929512 | T111: =IF(I111="","",I111+N(N111+O111)) -> 10.5 | U111: =IF(OR(T111="",F111=""),"",T111/(1+F111)) -> 9.4594595 | V111: =IF(OR(H111="",H111=0,U111="",U111=0),"",H111/U111) -> 0.37026429 | W111: =IF(I111="","",I111+N(N111+O111+P111)) -> 10.99 | X111: =IF(OR(W111="",F111=""),"",W111/(1+F111)) -> 9.9009009 | Y111: =IF(OR(H111="",H111=0,X111="",X111=0),"",H111/X111) -> 0.35375569
A112: ADD Bacon | B112: ADD Bacon new | C112: SNACK | D112: Instore | E112: FOOD | F112: =IF(E112="","",IF(E112="DRINKS",0.21,0.11)) -> 0.11 | G112: =IF(B112="","",SUMIF(RETETAR!A:A,B112,RETETAR!F:F)) -> 0.4896 | H112: =IF(B112="","",SUMIF(RETETAR!A:A,B112,RETETAR!H:H)) -> 0.4896 | I112: 5 | J112: =IF(OR(I112="",F112=""),"",I112/(1+F112)) -> 4.5045045 | K112: =IF(OR(G112="",G112=0,J112="",J112=0),"",G112/J112) -> 0.1086912 | L112: =IF(OR(H112="",H112=0,J112="",J112=0),"",H112/J112) -> 0.1086912 | N112: 0 | O112: 0 | P112: 0 | Q112: =IF(I112="","",I112+N(N112)) -> 5 | R112: =IF(OR(Q112="",F112=""),"",Q112/(1+F112)) -> 4.5045045 | S112: =IF(OR(H112="",H112=0,R112="",R112=0),"",H112/R112) -> 0.1086912 | T112: =IF(I112="","",I112+N(N112+O112)) -> 5 | U112: =IF(OR(T112="",F112=""),"",T112/(1+F112)) -> 4.5045045 | V112: =IF(OR(H112="",H112=0,U112="",U112=0),"",H112/U112) -> 0.1086912 | W112: =IF(I112="","",I112+N(N112+O112+P112)) -> 5 | X112: =IF(OR(W112="",F112=""),"",W112/(1+F112)) -> 4.5045045 | Y112: =IF(OR(H112="",H112=0,X112="",X112=0),"",H112/X112) -> 0.1086912
A113: ADD Bacon D | B113: ADD Bacon new D | C113: SNACK | D113: Delivery | E113: FOOD | F113: =IF(E113="","",IF(E113="DRINKS",0.21,0.11)) -> 0.11 | G113: =IF(B113="","",SUMIF(RETETAR!A:A,B113,RETETAR!F:F)) -> 0.4896 | H113: =IF(B113="","",SUMIF(RETETAR!A:A,B113,RETETAR!H:H)) -> 0.4896 | I113: 2 | J113: =IF(OR(I113="",F113=""),"",I113/(1+F113)) -> 1.8018018 | K113: =IF(OR(G113="",G113=0,J113="",J113=0),"",G113/J113) -> 0.271728 | L113: =IF(OR(H113="",H113=0,J113="",J113=0),"",H113/J113) -> 0.271728 | N113: 0 | O113: 0 | P113: 0 | Q113: =IF(I113="","",I113+N(N113)) -> 2 | R113: =IF(OR(Q113="",F113=""),"",Q113/(1+F113)) -> 1.8018018 | S113: =IF(OR(H113="",H113=0,R113="",R113=0),"",H113/R113) -> 0.271728 | T113: =IF(I113="","",I113+N(N113+O113)) -> 2 | U113: =IF(OR(T113="",F113=""),"",T113/(1+F113)) -> 1.8018018 | V113: =IF(OR(H113="",H113=0,U113="",U113=0),"",H113/U113) -> 0.271728 | W113: =IF(I113="","",I113+N(N113+O113+P113)) -> 2 | X113: =IF(OR(W113="",F113=""),"",W113/(1+F113)) -> 1.8018018 | Y113: =IF(OR(H113="",H113=0,X113="",X113=0),"",H113/X113) -> 0.271728
A114: ADD Felie Cheddar | B114: ADD FELIE CHEDDAR new | C114: SNACK | D114: Instore | E114: FOOD | F114: =IF(E114="","",IF(E114="DRINKS",0.21,0.11)) -> 0.11 | G114: =IF(B114="","",SUMIF(RETETAR!A:A,B114,RETETAR!F:F)) -> 0.61567 | H114: =IF(B114="","",SUMIF(RETETAR!A:A,B114,RETETAR!H:H)) -> 0.61567 | I114: 3 | J114: =IF(OR(I114="",F114=""),"",I114/(1+F114)) -> 2.7027027 | K114: =IF(OR(G114="",G114=0,J114="",J114=0),"",G114/J114) -> 0.2277979 | L114: =IF(OR(H114="",H114=0,J114="",J114=0),"",H114/J114) -> 0.2277979 | N114: 0 | O114: 0 | P114: 0 | Q114: =IF(I114="","",I114+N(N114)) -> 3 | R114: =IF(OR(Q114="",F114=""),"",Q114/(1+F114)) -> 2.7027027 | S114: =IF(OR(H114="",H114=0,R114="",R114=0),"",H114/R114) -> 0.2277979 | T114: =IF(I114="","",I114+N(N114+O114)) -> 3 | U114: =IF(OR(T114="",F114=""),"",T114/(1+F114)) -> 2.7027027 | V114: =IF(OR(H114="",H114=0,U114="",U114=0),"",H114/U114) -> 0.2277979 | W114: =IF(I114="","",I114+N(N114+O114+P114)) -> 3 | X114: =IF(OR(W114="",F114=""),"",W114/(1+F114)) -> 2.7027027 | Y114: =IF(OR(H114="",H114=0,X114="",X114=0),"",H114/X114) -> 0.2277979
A115: ADD Felie Cheddar D | B115: ADD Felie Cheddar new D | C115: SNACK | D115: Delivery | E115: FOOD | F115: =IF(E115="","",IF(E115="DRINKS",0.21,0.11)) -> 0.11 | G115: =IF(B115="","",SUMIF(RETETAR!A:A,B115,RETETAR!F:F)) -> 0.61567 | H115: =IF(B115="","",SUMIF(RETETAR!A:A,B115,RETETAR!H:H)) -> 0.61567 | I115: 3 | J115: =IF(OR(I115="",F115=""),"",I115/(1+F115)) -> 2.7027027 | K115: =IF(OR(G115="",G115=0,J115="",J115=0),"",G115/J115) -> 0.2277979 | L115: =IF(OR(H115="",H115=0,J115="",J115=0),"",H115/J115) -> 0.2277979 | N115: 0 | O115: 0 | P115: 0 | Q115: =IF(I115="","",I115+N(N115)) -> 3 | R115: =IF(OR(Q115="",F115=""),"",Q115/(1+F115)) -> 2.7027027 | S115: =IF(OR(H115="",H115=0,R115="",R115=0),"",H115/R115) -> 0.2277979 | T115: =IF(I115="","",I115+N(N115+O115)) -> 3 | U115: =IF(OR(T115="",F115=""),"",T115/(1+F115)) -> 2.7027027 | V115: =IF(OR(H115="",H115=0,U115="",U115=0),"",H115/U115) -> 0.2277979 | W115: =IF(I115="","",I115+N(N115+O115+P115)) -> 3 | X115: =IF(OR(W115="",F115=""),"",W115/(1+F115)) -> 2.7027027 | Y115: =IF(OR(H115="",H115=0,X115="",X115=0),"",H115/X115) -> 0.2277979
... A148: Sos SWEET CHILLI 25G D | B148: Sos SWEET CHILLI 25G NEW D | C148: SAUCES | D148: Delivery | E148: FOOD | F148: =IF(E148="","",IF(E148="DRINKS",0.21,0.11)) -> 0.11 | G148: =IF(B148="","",SUMIF(RETETAR!A:A,B148,RETETAR!F:F)) -> 1.43 | H148: =IF(B148="","",SUMIF(RETETAR!A:A,B148,RETETAR!H:H)) -> 1.43 | I148: 5.2 | J148: =IF(OR(I148="",F148=""),"",I148/(1+F148)) -> 4.6846847 | K148: =IF(OR(G148="",G148=0,J148="",J148=0),"",G148/J148) -> 0.30525 | L148: =IF(OR(H148="",H148=0,J148="",J148=0),"",H148/J148) -> 0.30525 | N148: 0.1 | O148: 0.2 | P148: 0.19 | Q148: =IF(I148="","",I148+N(N148)) -> 5.3 | R148: =IF(OR(Q148="",F148=""),"",Q148/(1+F148)) -> 4.7747748 | S148: =IF(OR(H148="",H148=0,R148="",R148=0),"",H148/R148) -> 0.29949057 | T148: =IF(I148="","",I148+N(N148+O148)) -> 5.5 | U148: =IF(OR(T148="",F148=""),"",T148/(1+F148)) -> 4.954955 | V148: =IF(OR(H148="",H148=0,U148="",U148=0),"",H148/U148) -> 0.2886 | W148: =IF(I148="","",I148+N(N148+O148+P148)) -> 5.69 | X148: =IF(OR(W148="",F148=""),"",W148/(1+F148)) -> 5.1261261 | Y148: =IF(OR(H148="",H148=0,X148="",X148=0),"",H148/X148) -> 0.27896309
A149: 2X Sos Ketchup 10ml/Mayoneza 10ml | B149: 2X Sos Ketchup 10ml D NEW | C149: SAUCES | D149: Instore | E149: FOOD | F149: =IF(E149="","",IF(E149="DRINKS",0.21,0.11)) -> 0.11 | G149: =IF(B149="","",SUMIF(RETETAR!A:A,B149,RETETAR!F:F)) -> 0.904 | H149: =IF(B149="","",SUMIF(RETETAR!A:A,B149,RETETAR!H:H)) -> 0.904 | I149: 5 | J149: =IF(OR(I149="",F149=""),"",I149/(1+F149)) -> 4.5045045 | K149: =IF(OR(G149="",G149=0,J149="",J149=0),"",G149/J149) -> 0.200688 | L149: =IF(OR(H149="",H149=0,J149="",J149=0),"",H149/J149) -> 0.200688 | M149: IN CAMPANII SI IN CATEGORIA CAMPANII INSIDE =SE ALEGE KETCHUP + MAYO SAU KETCHUP + KETCHUP | N149: 0.1 | O149: 0.2 | P149: 0.19 | Q149: =IF(I149="","",I149+N(N149)) -> 5.1 | R149: =IF(OR(Q149="",F149=""),"",Q149/(1+F149)) -> 4.5945946 | S149: =IF(OR(H149="",H149=0,R149="",R149=0),"",H149/R149) -> 0.19675294 | T149: =IF(I149="","",I149+N(N149+O149)) -> 5.3 | U149: =IF(OR(T149="",F149=""),"",T149/(1+F149)) -> 4.7747748 | V149: =IF(OR(H149="",H149=0,U149="",U149=0),"",H149/U149) -> 0.1893283 | W149: =IF(I149="","",I149+N(N149+O149+P149)) -> 5.49 | X149: =IF(OR(W149="",F149=""),"",W149/(1+F149)) -> 4.9459459 | Y149: =IF(OR(H149="",H149=0,X149="",X149=0),"",H149/X149) -> 0.18277596
A150: DIP N Cheddar 100 ML | B150: DIP N Cheddar 100 ML D NEW | C150: SAUCES | D150: Instore | E150: FOOD | F150: =IF(E150="","",IF(E150="DRINKS",0.21,0.11)) -> 0.11 | G150: =IF(B150="","",SUMIF(RETETAR!A:A,B150,RETETAR!F:F)) -> 4.887 | H150: =IF(B150="","",SUMIF(RETETAR!A:A,B150,RETETAR!H:H)) -> 4.887 | I150: 13.98 | J150: =IF(OR(I150="",F150=""),"",I150/(1+F150)) -> 12.594595 | K150: =IF(OR(G150="",G150=0,J150="",J150=0),"",G150/J150) -> 0.38802361 | L150: =IF(OR(H150="",H150=0,J150="",J150=0),"",H150/J150) -> 0.38802361 | N150: 0 | O150: 0 | P150: 0 | Q150: =IF(I150="","",I150+N(N150)) -> 13.98 | R150: =IF(OR(Q150="",F150=""),"",Q150/(1+F150)) -> 12.594595 | S150: =IF(OR(H150="",H150=0,R150="",R150=0),"",H150/R150) -> 0.38802361 | T150: =IF(I150="","",I150+N(N150+O150)) -> 13.98 | U150: =IF(OR(T150="",F150=""),"",T150/(1+F150)) -> 12.594595 | V150: =IF(OR(H150="",H150=0,U150="",U150=0),"",H150/U150) -> 0.38802361 | W150: =IF(I150="","",I150+N(N150+O150+P150)) -> 13.98 | X150: =IF(OR(W150="",F150=""),"",W150/(1+F150)) -> 12.594595 | Y150: =IF(OR(H150="",H150=0,X150="",X150=0),"",H150/X150) -> 0.38802361
A151: DIP N Cheddar 100 ML D | B151: DIP N Cheddar 100 ML D NEW D | C151: SAUCES | D151: Delivery | E151: FOOD | F151: =IF(E151="","",IF(E151="DRINKS",0.21,0.11)) -> 0.11 | G151: =IF(B151="","",SUMIF(RETETAR!A:A,B151,RETETAR!F:F)) -> 4.887 | H151: =IF(B151="","",SUMIF(RETETAR!A:A,B151,RETETAR!H:H)) -> 4.887 | I151: 13.98 | J151: =IF(OR(I151="",F151=""),"",I151/(1+F151)) -> 12.594595 | K151: =IF(OR(G151="",G151=0,J151="",J151=0),"",G151/J151) -> 0.38802361 | L151: =IF(OR(H151="",H151=0,J151="",J151=0),"",H151/J151) -> 0.38802361 | N151: 0 | O151: 0 | P151: 0 | Q151: =IF(I151="","",I151+N(N151)) -> 13.98 | R151: =IF(OR(Q151="",F151=""),"",Q151/(1+F151)) -> 12.594595 | S151: =IF(OR(H151="",H151=0,R151="",R151=0),"",H151/R151) -> 0.38802361 | T151: =IF(I151="","",I151+N(N151+O151)) -> 13.98 | U151: =IF(OR(T151="",F151=""),"",T151/(1+F151)) -> 12.594595 | V151: =IF(OR(H151="",H151=0,U151="",U151=0),"",H151/U151) -> 0.38802361 | W151: =IF(I151="","",I151+N(N151+O151+P151)) -> 13.98 | X151: =IF(OR(W151="",F151=""),"",W151/(1+F151)) -> 12.594595 | Y151: =IF(OR(H151="",H151=0,X151="",X151=0),"",H151/X151) -> 0.38802361
A152: DIP N FRYRANCH 100G | B152: DIP N FRYRANCH 100G NEW | C152: SAUCES | D152: Instore | E152: FOOD | F152: =IF(E152="","",IF(E152="DRINKS",0.21,0.11)) -> 0.11 | G152: =IF(B152="","",SUMIF(RETETAR!A:A,B152,RETETAR!F:F)) -> 2.993 | H152: =IF(B152="","",SUMIF(RETETAR!A:A,B152,RETETAR!H:H)) -> 2.993 | I152: 13.98 | J152: =IF(OR(I152="",F152=""),"",I152/(1+F152)) -> 12.594595 | K152: =IF(OR(G152="",G152=0,J152="",J152=0),"",G152/J152) -> 0.23764163 | L152: =IF(OR(H152="",H152=0,J152="",J152=0),"",H152/J152) -> 0.23764163 | N152: 0.1 | O152: 0.2 | P152: 0.19 | Q152: =IF(I152="","",I152+N(N152)) -> 14.08 | R152: =IF(OR(Q152="",F152=""),"",Q152/(1+F152)) -> 12.684685 | S152: =IF(OR(H152="",H152=0,R152="",R152=0),"",H152/R152) -> 0.23595384 | T152: =IF(I152="","",I152+N(N152+O152)) -> 14.28 | U152: =IF(OR(T152="",F152=""),"",T152/(1+F152)) -> 12.864865 | V152: =IF(OR(H152="",H152=0,U152="",U152=0),"",H152/U152) -> 0.23264916 | W152: =IF(I152="","",I152+N(N152+O152+P152)) -> 14.47 | X152: =IF(OR(W152="",F152=""),"",W152/(1+F152)) -> 13.036036 | Y152: =IF(OR(H152="",H152=0,X152="",X152=0),"",H152/X152) -> 0.22959433
A153: DIP N FRYRANCH 100G D | B153: DIP N FRYRANCH 100G NEW D | C153: SAUCES | D153: Delivery | E153: FOOD | F153: =IF(E153="","",IF(E153="DRINKS",0.21,0.11)) -> 0.11 | G153: =IF(B153="","",SUMIF(RETETAR!A:A,B153,RETETAR!F:F)) -> 2.993 | H153: =IF(B153="","",SUMIF(RETETAR!A:A,B153,RETETAR!H:H)) -> 2.993 | I153: 13.98 | J153: =IF(OR(I153="",F153=""),"",I153/(1+F153)) -> 12.594595 | K153: =IF(OR(G153="",G153=0,J153="",J153=0),"",G153/J153) -> 0.23764163 | L153: =IF(OR(H153="",H153=0,J153="",J153=0),"",H153/J153) -> 0.23764163 | N153: 0.1 | O153: 0.2 | P153: 0.19 | Q153: =IF(I153="","",I153+N(N153)) -> 14.08 | R153: =IF(OR(Q153="",F153=""),"",Q153/(1+F153)) -> 12.684685 | S153: =IF(OR(H153="",H153=0,R153="",R153=0),"",H153/R153) -> 0.23595384 | T153: =IF(I153="","",I153+N(N153+O153)) -> 14.28 | U153: =IF(OR(T153="",F153=""),"",T153/(1+F153)) -> 12.864865 | V153: =IF(OR(H153="",H153=0,U153="",U153=0),"",H153/U153) -> 0.23264916 | W153: =IF(I153="","",I153+N(N153+O153+P153)) -> 14.47 | X153: =IF(OR(W153="",F153=""),"",W153/(1+F153)) -> 13.036036 | Y153: =IF(OR(H153="",H153=0,X153="",X153=0),"",H153/X153) -> 0.22959433
A154: DIP N FRYRANCH 250G | B154: DIP N FRYRANCH 250G NEW | C154: SAUCES | D154: Instore | E154: FOOD | F154: =IF(E154="","",IF(E154="DRINKS",0.21,0.11)) -> 0.11 | G154: =IF(B154="","",SUMIF(RETETAR!A:A,B154,RETETAR!F:F)) -> 6.9255 | H154: =IF(B154="","",SUMIF(RETETAR!A:A,B154,RETETAR!H:H)) -> 6.9255 | I154: 25 | J154: =IF(OR(I154="",F154=""),"",I154/(1+F154)) -> 22.522523 | K154: =IF(OR(G154="",G154=0,J154="",J154=0),"",G154/J154) -> 0.3074922 | L154: =IF(OR(H154="",H154=0,J154="",J154=0),"",H154/J154) -> 0.3074922 | N154: 0.1 | O154: 0.2 | P154: 0.19 | Q154: =IF(I154="","",I154+N(N154)) -> 25.1 | R154: =IF(OR(Q154="",F154=""),"",Q154/(1+F154)) -> 22.612613 | S154: =IF(OR(H154="",H154=0,R154="",R154=0),"",H154/R154) -> 0.30626713 | T154: =IF(I154="","",I154+N(N154+O154)) -> 25.3 | U154: =IF(OR(T154="",F154=""),"",T154/(1+F154)) -> 22.792793 | V154: =IF(OR(H154="",H154=0,U154="",U154=0),"",H154/U154) -> 0.30384605 | W154: =IF(I154="","",I154+N(N154+O154+P154)) -> 25.49 | X154: =IF(OR(W154="",F154=""),"",W154/(1+F154)) -> 22.963964 | Y154: =IF(OR(H154="",H154=0,X154="",X154=0),"",H154/X154) -> 0.30158121
A155: DIP N FRYRANCH 250G D | B155: DIP N FRYRANCH 250G NEW D | C155: SAUCES | D155: Delivery | E155: FOOD | F155: =IF(E155="","",IF(E155="DRINKS",0.21,0.11)) -> 0.11 | G155: =IF(B155="","",SUMIF(RETETAR!A:A,B155,RETETAR!F:F)) -> 6.9255 | H155: =IF(B155="","",SUMIF(RETETAR!A:A,B155,RETETAR!H:H)) -> 6.9255 | I155: 25 | J155: =IF(OR(I155="",F155=""),"",I155/(1+F155)) -> 22.522523 | K155: =IF(OR(G155="",G155=0,J155="",J155=0),"",G155/J155) -> 0.3074922 | L155: =IF(OR(H155="",H155=0,J155="",J155=0),"",H155/J155) -> 0.3074922 | N155: 0.1 | O155: 0.2 | P155: 0.19 | Q155: =IF(I155="","",I155+N(N155)) -> 25.1 | R155: =IF(OR(Q155="",F155=""),"",Q155/(1+F155)) -> 22.612613 | S155: =IF(OR(H155="",H155=0,R155="",R155=0),"",H155/R155) -> 0.30626713 | T155: =IF(I155="","",I155+N(N155+O155)) -> 25.3 | U155: =IF(OR(T155="",F155=""),"",T155/(1+F155)) -> 22.792793 | V155: =IF(OR(H155="",H155=0,U155="",U155=0),"",H155/U155) -> 0.30384605 | W155: =IF(I155="","",I155+N(N155+O155+P155)) -> 25.49 | X155: =IF(OR(W155="",F155=""),"",W155/(1+F155)) -> 22.963964 | Y155: =IF(OR(H155="",H155=0,X155="",X155=0),"",H155/X155) -> 0.30158121
A156: DIP N FRYRANCH 400G | B156: DIP N FRYRANCH 400G NEW | C156: SAUCES | D156: Instore | E156: FOOD | F156: =IF(E156="","",IF(E156="DRINKS",0.21,0.11)) -> 0.11 | G156: =IF(B156="","",SUMIF(RETETAR!A:A,B156,RETETAR!F:F)) -> 10.896 | H156: =IF(B156="","",SUMIF(RETETAR!A:A,B156,RETETAR!H:H)) -> 10.896 | I156: 35 | J156: =IF(OR(I156="",F156=""),"",I156/(1+F156)) -> 31.531532 | K156: =IF(OR(G156="",G156=0,J156="",J156=0),"",G156/J156) -> 0.34555886 | L156: =IF(OR(H156="",H156=0,J156="",J156=0),"",H156/J156) -> 0.34555886 | N156: 0.1 | O156: 0.2 | P156: 0.19 | Q156: =IF(I156="","",I156+N(N156)) -> 35.1 | R156: =IF(OR(Q156="",F156=""),"",Q156/(1+F156)) -> 31.621622 | S156: =IF(OR(H156="",H156=0,R156="",R156=0),"",H156/R156) -> 0.34457436 | T156: =IF(I156="","",I156+N(N156+O156)) -> 35.3 | U156: =IF(OR(T156="",F156=""),"",T156/(1+F156)) -> 31.801802 | V156: =IF(OR(H156="",H156=0,U156="",U156=0),"",H156/U156) -> 0.3426221 | W156: =IF(I156="","",I156+N(N156+O156+P156)) -> 35.49 | X156: =IF(OR(W156="",F156=""),"",W156/(1+F156)) -> 31.972973 | Y156: =IF(OR(H156="",H156=0,X156="",X156=0),"",H156/X156) -> 0.34078783
A157: DIP N FRYRANCH 400G D | B157: DIP N FRYRANCH 400G NEW D | C157: SAUCES | D157: Delivery | E157: FOOD | F157: =IF(E157="","",IF(E157="DRINKS",0.21,0.11)) -> 0.11 | G157: =IF(B157="","",SUMIF(RETETAR!A:A,B157,RETETAR!F:F)) -> 10.896 | H157: =IF(B157="","",SUMIF(RETETAR!A:A,B157,RETETAR!H:H)) -> 10.896 | I157: 35 | J157: =IF(OR(I157="",F157=""),"",I157/(1+F157)) -> 31.531532 | K157: =IF(OR(G157="",G157=0,J157="",J157=0),"",G157/J157) -> 0.34555886 | L157: =IF(OR(H157="",H157=0,J157="",J157=0),"",H157/J157) -> 0.34555886 | N157: 0.1 | O157: 0.2 | P157: 0.19 | Q157: =IF(I157="","",I157+N(N157)) -> 35.1 | R157: =IF(OR(Q157="",F157=""),"",Q157/(1+F157)) -> 31.621622 | S157: =IF(OR(H157="",H157=0,R157="",R157=0),"",H157/R157) -> 0.34457436 | T157: =IF(I157="","",I157+N(N157+O157)) -> 35.3 | U157: =IF(OR(T157="",F157=""),"",T157/(1+F157)) -> 31.801802 | V157: =IF(OR(H157="",H157=0,U157="",U157=0),"",H157/U157) -> 0.3426221 | W157: =IF(I157="","",I157+N(N157+O157+P157)) -> 35.49 | X157: =IF(OR(W157="",F157=""),"",W157/(1+F157)) -> 31.972973 | Y157: =IF(OR(H157="",H157=0,X157="",X157=0),"",H157/X157) -> 0.34078783
A158: DIP N TRUFFLE 100G | B158: DIP N TRUFFLE 100G NEW | C158: SAUCES | D158: Instore | E158: FOOD | F158: =IF(E158="","",IF(E158="DRINKS",0.21,0.11)) -> 0.11 | G158: =IF(B158="","",SUMIF(RETETAR!A:A,B158,RETETAR!F:F)) -> 3.886 | H158: =IF(B158="","",SUMIF(RETETAR!A:A,B158,RETETAR!H:H)) -> 3.886 | I158: 13.98 | J158: =IF(OR(I158="",F158=""),"",I158/(1+F158)) -> 12.594595 | K158: =IF(OR(G158="",G158=0,J158="",J158=0),"",G158/J158) -> 0.30854506 | L158: =IF(OR(H158="",H158=0,J158="",J158=0),"",H158/J158) -> 0.30854506 | N158: 0 | O158: 0 | P158: 0 | Q158: =IF(I158="","",I158+N(N158)) -> 13.98 | R158: =IF(OR(Q158="",F158=""),"",Q158/(1+F158)) -> 12.594595 | S158: =IF(OR(H158="",H158=0,R158="",R158=0),"",H158/R158) -> 0.30854506 | T158: =IF(I158="","",I158+N(N158+O158)) -> 13.98 | U158: =IF(OR(T158="",F158=""),"",T158/(1+F158)) -> 12.594595 | V158: =IF(OR(H158="",H158=0,U158="",U158=0),"",H158/U158) -> 0.30854506 | W158: =IF(I158="","",I158+N(N158+O158+P158)) -> 13.98 | X158: =IF(OR(W158="",F158=""),"",W158/(1+F158)) -> 12.594595 | Y158: =IF(OR(H158="",H158=0,X158="",X158=0),"",H158/X158) -> 0.30854506
A159: DIP N TRUFFLE 100G D | B159: DIP N TRUFFLE 100G NEW D | C159: SAUCES | D159: Delivery | E159: FOOD | F159: =IF(E159="","",IF(E159="DRINKS",0.21,0.11)) -> 0.11 | G159: =IF(B159="","",SUMIF(RETETAR!A:A,B159,RETETAR!F:F)) -> 3.886 | H159: =IF(B159="","",SUMIF(RETETAR!A:A,B159,RETETAR!H:H)) -> 3.886 | I159: 13.98 | J159: =IF(OR(I159="",F159=""),"",I159/(1+F159)) -> 12.594595 | K159: =IF(OR(G159="",G159=0,J159="",J159=0),"",G159/J159) -> 0.30854506 | L159: =IF(OR(H159="",H159=0,J159="",J159=0),"",H159/J159) -> 0.30854506 | N159: 0 | O159: 0 | P159: 0 | Q159: =IF(I159="","",I159+N(N159)) -> 13.98 | R159: =IF(OR(Q159="",F159=""),"",Q159/(1+F159)) -> 12.594595 | S159: =IF(OR(H159="",H159=0,R159="",R159=0),"",H159/R159) -> 0.30854506 | T159: =IF(I159="","",I159+N(N159+O159)) -> 13.98 | U159: =IF(OR(T159="",F159=""),"",T159/(1+F159)) -> 12.594595 | V159: =IF(OR(H159="",H159=0,U159="",U159=0),"",H159/U159) -> 0.30854506 | W159: =IF(I159="","",I159+N(N159+O159+P159)) -> 13.98 | X159: =IF(OR(W159="",F159=""),"",W159/(1+F159)) -> 12.594595 | Y159: =IF(OR(H159="",H159=0,X159="",X159=0),"",H159/X159) -> 0.30854506
A160: APPLE PIE TOFFIE | B160: APPLE TOFFEE FRYPIE | C160: MILKSHAKE & DESSERT | D160: Instore | E160: FOOD | F160: =IF(E160="","",IF(E160="DRINKS",0.21,0.11)) -> 0.11 | G160: =IF(B160="","",SUMIF(RETETAR!A:A,B160,RETETAR!F:F)) -> 3.668 | H160: =IF(B160="","",SUMIF(RETETAR!A:A,B160,RETETAR!H:H)) -> 3.668 | I160: 10 | J160: =IF(OR(I160="",F160=""),"",I160/(1+F160)) -> 9.009009 | K160: =IF(OR(G160="",G160=0,J160="",J160=0),"",G160/J160) -> 0.407148 | L160: =IF(OR(H160="",H160=0,J160="",J160=0),"",H160/J160) -> 0.407148 | M160: REVIN CU CR-LANSARE 01 IUNIE | N160: 0 | O160: 0 | P160: 0 | Q160: =IF(I160="","",I160+N(N160)) -> 10 | R160: =IF(OR(Q160="",F160=""),"",Q160/(1+F160)) -> 9.009009 | S160: =IF(OR(H160="",H160=0,R160="",R160=0),"",H160/R160) -> 0.407148 | T160: =IF(I160="","",I160+N(N160+O160)) -> 10 | U160: =IF(OR(T160="",F160=""),"",T160/(1+F160)) -> 9.009009 | V160: =IF(OR(H160="",H160=0,U160="",U160=0),"",H160/U160) -> 0.407148 | W160: =IF(I160="","",I160+N(N160+O160+P160)) -> 10 | X160: =IF(OR(W160="",F160=""),"",W160/(1+F160)) -> 9.009009 | Y160: =IF(OR(H160="",H160=0,X160="",X160=0),"",H160/X160) -> 0.407148
A161: APPLE PIE TOFFIE D | B161: APPLE TOFFEE FRYPIE D | C161: MILKSHAKE & DESSERT | D161: Delivery | E161: FOOD | F161: =IF(E161="","",IF(E161="DRINKS",0.21,0.11)) -> 0.11 | G161: =IF(B161="","",SUMIF(RETETAR!A:A,B161,RETETAR!F:F)) -> 3.668 | H161: =IF(B161="","",SUMIF(RETETAR!A:A,B161,RETETAR!H:H)) -> 3.668 | I161: 10.9 | J161: =IF(OR(I161="",F161=""),"",I161/(1+F161)) -> 9.8198198 | K161: =IF(OR(G161="",G161=0,J161="",J161=0),"",G161/J161) -> 0.37353028 | L161: =IF(OR(H161="",H161=0,J161="",J161=0),"",H161/J161) -> 0.37353028 | N161: 0 | O161: 0 | P161: 0 | Q161: =IF(I161="","",I161+N(N161)) -> 10.9 | R161: =IF(OR(Q161="",F161=""),"",Q161/(1+F161)) -> 9.8198198 | S161: =IF(OR(H161="",H161=0,R161="",R161=0),"",H161/R161) -> 0.37353028 | T161: =IF(I161="","",I161+N(N161+O161)) -> 10.9 | U161: =IF(OR(T161="",F161=""),"",T161/(1+F161)) -> 9.8198198 | V161: =IF(OR(H161="",H161=0,U161="",U161=0),"",H161/U161) -> 0.37353028 | W161: =IF(I161="","",I161+N(N161+O161+P161)) -> 10.9 | X161: =IF(OR(W161="",F161=""),"",W161/(1+F161)) -> 9.8198198 | Y161: =IF(OR(H161="",H161=0,X161="",X161=0),"",H161/X161) -> 0.37353028
A162: Nutella Burger | B162: Nutella Burger NEW | C162: MILKSHAKE & DESSERT | D162: Instore | E162: FOOD | F162: =IF(E162="","",IF(E162="DRINKS",0.21,0.11)) -> 0.11 | G162: =IF(B162="","",SUMIF(RETETAR!A:A,B162,RETETAR!F:F)) -> 3.7981 | H162: =IF(B162="","",SUMIF(RETETAR!A:A,B162,RETETAR!H:H)) -> 3.7981 | I162: 10 | J162: =IF(OR(I162="",F162=""),"",I162/(1+F162)) -> 9.009009 | K162: =IF(OR(G162="",G162=0,J162="",J162=0),"",G162/J162) -> 0.4215891 | L162: =IF(OR(H162="",H162=0,J162="",J162=0),"",H162/J162) -> 0.4215891 | N162: 0 | O162: 0 | P162: 0 | Q162: =IF(I162="","",I162+N(N162)) -> 10 | R162: =IF(OR(Q162="",F162=""),"",Q162/(1+F162)) -> 9.009009 | S162: =IF(OR(H162="",H162=0,R162="",R162=0),"",H162/R162) -> 0.4215891 | T162: =IF(I162="","",I162+N(N162+O162)) -> 10 | U162: =IF(OR(T162="",F162=""),"",T162/(1+F162)) -> 9.009009 | V162: =IF(OR(H162="",H162=0,U162="",U162=0),"",H162/U162) -> 0.4215891 | W162: =IF(I162="","",I162+N(N162+O162+P162)) -> 10 | X162: =IF(OR(W162="",F162=""),"",W162/(1+F162)) -> 9.009009 | Y162: =IF(OR(H162="",H162=0,X162="",X162=0),"",H162/X162) -> 0.4215891
A163: Nutella Burger D | B163: Nutella Burger NEW D | C163: MILKSHAKE & DESSERT | D163: Delivery | E163: FOOD | F163: =IF(E163="","",IF(E163="DRINKS",0.21,0.11)) -> 0.11 | G163: =IF(B163="","",SUMIF(RETETAR!A:A,B163,RETETAR!F:F)) -> 3.7981 | H163: =IF(B163="","",SUMIF(RETETAR!A:A,B163,RETETAR!H:H)) -> 3.7981 | I163: 12 | J163: =IF(OR(I163="",F163=""),"",I163/(1+F163)) -> 10.810811 | K163: =IF(OR(G163="",G163=0,J163="",J163=0),"",G163/J163) -> 0.35132425 | L163: =IF(OR(H163="",H163=0,J163="",J163=0),"",H163/J163) -> 0.35132425 | N163: 0 | O163: 0 | P163: 0 | Q163: =IF(I163="","",I163+N(N163)) -> 12 | R163: =IF(OR(Q163="",F163=""),"",Q163/(1+F163)) -> 10.810811 | S163: =IF(OR(H163="",H163=0,R163="",R163=0),"",H163/R163) -> 0.35132425 | T163: =IF(I163="","",I163+N(N163+O163)) -> 12 | U163: =IF(OR(T163="",F163=""),"",T163/(1+F163)) -> 10.810811 | V163: =IF(OR(H163="",H163=0,U163="",U163=0),"",H163/U163) -> 0.35132425 | W163: =IF(I163="","",I163+N(N163+O163+P163)) -> 12 | X163: =IF(OR(W163="",F163=""),"",W163/(1+F163)) -> 10.810811 | Y163: =IF(OR(H163="",H163=0,X163="",X163=0),"",H163/X163) -> 0.35132425
A164: Nutella Burger Capsuni | B164: Nutella Burger Capsuni NEW | C164: MILKSHAKE & DESSERT | D164: Instore | E164: FOOD | F164: =IF(E164="","",IF(E164="DRINKS",0.21,0.11)) -> 0.11 | G164: =IF(B164="","",SUMIF(RETETAR!A:A,B164,RETETAR!F:F)) -> 4.5231 | H164: =IF(B164="","",SUMIF(RETETAR!A:A,B164,RETETAR!H:H)) -> 4.5231 | I164: 12 | J164: =IF(OR(I164="",F164=""),"",I164/(1+F164)) -> 10.810811 | K164: =IF(OR(G164="",G164=0,J164="",J164=0),"",G164/J164) -> 0.41838675 | L164: =IF(OR(H164="",H164=0,J164="",J164=0),"",H164/J164) -> 0.41838675 | N164: 0 | O164: 0 | P164: 0 | Q164: =IF(I164="","",I164+N(N164)) -> 12 | R164: =IF(OR(Q164="",F164=""),"",Q164/(1+F164)) -> 10.810811 | S164: =IF(OR(H164="",H164=0,R164="",R164=0),"",H164/R164) -> 0.41838675 | T164: =IF(I164="","",I164+N(N164+O164)) -> 12 | U164: =IF(OR(T164="",F164=""),"",T164/(1+F164)) -> 10.810811 | V164: =IF(OR(H164="",H164=0,U164="",U164=0),"",H164/U164) -> 0.41838675 | W164: =IF(I164="","",I164+N(N164+O164+P164)) -> 12 | X164: =IF(OR(W164="",F164=""),"",W164/(1+F164)) -> 10.810811 | Y164: =IF(OR(H164="",H164=0,X164="",X164=0),"",H164/X164) -> 0.41838675
A165: Nutella Burger Capsuni D | B165: Nutella Burger Capsuni NEW D | C165: MILKSHAKE & DESSERT | D165: Delivery | E165: FOOD | F165: =IF(E165="","",IF(E165="DRINKS",0.21,0.11)) -> 0.11 | G165: =IF(B165="","",SUMIF(RETETAR!A:A,B165,RETETAR!F:F)) -> 4.5231 | H165: =IF(B165="","",SUMIF(RETETAR!A:A,B165,RETETAR!H:H)) -> 4.5231 | I165: 14 | J165: =IF(OR(I165="",F165=""),"",I165/(1+F165)) -> 12.612613 | K165: =IF(OR(G165="",G165=0,J165="",J165=0),"",G165/J165) -> 0.35861721 | L165: =IF(OR(H165="",H165=0,J165="",J165=0),"",H165/J165) -> 0.35861721 | N165: 0 | O165: 0 | P165: 0 | Q165: =IF(I165="","",I165+N(N165)) -> 14 | R165: =IF(OR(Q165="",F165=""),"",Q165/(1+F165)) -> 12.612613 | S165: =IF(OR(H165="",H165=0,R165="",R165=0),"",H165/R165) -> 0.35861721 | T165: =IF(I165="","",I165+N(N165+O165)) -> 14 | U165: =IF(OR(T165="",F165=""),"",T165/(1+F165)) -> 12.612613 | V165: =IF(OR(H165="",H165=0,U165="",U165=0),"",H165/U165) -> 0.35861721 | W165: =IF(I165="","",I165+N(N165+O165+P165)) -> 14 | X165: =IF(OR(W165="",F165=""),"",W165/(1+F165)) -> 12.612613 | Y165: =IF(OR(H165="",H165=0,X165="",X165=0),"",H165/X165) -> 0.35861721
A166: Nutella Burger Banane | B166: Nutella Burger Banane NEW | C166: MILKSHAKE & DESSERT | D166: Instore | E166: FOOD | F166: =IF(E166="","",IF(E166="DRINKS",0.21,0.11)) -> 0.11 | G166: =IF(B166="","",SUMIF(RETETAR!A:A,B166,RETETAR!F:F)) -> 4.1231 | H166: =IF(B166="","",SUMIF(RETETAR!A:A,B166,RETETAR!H:H)) -> 4.1231 | I166: 12 | J166: =IF(OR(I166="",F166=""),"",I166/(1+F166)) -> 10.810811 | K166: =IF(OR(G166="",G166=0,J166="",J166=0),"",G166/J166) -> 0.38138675 | L166: =IF(OR(H166="",H166=0,J166="",J166=0),"",H166/J166) -> 0.38138675 | N166: 0 | O166: 0 | P166: 0 | Q166: =IF(I166="","",I166+N(N166)) -> 12 | R166: =IF(OR(Q166="",F166=""),"",Q166/(1+F166)) -> 10.810811 | S166: =IF(OR(H166="",H166=0,R166="",R166=0),"",H166/R166) -> 0.38138675 | T166: =IF(I166="","",I166+N(N166+O166)) -> 12 | U166: =IF(OR(T166="",F166=""),"",T166/(1+F166)) -> 10.810811 | V166: =IF(OR(H166="",H166=0,U166="",U166=0),"",H166/U166) -> 0.38138675 | W166: =IF(I166="","",I166+N(N166+O166+P166)) -> 12 | X166: =IF(OR(W166="",F166=""),"",W166/(1+F166)) -> 10.810811 | Y166: =IF(OR(H166="",H166=0,X166="",X166=0),"",H166/X166) -> 0.38138675
A167: Nutella Burger Banane D | B167: Nutella Burger Banane NEW D | C167: MILKSHAKE & DESSERT | D167: Delivery | E167: FOOD | F167: =IF(E167="","",IF(E167="DRINKS",0.21,0.11)) -> 0.11 | G167: =IF(B167="","",SUMIF(RETETAR!A:A,B167,RETETAR!F:F)) -> 4.1231 | H167: =IF(B167="","",SUMIF(RETETAR!A:A,B167,RETETAR!H:H)) -> 4.1231 | I167: 14 | J167: =IF(OR(I167="",F167=""),"",I167/(1+F167)) -> 12.612613 | K167: =IF(OR(G167="",G167=0,J167="",J167=0),"",G167/J167) -> 0.32690293 | L167: =IF(OR(H167="",H167=0,J167="",J167=0),"",H167/J167) -> 0.32690293 | N167: 0 | O167: 0 | P167: 0 | Q167: =IF(I167="","",I167+N(N167)) -> 14 | R167: =IF(OR(Q167="",F167=""),"",Q167/(1+F167)) -> 12.612613 | S167: =IF(OR(H167="",H167=0,R167="",R167=0),"",H167/R167) -> 0.32690293 | T167: =IF(I167="","",I167+N(N167+O167)) -> 14 | U167: =IF(OR(T167="",F167=""),"",T167/(1+F167)) -> 12.612613 | V167: =IF(OR(H167="",H167=0,U167="",U167=0),"",H167/U167) -> 0.32690293 | W167: =IF(I167="","",I167+N(N167+O167+P167)) -> 14 | X167: =IF(OR(W167="",F167=""),"",W167/(1+F167)) -> 12.612613 | Y167: =IF(OR(H167="",H167=0,X167="",X167=0),"",H167/X167) -> 0.32690293
A168: Milkshake Biscoff 300G | B168: Milkshake Biscoff NEW | C168: MILKSHAKE & DESSERT | D168: Instore | E168: FOOD | F168: =IF(E168="","",IF(E168="DRINKS",0.21,0.11)) -> 0.11 | G168: =IF(B168="","",SUMIF(RETETAR!A:A,B168,RETETAR!F:F)) -> 6.66 | H168: =IF(B168="","",SUMIF(RETETAR!A:A,B168,RETETAR!H:H)) -> 6.66 | I168: 18 | J168: =IF(OR(I168="",F168=""),"",I168/(1+F168)) -> 16.216216 | K168: =IF(OR(G168="",G168=0,J168="",J168=0),"",G168/J168) -> 0.4107 | L168: =IF(OR(H168="",H168=0,J168="",J168=0),"",H168/J168) -> 0.4107 | N168: 0 | O168: 0 | P168: 0 | Q168: =IF(I168="","",I168+N(N168)) -> 18 | R168: =IF(OR(Q168="",F168=""),"",Q168/(1+F168)) -> 16.216216 | S168: =IF(OR(H168="",H168=0,R168="",R168=0),"",H168/R168) -> 0.4107 | T168: =IF(I168="","",I168+N(N168+O168)) -> 18 | U168: =IF(OR(T168="",F168=""),"",T168/(1+F168)) -> 16.216216 | V168: =IF(OR(H168="",H168=0,U168="",U168=0),"",H168/U168) -> 0.4107 | W168: =IF(I168="","",I168+N(N168+O168+P168)) -> 18 | X168: =IF(OR(W168="",F168=""),"",W168/(1+F168)) -> 16.216216 | Y168: =IF(OR(H168="",H168=0,X168="",X168=0),"",H168/X168) -> 0.4107
A169: Milkshake Apple Cinnamon 300G | B169: Milkshake Apple Cinnamon NEW | C169: MILKSHAKE & DESSERT | D169: Instore | E169: FOOD | F169: =IF(E169="","",IF(E169="DRINKS",0.21,0.11)) -> 0.11 | G169: =IF(B169="","",SUMIF(RETETAR!A:A,B169,RETETAR!F:F)) -> 6.6574 | H169: =IF(B169="","",SUMIF(RETETAR!A:A,B169,RETETAR!H:H)) -> 6.6574 | I169: 18 | J169: =IF(OR(I169="",F169=""),"",I169/(1+F169)) -> 16.216216 | K169: =IF(OR(G169="",G169=0,J169="",J169=0),"",G169/J169) -> 0.41053967 | L169: =IF(OR(H169="",H169=0,J169="",J169=0),"",H169/J169) -> 0.41053967 | N169: 0 | O169: 0 | P169: 0 | Q169: =IF(I169="","",I169+N(N169)) -> 18 | R169: =IF(OR(Q169="",F169=""),"",Q169/(1+F169)) -> 16.216216 | S169: =IF(OR(H169="",H169=0,R169="",R169=0),"",H169/R169) -> 0.41053967 | T169: =IF(I169="","",I169+N(N169+O169)) -> 18 | U169: =IF(OR(T169="",F169=""),"",T169/(1+F169)) -> 16.216216 | V169: =IF(OR(H169="",H169=0,U169="",U169=0),"",H169/U169) -> 0.41053967 | W169: =IF(I169="","",I169+N(N169+O169+P169)) -> 18 | X169: =IF(OR(W169="",F169=""),"",W169/(1+F169)) -> 16.216216 | Y169: =IF(OR(H169="",H169=0,X169="",X169=0),"",H169/X169) -> 0.41053967
A170: Milkshake Vanilie 300G | B170: Milkshake Vanilie NEW | C170: MILKSHAKE & DESSERT | D170: Instore | E170: FOOD | F170: =IF(E170="","",IF(E170="DRINKS",0.21,0.11)) -> 0.11 | G170: =IF(B170="","",SUMIF(RETETAR!A:A,B170,RETETAR!F:F)) -> 5.151 | H170: =IF(B170="","",SUMIF(RETETAR!A:A,B170,RETETAR!H:H)) -> 5.151 | I170: 18 | J170: =IF(OR(I170="",F170=""),"",I170/(1+F170)) -> 16.216216 | K170: =IF(OR(G170="",G170=0,J170="",J170=0),"",G170/J170) -> 0.317645 | L170: =IF(OR(H170="",H170=0,J170="",J170=0),"",H170/J170) -> 0.317645 | N170: 0 | O170: 0 | P170: 0 | Q170: =IF(I170="","",I170+N(N170)) -> 18 | R170: =IF(OR(Q170="",F170=""),"",Q170/(1+F170)) -> 16.216216 | S170: =IF(OR(H170="",H170=0,R170="",R170=0),"",H170/R170) -> 0.317645 | T170: =IF(I170="","",I170+N(N170+O170)) -> 18 | U170: =IF(OR(T170="",F170=""),"",T170/(1+F170)) -> 16.216216 | V170: =IF(OR(H170="",H170=0,U170="",U170=0),"",H170/U170) -> 0.317645 | W170: =IF(I170="","",I170+N(N170+O170+P170)) -> 18 | X170: =IF(OR(W170="",F170=""),"",W170/(1+F170)) -> 16.216216 | Y170: =IF(OR(H170="",H170=0,X170="",X170=0),"",H170/X170) -> 0.317645
A171: Milkshake Banane 300G | B171: Milkshake Banane NEW | C171: MILKSHAKE & DESSERT | D171: Instore | E171: FOOD | F171: =IF(E171="","",IF(E171="DRINKS",0.21,0.11)) -> 0.11 | G171: =IF(B171="","",SUMIF(RETETAR!A:A,B171,RETETAR!F:F)) -> 6.46305 | H171: =IF(B171="","",SUMIF(RETETAR!A:A,B171,RETETAR!H:H)) -> 6.46305 | I171: 18 | J171: =IF(OR(I171="",F171=""),"",I171/(1+F171)) -> 16.216216 | K171: =IF(OR(G171="",G171=0,J171="",J171=0),"",G171/J171) -> 0.39855475 | L171: =IF(OR(H171="",H171=0,J171="",J171=0),"",H171/J171) -> 0.39855475 | N171: 0 | O171: 0 | P171: 0 | Q171: =IF(I171="","",I171+N(N171)) -> 18 | R171: =IF(OR(Q171="",F171=""),"",Q171/(1+F171)) -> 16.216216 | S171: =IF(OR(H171="",H171=0,R171="",R171=0),"",H171/R171) -> 0.39855475 | T171: =IF(I171="","",I171+N(N171+O171)) -> 18 | U171: =IF(OR(T171="",F171=""),"",T171/(1+F171)) -> 16.216216 | V171: =IF(OR(H171="",H171=0,U171="",U171=0),"",H171/U171) -> 0.39855475 | W171: =IF(I171="","",I171+N(N171+O171+P171)) -> 18 | X171: =IF(OR(W171="",F171=""),"",W171/(1+F171)) -> 16.216216 | Y171: =IF(OR(H171="",H171=0,X171="",X171=0),"",H171/X171) -> 0.39855475
A172: Milkshake Capsuni 300G | B172: Milkshake Capsuni NEW | C172: MILKSHAKE & DESSERT | D172: Instore | E172: FOOD | F172: =IF(E172="","",IF(E172="DRINKS",0.21,0.11)) -> 0.11 | G172: =IF(B172="","",SUMIF(RETETAR!A:A,B172,RETETAR!F:F)) -> 6.46305 | H172: =IF(B172="","",SUMIF(RETETAR!A:A,B172,RETETAR!H:H)) -> 6.46305 | I172: 18 | J172: =IF(OR(I172="",F172=""),"",I172/(1+F172)) -> 16.216216 | K172: =IF(OR(G172="",G172=0,J172="",J172=0),"",G172/J172) -> 0.39855475 | L172: =IF(OR(H172="",H172=0,J172="",J172=0),"",H172/J172) -> 0.39855475 | N172: 0 | O172: 0 | P172: 0 | Q172: =IF(I172="","",I172+N(N172)) -> 18 | R172: =IF(OR(Q172="",F172=""),"",Q172/(1+F172)) -> 16.216216 | S172: =IF(OR(H172="",H172=0,R172="",R172=0),"",H172/R172) -> 0.39855475 | T172: =IF(I172="","",I172+N(N172+O172)) -> 18 | U172: =IF(OR(T172="",F172=""),"",T172/(1+F172)) -> 16.216216 | V172: =IF(OR(H172="",H172=0,U172="",U172=0),"",H172/U172) -> 0.39855475 | W172: =IF(I172="","",I172+N(N172+O172+P172)) -> 18 | X172: =IF(OR(W172="",F172=""),"",W172/(1+F172)) -> 16.216216 | Y172: =IF(OR(H172="",H172=0,X172="",X172=0),"",H172/X172) -> 0.39855475
... A198: ApfelStorm X Toffee | B198: ApfelStorm X Toffee | C198: MILKSHAKE & DESSERT | D198: Instore | E198: FOOD | F198: =IF(E198="","",IF(E198="DRINKS",0.21,0.11)) -> 0.11 | G198: =IF(B198="","",SUMIF(RETETAR!A:A,B198,RETETAR!F:F)) -> 5.1634 | H198: =IF(B198="","",SUMIF(RETETAR!A:A,B198,RETETAR!H:H)) -> 5.1634 | I198: 19.9 | J198: =IF(OR(I198="",F198=""),"",I198/(1+F198)) -> 17.927928 | K198: =IF(OR(G198="",G198=0,J198="",J198=0),"",G198/J198) -> 0.28800874 | L198: =IF(OR(H198="",H198=0,J198="",J198=0),"",H198/J198) -> 0.28800874 | N198: 0 | O198: 0 | P198: 0 | Q198: =IF(I198="","",I198+N(N198)) -> 19.9 | R198: =IF(OR(Q198="",F198=""),"",Q198/(1+F198)) -> 17.927928 | S198: =IF(OR(H198="",H198=0,R198="",R198=0),"",H198/R198) -> 0.28800874 | T198: =IF(I198="","",I198+N(N198+O198)) -> 19.9 | U198: =IF(OR(T198="",F198=""),"",T198/(1+F198)) -> 17.927928 | V198: =IF(OR(H198="",H198=0,U198="",U198=0),"",H198/U198) -> 0.28800874 | W198: =IF(I198="","",I198+N(N198+O198+P198)) -> 19.9 | X198: =IF(OR(W198="",F198=""),"",W198/(1+F198)) -> 17.927928 | Y198: =IF(OR(H198="",H198=0,X198="",X198=0),"",H198/X198) -> 0.28800874
A199: Pepsi /PEPSI ZERO/7UP ZERO/MIRINDA ZERO/LIPTON 250ML | B199: Suc PET 250ml new | C199: DRINKS | D199: Instore | E199: DRINKS | F199: =IF(E199="","",IF(E199="DRINKS",0.21,0.11)) -> 0.21 | G199: =IF(B199="","",SUMIF(RETETAR!A:A,B199,RETETAR!F:F)) -> 2.5212004 | H199: =IF(B199="","",SUMIF(RETETAR!A:A,B199,RETETAR!H:H)) -> 2.5212004 | I199: 7 | J199: =IF(OR(I199="",F199=""),"",I199/(1+F199)) -> 5.785124 | K199: =IF(OR(G199="",G199=0,J199="",J199=0),"",G199/J199) -> 0.4358075 | L199: =IF(OR(H199="",H199=0,J199="",J199=0),"",H199/J199) -> 0.4358075 | M199: VOM AVEA RETETA ACTUALA LA 250 -DIN IUNIE TRECEM PE PAHARUL NOU DE 350 | N199: 0 | O199: 0 | P199: 0 | Q199: =IF(I199="","",I199+N(N199)) -> 7 | R199: =IF(OR(Q199="",F199=""),"",Q199/(1+F199)) -> 5.785124 | S199: =IF(OR(H199="",H199=0,R199="",R199=0),"",H199/R199) -> 0.4358075 | T199: =IF(I199="","",I199+N(N199+O199)) -> 7 | U199: =IF(OR(T199="",F199=""),"",T199/(1+F199)) -> 5.785124 | V199: =IF(OR(H199="",H199=0,U199="",U199=0),"",H199/U199) -> 0.4358075 | W199: =IF(I199="","",I199+N(N199+O199+P199)) -> 7 | X199: =IF(OR(W199="",F199=""),"",W199/(1+F199)) -> 5.785124 | Y199: =IF(OR(H199="",H199=0,X199="",X199=0),"",H199/X199) -> 0.4358075
A200: Pepsi /PEPSI ZERO/7UP ZERO/MIRINDA ZERO/LIPTON 500ML | B200: Suc PET 500ml new | C200: DRINKS | D200: Instore | E200: DRINKS | F200: =IF(E200="","",IF(E200="DRINKS",0.21,0.11)) -> 0.21 | G200: =IF(B200="","",SUMIF(RETETAR!A:A,B200,RETETAR!F:F)) -> 4.5494008 | H200: =IF(B200="","",SUMIF(RETETAR!A:A,B200,RETETAR!H:H)) -> 4.5494008 | I200: 10 | J200: =IF(OR(I200="",F200=""),"",I200/(1+F200)) -> 8.2644628 | K200: =IF(OR(G200="",G200=0,J200="",J200=0),"",G200/J200) -> 0.5504775 | L200: =IF(OR(H200="",H200=0,J200="",J200=0),"",H200/J200) -> 0.5504775 | M200: VOM AVEA RETETA ACTUALA LA 500 -DIN IUNIE TRECEM PE PAHARUL NOU DE 500 | N200: 0 | O200: 0 | P200: 0 | Q200: =IF(I200="","",I200+N(N200)) -> 10 | R200: =IF(OR(Q200="",F200=""),"",Q200/(1+F200)) -> 8.2644628 | S200: =IF(OR(H200="",H200=0,R200="",R200=0),"",H200/R200) -> 0.5504775 | T200: =IF(I200="","",I200+N(N200+O200)) -> 10 | U200: =IF(OR(T200="",F200=""),"",T200/(1+F200)) -> 8.2644628 | V200: =IF(OR(H200="",H200=0,U200="",U200=0),"",H200/U200) -> 0.5504775 | W200: =IF(I200="","",I200+N(N200+O200+P200)) -> 10 | X200: =IF(OR(W200="",F200=""),"",W200/(1+F200)) -> 8.2644628 | Y200: =IF(OR(H200="",H200=0,X200="",X200=0),"",H200/X200) -> 0.5504775
A201: Apa Plata AQUA CARPATICA | B201: Apa Plata AQUA CARPATICA new | C201: DRINKS | D201: Instore | E201: DRINKS | F201: =IF(E201="","",IF(E201="DRINKS",0.21,0.11)) -> 0.21 | G201: =IF(B201="","",SUMIF(RETETAR!A:A,B201,RETETAR!F:F)) -> 2.75 | H201: =IF(B201="","",SUMIF(RETETAR!A:A,B201,RETETAR!H:H)) -> 2.75 | I201: 10 | J201: =IF(OR(I201="",F201=""),"",I201/(1+F201)) -> 8.2644628 | K201: =IF(OR(G201="",G201=0,J201="",J201=0),"",G201/J201) -> 0.33275 | L201: =IF(OR(H201="",H201=0,J201="",J201=0),"",H201/J201) -> 0.33275 | N201: 0 | O201: 0 | P201: 0 | Q201: =IF(I201="","",I201+N(N201)) -> 10 | R201: =IF(OR(Q201="",F201=""),"",Q201/(1+F201)) -> 8.2644628 | S201: =IF(OR(H201="",H201=0,R201="",R201=0),"",H201/R201) -> 0.33275 | T201: =IF(I201="","",I201+N(N201+O201)) -> 10 | U201: =IF(OR(T201="",F201=""),"",T201/(1+F201)) -> 8.2644628 | V201: =IF(OR(H201="",H201=0,U201="",U201=0),"",H201/U201) -> 0.33275 | W201: =IF(I201="","",I201+N(N201+O201+P201)) -> 10 | X201: =IF(OR(W201="",F201=""),"",W201/(1+F201)) -> 8.2644628 | Y201: =IF(OR(H201="",H201=0,X201="",X201=0),"",H201/X201) -> 0.33275
A202: Apa Plata AQUA CARPATICA D | B202: Apa Plata AQUA CARPATICA new D | C202: DRINKS | D202: Delivery | E202: DRINKS | F202: =IF(E202="","",IF(E202="DRINKS",0.21,0.11)) -> 0.21 | G202: =IF(B202="","",SUMIF(RETETAR!A:A,B202,RETETAR!F:F)) -> 2.75 | H202: =IF(B202="","",SUMIF(RETETAR!A:A,B202,RETETAR!H:H)) -> 2.75 | I202: 11 | J202: =IF(OR(I202="",F202=""),"",I202/(1+F202)) -> 9.0909091 | K202: =IF(OR(G202="",G202=0,J202="",J202=0),"",G202/J202) -> 0.3025 | L202: =IF(OR(H202="",H202=0,J202="",J202=0),"",H202/J202) -> 0.3025 | N202: 0 | O202: 0 | P202: 0 | Q202: =IF(I202="","",I202+N(N202)) -> 11 | R202: =IF(OR(Q202="",F202=""),"",Q202/(1+F202)) -> 9.0909091 | S202: =IF(OR(H202="",H202=0,R202="",R202=0),"",H202/R202) -> 0.3025 | T202: =IF(I202="","",I202+N(N202+O202)) -> 11 | U202: =IF(OR(T202="",F202=""),"",T202/(1+F202)) -> 9.0909091 | V202: =IF(OR(H202="",H202=0,U202="",U202=0),"",H202/U202) -> 0.3025 | W202: =IF(I202="","",I202+N(N202+O202+P202)) -> 11 | X202: =IF(OR(W202="",F202=""),"",W202/(1+F202)) -> 9.0909091 | Y202: =IF(OR(H202="",H202=0,X202="",X202=0),"",H202/X202) -> 0.3025
A203: Apa Minerala AQUA CARPATICA | B203: Apa Minerala AQUA CARPATICA new | C203: DRINKS | D203: Instore | E203: DRINKS | F203: =IF(E203="","",IF(E203="DRINKS",0.21,0.11)) -> 0.21 | G203: =IF(B203="","",SUMIF(RETETAR!A:A,B203,RETETAR!F:F)) -> 2.75 | H203: =IF(B203="","",SUMIF(RETETAR!A:A,B203,RETETAR!H:H)) -> 2.75 | I203: 10 | J203: =IF(OR(I203="",F203=""),"",I203/(1+F203)) -> 8.2644628 | K203: =IF(OR(G203="",G203=0,J203="",J203=0),"",G203/J203) -> 0.33275 | L203: =IF(OR(H203="",H203=0,J203="",J203=0),"",H203/J203) -> 0.33275 | N203: 0 | O203: 0 | P203: 0 | Q203: =IF(I203="","",I203+N(N203)) -> 10 | R203: =IF(OR(Q203="",F203=""),"",Q203/(1+F203)) -> 8.2644628 | S203: =IF(OR(H203="",H203=0,R203="",R203=0),"",H203/R203) -> 0.33275 | T203: =IF(I203="","",I203+N(N203+O203)) -> 10 | U203: =IF(OR(T203="",F203=""),"",T203/(1+F203)) -> 8.2644628 | V203: =IF(OR(H203="",H203=0,U203="",U203=0),"",H203/U203) -> 0.33275 | W203: =IF(I203="","",I203+N(N203+O203+P203)) -> 10 | X203: =IF(OR(W203="",F203=""),"",W203/(1+F203)) -> 8.2644628 | Y203: =IF(OR(H203="",H203=0,X203="",X203=0),"",H203/X203) -> 0.33275
A204: Apa Minerala AQUA CARPATICA D | B204: Apa Minerala AQUA CARPATICA new D | C204: DRINKS | D204: Delivery | E204: DRINKS | F204: =IF(E204="","",IF(E204="DRINKS",0.21,0.11)) -> 0.21 | G204: =IF(B204="","",SUMIF(RETETAR!A:A,B204,RETETAR!F:F)) -> 2.75 | H204: =IF(B204="","",SUMIF(RETETAR!A:A,B204,RETETAR!H:H)) -> 2.75 | I204: 11 | J204: =IF(OR(I204="",F204=""),"",I204/(1+F204)) -> 9.0909091 | K204: =IF(OR(G204="",G204=0,J204="",J204=0),"",G204/J204) -> 0.3025 | L204: =IF(OR(H204="",H204=0,J204="",J204=0),"",H204/J204) -> 0.3025 | N204: 0 | O204: 0 | P204: 0 | Q204: =IF(I204="","",I204+N(N204)) -> 11 | R204: =IF(OR(Q204="",F204=""),"",Q204/(1+F204)) -> 9.0909091 | S204: =IF(OR(H204="",H204=0,R204="",R204=0),"",H204/R204) -> 0.3025 | T204: =IF(I204="","",I204+N(N204+O204)) -> 11 | U204: =IF(OR(T204="",F204=""),"",T204/(1+F204)) -> 9.0909091 | V204: =IF(OR(H204="",H204=0,U204="",U204=0),"",H204/U204) -> 0.3025 | W204: =IF(I204="","",I204+N(N204+O204+P204)) -> 11 | X204: =IF(OR(W204="",F204=""),"",W204/(1+F204)) -> 9.0909091 | Y204: =IF(OR(H204="",H204=0,X204="",X204=0),"",H204/X204) -> 0.3025
A205: Prigat Portocale/Capsuni &Banane | B205: Prigat Portocale new | C205: DRINKS | D205: Instore | E205: DRINKS | F205: =IF(E205="","",IF(E205="DRINKS",0.21,0.11)) -> 0.21 | G205: =IF(B205="","",SUMIF(RETETAR!A:A,B205,RETETAR!F:F)) -> 4.17 | H205: =IF(B205="","",SUMIF(RETETAR!A:A,B205,RETETAR!H:H)) -> 4.17 | I205: 10 | J205: =IF(OR(I205="",F205=""),"",I205/(1+F205)) -> 8.2644628 | K205: =IF(OR(G205="",G205=0,J205="",J205=0),"",G205/J205) -> 0.50457 | L205: =IF(OR(H205="",H205=0,J205="",J205=0),"",H205/J205) -> 0.50457 | M205: se delisteaza Prigat Limonada /Prigat Piersici | N205: 0 | O205: 0 | P205: 0 | Q205: =IF(I205="","",I205+N(N205)) -> 10 | R205: =IF(OR(Q205="",F205=""),"",Q205/(1+F205)) -> 8.2644628 | S205: =IF(OR(H205="",H205=0,R205="",R205=0),"",H205/R205) -> 0.50457 | T205: =IF(I205="","",I205+N(N205+O205)) -> 10 | U205: =IF(OR(T205="",F205=""),"",T205/(1+F205)) -> 8.2644628 | V205: =IF(OR(H205="",H205=0,U205="",U205=0),"",H205/U205) -> 0.50457 | W205: =IF(I205="","",I205+N(N205+O205+P205)) -> 10 | X205: =IF(OR(W205="",F205=""),"",W205/(1+F205)) -> 8.2644628 | Y205: =IF(OR(H205="",H205=0,X205="",X205=0),"",H205/X205) -> 0.50457
A206: Prigat Portocale/Capsuni &Banane D | B206: Prigat Portocale new D | C206: DRINKS | D206: Delivery | E206: DRINKS | F206: =IF(E206="","",IF(E206="DRINKS",0.21,0.11)) -> 0.21 | G206: =IF(B206="","",SUMIF(RETETAR!A:A,B206,RETETAR!F:F)) -> 4.17 | H206: =IF(B206="","",SUMIF(RETETAR!A:A,B206,RETETAR!H:H)) -> 4.17 | I206: 12 | J206: =IF(OR(I206="",F206=""),"",I206/(1+F206)) -> 9.9173554 | K206: =IF(OR(G206="",G206=0,J206="",J206=0),"",G206/J206) -> 0.420475 | L206: =IF(OR(H206="",H206=0,J206="",J206=0),"",H206/J206) -> 0.420475 | N206: 0 | O206: 0 | P206: 0 | Q206: =IF(I206="","",I206+N(N206)) -> 12 | R206: =IF(OR(Q206="",F206=""),"",Q206/(1+F206)) -> 9.9173554 | S206: =IF(OR(H206="",H206=0,R206="",R206=0),"",H206/R206) -> 0.420475 | T206: =IF(I206="","",I206+N(N206+O206)) -> 12 | U206: =IF(OR(T206="",F206=""),"",T206/(1+F206)) -> 9.9173554 | V206: =IF(OR(H206="",H206=0,U206="",U206=0),"",H206/U206) -> 0.420475 | W206: =IF(I206="","",I206+N(N206+O206+P206)) -> 12 | X206: =IF(OR(W206="",F206=""),"",W206/(1+F206)) -> 9.9173554 | Y206: =IF(OR(H206="",H206=0,X206="",X206=0),"",H206/X206) -> 0.420475
A207: Dr Pepper | B207: Dr Pepper new | C207: DRINKS | D207: Instore | E207: DRINKS | F207: =IF(E207="","",IF(E207="DRINKS",0.21,0.11)) -> 0.21 | G207: =IF(B207="","",SUMIF(RETETAR!A:A,B207,RETETAR!F:F)) -> 3.64 | H207: =IF(B207="","",SUMIF(RETETAR!A:A,B207,RETETAR!H:H)) -> 3.64 | I207: 11 | J207: =IF(OR(I207="",F207=""),"",I207/(1+F207)) -> 9.0909091 | K207: =IF(OR(G207="",G207=0,J207="",J207=0),"",G207/J207) -> 0.4004 | L207: =IF(OR(H207="",H207=0,J207="",J207=0),"",H207/J207) -> 0.4004 | N207: 0 | O207: 0 | P207: 0 | Q207: =IF(I207="","",I207+N(N207)) -> 11 | R207: =IF(OR(Q207="",F207=""),"",Q207/(1+F207)) -> 9.0909091 | S207: =IF(OR(H207="",H207=0,R207="",R207=0),"",H207/R207) -> 0.4004 | T207: =IF(I207="","",I207+N(N207+O207)) -> 11 | U207: =IF(OR(T207="",F207=""),"",T207/(1+F207)) -> 9.0909091 | V207: =IF(OR(H207="",H207=0,U207="",U207=0),"",H207/U207) -> 0.4004 | W207: =IF(I207="","",I207+N(N207+O207+P207)) -> 11 | X207: =IF(OR(W207="",F207=""),"",W207/(1+F207)) -> 9.0909091 | Y207: =IF(OR(H207="",H207=0,X207="",X207=0),"",H207/X207) -> 0.4004
A208: Dr Pepper D | B208: Dr Pepper new D | C208: DRINKS | D208: Delivery | E208: DRINKS | F208: =IF(E208="","",IF(E208="DRINKS",0.21,0.11)) -> 0.21 | G208: =IF(B208="","",SUMIF(RETETAR!A:A,B208,RETETAR!F:F)) -> 3.64 | H208: =IF(B208="","",SUMIF(RETETAR!A:A,B208,RETETAR!H:H)) -> 3.64 | I208: 12 | J208: =IF(OR(I208="",F208=""),"",I208/(1+F208)) -> 9.9173554 | K208: =IF(OR(G208="",G208=0,J208="",J208=0),"",G208/J208) -> 0.36703333 | L208: =IF(OR(H208="",H208=0,J208="",J208=0),"",H208/J208) -> 0.36703333 | N208: 0 | O208: 0 | P208: 0 | Q208: =IF(I208="","",I208+N(N208)) -> 12 | R208: =IF(OR(Q208="",F208=""),"",Q208/(1+F208)) -> 9.9173554 | S208: =IF(OR(H208="",H208=0,R208="",R208=0),"",H208/R208) -> 0.36703333 | T208: =IF(I208="","",I208+N(N208+O208)) -> 12 | U208: =IF(OR(T208="",F208=""),"",T208/(1+F208)) -> 9.9173554 | V208: =IF(OR(H208="",H208=0,U208="",U208=0),"",H208/U208) -> 0.36703333 | W208: =IF(I208="","",I208+N(N208+O208+P208)) -> 12 | X208: =IF(OR(W208="",F208=""),"",W208/(1+F208)) -> 9.9173554 | Y208: =IF(OR(H208="",H208=0,X208="",X208=0),"",H208/X208) -> 0.36703333
A209: Red Bull | B209: Red Bull new | C209: DRINKS | D209: Instore | E209: DRINKS | F209: =IF(E209="","",IF(E209="DRINKS",0.21,0.11)) -> 0.21 | G209: =IF(B209="","",SUMIF(RETETAR!A:A,B209,RETETAR!F:F)) -> 6.08 | H209: =IF(B209="","",SUMIF(RETETAR!A:A,B209,RETETAR!H:H)) -> 6.08 | I209: 15 | J209: =IF(OR(I209="",F209=""),"",I209/(1+F209)) -> 12.396694 | K209: =IF(OR(G209="",G209=0,J209="",J209=0),"",G209/J209) -> 0.49045333 | L209: =IF(OR(H209="",H209=0,J209="",J209=0),"",H209/J209) -> 0.49045333 | N209: 0 | O209: 0 | P209: 0 | Q209: =IF(I209="","",I209+N(N209)) -> 15 | R209: =IF(OR(Q209="",F209=""),"",Q209/(1+F209)) -> 12.396694 | S209: =IF(OR(H209="",H209=0,R209="",R209=0),"",H209/R209) -> 0.49045333 | T209: =IF(I209="","",I209+N(N209+O209)) -> 15 | U209: =IF(OR(T209="",F209=""),"",T209/(1+F209)) -> 12.396694 | V209: =IF(OR(H209="",H209=0,U209="",U209=0),"",H209/U209) -> 0.49045333 | W209: =IF(I209="","",I209+N(N209+O209+P209)) -> 15 | X209: =IF(OR(W209="",F209=""),"",W209/(1+F209)) -> 12.396694 | Y209: =IF(OR(H209="",H209=0,X209="",X209=0),"",H209/X209) -> 0.49045333
A210: Red Bull D | B210: Red Bull new D | C210: DRINKS | D210: Delivery | E210: DRINKS | F210: =IF(E210="","",IF(E210="DRINKS",0.21,0.11)) -> 0.21 | G210: =IF(B210="","",SUMIF(RETETAR!A:A,B210,RETETAR!F:F)) -> 6.08 | H210: =IF(B210="","",SUMIF(RETETAR!A:A,B210,RETETAR!H:H)) -> 6.08 | I210: 17 | J210: =IF(OR(I210="",F210=""),"",I210/(1+F210)) -> 14.049587 | K210: =IF(OR(G210="",G210=0,J210="",J210=0),"",G210/J210) -> 0.43275294 | L210: =IF(OR(H210="",H210=0,J210="",J210=0),"",H210/J210) -> 0.43275294 | N210: 0 | O210: 0 | P210: 0 | Q210: =IF(I210="","",I210+N(N210)) -> 17 | R210: =IF(OR(Q210="",F210=""),"",Q210/(1+F210)) -> 14.049587 | S210: =IF(OR(H210="",H210=0,R210="",R210=0),"",H210/R210) -> 0.43275294 | T210: =IF(I210="","",I210+N(N210+O210)) -> 17 | U210: =IF(OR(T210="",F210=""),"",T210/(1+F210)) -> 14.049587 | V210: =IF(OR(H210="",H210=0,U210="",U210=0),"",H210/U210) -> 0.43275294 | W210: =IF(I210="","",I210+N(N210+O210+P210)) -> 17 | X210: =IF(OR(W210="",F210=""),"",W210/(1+F210)) -> 14.049587 | Y210: =IF(OR(H210="",H210=0,X210="",X210=0),"",H210/X210) -> 0.43275294
A211: Corona | B211: Bere Corona new | C211: DRINKS | D211: Instore | E211: DRINKS | F211: =IF(E211="","",IF(E211="DRINKS",0.21,0.11)) -> 0.21 | G211: =IF(B211="","",SUMIF(RETETAR!A:A,B211,RETETAR!F:F)) -> 6.97 | H211: =IF(B211="","",SUMIF(RETETAR!A:A,B211,RETETAR!H:H)) -> 6.97 | I211: 15 | J211: =IF(OR(I211="",F211=""),"",I211/(1+F211)) -> 12.396694 | K211: =IF(OR(G211="",G211=0,J211="",J211=0),"",G211/J211) -> 0.56224667 | L211: =IF(OR(H211="",H211=0,J211="",J211=0),"",H211/J211) -> 0.56224667 | N211: 0 | O211: 0 | P211: 0 | Q211: =IF(I211="","",I211+N(N211)) -> 15 | R211: =IF(OR(Q211="",F211=""),"",Q211/(1+F211)) -> 12.396694 | S211: =IF(OR(H211="",H211=0,R211="",R211=0),"",H211/R211) -> 0.56224667 | T211: =IF(I211="","",I211+N(N211+O211)) -> 15 | U211: =IF(OR(T211="",F211=""),"",T211/(1+F211)) -> 12.396694 | V211: =IF(OR(H211="",H211=0,U211="",U211=0),"",H211/U211) -> 0.56224667 | W211: =IF(I211="","",I211+N(N211+O211+P211)) -> 15 | X211: =IF(OR(W211="",F211=""),"",W211/(1+F211)) -> 12.396694 | Y211: =IF(OR(H211="",H211=0,X211="",X211=0),"",H211/X211) -> 0.56224667
A212: Corona D | B212: Bere Corona new D | C212: DRINKS | D212: Delivery | E212: DRINKS | F212: =IF(E212="","",IF(E212="DRINKS",0.21,0.11)) -> 0.21 | G212: =IF(B212="","",SUMIF(RETETAR!A:A,B212,RETETAR!F:F)) -> 6.97 | H212: =IF(B212="","",SUMIF(RETETAR!A:A,B212,RETETAR!H:H)) -> 6.97 | I212: 19 | J212: =IF(OR(I212="",F212=""),"",I212/(1+F212)) -> 15.702479 | K212: =IF(OR(G212="",G212=0,J212="",J212=0),"",G212/J212) -> 0.44387895 | L212: =IF(OR(H212="",H212=0,J212="",J212=0),"",H212/J212) -> 0.44387895 | N212: 0 | O212: 0 | P212: 0 | Q212: =IF(I212="","",I212+N(N212)) -> 19 | R212: =IF(OR(Q212="",F212=""),"",Q212/(1+F212)) -> 15.702479 | S212: =IF(OR(H212="",H212=0,R212="",R212=0),"",H212/R212) -> 0.44387895 | T212: =IF(I212="","",I212+N(N212+O212)) -> 19 | U212: =IF(OR(T212="",F212=""),"",T212/(1+F212)) -> 15.702479 | V212: =IF(OR(H212="",H212=0,U212="",U212=0),"",H212/U212) -> 0.44387895 | W212: =IF(I212="","",I212+N(N212+O212+P212)) -> 19 | X212: =IF(OR(W212="",F212=""),"",W212/(1+F212)) -> 15.702479 | Y212: =IF(OR(H212="",H212=0,X212="",X212=0),"",H212/X212) -> 0.44387895
A213: Budweiser | B213: Budweiser new | C213: DRINKS | D213: Instore | E213: DRINKS | F213: =IF(E213="","",IF(E213="DRINKS",0.21,0.11)) -> 0.21 | G213: =IF(B213="","",SUMIF(RETETAR!A:A,B213,RETETAR!F:F)) -> 6.23 | H213: =IF(B213="","",SUMIF(RETETAR!A:A,B213,RETETAR!H:H)) -> 6.23 | I213: 15 | J213: =IF(OR(I213="",F213=""),"",I213/(1+F213)) -> 12.396694 | K213: =IF(OR(G213="",G213=0,J213="",J213=0),"",G213/J213) -> 0.50255333 | L213: =IF(OR(H213="",H213=0,J213="",J213=0),"",H213/J213) -> 0.50255333 | N213: 0 | O213: 0 | P213: 0 | Q213: =IF(I213="","",I213+N(N213)) -> 15 | R213: =IF(OR(Q213="",F213=""),"",Q213/(1+F213)) -> 12.396694 | S213: =IF(OR(H213="",H213=0,R213="",R213=0),"",H213/R213) -> 0.50255333 | T213: =IF(I213="","",I213+N(N213+O213)) -> 15 | U213: =IF(OR(T213="",F213=""),"",T213/(1+F213)) -> 12.396694 | V213: =IF(OR(H213="",H213=0,U213="",U213=0),"",H213/U213) -> 0.50255333 | W213: =IF(I213="","",I213+N(N213+O213+P213)) -> 15 | X213: =IF(OR(W213="",F213=""),"",W213/(1+F213)) -> 12.396694 | Y213: =IF(OR(H213="",H213=0,X213="",X213=0),"",H213/X213) -> 0.50255333
A214: Budweiser D | B214: Budweiser new D | C214: DRINKS | D214: Delivery | E214: DRINKS | F214: =IF(E214="","",IF(E214="DRINKS",0.21,0.11)) -> 0.21 | G214: =IF(B214="","",SUMIF(RETETAR!A:A,B214,RETETAR!F:F)) -> 6.23 | H214: =IF(B214="","",SUMIF(RETETAR!A:A,B214,RETETAR!H:H)) -> 6.23 | I214: 18 | J214: =IF(OR(I214="",F214=""),"",I214/(1+F214)) -> 14.876033 | K214: =IF(OR(G214="",G214=0,J214="",J214=0),"",G214/J214) -> 0.41879444 | L214: =IF(OR(H214="",H214=0,J214="",J214=0),"",H214/J214) -> 0.41879444 | N214: 0 | O214: 0 | P214: 0 | Q214: =IF(I214="","",I214+N(N214)) -> 18 | R214: =IF(OR(Q214="",F214=""),"",Q214/(1+F214)) -> 14.876033 | S214: =IF(OR(H214="",H214=0,R214="",R214=0),"",H214/R214) -> 0.41879444 | T214: =IF(I214="","",I214+N(N214+O214)) -> 18 | U214: =IF(OR(T214="",F214=""),"",T214/(1+F214)) -> 14.876033 | V214: =IF(OR(H214="",H214=0,U214="",U214=0),"",H214/U214) -> 0.41879444 | W214: =IF(I214="","",I214+N(N214+O214+P214)) -> 18 | X214: =IF(OR(W214="",F214=""),"",W214/(1+F214)) -> 14.876033 | Y214: =IF(OR(H214="",H214=0,X214="",X214=0),"",H214/X214) -> 0.41879444
A215: Apa Evian | B215: Apa Evian new | C215: DRINKS | D215: Instore | E215: DRINKS | F215: =IF(E215="","",IF(E215="DRINKS",0.21,0.11)) -> 0.21 | G215: =IF(B215="","",SUMIF(RETETAR!A:A,B215,RETETAR!F:F)) -> 6.57 | H215: =IF(B215="","",SUMIF(RETETAR!A:A,B215,RETETAR!H:H)) -> 6.57 | I215: 15 | J215: =IF(OR(I215="",F215=""),"",I215/(1+F215)) -> 12.396694 | K215: =IF(OR(G215="",G215=0,J215="",J215=0),"",G215/J215) -> 0.52998 | L215: =IF(OR(H215="",H215=0,J215="",J215=0),"",H215/J215) -> 0.52998 | N215: 0 | O215: 0 | P215: 0 | Q215: =IF(I215="","",I215+N(N215)) -> 15 | R215: =IF(OR(Q215="",F215=""),"",Q215/(1+F215)) -> 12.396694 | S215: =IF(OR(H215="",H215=0,R215="",R215=0),"",H215/R215) -> 0.52998 | T215: =IF(I215="","",I215+N(N215+O215)) -> 15 | U215: =IF(OR(T215="",F215=""),"",T215/(1+F215)) -> 12.396694 | V215: =IF(OR(H215="",H215=0,U215="",U215=0),"",H215/U215) -> 0.52998 | W215: =IF(I215="","",I215+N(N215+O215+P215)) -> 15 | X215: =IF(OR(W215="",F215=""),"",W215/(1+F215)) -> 12.396694 | Y215: =IF(OR(H215="",H215=0,X215="",X215=0),"",H215/X215) -> 0.52998
A216: Apa Evian D | B216: Apa Evian new D | C216: DRINKS | D216: Delivery | E216: DRINKS | F216: =IF(E216="","",IF(E216="DRINKS",0.21,0.11)) -> 0.21 | G216: =IF(B216="","",SUMIF(RETETAR!A:A,B216,RETETAR!F:F)) -> 6.57 | H216: =IF(B216="","",SUMIF(RETETAR!A:A,B216,RETETAR!H:H)) -> 6.57 | I216: 17 | J216: =IF(OR(I216="",F216=""),"",I216/(1+F216)) -> 14.049587 | K216: =IF(OR(G216="",G216=0,J216="",J216=0),"",G216/J216) -> 0.46762941 | L216: =IF(OR(H216="",H216=0,J216="",J216=0),"",H216/J216) -> 0.46762941 | N216: 0 | O216: 0 | P216: 0 | Q216: =IF(I216="","",I216+N(N216)) -> 17 | R216: =IF(OR(Q216="",F216=""),"",Q216/(1+F216)) -> 14.049587 | S216: =IF(OR(H216="",H216=0,R216="",R216=0),"",H216/R216) -> 0.46762941 | T216: =IF(I216="","",I216+N(N216+O216)) -> 17 | U216: =IF(OR(T216="",F216=""),"",T216/(1+F216)) -> 14.049587 | V216: =IF(OR(H216="",H216=0,U216="",U216=0),"",H216/U216) -> 0.46762941 | W216: =IF(I216="","",I216+N(N216+O216+P216)) -> 17 | X216: =IF(OR(W216="",F216=""),"",W216/(1+F216)) -> 14.049587 | Y216: =IF(OR(H216="",H216=0,X216="",X216=0),"",H216/X216) -> 0.46762941
A217: FRYZZZ CAPSUNI | B217: FRYZZZ CAPSUNI new | C217: DRINKS | D217: Instore | E217: DRINKS | F217: =IF(E217="","",IF(E217="DRINKS",0.21,0.11)) -> 0.21 | G217: =IF(B217="","",SUMIF(RETETAR!A:A,B217,RETETAR!F:F)) -> 3.393092 | H217: =IF(B217="","",SUMIF(RETETAR!A:A,B217,RETETAR!H:H)) -> 3.393092 | I217: 13 | J217: =IF(OR(I217="",F217=""),"",I217/(1+F217)) -> 10.743802 | K217: =IF(OR(G217="",G217=0,J217="",J217=0),"",G217/J217) -> 0.31581856 | L217: =IF(OR(H217="",H217=0,J217="",J217=0),"",H217/J217) -> 0.31581856 | N217: 0 | O217: 0 | P217: 0 | Q217: =IF(I217="","",I217+N(N217)) -> 13 | R217: =IF(OR(Q217="",F217=""),"",Q217/(1+F217)) -> 10.743802 | S217: =IF(OR(H217="",H217=0,R217="",R217=0),"",H217/R217) -> 0.31581856 | T217: =IF(I217="","",I217+N(N217+O217)) -> 13 | U217: =IF(OR(T217="",F217=""),"",T217/(1+F217)) -> 10.743802 | V217: =IF(OR(H217="",H217=0,U217="",U217=0),"",H217/U217) -> 0.31581856 | W217: =IF(I217="","",I217+N(N217+O217+P217)) -> 13 | X217: =IF(OR(W217="",F217=""),"",W217/(1+F217)) -> 10.743802 | Y217: =IF(OR(H217="",H217=0,X217="",X217=0),"",H217/X217) -> 0.31581856
... A287: Junior Meal 4 Nuggets D | B287: Junior Meal 4 Nuggets new D | C287: JUNIOR | D287: Delivery | E287: FOOD | F287: =IF(E287="","",IF(E287="DRINKS",0.21,0.11)) -> 0.11 | G287: =IF(B287="","",SUMIF(RETETAR!A:A,B287,RETETAR!F:F)) -> 20.36112 | H287: =IF(B287="","",SUMIF(RETETAR!A:A,B287,RETETAR!H:H)) -> 20.36112 | I287: 39 | J287: =IF(OR(I287="",F287=""),"",I287/(1+F287)) -> 35.135135 | K287: =IF(OR(G287="",G287=0,J287="",J287=0),"",G287/J287) -> 0.57950881 | L287: =IF(OR(H287="",H287=0,J287="",J287=0),"",H287/J287) -> 0.57950881 | N287: 0.25 | O287: 0.25 | P287: 0.49 | Q287: =IF(I287="","",I287+N(N287)) -> 39.25 | R287: =IF(OR(Q287="",F287=""),"",Q287/(1+F287)) -> 35.36036 | S287: =IF(OR(H287="",H287=0,R287="",R287=0),"",H287/R287) -> 0.57581767 | T287: =IF(I287="","",I287+N(N287+O287)) -> 39.5 | U287: =IF(OR(T287="",F287=""),"",T287/(1+F287)) -> 35.585586 | V287: =IF(OR(H287="",H287=0,U287="",U287=0),"",H287/U287) -> 0.57217326 | W287: =IF(I287="","",I287+N(N287+O287+P287)) -> 39.99 | X287: =IF(OR(W287="",F287=""),"",W287/(1+F287)) -> 36.027027 | Y287: =IF(OR(H287="",H287=0,X287="",X287=0),"",H287/X287) -> 0.56516238
F289: =IF(E289="","",IF(E289="DRINKS",0.21,0.11)) | G289: =IF(B289="","",SUMIF(RETETAR!A:A,B289,RETETAR!F:F)) | H289: =IF(B289="","",SUMIF(RETETAR!A:A,B289,RETETAR!H:H)) | J289: =IF(OR(I289="",F289=""),"",I289/(1+F289)) | K289: =IF(OR(G289="",G289=0,J289="",J289=0),"",G289/J289) | L289: =IF(OR(H289="",H289=0,J289="",J289=0),"",H289/J289)
F290: =IF(E290="","",IF(E290="DRINKS",0.21,0.11)) | G290: =IF(B290="","",SUMIF(RETETAR!A:A,B290,RETETAR!F:F)) | H290: =IF(B290="","",SUMIF(RETETAR!A:A,B290,RETETAR!H:H)) | J290: =IF(OR(I290="",F290=""),"",I290/(1+F290)) | K290: =IF(OR(G290="",G290=0,J290="",J290=0),"",G290/J290) | L290: =IF(OR(H290="",H290=0,J290="",J290=0),"",H290/J290)
F291: =IF(E291="","",IF(E291="DRINKS",0.21,0.11)) | G291: =IF(B291="","",SUMIF(RETETAR!A:A,B291,RETETAR!F:F)) | H291: =IF(B291="","",SUMIF(RETETAR!A:A,B291,RETETAR!H:H)) | J291: =IF(OR(I291="",F291=""),"",I291/(1+F291)) | K291: =IF(OR(G291="",G291=0,J291="",J291=0),"",G291/J291) | L291: =IF(OR(H291="",H291=0,J291="",J291=0),"",H291/J291)
F292: =IF(E292="","",IF(E292="DRINKS",0.21,0.11)) | G292: =IF(B292="","",SUMIF(RETETAR!A:A,B292,RETETAR!F:F)) | H292: =IF(B292="","",SUMIF(RETETAR!A:A,B292,RETETAR!H:H)) | J292: =IF(OR(I292="",F292=""),"",I292/(1+F292)) | K292: =IF(OR(G292="",G292=0,J292="",J292=0),"",G292/J292) | L292: =IF(OR(H292="",H292=0,J292="",J292=0),"",H292/J292)
F293: =IF(E293="","",IF(E293="DRINKS",0.21,0.11)) | G293: =IF(B293="","",SUMIF(RETETAR!A:A,B293,RETETAR!F:F)) | H293: =IF(B293="","",SUMIF(RETETAR!A:A,B293,RETETAR!H:H)) | J293: =IF(OR(I293="",F293=""),"",I293/(1+F293)) | K293: =IF(OR(G293="",G293=0,J293="",J293=0),"",G293/J293) | L293: =IF(OR(H293="",H293=0,J293="",J293=0),"",H293/J293)
F294: =IF(E294="","",IF(E294="DRINKS",0.21,0.11)) | G294: =IF(B294="","",SUMIF(RETETAR!A:A,B294,RETETAR!F:F)) | H294: =IF(B294="","",SUMIF(RETETAR!A:A,B294,RETETAR!H:H)) | J294: =IF(OR(I294="",F294=""),"",I294/(1+F294)) | K294: =IF(OR(G294="",G294=0,J294="",J294=0),"",G294/J294) | L294: =IF(OR(H294="",H294=0,J294="",J294=0),"",H294/J294)
F295: =IF(E295="","",IF(E295="DRINKS",0.21,0.11)) | G295: =IF(B295="","",SUMIF(RETETAR!A:A,B295,RETETAR!F:F)) | H295: =IF(B295="","",SUMIF(RETETAR!A:A,B295,RETETAR!H:H)) | J295: =IF(OR(I295="",F295=""),"",I295/(1+F295)) | K295: =IF(OR(G295="",G295=0,J295="",J295=0),"",G295/J295) | L295: =IF(OR(H295="",H295=0,J295="",J295=0),"",H295/J295)
F296: =IF(E296="","",IF(E296="DRINKS",0.21,0.11)) | G296: =IF(B296="","",SUMIF(RETETAR!A:A,B296,RETETAR!F:F)) | H296: =IF(B296="","",SUMIF(RETETAR!A:A,B296,RETETAR!H:H)) | J296: =IF(OR(I296="",F296=""),"",I296/(1+F296)) | K296: =IF(OR(G296="",G296=0,J296="",J296=0),"",G296/J296) | L296: =IF(OR(H296="",H296=0,J296="",J296=0),"",H296/J296)
F297: =IF(E297="","",IF(E297="DRINKS",0.21,0.11)) | G297: =IF(B297="","",SUMIF(RETETAR!A:A,B297,RETETAR!F:F)) | H297: =IF(B297="","",SUMIF(RETETAR!A:A,B297,RETETAR!H:H)) | J297: =IF(OR(I297="",F297=""),"",I297/(1+F297)) | K297: =IF(OR(G297="",G297=0,J297="",J297=0),"",G297/J297) | L297: =IF(OR(H297="",H297=0,J297="",J297=0),"",H297/J297)
F298: =IF(E298="","",IF(E298="DRINKS",0.21,0.11)) | G298: =IF(B298="","",SUMIF(RETETAR!A:A,B298,RETETAR!F:F)) | H298: =IF(B298="","",SUMIF(RETETAR!A:A,B298,RETETAR!H:H)) | J298: =IF(OR(I298="",F298=""),"",I298/(1+F298)) | K298: =IF(OR(G298="",G298=0,J298="",J298=0),"",G298/J298) | L298: =IF(OR(H298="",H298=0,J298="",J298=0),"",H298/J298)
F299: =IF(E299="","",IF(E299="DRINKS",0.21,0.11)) | G299: =IF(B299="","",SUMIF(RETETAR!A:A,B299,RETETAR!F:F)) | H299: =IF(B299="","",SUMIF(RETETAR!A:A,B299,RETETAR!H:H)) | J299: =IF(OR(I299="",F299=""),"",I299/(1+F299)) | K299: =IF(OR(G299="",G299=0,J299="",J299=0),"",G299/J299) | L299: =IF(OR(H299="",H299=0,J299="",J299=0),"",H299/J299)
F300: =IF(E300="","",IF(E300="DRINKS",0.21,0.11)) | G300: =IF(B300="","",SUMIF(RETETAR!A:A,B300,RETETAR!F:F)) | H300: =IF(B300="","",SUMIF(RETETAR!A:A,B300,RETETAR!H:H)) | J300: =IF(OR(I300="",F300=""),"",I300/(1+F300)) | K300: =IF(OR(G300="",G300=0,J300="",J300=0),"",G300/J300) | L300: =IF(OR(H300="",H300=0,J300="",J300=0),"",H300/J300)
... F348: =IF(E348="","",IF(E348="DRINKS",0.21,0.11)) | G348: =IF(B348="","",SUMIF(RETETAR!A:A,B348,RETETAR!F:F)) | H348: =IF(B348="","",SUMIF(RETETAR!A:A,B348,RETETAR!H:H)) | J348: =IF(OR(I348="",F348=""),"",I348/(1+F348)) | K348: =IF(OR(G348="",G348=0,J348="",J348=0),"",G348/J348) | L348: =IF(OR(H348="",H348=0,J348="",J348=0),"",H348/J348)

Sheet FC PMIX
A1: FC PMIX iunie — food cost pe 4 etape
A2: Buc=PMIX iunie. Preț&MC din FOOD COST (Δ editabile acolo). FC = Σ MC tot / Σ Sales fără TVA.
A3: NBO Net Sales iunie (editabil): | C3: 15961732
A4: Actual = MC actual TOT (cu free+delistate) / NBO. Aug/Oct/Dec = MC nou DOAR meniu / Sales listă etapă (fără free/discount/delistate).
E5: Etapă | F5: Bază (lei) | G5: FC | H5: Δ vs Actual (pp)
E6: Actual | F6: =$C$3 -> 15961732 | G6: =J295/$C$3 -> 0.44974733 | H6: =IF(OR(G6="",$G$6=""),"",(G6-$G$6)*100) -> 0
E7: August | F7: =IF(N(M295)=0,"",M295) -> 16350953 | G7: =IF(N(M295)=0,"",(K295-K294)/M295) -> 0.45130052 | H7: =IF(OR(G7="",$G$6=""),"",(G7-$G$6)*100) -> 0.15531887
E8: Octombrie | F8: =IF(N(N295)=0,"",N295) -> 16556461 | G8: =IF(N(N295)=0,"",(K295-K294)/N295) -> 0.44569873 | H8: =IF(OR(G8="",$G$6=""),"",(G8-$G$6)*100) -> -0.40486007
E9: Decembrie | F9: =IF(N(O295)=0,"",O295) -> 16840112 | G9: =IF(N(O295)=0,"",(K295-K294)/O295) -> 0.43819149 | H9: =IF(OR(G9="",$G$6=""),"",(G9-$G$6)*100) -> -1.1555836
A10: Denumire comercială | B10: Canal | C10: Buc iunie | D10: MC actual | E10: MC nou | F10: Preț fT Act | G10: Preț fT Aug | H10: Preț fT Oct | I10: Preț fT Dec | J10: MC tot act | K10: MC tot nou | L10: Sales Act | M10: Sales Aug | N10: Sales Oct | O10: Sales Dec
A11: HAMBURGER | B11: Instore | C11: 17589 | D11: =IFERROR(VLOOKUP("HAMBURGER",'FOOD COST'!$A:$Y,7,0),"") -> 5.765942 | E11: =IFERROR(VLOOKUP("HAMBURGER",'FOOD COST'!$A:$Y,8,0),"") -> 6.183612 | F11: =IFERROR(VLOOKUP("HAMBURGER",'FOOD COST'!$A:$Y,10,0),"") -> 7.2072072 | G11: =IFERROR(VLOOKUP("HAMBURGER",'FOOD COST'!$A:$Y,18,0),"") -> 7.2072072 | H11: =IFERROR(VLOOKUP("HAMBURGER",'FOOD COST'!$A:$Y,21,0),"") -> 7.6486486 | I11: =IFERROR(VLOOKUP("HAMBURGER",'FOOD COST'!$A:$Y,24,0),"") -> 8.0990991 | J11: =IF(OR(C11="",NOT(ISNUMBER(D11))),"",C11*D11) -> 101417.15 | K11: =IF(OR(C11="",NOT(ISNUMBER(E11))),"",C11*E11) -> 108763.55 | L11: =IF(OR(C11="",NOT(ISNUMBER(F11))),"",C11*F11) -> 126767.57 | M11: =IF(OR(C11="",NOT(ISNUMBER(G11))),"",C11*G11) -> 126767.57 | N11: =IF(OR(C11="",NOT(ISNUMBER(H11))),"",C11*H11) -> 134532.08 | O11: =IF(OR(C11="",NOT(ISNUMBER(I11))),"",C11*I11) -> 142455.05
A12: HAMBURGER D | B12: Delivery | C12: 4393 | D12: =IFERROR(VLOOKUP("HAMBURGER D",'FOOD COST'!$A:$Y,7,0),"") -> 5.765942 | E12: =IFERROR(VLOOKUP("HAMBURGER D",'FOOD COST'!$A:$Y,8,0),"") -> 6.183612 | F12: =IFERROR(VLOOKUP("HAMBURGER D",'FOOD COST'!$A:$Y,10,0),"") -> 9.009009 | G12: =IFERROR(VLOOKUP("HAMBURGER D",'FOOD COST'!$A:$Y,18,0),"") -> 9.009009 | H12: =IFERROR(VLOOKUP("HAMBURGER D",'FOOD COST'!$A:$Y,21,0),"") -> 9.4504505 | I12: =IFERROR(VLOOKUP("HAMBURGER D",'FOOD COST'!$A:$Y,24,0),"") -> 9.9009009 | J12: =IF(OR(C12="",NOT(ISNUMBER(D12))),"",C12*D12) -> 25329.783 | K12: =IF(OR(C12="",NOT(ISNUMBER(E12))),"",C12*E12) -> 27164.608 | L12: =IF(OR(C12="",NOT(ISNUMBER(F12))),"",C12*F12) -> 39576.577 | M12: =IF(OR(C12="",NOT(ISNUMBER(G12))),"",C12*G12) -> 39576.577 | N12: =IF(OR(C12="",NOT(ISNUMBER(H12))),"",C12*H12) -> 41515.829 | O12: =IF(OR(C12="",NOT(ISNUMBER(I12))),"",C12*I12) -> 43494.658
A13: DUBLU HAMBURGER | B13: Instore | C13: 2251 | D13: =IFERROR(VLOOKUP("DUBLU HAMBURGER",'FOOD COST'!$A:$Y,7,0),"") -> 8.799884 | E13: =IFERROR(VLOOKUP("DUBLU HAMBURGER",'FOOD COST'!$A:$Y,8,0),"") -> 9.635224 | F13: =IFERROR(VLOOKUP("DUBLU HAMBURGER",'FOOD COST'!$A:$Y,10,0),"") -> 12.612613 | G13: =IFERROR(VLOOKUP("DUBLU HAMBURGER",'FOOD COST'!$A:$Y,18,0),"") -> 13.504505 | H13: =IFERROR(VLOOKUP("DUBLU HAMBURGER",'FOOD COST'!$A:$Y,21,0),"") -> 13.504505 | I13: =IFERROR(VLOOKUP("DUBLU HAMBURGER",'FOOD COST'!$A:$Y,24,0),"") -> 13.954955 | J13: =IF(OR(C13="",NOT(ISNUMBER(D13))),"",C13*D13) -> 19808.539 | K13: =IF(OR(C13="",NOT(ISNUMBER(E13))),"",C13*E13) -> 21688.889 | L13: =IF(OR(C13="",NOT(ISNUMBER(F13))),"",C13*F13) -> 28390.991 | M13: =IF(OR(C13="",NOT(ISNUMBER(G13))),"",C13*G13) -> 30398.64 | N13: =IF(OR(C13="",NOT(ISNUMBER(H13))),"",C13*H13) -> 30398.64 | O13: =IF(OR(C13="",NOT(ISNUMBER(I13))),"",C13*I13) -> 31412.604
A14: DUBLU HAMBURGER D | B14: Delivery | C14: 1656 | D14: =IFERROR(VLOOKUP("DUBLU HAMBURGER D",'FOOD COST'!$A:$Y,7,0),"") -> 8.799884 | E14: =IFERROR(VLOOKUP("DUBLU HAMBURGER D",'FOOD COST'!$A:$Y,8,0),"") -> 9.635224 | F14: =IFERROR(VLOOKUP("DUBLU HAMBURGER D",'FOOD COST'!$A:$Y,10,0),"") -> 14.414414 | G14: =IFERROR(VLOOKUP("DUBLU HAMBURGER D",'FOOD COST'!$A:$Y,18,0),"") -> 15.306306 | H14: =IFERROR(VLOOKUP("DUBLU HAMBURGER D",'FOOD COST'!$A:$Y,21,0),"") -> 15.306306 | I14: =IFERROR(VLOOKUP("DUBLU HAMBURGER D",'FOOD COST'!$A:$Y,24,0),"") -> 15.756757 | J14: =IF(OR(C14="",NOT(ISNUMBER(D14))),"",C14*D14) -> 14572.608 | K14: =IF(OR(C14="",NOT(ISNUMBER(E14))),"",C14*E14) -> 15955.931 | L14: =IF(OR(C14="",NOT(ISNUMBER(F14))),"",C14*F14) -> 23870.27 | M14: =IF(OR(C14="",NOT(ISNUMBER(G14))),"",C14*G14) -> 25347.243 | N14: =IF(OR(C14="",NOT(ISNUMBER(H14))),"",C14*H14) -> 25347.243 | O14: =IF(OR(C14="",NOT(ISNUMBER(I14))),"",C14*I14) -> 26093.189
A15: CHEESEBURGER | B15: Instore | C15: 24912 | D15: =IFERROR(VLOOKUP("CHEESEBURGER",'FOOD COST'!$A:$Y,7,0),"") -> 6.381612 | E15: =IFERROR(VLOOKUP("CHEESEBURGER",'FOOD COST'!$A:$Y,8,0),"") -> 6.799282 | F15: =IFERROR(VLOOKUP("CHEESEBURGER",'FOOD COST'!$A:$Y,10,0),"") -> 9.9099099 | G15: =IFERROR(VLOOKUP("CHEESEBURGER",'FOOD COST'!$A:$Y,18,0),"") -> 10.351351 | H15: =IFERROR(VLOOKUP("CHEESEBURGER",'FOOD COST'!$A:$Y,21,0),"") -> 10.351351 | I15: =IFERROR(VLOOKUP("CHEESEBURGER",'FOOD COST'!$A:$Y,24,0),"") -> 10.801802 | J15: =IF(OR(C15="",NOT(ISNUMBER(D15))),"",C15*D15) -> 158978.72 | K15: =IF(OR(C15="",NOT(ISNUMBER(E15))),"",C15*E15) -> 169383.71 | L15: =IF(OR(C15="",NOT(ISNUMBER(F15))),"",C15*F15) -> 246875.68 | M15: =IF(OR(C15="",NOT(ISNUMBER(G15))),"",C15*G15) -> 257872.86 | N15: =IF(OR(C15="",NOT(ISNUMBER(H15))),"",C15*H15) -> 257872.86 | O15: =IF(OR(C15="",NOT(ISNUMBER(I15))),"",C15*I15) -> 269094.49
A16: CHEESEBURGER D | B16: Delivery | C16: 7262 | D16: =IFERROR(VLOOKUP("CHEESEBURGER D",'FOOD COST'!$A:$Y,7,0),"") -> 6.381612 | E16: =IFERROR(VLOOKUP("CHEESEBURGER D",'FOOD COST'!$A:$Y,8,0),"") -> 6.799282 | F16: =IFERROR(VLOOKUP("CHEESEBURGER D",'FOOD COST'!$A:$Y,10,0),"") -> 11.711712 | G16: =IFERROR(VLOOKUP("CHEESEBURGER D",'FOOD COST'!$A:$Y,18,0),"") -> 12.153153 | H16: =IFERROR(VLOOKUP("CHEESEBURGER D",'FOOD COST'!$A:$Y,21,0),"") -> 12.153153 | I16: =IFERROR(VLOOKUP("CHEESEBURGER D",'FOOD COST'!$A:$Y,24,0),"") -> 12.603604 | J16: =IF(OR(C16="",NOT(ISNUMBER(D16))),"",C16*D16) -> 46343.266 | K16: =IF(OR(C16="",NOT(ISNUMBER(E16))),"",C16*E16) -> 49376.386 | L16: =IF(OR(C16="",NOT(ISNUMBER(F16))),"",C16*F16) -> 85050.45 | M16: =IF(OR(C16="",NOT(ISNUMBER(G16))),"",C16*G16) -> 88256.198 | N16: =IF(OR(C16="",NOT(ISNUMBER(H16))),"",C16*H16) -> 88256.198 | O16: =IF(OR(C16="",NOT(ISNUMBER(I16))),"",C16*I16) -> 91527.369
A17: DUBLU CHEESEBURGER | B17: Instore | C17: 15886 | D17: =IFERROR(VLOOKUP("DUBLU CHEESEBURGER",'FOOD COST'!$A:$Y,7,0),"") -> 10.031224 | E17: =IFERROR(VLOOKUP("DUBLU CHEESEBURGER",'FOOD COST'!$A:$Y,8,0),"") -> 10.866564 | F17: =IFERROR(VLOOKUP("DUBLU CHEESEBURGER",'FOOD COST'!$A:$Y,10,0),"") -> 15.315315 | G17: =IFERROR(VLOOKUP("DUBLU CHEESEBURGER",'FOOD COST'!$A:$Y,18,0),"") -> 16.207207 | H17: =IFERROR(VLOOKUP("DUBLU CHEESEBURGER",'FOOD COST'!$A:$Y,21,0),"") -> 16.207207 | I17: =IFERROR(VLOOKUP("DUBLU CHEESEBURGER",'FOOD COST'!$A:$Y,24,0),"") -> 16.657658 | J17: =IF(OR(C17="",NOT(ISNUMBER(D17))),"",C17*D17) -> 159356.02 | K17: =IF(OR(C17="",NOT(ISNUMBER(E17))),"",C17*E17) -> 172626.24 | L17: =IF(OR(C17="",NOT(ISNUMBER(F17))),"",C17*F17) -> 243299.1 | M17: =IF(OR(C17="",NOT(ISNUMBER(G17))),"",C17*G17) -> 257467.69 | N17: =IF(OR(C17="",NOT(ISNUMBER(H17))),"",C17*H17) -> 257467.69 | O17: =IF(OR(C17="",NOT(ISNUMBER(I17))),"",C17*I17) -> 264623.55
A18: DUBLU CHEESEBURGER D | B18: Delivery | C18: 20436 | D18: =IFERROR(VLOOKUP("DUBLU CHEESEBURGER D",'FOOD COST'!$A:$Y,7,0),"") -> 10.031224 | E18: =IFERROR(VLOOKUP("DUBLU CHEESEBURGER D",'FOOD COST'!$A:$Y,8,0),"") -> 10.866564 | F18: =IFERROR(VLOOKUP("DUBLU CHEESEBURGER D",'FOOD COST'!$A:$Y,10,0),"") -> 17.117117 | G18: =IFERROR(VLOOKUP("DUBLU CHEESEBURGER D",'FOOD COST'!$A:$Y,18,0),"") -> 18.009009 | H18: =IFERROR(VLOOKUP("DUBLU CHEESEBURGER D",'FOOD COST'!$A:$Y,21,0),"") -> 18.009009 | I18: =IFERROR(VLOOKUP("DUBLU CHEESEBURGER D",'FOOD COST'!$A:$Y,24,0),"") -> 18.459459 | J18: =IF(OR(C18="",NOT(ISNUMBER(D18))),"",C18*D18) -> 204998.09 | K18: =IF(OR(C18="",NOT(ISNUMBER(E18))),"",C18*E18) -> 222069.1 | L18: =IF(OR(C18="",NOT(ISNUMBER(F18))),"",C18*F18) -> 349805.41 | M18: =IF(OR(C18="",NOT(ISNUMBER(G18))),"",C18*G18) -> 368032.11 | N18: =IF(OR(C18="",NOT(ISNUMBER(H18))),"",C18*H18) -> 368032.11 | O18: =IF(OR(C18="",NOT(ISNUMBER(I18))),"",C18*I18) -> 377237.51
A19: AMERICAN CHEESEBURGER | B19: Instore | C19: 35649 | D19: =IFERROR(VLOOKUP("AMERICAN CHEESEBURGER",'FOOD COST'!$A:$Y,7,0),"") -> 6.059 | E19: =IFERROR(VLOOKUP("AMERICAN CHEESEBURGER",'FOOD COST'!$A:$Y,8,0),"") -> 6.47667 | F19: =IFERROR(VLOOKUP("AMERICAN CHEESEBURGER",'FOOD COST'!$A:$Y,10,0),"") -> 9.009009 | G19: =IFERROR(VLOOKUP("AMERICAN CHEESEBURGER",'FOOD COST'!$A:$Y,18,0),"") -> 9.009009 | H19: =IFERROR(VLOOKUP("AMERICAN CHEESEBURGER",'FOOD COST'!$A:$Y,21,0),"") -> 9.4504505 | I19: =IFERROR(VLOOKUP("AMERICAN CHEESEBURGER",'FOOD COST'!$A:$Y,24,0),"") -> 9.9009009 | J19: =IF(OR(C19="",NOT(ISNUMBER(D19))),"",C19*D19) -> 215997.29 | K19: =IF(OR(C19="",NOT(ISNUMBER(E19))),"",C19*E19) -> 230886.81 | L19: =IF(OR(C19="",NOT(ISNUMBER(F19))),"",C19*F19) -> 321162.16 | M19: =IF(OR(C19="",NOT(ISNUMBER(G19))),"",C19*G19) -> 321162.16 | N19: =IF(OR(C19="",NOT(ISNUMBER(H19))),"",C19*H19) -> 336899.11 | O19: =IF(OR(C19="",NOT(ISNUMBER(I19))),"",C19*I19) -> 352957.22
A20: AMERICAN CHEESEBURGER D | B20: Delivery | C20: 5493 | D20: =IFERROR(VLOOKUP("AMERICAN CHEESEBURGER D",'FOOD COST'!$A:$Y,7,0),"") -> 6.059 | E20: =IFERROR(VLOOKUP("AMERICAN CHEESEBURGER D",'FOOD COST'!$A:$Y,8,0),"") -> 6.47667 | F20: =IFERROR(VLOOKUP("AMERICAN CHEESEBURGER D",'FOOD COST'!$A:$Y,10,0),"") -> 11.711712 | G20: =IFERROR(VLOOKUP("AMERICAN CHEESEBURGER D",'FOOD COST'!$A:$Y,18,0),"") -> 11.711712 | H20: =IFERROR(VLOOKUP("AMERICAN CHEESEBURGER D",'FOOD COST'!$A:$Y,21,0),"") -> 12.153153 | I20: =IFERROR(VLOOKUP("AMERICAN CHEESEBURGER D",'FOOD COST'!$A:$Y,24,0),"") -> 12.603604 | J20: =IF(OR(C20="",NOT(ISNUMBER(D20))),"",C20*D20) -> 33282.087 | K20: =IF(OR(C20="",NOT(ISNUMBER(E20))),"",C20*E20) -> 35576.348 | L20: =IF(OR(C20="",NOT(ISNUMBER(F20))),"",C20*F20) -> 64332.432 | M20: =IF(OR(C20="",NOT(ISNUMBER(G20))),"",C20*G20) -> 64332.432 | N20: =IF(OR(C20="",NOT(ISNUMBER(H20))),"",C20*H20) -> 66757.27 | O20: =IF(OR(C20="",NOT(ISNUMBER(I20))),"",C20*I20) -> 69231.595
A21: AMERICAN DUBLU CHEESEBURGER | B21: Instore | C21: 21099 | D21: =IFERROR(VLOOKUP("AMERICAN DUBLU CHEESEBURGER",'FOOD COST'!$A:$Y,7,0),"") -> 9.607 | E21: =IFERROR(VLOOKUP("AMERICAN DUBLU CHEESEBURGER",'FOOD COST'!$A:$Y,8,0),"") -> 10.44234 | F21: =IFERROR(VLOOKUP("AMERICAN DUBLU CHEESEBURGER",'FOOD COST'!$A:$Y,10,0),"") -> 14.414414 | G21: =IFERROR(VLOOKUP("AMERICAN DUBLU CHEESEBURGER",'FOOD COST'!$A:$Y,18,0),"") -> 14.414414 | H21: =IFERROR(VLOOKUP("AMERICAN DUBLU CHEESEBURGER",'FOOD COST'!$A:$Y,21,0),"") -> 15.306306 | I21: =IFERROR(VLOOKUP("AMERICAN DUBLU CHEESEBURGER",'FOOD COST'!$A:$Y,24,0),"") -> 15.756757 | J21: =IF(OR(C21="",NOT(ISNUMBER(D21))),"",C21*D21) -> 202698.09 | K21: =IF(OR(C21="",NOT(ISNUMBER(E21))),"",C21*E21) -> 220322.93 | L21: =IF(OR(C21="",NOT(ISNUMBER(F21))),"",C21*F21) -> 304129.73 | M21: =IF(OR(C21="",NOT(ISNUMBER(G21))),"",C21*G21) -> 304129.73 | N21: =IF(OR(C21="",NOT(ISNUMBER(H21))),"",C21*H21) -> 322947.76 | O21: =IF(OR(C21="",NOT(ISNUMBER(I21))),"",C21*I21) -> 332451.81
A22: AMERICAN DUBLU CHEESEBURGER D | B22: Delivery | C22: 5572 | D22: =IFERROR(VLOOKUP("AMERICAN DUBLU CHEESEBURGER D",'FOOD COST'!$A:$Y,7,0),"") -> 9.607 | E22: =IFERROR(VLOOKUP("AMERICAN DUBLU CHEESEBURGER D",'FOOD COST'!$A:$Y,8,0),"") -> 10.44234 | F22: =IFERROR(VLOOKUP("AMERICAN DUBLU CHEESEBURGER D",'FOOD COST'!$A:$Y,10,0),"") -> 17.117117 | G22: =IFERROR(VLOOKUP("AMERICAN DUBLU CHEESEBURGER D",'FOOD COST'!$A:$Y,18,0),"") -> 17.117117 | H22: =IFERROR(VLOOKUP("AMERICAN DUBLU CHEESEBURGER D",'FOOD COST'!$A:$Y,21,0),"") -> 18.009009 | I22: =IFERROR(VLOOKUP("AMERICAN DUBLU CHEESEBURGER D",'FOOD COST'!$A:$Y,24,0),"") -> 18.459459 | J22: =IF(OR(C22="",NOT(ISNUMBER(D22))),"",C22*D22) -> 53530.204 | K22: =IF(OR(C22="",NOT(ISNUMBER(E22))),"",C22*E22) -> 58184.718 | L22: =IF(OR(C22="",NOT(ISNUMBER(F22))),"",C22*F22) -> 95376.577 | M22: =IF(OR(C22="",NOT(ISNUMBER(G22))),"",C22*G22) -> 95376.577 | N22: =IF(OR(C22="",NOT(ISNUMBER(H22))),"",C22*H22) -> 100346.2 | O22: =IF(OR(C22="",NOT(ISNUMBER(I22))),"",C22*I22) -> 102856.11
A23: AMERICAN TRIPLU CHEESEBURGER | B23: Instore | C23: 10334 | D23: =IFERROR(VLOOKUP("AMERICAN TRIPLU CHEESEBURGER",'FOOD COST'!$A:$Y,7,0),"") -> 13.155 | E23: =IFERROR(VLOOKUP("AMERICAN TRIPLU CHEESEBURGER",'FOOD COST'!$A:$Y,8,0),"") -> 14.40801 | F23: =IFERROR(VLOOKUP("AMERICAN TRIPLU CHEESEBURGER",'FOOD COST'!$A:$Y,10,0),"") -> 19.81982 | G23: =IFERROR(VLOOKUP("AMERICAN TRIPLU CHEESEBURGER",'FOOD COST'!$A:$Y,18,0),"") -> 19.81982 | H23: =IFERROR(VLOOKUP("AMERICAN TRIPLU CHEESEBURGER",'FOOD COST'!$A:$Y,21,0),"") -> 21.162162 | I23: =IFERROR(VLOOKUP("AMERICAN TRIPLU CHEESEBURGER",'FOOD COST'!$A:$Y,24,0),"") -> 21.612613 | J23: =IF(OR(C23="",NOT(ISNUMBER(D23))),"",C23*D23) -> 135943.77 | K23: =IF(OR(C23="",NOT(ISNUMBER(E23))),"",C23*E23) -> 148892.38 | L23: =IF(OR(C23="",NOT(ISNUMBER(F23))),"",C23*F23) -> 204818.02 | M23: =IF(OR(C23="",NOT(ISNUMBER(G23))),"",C23*G23) -> 204818.02 | N23: =IF(OR(C23="",NOT(ISNUMBER(H23))),"",C23*H23) -> 218689.78 | O23: =IF(OR(C23="",NOT(ISNUMBER(I23))),"",C23*I23) -> 223344.74
A24: AMERICAN TRIPLU CHEESEBURGER D | B24: Delivery | C24: 6706 | D24: =IFERROR(VLOOKUP("AMERICAN TRIPLU CHEESEBURGER D",'FOOD COST'!$A:$Y,7,0),"") -> 13.155 | E24: =IFERROR(VLOOKUP("AMERICAN TRIPLU CHEESEBURGER D",'FOOD COST'!$A:$Y,8,0),"") -> 14.40801 | F24: =IFERROR(VLOOKUP("AMERICAN TRIPLU CHEESEBURGER D",'FOOD COST'!$A:$Y,10,0),"") -> 22.522523 | G24: =IFERROR(VLOOKUP("AMERICAN TRIPLU CHEESEBURGER D",'FOOD COST'!$A:$Y,18,0),"") -> 22.522523 | H24: =IFERROR(VLOOKUP("AMERICAN TRIPLU CHEESEBURGER D",'FOOD COST'!$A:$Y,21,0),"") -> 23.864865 | I24: =IFERROR(VLOOKUP("AMERICAN TRIPLU CHEESEBURGER D",'FOOD COST'!$A:$Y,24,0),"") -> 24.315315 | J24: =IF(OR(C24="",NOT(ISNUMBER(D24))),"",C24*D24) -> 88217.43 | K24: =IF(OR(C24="",NOT(ISNUMBER(E24))),"",C24*E24) -> 96620.115 | L24: =IF(OR(C24="",NOT(ISNUMBER(F24))),"",C24*F24) -> 151036.04 | M24: =IF(OR(C24="",NOT(ISNUMBER(G24))),"",C24*G24) -> 151036.04 | N24: =IF(OR(C24="",NOT(ISNUMBER(H24))),"",C24*H24) -> 160037.78 | O24: =IF(OR(C24="",NOT(ISNUMBER(I24))),"",C24*I24) -> 163058.5
A25: SMASHED BURGER | B25: Instore | C25: 14682 | D25: =IFERROR(VLOOKUP("SMASHED BURGER",'FOOD COST'!$A:$Y,7,0),"") -> 7.600648 | E25: =IFERROR(VLOOKUP("SMASHED BURGER",'FOOD COST'!$A:$Y,8,0),"") -> 8.018318 | F25: =IFERROR(VLOOKUP("SMASHED BURGER",'FOOD COST'!$A:$Y,10,0),"") -> 18.90991 | G25: =IFERROR(VLOOKUP("SMASHED BURGER",'FOOD COST'!$A:$Y,18,0),"") -> 19.801802 | H25: =IFERROR(VLOOKUP("SMASHED BURGER",'FOOD COST'!$A:$Y,21,0),"") -> 19.801802 | I25: =IFERROR(VLOOKUP("SMASHED BURGER",'FOOD COST'!$A:$Y,24,0),"") -> 19.801802 | J25: =IF(OR(C25="",NOT(ISNUMBER(D25))),"",C25*D25) -> 111592.71 | K25: =IF(OR(C25="",NOT(ISNUMBER(E25))),"",C25*E25) -> 117724.94 | L25: =IF(OR(C25="",NOT(ISNUMBER(F25))),"",C25*F25) -> 277635.3 | M25: =IF(OR(C25="",NOT(ISNUMBER(G25))),"",C25*G25) -> 290730.05 | N25: =IF(OR(C25="",NOT(ISNUMBER(H25))),"",C25*H25) -> 290730.05 | O25: =IF(OR(C25="",NOT(ISNUMBER(I25))),"",C25*I25) -> 290730.05
A26: SMASHED BURGER D | B26: Delivery | C26: 5447 | D26: =IFERROR(VLOOKUP("SMASHED BURGER D",'FOOD COST'!$A:$Y,7,0),"") -> 7.600648 | E26: =IFERROR(VLOOKUP("SMASHED BURGER D",'FOOD COST'!$A:$Y,8,0),"") -> 8.018318 | F26: =IFERROR(VLOOKUP("SMASHED BURGER D",'FOOD COST'!$A:$Y,10,0),"") -> 22.072072 | G26: =IFERROR(VLOOKUP("SMASHED BURGER D",'FOOD COST'!$A:$Y,18,0),"") -> 22.963964 | H26: =IFERROR(VLOOKUP("SMASHED BURGER D",'FOOD COST'!$A:$Y,21,0),"") -> 22.963964 | I26: =IFERROR(VLOOKUP("SMASHED BURGER D",'FOOD COST'!$A:$Y,24,0),"") -> 22.963964 | J26: =IF(OR(C26="",NOT(ISNUMBER(D26))),"",C26*D26) -> 41400.73 | K26: =IF(OR(C26="",NOT(ISNUMBER(E26))),"",C26*E26) -> 43675.778 | L26: =IF(OR(C26="",NOT(ISNUMBER(F26))),"",C26*F26) -> 120226.58 | M26: =IF(OR(C26="",NOT(ISNUMBER(G26))),"",C26*G26) -> 125084.71 | N26: =IF(OR(C26="",NOT(ISNUMBER(H26))),"",C26*H26) -> 125084.71 | O26: =IF(OR(C26="",NOT(ISNUMBER(I26))),"",C26*I26) -> 125084.71
A27: DUBLU SMASHED BURGER | B27: Instore | C27: 18675 | D27: =IFERROR(VLOOKUP("DUBLU SMASHED BURGER",'FOOD COST'!$A:$Y,7,0),"") -> 11.418948 | E27: =IFERROR(VLOOKUP("DUBLU SMASHED BURGER",'FOOD COST'!$A:$Y,8,0),"") -> 12.254288 | F27: =IFERROR(VLOOKUP("DUBLU SMASHED BURGER",'FOOD COST'!$A:$Y,10,0),"") -> 24.315315 | G27: =IFERROR(VLOOKUP("DUBLU SMASHED BURGER",'FOOD COST'!$A:$Y,18,0),"") -> 26.108108 | H27: =IFERROR(VLOOKUP("DUBLU SMASHED BURGER",'FOOD COST'!$A:$Y,21,0),"") -> 26.108108 | I27: =IFERROR(VLOOKUP("DUBLU SMASHED BURGER",'FOOD COST'!$A:$Y,24,0),"") -> 26.108108 | J27: =IF(OR(C27="",NOT(ISNUMBER(D27))),"",C27*D27) -> 213248.85 | K27: =IF(OR(C27="",NOT(ISNUMBER(E27))),"",C27*E27) -> 228848.83 | L27: =IF(OR(C27="",NOT(ISNUMBER(F27))),"",C27*F27) -> 454088.51 | M27: =IF(OR(C27="",NOT(ISNUMBER(G27))),"",C27*G27) -> 487568.92 | N27: =IF(OR(C27="",NOT(ISNUMBER(H27))),"",C27*H27) -> 487568.92 | O27: =IF(OR(C27="",NOT(ISNUMBER(I27))),"",C27*I27) -> 487568.92
A28: DUBLU SMASHED BURGER D | B28: Delivery | C28: 11289 | D28: =IFERROR(VLOOKUP("DUBLU SMASHED BURGER D",'FOOD COST'!$A:$Y,7,0),"") -> 11.418948 | E28: =IFERROR(VLOOKUP("DUBLU SMASHED BURGER D",'FOOD COST'!$A:$Y,8,0),"") -> 12.254288 | F28: =IFERROR(VLOOKUP("DUBLU SMASHED BURGER D",'FOOD COST'!$A:$Y,10,0),"") -> 27.477477 | G28: =IFERROR(VLOOKUP("DUBLU SMASHED BURGER D",'FOOD COST'!$A:$Y,18,0),"") -> 29.27027 | H28: =IFERROR(VLOOKUP("DUBLU SMASHED BURGER D",'FOOD COST'!$A:$Y,21,0),"") -> 29.27027 | I28: =IFERROR(VLOOKUP("DUBLU SMASHED BURGER D",'FOOD COST'!$A:$Y,24,0),"") -> 29.27027 | J28: =IF(OR(C28="",NOT(ISNUMBER(D28))),"",C28*D28) -> 128908.5 | K28: =IF(OR(C28="",NOT(ISNUMBER(E28))),"",C28*E28) -> 138338.66 | L28: =IF(OR(C28="",NOT(ISNUMBER(F28))),"",C28*F28) -> 310193.24 | M28: =IF(OR(C28="",NOT(ISNUMBER(G28))),"",C28*G28) -> 330432.08 | N28: =IF(OR(C28="",NOT(ISNUMBER(H28))),"",C28*H28) -> 330432.08 | O28: =IF(OR(C28="",NOT(ISNUMBER(I28))),"",C28*I28) -> 330432.08
A29: BLACK TRUFFLE SMASHED | B29: Instore | C29: 15161 | D29: =IFERROR(VLOOKUP("BLACK TRUFFLE SMASHED",'FOOD COST'!$A:$Y,7,0),"") -> 8.1968 | E29: =IFERROR(VLOOKUP("BLACK TRUFFLE SMASHED",'FOOD COST'!$A:$Y,8,0),"") -> 8.61447 | F29: =IFERROR(VLOOKUP("BLACK TRUFFLE SMASHED",'FOOD COST'!$A:$Y,10,0),"") -> 19.81982 | G29: =IFERROR(VLOOKUP("BLACK TRUFFLE SMASHED",'FOOD COST'!$A:$Y,18,0),"") -> 20.711712 | H29: =IFERROR(VLOOKUP("BLACK TRUFFLE SMASHED",'FOOD COST'!$A:$Y,21,0),"") -> 20.711712 | I29: =IFERROR(VLOOKUP("BLACK TRUFFLE SMASHED",'FOOD COST'!$A:$Y,24,0),"") -> 20.711712 | J29: =IF(OR(C29="",NOT(ISNUMBER(D29))),"",C29*D29) -> 124271.68 | K29: =IF(OR(C29="",NOT(ISNUMBER(E29))),"",C29*E29) -> 130603.98 | L29: =IF(OR(C29="",NOT(ISNUMBER(F29))),"",C29*F29) -> 300488.29 | M29: =IF(OR(C29="",NOT(ISNUMBER(G29))),"",C29*G29) -> 314010.26 | N29: =IF(OR(C29="",NOT(ISNUMBER(H29))),"",C29*H29) -> 314010.26 | O29: =IF(OR(C29="",NOT(ISNUMBER(I29))),"",C29*I29) -> 314010.26
A30: BLACK TRUFFLE SMASHED D | B30: Delivery | C30: 5118 | D30: =IFERROR(VLOOKUP("BLACK TRUFFLE SMASHED D",'FOOD COST'!$A:$Y,7,0),"") -> 8.1968 | E30: =IFERROR(VLOOKUP("BLACK TRUFFLE SMASHED D",'FOOD COST'!$A:$Y,8,0),"") -> 8.61447 | F30: =IFERROR(VLOOKUP("BLACK TRUFFLE SMASHED D",'FOOD COST'!$A:$Y,10,0),"") -> 22.522523 | G30: =IFERROR(VLOOKUP("BLACK TRUFFLE SMASHED D",'FOOD COST'!$A:$Y,18,0),"") -> 23.414414 | H30: =IFERROR(VLOOKUP("BLACK TRUFFLE SMASHED D",'FOOD COST'!$A:$Y,21,0),"") -> 23.414414 | I30: =IFERROR(VLOOKUP("BLACK TRUFFLE SMASHED D",'FOOD COST'!$A:$Y,24,0),"") -> 23.414414 | J30: =IF(OR(C30="",NOT(ISNUMBER(D30))),"",C30*D30) -> 41951.222 | K30: =IF(OR(C30="",NOT(ISNUMBER(E30))),"",C30*E30) -> 44088.857 | L30: =IF(OR(C30="",NOT(ISNUMBER(F30))),"",C30*F30) -> 115270.27 | M30: =IF(OR(C30="",NOT(ISNUMBER(G30))),"",C30*G30) -> 119834.97 | N30: =IF(OR(C30="",NOT(ISNUMBER(H30))),"",C30*H30) -> 119834.97 | O30: =IF(OR(C30="",NOT(ISNUMBER(I30))),"",C30*I30) -> 119834.97
A31: DUBLU BLACK TRUFFLE SMASHED | B31: Instore | C31: 20703 | D31: =IFERROR(VLOOKUP("DUBLU BLACK TRUFFLE SMASHED",'FOOD COST'!$A:$Y,7,0),"") -> 12.0954 | E31: =IFERROR(VLOOKUP("DUBLU BLACK TRUFFLE SMASHED",'FOOD COST'!$A:$Y,8,0),"") -> 12.93074 | F31: =IFERROR(VLOOKUP("DUBLU BLACK TRUFFLE SMASHED",'FOOD COST'!$A:$Y,10,0),"") -> 25.225225 | G31: =IFERROR(VLOOKUP("DUBLU BLACK TRUFFLE SMASHED",'FOOD COST'!$A:$Y,18,0),"") -> 27.018018 | H31: =IFERROR(VLOOKUP("DUBLU BLACK TRUFFLE SMASHED",'FOOD COST'!$A:$Y,21,0),"") -> 27.018018 | I31: =IFERROR(VLOOKUP("DUBLU BLACK TRUFFLE SMASHED",'FOOD COST'!$A:$Y,24,0),"") -> 27.018018 | J31: =IF(OR(C31="",NOT(ISNUMBER(D31))),"",C31*D31) -> 250411.07 | K31: =IF(OR(C31="",NOT(ISNUMBER(E31))),"",C31*E31) -> 267705.11 | L31: =IF(OR(C31="",NOT(ISNUMBER(F31))),"",C31*F31) -> 522237.84 | M31: =IF(OR(C31="",NOT(ISNUMBER(G31))),"",C31*G31) -> 559354.03 | N31: =IF(OR(C31="",NOT(ISNUMBER(H31))),"",C31*H31) -> 559354.03 | O31: =IF(OR(C31="",NOT(ISNUMBER(I31))),"",C31*I31) -> 559354.03
A32: DUBLU BLACK TRUFFLE SMASHED D | B32: Delivery | C32: 15509 | D32: =IFERROR(VLOOKUP("DUBLU BLACK TRUFFLE SMASHED D",'FOOD COST'!$A:$Y,7,0),"") -> 12.0954 | E32: =IFERROR(VLOOKUP("DUBLU BLACK TRUFFLE SMASHED D",'FOOD COST'!$A:$Y,8,0),"") -> 12.93074 | F32: =IFERROR(VLOOKUP("DUBLU BLACK TRUFFLE SMASHED D",'FOOD COST'!$A:$Y,10,0),"") -> 27.927928 | G32: =IFERROR(VLOOKUP("DUBLU BLACK TRUFFLE SMASHED D",'FOOD COST'!$A:$Y,18,0),"") -> 29.720721 | H32: =IFERROR(VLOOKUP("DUBLU BLACK TRUFFLE SMASHED D",'FOOD COST'!$A:$Y,21,0),"") -> 29.720721 | I32: =IFERROR(VLOOKUP("DUBLU BLACK TRUFFLE SMASHED D",'FOOD COST'!$A:$Y,24,0),"") -> 29.720721 | J32: =IF(OR(C32="",NOT(ISNUMBER(D32))),"",C32*D32) -> 187587.56 | K32: =IF(OR(C32="",NOT(ISNUMBER(E32))),"",C32*E32) -> 200542.85 | L32: =IF(OR(C32="",NOT(ISNUMBER(F32))),"",C32*F32) -> 433134.23 | M32: =IF(OR(C32="",NOT(ISNUMBER(G32))),"",C32*G32) -> 460938.66 | N32: =IF(OR(C32="",NOT(ISNUMBER(H32))),"",C32*H32) -> 460938.66 | O32: =IF(OR(C32="",NOT(ISNUMBER(I32))),"",C32*I32) -> 460938.66
A33: RED PEPPER SMASHED | B33: Instore | C33: 3443 | D33: =IFERROR(VLOOKUP("RED PEPPER SMASHED",'FOOD COST'!$A:$Y,7,0),"") -> 9.40848 | E33: =IFERROR(VLOOKUP("RED PEPPER SMASHED",'FOOD COST'!$A:$Y,8,0),"") -> 9.82615 | F33: =IFERROR(VLOOKUP("RED PEPPER SMASHED",'FOOD COST'!$A:$Y,10,0),"") -> 23.423423 | G33: =IFERROR(VLOOKUP("RED PEPPER SMASHED",'FOOD COST'!$A:$Y,18,0),"") -> 24.315315 | H33: =IFERROR(VLOOKUP("RED PEPPER SMASHED",'FOOD COST'!$A:$Y,21,0),"") -> 24.315315 | I33: =IFERROR(VLOOKUP("RED PEPPER SMASHED",'FOOD COST'!$A:$Y,24,0),"") -> 24.315315 | J33: =IF(OR(C33="",NOT(ISNUMBER(D33))),"",C33*D33) -> 32393.397 | K33: =IF(OR(C33="",NOT(ISNUMBER(E33))),"",C33*E33) -> 33831.434 | L33: =IF(OR(C33="",NOT(ISNUMBER(F33))),"",C33*F33) -> 80646.847 | M33: =IF(OR(C33="",NOT(ISNUMBER(G33))),"",C33*G33) -> 83717.631 | N33: =IF(OR(C33="",NOT(ISNUMBER(H33))),"",C33*H33) -> 83717.631 | O33: =IF(OR(C33="",NOT(ISNUMBER(I33))),"",C33*I33) -> 83717.631
A34: RED PEPPER SMASHED D | B34: Delivery | C34: 1609 | D34: =IFERROR(VLOOKUP("RED PEPPER SMASHED D",'FOOD COST'!$A:$Y,7,0),"") -> 9.40848 | E34: =IFERROR(VLOOKUP("RED PEPPER SMASHED D",'FOOD COST'!$A:$Y,8,0),"") -> 9.82615 | F34: =IFERROR(VLOOKUP("RED PEPPER SMASHED D",'FOOD COST'!$A:$Y,10,0),"") -> 26.126126 | G34: =IFERROR(VLOOKUP("RED PEPPER SMASHED D",'FOOD COST'!$A:$Y,18,0),"") -> 27.018018 | H34: =IFERROR(VLOOKUP("RED PEPPER SMASHED D",'FOOD COST'!$A:$Y,21,0),"") -> 27.018018 | I34: =IFERROR(VLOOKUP("RED PEPPER SMASHED D",'FOOD COST'!$A:$Y,24,0),"") -> 27.018018 | J34: =IF(OR(C34="",NOT(ISNUMBER(D34))),"",C34*D34) -> 15138.244 | K34: =IF(OR(C34="",NOT(ISNUMBER(E34))),"",C34*E34) -> 15810.275 | L34: =IF(OR(C34="",NOT(ISNUMBER(F34))),"",C34*F34) -> 42036.937 | M34: =IF(OR(C34="",NOT(ISNUMBER(G34))),"",C34*G34) -> 43471.991 | N34: =IF(OR(C34="",NOT(ISNUMBER(H34))),"",C34*H34) -> 43471.991 | O34: =IF(OR(C34="",NOT(ISNUMBER(I34))),"",C34*I34) -> 43471.991
A35: DUBLU RED PEPPER SMASHED | B35: Instore | C35: 3863 | D35: =IFERROR(VLOOKUP("DUBLU RED PEPPER SMASHED",'FOOD COST'!$A:$Y,7,0),"") -> 13.55128 | E35: =IFERROR(VLOOKUP("DUBLU RED PEPPER SMASHED",'FOOD COST'!$A:$Y,8,0),"") -> 14.38662 | F35: =IFERROR(VLOOKUP("DUBLU RED PEPPER SMASHED",'FOOD COST'!$A:$Y,10,0),"") -> 28.828829 | G35: =IFERROR(VLOOKUP("DUBLU RED PEPPER SMASHED",'FOOD COST'!$A:$Y,18,0),"") -> 30.621622 | H35: =IFERROR(VLOOKUP("DUBLU RED PEPPER SMASHED",'FOOD COST'!$A:$Y,21,0),"") -> 30.621622 | I35: =IFERROR(VLOOKUP("DUBLU RED PEPPER SMASHED",'FOOD COST'!$A:$Y,24,0),"") -> 30.621622 | J35: =IF(OR(C35="",NOT(ISNUMBER(D35))),"",C35*D35) -> 52348.595 | K35: =IF(OR(C35="",NOT(ISNUMBER(E35))),"",C35*E35) -> 55575.513 | L35: =IF(OR(C35="",NOT(ISNUMBER(F35))),"",C35*F35) -> 111365.77 | M35: =IF(OR(C35="",NOT(ISNUMBER(G35))),"",C35*G35) -> 118291.32 | N35: =IF(OR(C35="",NOT(ISNUMBER(H35))),"",C35*H35) -> 118291.32 | O35: =IF(OR(C35="",NOT(ISNUMBER(I35))),"",C35*I35) -> 118291.32
A36: DUBLU RED PEPPER SMASHED D | B36: Delivery | C36: 1943 | D36: =IFERROR(VLOOKUP("DUBLU RED PEPPER SMASHED D",'FOOD COST'!$A:$Y,7,0),"") -> 13.55128 | E36: =IFERROR(VLOOKUP("DUBLU RED PEPPER SMASHED D",'FOOD COST'!$A:$Y,8,0),"") -> 14.38662 | F36: =IFERROR(VLOOKUP("DUBLU RED PEPPER SMASHED D",'FOOD COST'!$A:$Y,10,0),"") -> 31.531532 | G36: =IFERROR(VLOOKUP("DUBLU RED PEPPER SMASHED D",'FOOD COST'!$A:$Y,18,0),"") -> 33.324324 | H36: =IFERROR(VLOOKUP("DUBLU RED PEPPER SMASHED D",'FOOD COST'!$A:$Y,21,0),"") -> 33.324324 | I36: =IFERROR(VLOOKUP("DUBLU RED PEPPER SMASHED D",'FOOD COST'!$A:$Y,24,0),"") -> 33.324324 | J36: =IF(OR(C36="",NOT(ISNUMBER(D36))),"",C36*D36) -> 26330.137 | K36: =IF(OR(C36="",NOT(ISNUMBER(E36))),"",C36*E36) -> 27953.203 | L36: =IF(OR(C36="",NOT(ISNUMBER(F36))),"",C36*F36) -> 61265.766 | M36: =IF(OR(C36="",NOT(ISNUMBER(G36))),"",C36*G36) -> 64749.162 | N36: =IF(OR(C36="",NOT(ISNUMBER(H36))),"",C36*H36) -> 64749.162 | O36: =IF(OR(C36="",NOT(ISNUMBER(I36))),"",C36*I36) -> 64749.162
A37: AMERICAN TRIPLU CHEESEBURGER LETTUCE WRAP | B37: Instore | C37: 8901 | D37: =IFERROR(VLOOKUP("AMERICAN TRIPLU CHEESEBURGER LETTUCE WRAP",'FOOD COST'!$A:$Y,7,0),"") -> 13.23 | E37: =IFERROR(VLOOKUP("AMERICAN TRIPLU CHEESEBURGER LETTUCE WRAP",'FOOD COST'!$A:$Y,8,0),"") -> 14.48301 | F37: =IFERROR(VLOOKUP("AMERICAN TRIPLU CHEESEBURGER LETTUCE WRAP",'FOOD COST'!$A:$Y,10,0),"") -> 19.81982 | G37: =IFERROR(VLOOKUP("AMERICAN TRIPLU CHEESEBURGER LETTUCE WRAP",'FOOD COST'!$A:$Y,18,0),"") -> 20.711712 | H37: =IFERROR(VLOOKUP("AMERICAN TRIPLU CHEESEBURGER LETTUCE WRAP",'FOOD COST'!$A:$Y,21,0),"") -> 20.711712 | I37: =IFERROR(VLOOKUP("AMERICAN TRIPLU CHEESEBURGER LETTUCE WRAP",'FOOD COST'!$A:$Y,24,0),"") -> 20.711712 | J37: =IF(OR(C37="",NOT(ISNUMBER(D37))),"",C37*D37) -> 117760.23 | K37: =IF(OR(C37="",NOT(ISNUMBER(E37))),"",C37*E37) -> 128913.27 | L37: =IF(OR(C37="",NOT(ISNUMBER(F37))),"",C37*F37) -> 176416.22 | M37: =IF(OR(C37="",NOT(ISNUMBER(G37))),"",C37*G37) -> 184354.95 | N37: =IF(OR(C37="",NOT(ISNUMBER(H37))),"",C37*H37) -> 184354.95 | O37: =IF(OR(C37="",NOT(ISNUMBER(I37))),"",C37*I37) -> 184354.95
A38: AMERICAN TRIPLU CHEESEBURGER LETTUCE WRAP D | B38: Delivery | C38: 5528 | D38: =IFERROR(VLOOKUP("AMERICAN TRIPLU CHEESEBURGER LETTUCE WRAP D",'FOOD COST'!$A:$Y,7,0),"") -> 13.23 | E38: =IFERROR(VLOOKUP("AMERICAN TRIPLU CHEESEBURGER LETTUCE WRAP D",'FOOD COST'!$A:$Y,8,0),"") -> 14.48301 | F38: =IFERROR(VLOOKUP("AMERICAN TRIPLU CHEESEBURGER LETTUCE WRAP D",'FOOD COST'!$A:$Y,10,0),"") -> 22.522523 | G38: =IFERROR(VLOOKUP("AMERICAN TRIPLU CHEESEBURGER LETTUCE WRAP D",'FOOD COST'!$A:$Y,18,0),"") -> 23.414414 | H38: =IFERROR(VLOOKUP("AMERICAN TRIPLU CHEESEBURGER LETTUCE WRAP D",'FOOD COST'!$A:$Y,21,0),"") -> 23.414414 | I38: =IFERROR(VLOOKUP("AMERICAN TRIPLU CHEESEBURGER LETTUCE WRAP D",'FOOD COST'!$A:$Y,24,0),"") -> 23.414414 | J38: =IF(OR(C38="",NOT(ISNUMBER(D38))),"",C38*D38) -> 73135.44 | K38: =IF(OR(C38="",NOT(ISNUMBER(E38))),"",C38*E38) -> 80062.079 | L38: =IF(OR(C38="",NOT(ISNUMBER(F38))),"",C38*F38) -> 124504.5 | M38: =IF(OR(C38="",NOT(ISNUMBER(G38))),"",C38*G38) -> 129434.88 | N38: =IF(OR(C38="",NOT(ISNUMBER(H38))),"",C38*H38) -> 129434.88 | O38: =IF(OR(C38="",NOT(ISNUMBER(I38))),"",C38*I38) -> 129434.88
A39: PUI BURGER | B39: Instore | C39: 36505 | D39: =IFERROR(VLOOKUP("PUI BURGER",'FOOD COST'!$A:$Y,7,0),"") -> 4.337024 | E39: =IFERROR(VLOOKUP("PUI BURGER",'FOOD COST'!$A:$Y,8,0),"") -> 4.337024 | F39: =IFERROR(VLOOKUP("PUI BURGER",'FOOD COST'!$A:$Y,10,0),"") -> 6.3063063 | G39: =IFERROR(VLOOKUP("PUI BURGER",'FOOD COST'!$A:$Y,18,0),"") -> 6.3063063 | H39: =IFERROR(VLOOKUP("PUI BURGER",'FOOD COST'!$A:$Y,21,0),"") -> 6.7477477 | I39: =IFERROR(VLOOKUP("PUI BURGER",'FOOD COST'!$A:$Y,24,0),"") -> 7.1981982 | J39: =IF(OR(C39="",NOT(ISNUMBER(D39))),"",C39*D39) -> 158323.06 | K39: =IF(OR(C39="",NOT(ISNUMBER(E39))),"",C39*E39) -> 158323.06 | L39: =IF(OR(C39="",NOT(ISNUMBER(F39))),"",C39*F39) -> 230211.71 | M39: =IF(OR(C39="",NOT(ISNUMBER(G39))),"",C39*G39) -> 230211.71 | N39: =IF(OR(C39="",NOT(ISNUMBER(H39))),"",C39*H39) -> 246326.53 | O39: =IF(OR(C39="",NOT(ISNUMBER(I39))),"",C39*I39) -> 262770.23
A40: PUI BURGER D | B40: Delivery | C40: 9356 | D40: =IFERROR(VLOOKUP("PUI BURGER D",'FOOD COST'!$A:$Y,7,0),"") -> 4.337024 | E40: =IFERROR(VLOOKUP("PUI BURGER D",'FOOD COST'!$A:$Y,8,0),"") -> 4.337024 | F40: =IFERROR(VLOOKUP("PUI BURGER D",'FOOD COST'!$A:$Y,10,0),"") -> 9.009009 | G40: =IFERROR(VLOOKUP("PUI BURGER D",'FOOD COST'!$A:$Y,18,0),"") -> 9.009009 | H40: =IFERROR(VLOOKUP("PUI BURGER D",'FOOD COST'!$A:$Y,21,0),"") -> 9.4504505 | I40: =IFERROR(VLOOKUP("PUI BURGER D",'FOOD COST'!$A:$Y,24,0),"") -> 9.9009009 | J40: =IF(OR(C40="",NOT(ISNUMBER(D40))),"",C40*D40) -> 40577.197 | K40: =IF(OR(C40="",NOT(ISNUMBER(E40))),"",C40*E40) -> 40577.197 | L40: =IF(OR(C40="",NOT(ISNUMBER(F40))),"",C40*F40) -> 84288.288 | M40: =IF(OR(C40="",NOT(ISNUMBER(G40))),"",C40*G40) -> 84288.288 | N40: =IF(OR(C40="",NOT(ISNUMBER(H40))),"",C40*H40) -> 88418.414 | O40: =IF(OR(C40="",NOT(ISNUMBER(I40))),"",C40*I40) -> 92632.829
A41: DUBLU PUI BURGER | B41: Instore | C41: 4418 | D41: =IFERROR(VLOOKUP("DUBLU PUI BURGER",'FOOD COST'!$A:$Y,7,0),"") -> 6.368024 | E41: =IFERROR(VLOOKUP("DUBLU PUI BURGER",'FOOD COST'!$A:$Y,8,0),"") -> 6.368024 | F41: =IFERROR(VLOOKUP("DUBLU PUI BURGER",'FOOD COST'!$A:$Y,10,0),"") -> 13.513514 | G41: =IFERROR(VLOOKUP("DUBLU PUI BURGER",'FOOD COST'!$A:$Y,18,0),"") -> 13.954955 | H41: =IFERROR(VLOOKUP("DUBLU PUI BURGER",'FOOD COST'!$A:$Y,21,0),"") -> 14.405405 | I41: =IFERROR(VLOOKUP("DUBLU PUI BURGER",'FOOD COST'!$A:$Y,24,0),"") -> 14.855856 | J41: =IF(OR(C41="",NOT(ISNUMBER(D41))),"",C41*D41) -> 28133.93 | K41: =IF(OR(C41="",NOT(ISNUMBER(E41))),"",C41*E41) -> 28133.93 | L41: =IF(OR(C41="",NOT(ISNUMBER(F41))),"",C41*F41) -> 59702.703 | M41: =IF(OR(C41="",NOT(ISNUMBER(G41))),"",C41*G41) -> 61652.991 | N41: =IF(OR(C41="",NOT(ISNUMBER(H41))),"",C41*H41) -> 63643.081 | O41: =IF(OR(C41="",NOT(ISNUMBER(I41))),"",C41*I41) -> 65633.171
A42: DUBLU PUI BURGER D | B42: Delivery | C42: 4259 | D42: =IFERROR(VLOOKUP("DUBLU PUI BURGER D",'FOOD COST'!$A:$Y,7,0),"") -> 6.368024 | E42: =IFERROR(VLOOKUP("DUBLU PUI BURGER D",'FOOD COST'!$A:$Y,8,0),"") -> 6.368024 | F42: =IFERROR(VLOOKUP("DUBLU PUI BURGER D",'FOOD COST'!$A:$Y,10,0),"") -> 16.216216 | G42: =IFERROR(VLOOKUP("DUBLU PUI BURGER D",'FOOD COST'!$A:$Y,18,0),"") -> 16.657658 | H42: =IFERROR(VLOOKUP("DUBLU PUI BURGER D",'FOOD COST'!$A:$Y,21,0),"") -> 17.108108 | I42: =IFERROR(VLOOKUP("DUBLU PUI BURGER D",'FOOD COST'!$A:$Y,24,0),"") -> 17.558559 | J42: =IF(OR(C42="",NOT(ISNUMBER(D42))),"",C42*D42) -> 27121.414 | K42: =IF(OR(C42="",NOT(ISNUMBER(E42))),"",C42*E42) -> 27121.414 | L42: =IF(OR(C42="",NOT(ISNUMBER(F42))),"",C42*F42) -> 69064.865 | M42: =IF(OR(C42="",NOT(ISNUMBER(G42))),"",C42*G42) -> 70944.964 | N42: =IF(OR(C42="",NOT(ISNUMBER(H42))),"",C42*H42) -> 72863.432 | O42: =IF(OR(C42="",NOT(ISNUMBER(I42))),"",C42*I42) -> 74781.901
A43: HOMESTYLE CHICKEN PESTO | B43: Instore | C43: 1850 | D43: =IFERROR(VLOOKUP("HOMESTYLE CHICKEN PESTO",'FOOD COST'!$A:$Y,7,0),"") -> 10.961048 | E43: =IFERROR(VLOOKUP("HOMESTYLE CHICKEN PESTO",'FOOD COST'!$A:$Y,8,0),"") -> 10.961048 | F43: =IFERROR(VLOOKUP("HOMESTYLE CHICKEN PESTO",'FOOD COST'!$A:$Y,10,0),"") -> 23.423423 | G43: =IFERROR(VLOOKUP("HOMESTYLE CHICKEN PESTO",'FOOD COST'!$A:$Y,18,0),"") -> 24.315315 | H43: =IFERROR(VLOOKUP("HOMESTYLE CHICKEN PESTO",'FOOD COST'!$A:$Y,21,0),"") -> 24.315315 | I43: =IFERROR(VLOOKUP("HOMESTYLE CHICKEN PESTO",'FOOD COST'!$A:$Y,24,0),"") -> 24.315315 | J43: =IF(OR(C43="",NOT(ISNUMBER(D43))),"",C43*D43) -> 20277.939 | K43: =IF(OR(C43="",NOT(ISNUMBER(E43))),"",C43*E43) -> 20277.939 | L43: =IF(OR(C43="",NOT(ISNUMBER(F43))),"",C43*F43) -> 43333.333 | M43: =IF(OR(C43="",NOT(ISNUMBER(G43))),"",C43*G43) -> 44983.333 | N43: =IF(OR(C43="",NOT(ISNUMBER(H43))),"",C43*H43) -> 44983.333 | O43: =IF(OR(C43="",NOT(ISNUMBER(I43))),"",C43*I43) -> 44983.333
A44: HOMESTYLE CHICKEN PESTO D | B44: Delivery | C44: 939 | D44: =IFERROR(VLOOKUP("HOMESTYLE CHICKEN PESTO D",'FOOD COST'!$A:$Y,7,0),"") -> 10.961048 | E44: =IFERROR(VLOOKUP("HOMESTYLE CHICKEN PESTO D",'FOOD COST'!$A:$Y,8,0),"") -> 10.961048 | F44: =IFERROR(VLOOKUP("HOMESTYLE CHICKEN PESTO D",'FOOD COST'!$A:$Y,10,0),"") -> 25.675676 | G44: =IFERROR(VLOOKUP("HOMESTYLE CHICKEN PESTO D",'FOOD COST'!$A:$Y,18,0),"") -> 26.567568 | H44: =IFERROR(VLOOKUP("HOMESTYLE CHICKEN PESTO D",'FOOD COST'!$A:$Y,21,0),"") -> 26.567568 | I44: =IFERROR(VLOOKUP("HOMESTYLE CHICKEN PESTO D",'FOOD COST'!$A:$Y,24,0),"") -> 26.567568 | J44: =IF(OR(C44="",NOT(ISNUMBER(D44))),"",C44*D44) -> 10292.424 | K44: =IF(OR(C44="",NOT(ISNUMBER(E44))),"",C44*E44) -> 10292.424 | L44: =IF(OR(C44="",NOT(ISNUMBER(F44))),"",C44*F44) -> 24109.459 | M44: =IF(OR(C44="",NOT(ISNUMBER(G44))),"",C44*G44) -> 24946.946 | N44: =IF(OR(C44="",NOT(ISNUMBER(H44))),"",C44*H44) -> 24946.946 | O44: =IF(OR(C44="",NOT(ISNUMBER(I44))),"",C44*I44) -> 24946.946
A45: HOMESTYLE CHICKEN LEMON | B45: Instore | C45: 4017 | D45: =IFERROR(VLOOKUP("HOMESTYLE CHICKEN LEMON",'FOOD COST'!$A:$Y,7,0),"") -> 10.811248 | E45: =IFERROR(VLOOKUP("HOMESTYLE CHICKEN LEMON",'FOOD COST'!$A:$Y,8,0),"") -> 10.811248 | F45: =IFERROR(VLOOKUP("HOMESTYLE CHICKEN LEMON",'FOOD COST'!$A:$Y,10,0),"") -> 23.423423 | G45: =IFERROR(VLOOKUP("HOMESTYLE CHICKEN LEMON",'FOOD COST'!$A:$Y,18,0),"") -> 24.315315 | H45: =IFERROR(VLOOKUP("HOMESTYLE CHICKEN LEMON",'FOOD COST'!$A:$Y,21,0),"") -> 24.315315 | I45: =IFERROR(VLOOKUP("HOMESTYLE CHICKEN LEMON",'FOOD COST'!$A:$Y,24,0),"") -> 24.315315 | J45: =IF(OR(C45="",NOT(ISNUMBER(D45))),"",C45*D45) -> 43428.783 | K45: =IF(OR(C45="",NOT(ISNUMBER(E45))),"",C45*E45) -> 43428.783 | L45: =IF(OR(C45="",NOT(ISNUMBER(F45))),"",C45*F45) -> 94091.892 | M45: =IF(OR(C45="",NOT(ISNUMBER(G45))),"",C45*G45) -> 97674.622 | N45: =IF(OR(C45="",NOT(ISNUMBER(H45))),"",C45*H45) -> 97674.622 | O45: =IF(OR(C45="",NOT(ISNUMBER(I45))),"",C45*I45) -> 97674.622
A46: HOMESTYLE CHICKEN LEMON D | B46: Delivery | C46: 1177 | D46: =IFERROR(VLOOKUP("HOMESTYLE CHICKEN LEMON D",'FOOD COST'!$A:$Y,7,0),"") -> 10.811248 | E46: =IFERROR(VLOOKUP("HOMESTYLE CHICKEN LEMON D",'FOOD COST'!$A:$Y,8,0),"") -> 10.811248 | F46: =IFERROR(VLOOKUP("HOMESTYLE CHICKEN LEMON D",'FOOD COST'!$A:$Y,10,0),"") -> 25.225225 | G46: =IFERROR(VLOOKUP("HOMESTYLE CHICKEN LEMON D",'FOOD COST'!$A:$Y,18,0),"") -> 26.117117 | H46: =IFERROR(VLOOKUP("HOMESTYLE CHICKEN LEMON D",'FOOD COST'!$A:$Y,21,0),"") -> 26.117117 | I46: =IFERROR(VLOOKUP("HOMESTYLE CHICKEN LEMON D",'FOOD COST'!$A:$Y,24,0),"") -> 26.117117 | J46: =IF(OR(C46="",NOT(ISNUMBER(D46))),"",C46*D46) -> 12724.839 | K46: =IF(OR(C46="",NOT(ISNUMBER(E46))),"",C46*E46) -> 12724.839 | L46: =IF(OR(C46="",NOT(ISNUMBER(F46))),"",C46*F46) -> 29690.09 | M46: =IF(OR(C46="",NOT(ISNUMBER(G46))),"",C46*G46) -> 30739.847 | N46: =IF(OR(C46="",NOT(ISNUMBER(H46))),"",C46*H46) -> 30739.847 | O46: =IF(OR(C46="",NOT(ISNUMBER(I46))),"",C46*I46) -> 30739.847
A47: HOMESTYLE CHICKEN RANCH | B47: Instore | C47: 10348 | D47: =IFERROR(VLOOKUP("HOMESTYLE CHICKEN RANCH",'FOOD COST'!$A:$Y,7,0),"") -> 10.196948 | E47: =IFERROR(VLOOKUP("HOMESTYLE CHICKEN RANCH",'FOOD COST'!$A:$Y,8,0),"") -> 10.196948 | F47: =IFERROR(VLOOKUP("HOMESTYLE CHICKEN RANCH",'FOOD COST'!$A:$Y,10,0),"") -> 23.423423 | G47: =IFERROR(VLOOKUP("HOMESTYLE CHICKEN RANCH",'FOOD COST'!$A:$Y,18,0),"") -> 24.315315 | H47: =IFERROR(VLOOKUP("HOMESTYLE CHICKEN RANCH",'FOOD COST'!$A:$Y,21,0),"") -> 24.315315 | I47: =IFERROR(VLOOKUP("HOMESTYLE CHICKEN RANCH",'FOOD COST'!$A:$Y,24,0),"") -> 24.315315 | J47: =IF(OR(C47="",NOT(ISNUMBER(D47))),"",C47*D47) -> 105518.02 | K47: =IF(OR(C47="",NOT(ISNUMBER(E47))),"",C47*E47) -> 105518.02 | L47: =IF(OR(C47="",NOT(ISNUMBER(F47))),"",C47*F47) -> 242385.59 | M47: =IF(OR(C47="",NOT(ISNUMBER(G47))),"",C47*G47) -> 251614.88 | N47: =IF(OR(C47="",NOT(ISNUMBER(H47))),"",C47*H47) -> 251614.88 | O47: =IF(OR(C47="",NOT(ISNUMBER(I47))),"",C47*I47) -> 251614.88
A48: HOMESTYLE CHICKEN RANCH D | B48: Delivery | C48: 4620 | D48: =IFERROR(VLOOKUP("HOMESTYLE CHICKEN RANCH D",'FOOD COST'!$A:$Y,7,0),"") -> 10.196948 | E48: =IFERROR(VLOOKUP("HOMESTYLE CHICKEN RANCH D",'FOOD COST'!$A:$Y,8,0),"") -> 10.196948 | F48: =IFERROR(VLOOKUP("HOMESTYLE CHICKEN RANCH D",'FOOD COST'!$A:$Y,10,0),"") -> 25.225225 | G48: =IFERROR(VLOOKUP("HOMESTYLE CHICKEN RANCH D",'FOOD COST'!$A:$Y,18,0),"") -> 26.117117 | H48: =IFERROR(VLOOKUP("HOMESTYLE CHICKEN RANCH D",'FOOD COST'!$A:$Y,21,0),"") -> 26.117117 | I48: =IFERROR(VLOOKUP("HOMESTYLE CHICKEN RANCH D",'FOOD COST'!$A:$Y,24,0),"") -> 26.117117 | J48: =IF(OR(C48="",NOT(ISNUMBER(D48))),"",C48*D48) -> 47109.9 | K48: =IF(OR(C48="",NOT(ISNUMBER(E48))),"",C48*E48) -> 47109.9 | L48: =IF(OR(C48="",NOT(ISNUMBER(F48))),"",C48*F48) -> 116540.54 | M48: =IF(OR(C48="",NOT(ISNUMBER(G48))),"",C48*G48) -> 120661.08 | N48: =IF(OR(C48="",NOT(ISNUMBER(H48))),"",C48*H48) -> 120661.08 | O48: =IF(OR(C48="",NOT(ISNUMBER(I48))),"",C48*I48) -> 120661.08
A49: CHICKEN TRUFFLE | B49: Instore | C49: 8204 | D49: =IFERROR(VLOOKUP("CHICKEN TRUFFLE",'FOOD COST'!$A:$Y,7,0),"") -> 5.615394 | E49: =IFERROR(VLOOKUP("CHICKEN TRUFFLE",'FOOD COST'!$A:$Y,8,0),"") -> 5.615394 | F49: =IFERROR(VLOOKUP("CHICKEN TRUFFLE",'FOOD COST'!$A:$Y,10,0),"") -> 12.612613 | G49: =IFERROR(VLOOKUP("CHICKEN TRUFFLE",'FOOD COST'!$A:$Y,18,0),"") -> 13.054054 | H49: =IFERROR(VLOOKUP("CHICKEN TRUFFLE",'FOOD COST'!$A:$Y,21,0),"") -> 13.054054 | I49: =IFERROR(VLOOKUP("CHICKEN TRUFFLE",'FOOD COST'!$A:$Y,24,0),"") -> 13.054054 | J49: =IF(OR(C49="",NOT(ISNUMBER(D49))),"",C49*D49) -> 46068.692 | K49: =IF(OR(C49="",NOT(ISNUMBER(E49))),"",C49*E49) -> 46068.692 | L49: =IF(OR(C49="",NOT(ISNUMBER(F49))),"",C49*F49) -> 103473.87 | M49: =IF(OR(C49="",NOT(ISNUMBER(G49))),"",C49*G49) -> 107095.46 | N49: =IF(OR(C49="",NOT(ISNUMBER(H49))),"",C49*H49) -> 107095.46 | O49: =IF(OR(C49="",NOT(ISNUMBER(I49))),"",C49*I49) -> 107095.46
A50: CHICKEN TRUFFLE D | B50: Delivery | C50: 3203 | D50: =IFERROR(VLOOKUP("CHICKEN TRUFFLE D",'FOOD COST'!$A:$Y,7,0),"") -> 5.615394 | E50: =IFERROR(VLOOKUP("CHICKEN TRUFFLE D",'FOOD COST'!$A:$Y,8,0),"") -> 5.615394 | F50: =IFERROR(VLOOKUP("CHICKEN TRUFFLE D",'FOOD COST'!$A:$Y,10,0),"") -> 14.414414 | G50: =IFERROR(VLOOKUP("CHICKEN TRUFFLE D",'FOOD COST'!$A:$Y,18,0),"") -> 14.855856 | H50: =IFERROR(VLOOKUP("CHICKEN TRUFFLE D",'FOOD COST'!$A:$Y,21,0),"") -> 14.855856 | I50: =IFERROR(VLOOKUP("CHICKEN TRUFFLE D",'FOOD COST'!$A:$Y,24,0),"") -> 14.855856 | J50: =IF(OR(C50="",NOT(ISNUMBER(D50))),"",C50*D50) -> 17986.107 | K50: =IF(OR(C50="",NOT(ISNUMBER(E50))),"",C50*E50) -> 17986.107 | L50: =IF(OR(C50="",NOT(ISNUMBER(F50))),"",C50*F50) -> 46169.369 | M50: =IF(OR(C50="",NOT(ISNUMBER(G50))),"",C50*G50) -> 47583.306 | N50: =IF(OR(C50="",NOT(ISNUMBER(H50))),"",C50*H50) -> 47583.306 | O50: =IF(OR(C50="",NOT(ISNUMBER(I50))),"",C50*I50) -> 47583.306
A51: DUBLU CHICKEN TRUFFLE | B51: Instore | C51: 3085 | D51: =IFERROR(VLOOKUP("DUBLU CHICKEN TRUFFLE",'FOOD COST'!$A:$Y,7,0),"") -> 7.761518 | E51: =IFERROR(VLOOKUP("DUBLU CHICKEN TRUFFLE",'FOOD COST'!$A:$Y,8,0),"") -> 7.761518 | F51: =IFERROR(VLOOKUP("DUBLU CHICKEN TRUFFLE",'FOOD COST'!$A:$Y,10,0),"") -> 17.117117 | G51: =IFERROR(VLOOKUP("DUBLU CHICKEN TRUFFLE",'FOOD COST'!$A:$Y,18,0),"") -> 18.009009 | H51: =IFERROR(VLOOKUP("DUBLU CHICKEN TRUFFLE",'FOOD COST'!$A:$Y,21,0),"") -> 18.009009 | I51: =IFERROR(VLOOKUP("DUBLU CHICKEN TRUFFLE",'FOOD COST'!$A:$Y,24,0),"") -> 18.009009 | J51: =IF(OR(C51="",NOT(ISNUMBER(D51))),"",C51*D51) -> 23944.283 | K51: =IF(OR(C51="",NOT(ISNUMBER(E51))),"",C51*E51) -> 23944.283 | L51: =IF(OR(C51="",NOT(ISNUMBER(F51))),"",C51*F51) -> 52806.306 | M51: =IF(OR(C51="",NOT(ISNUMBER(G51))),"",C51*G51) -> 55557.793 | N51: =IF(OR(C51="",NOT(ISNUMBER(H51))),"",C51*H51) -> 55557.793 | O51: =IF(OR(C51="",NOT(ISNUMBER(I51))),"",C51*I51) -> 55557.793
A52: DUBLU CHICKEN TRUFFLE D | B52: Delivery | C52: 4983 | D52: =IFERROR(VLOOKUP("DUBLU CHICKEN TRUFFLE D",'FOOD COST'!$A:$Y,7,0),"") -> 7.761518 | E52: =IFERROR(VLOOKUP("DUBLU CHICKEN TRUFFLE D",'FOOD COST'!$A:$Y,8,0),"") -> 7.761518 | F52: =IFERROR(VLOOKUP("DUBLU CHICKEN TRUFFLE D",'FOOD COST'!$A:$Y,10,0),"") -> 18.918919 | G52: =IFERROR(VLOOKUP("DUBLU CHICKEN TRUFFLE D",'FOOD COST'!$A:$Y,18,0),"") -> 19.810811 | H52: =IFERROR(VLOOKUP("DUBLU CHICKEN TRUFFLE D",'FOOD COST'!$A:$Y,21,0),"") -> 19.810811 | I52: =IFERROR(VLOOKUP("DUBLU CHICKEN TRUFFLE D",'FOOD COST'!$A:$Y,24,0),"") -> 19.810811 | J52: =IF(OR(C52="",NOT(ISNUMBER(D52))),"",C52*D52) -> 38675.644 | K52: =IF(OR(C52="",NOT(ISNUMBER(E52))),"",C52*E52) -> 38675.644 | L52: =IF(OR(C52="",NOT(ISNUMBER(F52))),"",C52*F52) -> 94272.973 | M52: =IF(OR(C52="",NOT(ISNUMBER(G52))),"",C52*G52) -> 98717.27 | N52: =IF(OR(C52="",NOT(ISNUMBER(H52))),"",C52*H52) -> 98717.27 | O52: =IF(OR(C52="",NOT(ISNUMBER(I52))),"",C52*I52) -> 98717.27
A53: Chicken FryRanch XRemus | B53: Instore | C53: 2661 | D53: =IFERROR(VLOOKUP("Chicken FryRanch XRemus",'FOOD COST'!$A:$Y,7,0),"") -> 4.981324 | E53: =IFERROR(VLOOKUP("Chicken FryRanch XRemus",'FOOD COST'!$A:$Y,8,0),"") -> 4.981324 | F53: =IFERROR(VLOOKUP("Chicken FryRanch XRemus",'FOOD COST'!$A:$Y,10,0),"") -> 16.216216 | G53: =IFERROR(VLOOKUP("Chicken FryRanch XRemus",'FOOD COST'!$A:$Y,18,0),"") -> 16.216216 | H53: =IFERROR(VLOOKUP("Chicken FryRanch XRemus",'FOOD COST'!$A:$Y,21,0),"") -> 16.216216 | I53: =IFERROR(VLOOKUP("Chicken FryRanch XRemus",'FOOD COST'!$A:$Y,24,0),"") -> 16.216216 | J53: =IF(OR(C53="",NOT(ISNUMBER(D53))),"",C53*D53) -> 13255.303 | K53: =IF(OR(C53="",NOT(ISNUMBER(E53))),"",C53*E53) -> 13255.303 | L53: =IF(OR(C53="",NOT(ISNUMBER(F53))),"",C53*F53) -> 43151.351 | M53: =IF(OR(C53="",NOT(ISNUMBER(G53))),"",C53*G53) -> 43151.351 | N53: =IF(OR(C53="",NOT(ISNUMBER(H53))),"",C53*H53) -> 43151.351 | O53: =IF(OR(C53="",NOT(ISNUMBER(I53))),"",C53*I53) -> 43151.351
A54: HOMESTYLE CHICKEN FRYRANCH LETTUCE WRAP | B54: Instore | C54: 1604 | D54: =IFERROR(VLOOKUP("HOMESTYLE CHICKEN FRYRANCH LETTUCE WRAP",'FOOD COST'!$A:$Y,7,0),"") -> 10.271948 | E54: =IFERROR(VLOOKUP("HOMESTYLE CHICKEN FRYRANCH LETTUCE WRAP",'FOOD COST'!$A:$Y,8,0),"") -> 10.271948 | F54: =IFERROR(VLOOKUP("HOMESTYLE CHICKEN FRYRANCH LETTUCE WRAP",'FOOD COST'!$A:$Y,10,0),"") -> 23.423423 | G54: =IFERROR(VLOOKUP("HOMESTYLE CHICKEN FRYRANCH LETTUCE WRAP",'FOOD COST'!$A:$Y,18,0),"") -> 24.315315 | H54: =IFERROR(VLOOKUP("HOMESTYLE CHICKEN FRYRANCH LETTUCE WRAP",'FOOD COST'!$A:$Y,21,0),"") -> 24.315315 | I54: =IFERROR(VLOOKUP("HOMESTYLE CHICKEN FRYRANCH LETTUCE WRAP",'FOOD COST'!$A:$Y,24,0),"") -> 24.315315 | J54: =IF(OR(C54="",NOT(ISNUMBER(D54))),"",C54*D54) -> 16476.205 | K54: =IF(OR(C54="",NOT(ISNUMBER(E54))),"",C54*E54) -> 16476.205 | L54: =IF(OR(C54="",NOT(ISNUMBER(F54))),"",C54*F54) -> 37571.171 | M54: =IF(OR(C54="",NOT(ISNUMBER(G54))),"",C54*G54) -> 39001.766 | N54: =IF(OR(C54="",NOT(ISNUMBER(H54))),"",C54*H54) -> 39001.766 | O54: =IF(OR(C54="",NOT(ISNUMBER(I54))),"",C54*I54) -> 39001.766
A55: HOMESTYLE CHICKEN FRYRANCH LETTUCE WRAP D | B55: Delivery | C55: 1580 | D55: =IFERROR(VLOOKUP("HOMESTYLE CHICKEN FRYRANCH LETTUCE WRAP D",'FOOD COST'!$A:$Y,7,0),"") -> 10.271948 | E55: =IFERROR(VLOOKUP("HOMESTYLE CHICKEN FRYRANCH LETTUCE WRAP D",'FOOD COST'!$A:$Y,8,0),"") -> 10.271948 | F55: =IFERROR(VLOOKUP("HOMESTYLE CHICKEN FRYRANCH LETTUCE WRAP D",'FOOD COST'!$A:$Y,10,0),"") -> 25.225225 | G55: =IFERROR(VLOOKUP("HOMESTYLE CHICKEN FRYRANCH LETTUCE WRAP D",'FOOD COST'!$A:$Y,18,0),"") -> 26.117117 | H55: =IFERROR(VLOOKUP("HOMESTYLE CHICKEN FRYRANCH LETTUCE WRAP D",'FOOD COST'!$A:$Y,21,0),"") -> 26.117117 | I55: =IFERROR(VLOOKUP("HOMESTYLE CHICKEN FRYRANCH LETTUCE WRAP D",'FOOD COST'!$A:$Y,24,0),"") -> 26.117117 | J55: =IF(OR(C55="",NOT(ISNUMBER(D55))),"",C55*D55) -> 16229.678 | K55: =IF(OR(C55="",NOT(ISNUMBER(E55))),"",C55*E55) -> 16229.678 | L55: =IF(OR(C55="",NOT(ISNUMBER(F55))),"",C55*F55) -> 39855.856 | M55: =IF(OR(C55="",NOT(ISNUMBER(G55))),"",C55*G55) -> 41265.045 | N55: =IF(OR(C55="",NOT(ISNUMBER(H55))),"",C55*H55) -> 41265.045 | O55: =IF(OR(C55="",NOT(ISNUMBER(I55))),"",C55*I55) -> 41265.045
A56: HOMESTYLE CHICKEN LEMON LETTUCE WRAP | B56: Instore | C56: 1116 | D56: =IFERROR(VLOOKUP("HOMESTYLE CHICKEN LEMON LETTUCE WRAP",'FOOD COST'!$A:$Y,7,0),"") -> 10.886248 | E56: =IFERROR(VLOOKUP("HOMESTYLE CHICKEN LEMON LETTUCE WRAP",'FOOD COST'!$A:$Y,8,0),"") -> 10.886248 | F56: =IFERROR(VLOOKUP("HOMESTYLE CHICKEN LEMON LETTUCE WRAP",'FOOD COST'!$A:$Y,10,0),"") -> 23.423423 | G56: =IFERROR(VLOOKUP("HOMESTYLE CHICKEN LEMON LETTUCE WRAP",'FOOD COST'!$A:$Y,18,0),"") -> 24.315315 | H56: =IFERROR(VLOOKUP("HOMESTYLE CHICKEN LEMON LETTUCE WRAP",'FOOD COST'!$A:$Y,21,0),"") -> 24.315315 | I56: =IFERROR(VLOOKUP("HOMESTYLE CHICKEN LEMON LETTUCE WRAP",'FOOD COST'!$A:$Y,24,0),"") -> 24.315315 | J56: =IF(OR(C56="",NOT(ISNUMBER(D56))),"",C56*D56) -> 12149.053 | K56: =IF(OR(C56="",NOT(ISNUMBER(E56))),"",C56*E56) -> 12149.053 | L56: =IF(OR(C56="",NOT(ISNUMBER(F56))),"",C56*F56) -> 26140.541 | M56: =IF(OR(C56="",NOT(ISNUMBER(G56))),"",C56*G56) -> 27135.892 | N56: =IF(OR(C56="",NOT(ISNUMBER(H56))),"",C56*H56) -> 27135.892 | O56: =IF(OR(C56="",NOT(ISNUMBER(I56))),"",C56*I56) -> 27135.892
A57: HOMESTYLE CHICKEN LEMON LETTUCE WRAP D | B57: Delivery | C57: 898 | D57: =IFERROR(VLOOKUP("HOMESTYLE CHICKEN LEMON LETTUCE WRAP D",'FOOD COST'!$A:$Y,7,0),"") -> 10.886248 | E57: =IFERROR(VLOOKUP("HOMESTYLE CHICKEN LEMON LETTUCE WRAP D",'FOOD COST'!$A:$Y,8,0),"") -> 10.886248 | F57: =IFERROR(VLOOKUP("HOMESTYLE CHICKEN LEMON LETTUCE WRAP D",'FOOD COST'!$A:$Y,10,0),"") -> 25.225225 | G57: =IFERROR(VLOOKUP("HOMESTYLE CHICKEN LEMON LETTUCE WRAP D",'FOOD COST'!$A:$Y,18,0),"") -> 26.117117 | H57: =IFERROR(VLOOKUP("HOMESTYLE CHICKEN LEMON LETTUCE WRAP D",'FOOD COST'!$A:$Y,21,0),"") -> 26.117117 | I57: =IFERROR(VLOOKUP("HOMESTYLE CHICKEN LEMON LETTUCE WRAP D",'FOOD COST'!$A:$Y,24,0),"") -> 26.117117 | J57: =IF(OR(C57="",NOT(ISNUMBER(D57))),"",C57*D57) -> 9775.8507 | K57: =IF(OR(C57="",NOT(ISNUMBER(E57))),"",C57*E57) -> 9775.8507 | L57: =IF(OR(C57="",NOT(ISNUMBER(F57))),"",C57*F57) -> 22652.252 | M57: =IF(OR(C57="",NOT(ISNUMBER(G57))),"",C57*G57) -> 23453.171 | N57: =IF(OR(C57="",NOT(ISNUMBER(H57))),"",C57*H57) -> 23453.171 | O57: =IF(OR(C57="",NOT(ISNUMBER(I57))),"",C57*I57) -> 23453.171
A58: TRIPLU PUI BURGER | B58: Instore | C58: 334 | D58: =IFERROR(VLOOKUP("TRIPLU PUI BURGER",'FOOD COST'!$A:$Y,7,0),"") -> 7.877024 | E58: =IFERROR(VLOOKUP("TRIPLU PUI BURGER",'FOOD COST'!$A:$Y,8,0),"") -> 7.877024 | F58: =IFERROR(VLOOKUP("TRIPLU PUI BURGER",'FOOD COST'!$A:$Y,10,0),"") -> 18.018018 | G58: =IFERROR(VLOOKUP("TRIPLU PUI BURGER",'FOOD COST'!$A:$Y,18,0),"") -> 18.90991 | H58: =IFERROR(VLOOKUP("TRIPLU PUI BURGER",'FOOD COST'!$A:$Y,21,0),"") -> 19.36036 | I58: =IFERROR(VLOOKUP("TRIPLU PUI BURGER",'FOOD COST'!$A:$Y,24,0),"") -> 19.810811 | J58: =IF(OR(C58="",NOT(ISNUMBER(D58))),"",C58*D58) -> 2630.926 | K58: =IF(OR(C58="",NOT(ISNUMBER(E58))),"",C58*E58) -> 2630.926 | L58: =IF(OR(C58="",NOT(ISNUMBER(F58))),"",C58*F58) -> 6018.018 | M58: =IF(OR(C58="",NOT(ISNUMBER(G58))),"",C58*G58) -> 6315.9099 | N58: =IF(OR(C58="",NOT(ISNUMBER(H58))),"",C58*H58) -> 6466.3604 | O58: =IF(OR(C58="",NOT(ISNUMBER(I58))),"",C58*I58) -> 6616.8108
A59: TRIPLU CHICKEN TRUFFLE | B59: Instore | C59: 440 | D59: =IFERROR(VLOOKUP("TRIPLU CHICKEN TRUFFLE",'FOOD COST'!$A:$Y,7,0),"") -> 9.886188 | E59: =IFERROR(VLOOKUP("TRIPLU CHICKEN TRUFFLE",'FOOD COST'!$A:$Y,8,0),"") -> 9.886188 | F59: =IFERROR(VLOOKUP("TRIPLU CHICKEN TRUFFLE",'FOOD COST'!$A:$Y,10,0),"") -> 21.621622 | G59: =IFERROR(VLOOKUP("TRIPLU CHICKEN TRUFFLE",'FOOD COST'!$A:$Y,18,0),"") -> 22.063063 | H59: =IFERROR(VLOOKUP("TRIPLU CHICKEN TRUFFLE",'FOOD COST'!$A:$Y,21,0),"") -> 22.063063 | I59: =IFERROR(VLOOKUP("TRIPLU CHICKEN TRUFFLE",'FOOD COST'!$A:$Y,24,0),"") -> 22.063063 | J59: =IF(OR(C59="",NOT(ISNUMBER(D59))),"",C59*D59) -> 4349.9227 | K59: =IF(OR(C59="",NOT(ISNUMBER(E59))),"",C59*E59) -> 4349.9227 | L59: =IF(OR(C59="",NOT(ISNUMBER(F59))),"",C59*F59) -> 9513.5135 | M59: =IF(OR(C59="",NOT(ISNUMBER(G59))),"",C59*G59) -> 9707.7477 | N59: =IF(OR(C59="",NOT(ISNUMBER(H59))),"",C59*H59) -> 9707.7477 | O59: =IF(OR(C59="",NOT(ISNUMBER(I59))),"",C59*I59) -> 9707.7477
A60: ALMETTE FRESH PUI | B60: Instore | C60: 875 | D60: =IFERROR(VLOOKUP("ALMETTE FRESH PUI",'FOOD COST'!$A:$Y,7,0),"") -> 6.586 | E60: =IFERROR(VLOOKUP("ALMETTE FRESH PUI",'FOOD COST'!$A:$Y,8,0),"") -> 6.586 | F60: =IFERROR(VLOOKUP("ALMETTE FRESH PUI",'FOOD COST'!$A:$Y,10,0),"") -> 15.315315 | G60: =IFERROR(VLOOKUP("ALMETTE FRESH PUI",'FOOD COST'!$A:$Y,18,0),"") -> 15.315315 | H60: =IFERROR(VLOOKUP("ALMETTE FRESH PUI",'FOOD COST'!$A:$Y,21,0),"") -> 15.315315 | I60: =IFERROR(VLOOKUP("ALMETTE FRESH PUI",'FOOD COST'!$A:$Y,24,0),"") -> 15.315315 | J60: =IF(OR(C60="",NOT(ISNUMBER(D60))),"",C60*D60) -> 5762.75 | K60: =IF(OR(C60="",NOT(ISNUMBER(E60))),"",C60*E60) -> 5762.75 | L60: =IF(OR(C60="",NOT(ISNUMBER(F60))),"",C60*F60) -> 13400.901 | M60: =IF(OR(C60="",NOT(ISNUMBER(G60))),"",C60*G60) -> 13400.901 | N60: =IF(OR(C60="",NOT(ISNUMBER(H60))),"",C60*H60) -> 13400.901 | O60: =IF(OR(C60="",NOT(ISNUMBER(I60))),"",C60*I60) -> 13400.901
A61: ALMETTE FRESH PUI D | B61: Delivery | C61: 205 | D61: =IFERROR(VLOOKUP("ALMETTE FRESH PUI D",'FOOD COST'!$A:$Y,7,0),"") -> 6.586 | E61: =IFERROR(VLOOKUP("ALMETTE FRESH PUI D",'FOOD COST'!$A:$Y,8,0),"") -> 6.586 | F61: =IFERROR(VLOOKUP("ALMETTE FRESH PUI D",'FOOD COST'!$A:$Y,10,0),"") -> 18.018018 | G61: =IFERROR(VLOOKUP("ALMETTE FRESH PUI D",'FOOD COST'!$A:$Y,18,0),"") -> 18.018018 | H61: =IFERROR(VLOOKUP("ALMETTE FRESH PUI D",'FOOD COST'!$A:$Y,21,0),"") -> 18.018018 | I61: =IFERROR(VLOOKUP("ALMETTE FRESH PUI D",'FOOD COST'!$A:$Y,24,0),"") -> 18.018018 | J61: =IF(OR(C61="",NOT(ISNUMBER(D61))),"",C61*D61) -> 1350.13 | K61: =IF(OR(C61="",NOT(ISNUMBER(E61))),"",C61*E61) -> 1350.13 | L61: =IF(OR(C61="",NOT(ISNUMBER(F61))),"",C61*F61) -> 3693.6937 | M61: =IF(OR(C61="",NOT(ISNUMBER(G61))),"",C61*G61) -> 3693.6937 | N61: =IF(OR(C61="",NOT(ISNUMBER(H61))),"",C61*H61) -> 3693.6937 | O61: =IF(OR(C61="",NOT(ISNUMBER(I61))),"",C61*I61) -> 3693.6937
A62: ALMETTE BASIL PUI | B62: Instore | C62: 265 | D62: =IFERROR(VLOOKUP("ALMETTE BASIL PUI",'FOOD COST'!$A:$Y,7,0),"") -> 6.9951 | E62: =IFERROR(VLOOKUP("ALMETTE BASIL PUI",'FOOD COST'!$A:$Y,8,0),"") -> 6.9951 | F62: =IFERROR(VLOOKUP("ALMETTE BASIL PUI",'FOOD COST'!$A:$Y,10,0),"") -> 15.315315 | G62: =IFERROR(VLOOKUP("ALMETTE BASIL PUI",'FOOD COST'!$A:$Y,18,0),"") -> 15.315315 | H62: =IFERROR(VLOOKUP("ALMETTE BASIL PUI",'FOOD COST'!$A:$Y,21,0),"") -> 15.315315 | I62: =IFERROR(VLOOKUP("ALMETTE BASIL PUI",'FOOD COST'!$A:$Y,24,0),"") -> 15.315315 | J62: =IF(OR(C62="",NOT(ISNUMBER(D62))),"",C62*D62) -> 1853.7015 | K62: =IF(OR(C62="",NOT(ISNUMBER(E62))),"",C62*E62) -> 1853.7015 | L62: =IF(OR(C62="",NOT(ISNUMBER(F62))),"",C62*F62) -> 4058.5586 | M62: =IF(OR(C62="",NOT(ISNUMBER(G62))),"",C62*G62) -> 4058.5586 | N62: =IF(OR(C62="",NOT(ISNUMBER(H62))),"",C62*H62) -> 4058.5586 | O62: =IF(OR(C62="",NOT(ISNUMBER(I62))),"",C62*I62) -> 4058.5586
A63: ALMETTE BASIL PUI D | B63: Delivery | C63: 124 | D63: =IFERROR(VLOOKUP("ALMETTE BASIL PUI D",'FOOD COST'!$A:$Y,7,0),"") -> 6.9951 | E63: =IFERROR(VLOOKUP("ALMETTE BASIL PUI D",'FOOD COST'!$A:$Y,8,0),"") -> 6.9951 | F63: =IFERROR(VLOOKUP("ALMETTE BASIL PUI D",'FOOD COST'!$A:$Y,10,0),"") -> 18.018018 | G63: =IFERROR(VLOOKUP("ALMETTE BASIL PUI D",'FOOD COST'!$A:$Y,18,0),"") -> 18.018018 | H63: =IFERROR(VLOOKUP("ALMETTE BASIL PUI D",'FOOD COST'!$A:$Y,21,0),"") -> 18.018018 | I63: =IFERROR(VLOOKUP("ALMETTE BASIL PUI D",'FOOD COST'!$A:$Y,24,0),"") -> 18.018018 | J63: =IF(OR(C63="",NOT(ISNUMBER(D63))),"",C63*D63) -> 867.3924 | K63: =IF(OR(C63="",NOT(ISNUMBER(E63))),"",C63*E63) -> 867.3924 | L63: =IF(OR(C63="",NOT(ISNUMBER(F63))),"",C63*F63) -> 2234.2342 | M63: =IF(OR(C63="",NOT(ISNUMBER(G63))),"",C63*G63) -> 2234.2342 | N63: =IF(OR(C63="",NOT(ISNUMBER(H63))),"",C63*H63) -> 2234.2342 | O63: =IF(OR(C63="",NOT(ISNUMBER(I63))),"",C63*I63) -> 2234.2342
A64: ALMETTE FRESH PORC | B64: Instore | C64: 174 | D64: =IFERROR(VLOOKUP("ALMETTE FRESH PORC",'FOOD COST'!$A:$Y,7,0),"") -> 7.548 | E64: =IFERROR(VLOOKUP("ALMETTE FRESH PORC",'FOOD COST'!$A:$Y,8,0),"") -> 7.548 | F64: =IFERROR(VLOOKUP("ALMETTE FRESH PORC",'FOOD COST'!$A:$Y,10,0),"") -> 15.315315 | G64: =IFERROR(VLOOKUP("ALMETTE FRESH PORC",'FOOD COST'!$A:$Y,18,0),"") -> 15.315315 | H64: =IFERROR(VLOOKUP("ALMETTE FRESH PORC",'FOOD COST'!$A:$Y,21,0),"") -> 15.315315 | I64: =IFERROR(VLOOKUP("ALMETTE FRESH PORC",'FOOD COST'!$A:$Y,24,0),"") -> 15.315315 | J64: =IF(OR(C64="",NOT(ISNUMBER(D64))),"",C64*D64) -> 1313.352 | K64: =IF(OR(C64="",NOT(ISNUMBER(E64))),"",C64*E64) -> 1313.352 | L64: =IF(OR(C64="",NOT(ISNUMBER(F64))),"",C64*F64) -> 2664.8649 | M64: =IF(OR(C64="",NOT(ISNUMBER(G64))),"",C64*G64) -> 2664.8649 | N64: =IF(OR(C64="",NOT(ISNUMBER(H64))),"",C64*H64) -> 2664.8649 | O64: =IF(OR(C64="",NOT(ISNUMBER(I64))),"",C64*I64) -> 2664.8649
A65: ALMETTE FRESH PORC D | B65: Delivery | C65: 45 | D65: =IFERROR(VLOOKUP("ALMETTE FRESH PORC D",'FOOD COST'!$A:$Y,7,0),"") -> 7.548 | E65: =IFERROR(VLOOKUP("ALMETTE FRESH PORC D",'FOOD COST'!$A:$Y,8,0),"") -> 7.548 | F65: =IFERROR(VLOOKUP("ALMETTE FRESH PORC D",'FOOD COST'!$A:$Y,10,0),"") -> 18.018018 | G65: =IFERROR(VLOOKUP("ALMETTE FRESH PORC D",'FOOD COST'!$A:$Y,18,0),"") -> 18.018018 | H65: =IFERROR(VLOOKUP("ALMETTE FRESH PORC D",'FOOD COST'!$A:$Y,21,0),"") -> 18.018018 | I65: =IFERROR(VLOOKUP("ALMETTE FRESH PORC D",'FOOD COST'!$A:$Y,24,0),"") -> 18.018018 | J65: =IF(OR(C65="",NOT(ISNUMBER(D65))),"",C65*D65) -> 339.66 | K65: =IF(OR(C65="",NOT(ISNUMBER(E65))),"",C65*E65) -> 339.66 | L65: =IF(OR(C65="",NOT(ISNUMBER(F65))),"",C65*F65) -> 810.81081 | M65: =IF(OR(C65="",NOT(ISNUMBER(G65))),"",C65*G65) -> 810.81081 | N65: =IF(OR(C65="",NOT(ISNUMBER(H65))),"",C65*H65) -> 810.81081 | O65: =IF(OR(C65="",NOT(ISNUMBER(I65))),"",C65*I65) -> 810.81081
A66: ALMETTE BASIL PORC | B66: Instore | C66: 124 | D66: =IFERROR(VLOOKUP("ALMETTE BASIL PORC",'FOOD COST'!$A:$Y,7,0),"") -> 7.805 | E66: =IFERROR(VLOOKUP("ALMETTE BASIL PORC",'FOOD COST'!$A:$Y,8,0),"") -> 7.805 | F66: =IFERROR(VLOOKUP("ALMETTE BASIL PORC",'FOOD COST'!$A:$Y,10,0),"") -> 15.315315 | G66: =IFERROR(VLOOKUP("ALMETTE BASIL PORC",'FOOD COST'!$A:$Y,18,0),"") -> 15.315315 | H66: =IFERROR(VLOOKUP("ALMETTE BASIL PORC",'FOOD COST'!$A:$Y,21,0),"") -> 15.315315 | I66: =IFERROR(VLOOKUP("ALMETTE BASIL PORC",'FOOD COST'!$A:$Y,24,0),"") -> 15.315315 | J66: =IF(OR(C66="",NOT(ISNUMBER(D66))),"",C66*D66) -> 967.82 | K66: =IF(OR(C66="",NOT(ISNUMBER(E66))),"",C66*E66) -> 967.82 | L66: =IF(OR(C66="",NOT(ISNUMBER(F66))),"",C66*F66) -> 1899.0991 | M66: =IF(OR(C66="",NOT(ISNUMBER(G66))),"",C66*G66) -> 1899.0991 | N66: =IF(OR(C66="",NOT(ISNUMBER(H66))),"",C66*H66) -> 1899.0991 | O66: =IF(OR(C66="",NOT(ISNUMBER(I66))),"",C66*I66) -> 1899.0991
A67: ALMETTE BASIL PORC D | B67: Delivery | C67: 16 | D67: =IFERROR(VLOOKUP("ALMETTE BASIL PORC D",'FOOD COST'!$A:$Y,7,0),"") -> 7.805 | E67: =IFERROR(VLOOKUP("ALMETTE BASIL PORC D",'FOOD COST'!$A:$Y,8,0),"") -> 7.805 | F67: =IFERROR(VLOOKUP("ALMETTE BASIL PORC D",'FOOD COST'!$A:$Y,10,0),"") -> 18.018018 | G67: =IFERROR(VLOOKUP("ALMETTE BASIL PORC D",'FOOD COST'!$A:$Y,18,0),"") -> 18.018018 | H67: =IFERROR(VLOOKUP("ALMETTE BASIL PORC D",'FOOD COST'!$A:$Y,21,0),"") -> 18.018018 | I67: =IFERROR(VLOOKUP("ALMETTE BASIL PORC D",'FOOD COST'!$A:$Y,24,0),"") -> 18.018018 | J67: =IF(OR(C67="",NOT(ISNUMBER(D67))),"",C67*D67) -> 124.88 | K67: =IF(OR(C67="",NOT(ISNUMBER(E67))),"",C67*E67) -> 124.88 | L67: =IF(OR(C67="",NOT(ISNUMBER(F67))),"",C67*F67) -> 288.28829 | M67: =IF(OR(C67="",NOT(ISNUMBER(G67))),"",C67*G67) -> 288.28829 | N67: =IF(OR(C67="",NOT(ISNUMBER(H67))),"",C67*H67) -> 288.28829 | O67: =IF(OR(C67="",NOT(ISNUMBER(I67))),"",C67*I67) -> 288.28829
A68: ROSTI SAUSAGE BURGER | B68: Instore | C68: 177 | D68: =IFERROR(VLOOKUP("ROSTI SAUSAGE BURGER",'FOOD COST'!$A:$Y,7,0),"") -> 7.552718 | E68: =IFERROR(VLOOKUP("ROSTI SAUSAGE BURGER",'FOOD COST'!$A:$Y,8,0),"") -> 7.552718 | F68: =IFERROR(VLOOKUP("ROSTI SAUSAGE BURGER",'FOOD COST'!$A:$Y,10,0),"") -> 18.018018 | G68: =IFERROR(VLOOKUP("ROSTI SAUSAGE BURGER",'FOOD COST'!$A:$Y,18,0),"") -> 18.018018 | H68: =IFERROR(VLOOKUP("ROSTI SAUSAGE BURGER",'FOOD COST'!$A:$Y,21,0),"") -> 18.018018 | I68: =IFERROR(VLOOKUP("ROSTI SAUSAGE BURGER",'FOOD COST'!$A:$Y,24,0),"") -> 18.018018 | J68: =IF(OR(C68="",NOT(ISNUMBER(D68))),"",C68*D68) -> 1336.8311 | K68: =IF(OR(C68="",NOT(ISNUMBER(E68))),"",C68*E68) -> 1336.8311 | L68: =IF(OR(C68="",NOT(ISNUMBER(F68))),"",C68*F68) -> 3189.1892 | M68: =IF(OR(C68="",NOT(ISNUMBER(G68))),"",C68*G68) -> 3189.1892 | N68: =IF(OR(C68="",NOT(ISNUMBER(H68))),"",C68*H68) -> 3189.1892 | O68: =IF(OR(C68="",NOT(ISNUMBER(I68))),"",C68*I68) -> 3189.1892
A69: ROSTI SAUSAGE BURGER D | B69: Delivery | C69: 95 | D69: =IFERROR(VLOOKUP("ROSTI SAUSAGE BURGER D",'FOOD COST'!$A:$Y,7,0),"") -> 7.552718 | E69: =IFERROR(VLOOKUP("ROSTI SAUSAGE BURGER D",'FOOD COST'!$A:$Y,8,0),"") -> 7.552718 | F69: =IFERROR(VLOOKUP("ROSTI SAUSAGE BURGER D",'FOOD COST'!$A:$Y,10,0),"") -> 20.720721 | G69: =IFERROR(VLOOKUP("ROSTI SAUSAGE BURGER D",'FOOD COST'!$A:$Y,18,0),"") -> 20.720721 | H69: =IFERROR(VLOOKUP("ROSTI SAUSAGE BURGER D",'FOOD COST'!$A:$Y,21,0),"") -> 20.720721 | I69: =IFERROR(VLOOKUP("ROSTI SAUSAGE BURGER D",'FOOD COST'!$A:$Y,24,0),"") -> 20.720721 | J69: =IF(OR(C69="",NOT(ISNUMBER(D69))),"",C69*D69) -> 717.50821 | K69: =IF(OR(C69="",NOT(ISNUMBER(E69))),"",C69*E69) -> 717.50821 | L69: =IF(OR(C69="",NOT(ISNUMBER(F69))),"",C69*F69) -> 1968.4685 | M69: =IF(OR(C69="",NOT(ISNUMBER(G69))),"",C69*G69) -> 1968.4685 | N69: =IF(OR(C69="",NOT(ISNUMBER(H69))),"",C69*H69) -> 1968.4685 | O69: =IF(OR(C69="",NOT(ISNUMBER(I69))),"",C69*I69) -> 1968.4685
A70: SHRIMP BURGER | B70: Instore | C70: 2213 | D70: =IFERROR(VLOOKUP("SHRIMP BURGER",'FOOD COST'!$A:$Y,7,0),"") -> 10.673 | E70: =IFERROR(VLOOKUP("SHRIMP BURGER",'FOOD COST'!$A:$Y,8,0),"") -> 10.673 | F70: =IFERROR(VLOOKUP("SHRIMP BURGER",'FOOD COST'!$A:$Y,10,0),"") -> 22.522523 | G70: =IFERROR(VLOOKUP("SHRIMP BURGER",'FOOD COST'!$A:$Y,18,0),"") -> 23.414414 | H70: =IFERROR(VLOOKUP("SHRIMP BURGER",'FOOD COST'!$A:$Y,21,0),"") -> 23.414414 | I70: =IFERROR(VLOOKUP("SHRIMP BURGER",'FOOD COST'!$A:$Y,24,0),"") -> 23.414414 | J70: =IF(OR(C70="",NOT(ISNUMBER(D70))),"",C70*D70) -> 23619.349 | K70: =IF(OR(C70="",NOT(ISNUMBER(E70))),"",C70*E70) -> 23619.349 | L70: =IF(OR(C70="",NOT(ISNUMBER(F70))),"",C70*F70) -> 49842.342 | M70: =IF(OR(C70="",NOT(ISNUMBER(G70))),"",C70*G70) -> 51816.099 | N70: =IF(OR(C70="",NOT(ISNUMBER(H70))),"",C70*H70) -> 51816.099 | O70: =IF(OR(C70="",NOT(ISNUMBER(I70))),"",C70*I70) -> 51816.099
A71: SHRIMP BURGER D | B71: Delivery | C71: 2087 | D71: =IFERROR(VLOOKUP("SHRIMP BURGER D",'FOOD COST'!$A:$Y,7,0),"") -> 10.673 | E71: =IFERROR(VLOOKUP("SHRIMP BURGER D",'FOOD COST'!$A:$Y,8,0),"") -> 10.673 | F71: =IFERROR(VLOOKUP("SHRIMP BURGER D",'FOOD COST'!$A:$Y,10,0),"") -> 25.225225 | G71: =IFERROR(VLOOKUP("SHRIMP BURGER D",'FOOD COST'!$A:$Y,18,0),"") -> 26.117117 | H71: =IFERROR(VLOOKUP("SHRIMP BURGER D",'FOOD COST'!$A:$Y,21,0),"") -> 26.117117 | I71: =IFERROR(VLOOKUP("SHRIMP BURGER D",'FOOD COST'!$A:$Y,24,0),"") -> 26.117117 | J71: =IF(OR(C71="",NOT(ISNUMBER(D71))),"",C71*D71) -> 22274.551 | K71: =IF(OR(C71="",NOT(ISNUMBER(E71))),"",C71*E71) -> 22274.551 | L71: =IF(OR(C71="",NOT(ISNUMBER(F71))),"",C71*F71) -> 52645.045 | M71: =IF(OR(C71="",NOT(ISNUMBER(G71))),"",C71*G71) -> 54506.423 | N71: =IF(OR(C71="",NOT(ISNUMBER(H71))),"",C71*H71) -> 54506.423 | O71: =IF(OR(C71="",NOT(ISNUMBER(I71))),"",C71*I71) -> 54506.423
A72: BURGER VEGETARIAN | B72: Instore | C72: 2146 | D72: =IFERROR(VLOOKUP("BURGER VEGETARIAN",'FOOD COST'!$A:$Y,7,0),"") -> 7.148024 | E72: =IFERROR(VLOOKUP("BURGER VEGETARIAN",'FOOD COST'!$A:$Y,8,0),"") -> 7.148024 | F72: =IFERROR(VLOOKUP("BURGER VEGETARIAN",'FOOD COST'!$A:$Y,10,0),"") -> 18.018018 | G72: =IFERROR(VLOOKUP("BURGER VEGETARIAN",'FOOD COST'!$A:$Y,18,0),"") -> 18.90991 | H72: =IFERROR(VLOOKUP("BURGER VEGETARIAN",'FOOD COST'!$A:$Y,21,0),"") -> 18.90991 | I72: =IFERROR(VLOOKUP("BURGER VEGETARIAN",'FOOD COST'!$A:$Y,24,0),"") -> 18.90991 | J72: =IF(OR(C72="",NOT(ISNUMBER(D72))),"",C72*D72) -> 15339.66 | K72: =IF(OR(C72="",NOT(ISNUMBER(E72))),"",C72*E72) -> 15339.66 | L72: =IF(OR(C72="",NOT(ISNUMBER(F72))),"",C72*F72) -> 38666.667 | M72: =IF(OR(C72="",NOT(ISNUMBER(G72))),"",C72*G72) -> 40580.667 | N72: =IF(OR(C72="",NOT(ISNUMBER(H72))),"",C72*H72) -> 40580.667 | O72: =IF(OR(C72="",NOT(ISNUMBER(I72))),"",C72*I72) -> 40580.667
A73: BURGER VEGETARIAN D | B73: Delivery | C73: 1075 | D73: =IFERROR(VLOOKUP("BURGER VEGETARIAN D",'FOOD COST'!$A:$Y,7,0),"") -> 7.148024 | E73: =IFERROR(VLOOKUP("BURGER VEGETARIAN D",'FOOD COST'!$A:$Y,8,0),"") -> 7.148024 | F73: =IFERROR(VLOOKUP("BURGER VEGETARIAN D",'FOOD COST'!$A:$Y,10,0),"") -> 20.720721 | G73: =IFERROR(VLOOKUP("BURGER VEGETARIAN D",'FOOD COST'!$A:$Y,18,0),"") -> 21.612613 | H73: =IFERROR(VLOOKUP("BURGER VEGETARIAN D",'FOOD COST'!$A:$Y,21,0),"") -> 21.612613 | I73: =IFERROR(VLOOKUP("BURGER VEGETARIAN D",'FOOD COST'!$A:$Y,24,0),"") -> 21.612613 | J73: =IF(OR(C73="",NOT(ISNUMBER(D73))),"",C73*D73) -> 7684.1258 | K73: =IF(OR(C73="",NOT(ISNUMBER(E73))),"",C73*E73) -> 7684.1258 | L73: =IF(OR(C73="",NOT(ISNUMBER(F73))),"",C73*F73) -> 22274.775 | M73: =IF(OR(C73="",NOT(ISNUMBER(G73))),"",C73*G73) -> 23233.559 | N73: =IF(OR(C73="",NOT(ISNUMBER(H73))),"",C73*H73) -> 23233.559 | O73: =IF(OR(C73="",NOT(ISNUMBER(I73))),"",C73*I73) -> 23233.559
A74: 4 NUGGETS | B74: Instore | C74: 4024 | D74: =IFERROR(VLOOKUP("4 NUGGETS",'FOOD COST'!$A:$Y,7,0),"") -> 3.09672 | E74: =IFERROR(VLOOKUP("4 NUGGETS",'FOOD COST'!$A:$Y,8,0),"") -> 3.09672 | F74: =IFERROR(VLOOKUP("4 NUGGETS",'FOOD COST'!$A:$Y,10,0),"") -> 8.1081081 | G74: =IFERROR(VLOOKUP("4 NUGGETS",'FOOD COST'!$A:$Y,18,0),"") -> 8.3333333 | H74: =IFERROR(VLOOKUP("4 NUGGETS",'FOOD COST'!$A:$Y,21,0),"") -> 8.5585586 | I74: =IFERROR(VLOOKUP("4 NUGGETS",'FOOD COST'!$A:$Y,24,0),"") -> 9 | J74: =IF(OR(C74="",NOT(ISNUMBER(D74))),"",C74*D74) -> 12461.201 | K74: =IF(OR(C74="",NOT(ISNUMBER(E74))),"",C74*E74) -> 12461.201 | L74: =IF(OR(C74="",NOT(ISNUMBER(F74))),"",C74*F74) -> 32627.027 | M74: =IF(OR(C74="",NOT(ISNUMBER(G74))),"",C74*G74) -> 33533.333 | N74: =IF(OR(C74="",NOT(ISNUMBER(H74))),"",C74*H74) -> 34439.64 | O74: =IF(OR(C74="",NOT(ISNUMBER(I74))),"",C74*I74) -> 36216
A75: 4 NUGGETS D | B75: Delivery | C75: 2006 | D75: =IFERROR(VLOOKUP("4 NUGGETS D",'FOOD COST'!$A:$Y,7,0),"") -> 3.09672 | E75: =IFERROR(VLOOKUP("4 NUGGETS D",'FOOD COST'!$A:$Y,8,0),"") -> 3.09672 | F75: =IFERROR(VLOOKUP("4 NUGGETS D",'FOOD COST'!$A:$Y,10,0),"") -> 10.810811 | G75: =IFERROR(VLOOKUP("4 NUGGETS D",'FOOD COST'!$A:$Y,18,0),"") -> 11.036036 | H75: =IFERROR(VLOOKUP("4 NUGGETS D",'FOOD COST'!$A:$Y,21,0),"") -> 11.261261 | I75: =IFERROR(VLOOKUP("4 NUGGETS D",'FOOD COST'!$A:$Y,24,0),"") -> 11.702703 | J75: =IF(OR(C75="",NOT(ISNUMBER(D75))),"",C75*D75) -> 6212.0203 | K75: =IF(OR(C75="",NOT(ISNUMBER(E75))),"",C75*E75) -> 6212.0203 | L75: =IF(OR(C75="",NOT(ISNUMBER(F75))),"",C75*F75) -> 21686.486 | M75: =IF(OR(C75="",NOT(ISNUMBER(G75))),"",C75*G75) -> 22138.288 | N75: =IF(OR(C75="",NOT(ISNUMBER(H75))),"",C75*H75) -> 22590.09 | O75: =IF(OR(C75="",NOT(ISNUMBER(I75))),"",C75*I75) -> 23475.622
A76: 6 NUGGETS | B76: Instore | C76: 3354 | D76: =IFERROR(VLOOKUP("6 NUGGETS",'FOOD COST'!$A:$Y,7,0),"") -> 4.80258 | E76: =IFERROR(VLOOKUP("6 NUGGETS",'FOOD COST'!$A:$Y,8,0),"") -> 4.80258 | F76: =IFERROR(VLOOKUP("6 NUGGETS",'FOOD COST'!$A:$Y,10,0),"") -> 14.414414 | G76: =IFERROR(VLOOKUP("6 NUGGETS",'FOOD COST'!$A:$Y,18,0),"") -> 14.63964 | H76: =IFERROR(VLOOKUP("6 NUGGETS",'FOOD COST'!$A:$Y,21,0),"") -> 14.864865 | I76: =IFERROR(VLOOKUP("6 NUGGETS",'FOOD COST'!$A:$Y,24,0),"") -> 15.306306 | J76: =IF(OR(C76="",NOT(ISNUMBER(D76))),"",C76*D76) -> 16107.853 | K76: =IF(OR(C76="",NOT(ISNUMBER(E76))),"",C76*E76) -> 16107.853 | L76: =IF(OR(C76="",NOT(ISNUMBER(F76))),"",C76*F76) -> 48345.946 | M76: =IF(OR(C76="",NOT(ISNUMBER(G76))),"",C76*G76) -> 49101.351 | N76: =IF(OR(C76="",NOT(ISNUMBER(H76))),"",C76*H76) -> 49856.757 | O76: =IF(OR(C76="",NOT(ISNUMBER(I76))),"",C76*I76) -> 51337.351
A77: 6 NUGGETS D | B77: Delivery | C77: 2934 | D77: =IFERROR(VLOOKUP("6 NUGGETS D",'FOOD COST'!$A:$Y,7,0),"") -> 4.80258 | E77: =IFERROR(VLOOKUP("6 NUGGETS D",'FOOD COST'!$A:$Y,8,0),"") -> 4.80258 | F77: =IFERROR(VLOOKUP("6 NUGGETS D",'FOOD COST'!$A:$Y,10,0),"") -> 17.117117 | G77: =IFERROR(VLOOKUP("6 NUGGETS D",'FOOD COST'!$A:$Y,18,0),"") -> 17.342342 | H77: =IFERROR(VLOOKUP("6 NUGGETS D",'FOOD COST'!$A:$Y,21,0),"") -> 17.567568 | I77: =IFERROR(VLOOKUP("6 NUGGETS D",'FOOD COST'!$A:$Y,24,0),"") -> 18.009009 | J77: =IF(OR(C77="",NOT(ISNUMBER(D77))),"",C77*D77) -> 14090.77 | K77: =IF(OR(C77="",NOT(ISNUMBER(E77))),"",C77*E77) -> 14090.77 | L77: =IF(OR(C77="",NOT(ISNUMBER(F77))),"",C77*F77) -> 50221.622 | M77: =IF(OR(C77="",NOT(ISNUMBER(G77))),"",C77*G77) -> 50882.432 | N77: =IF(OR(C77="",NOT(ISNUMBER(H77))),"",C77*H77) -> 51543.243 | O77: =IF(OR(C77="",NOT(ISNUMBER(I77))),"",C77*I77) -> 52838.432
A78: 9 NUGGETS | B78: Instore | C78: 2189 | D78: =IFERROR(VLOOKUP("9 NUGGETS",'FOOD COST'!$A:$Y,7,0),"") -> 6.80887 | E78: =IFERROR(VLOOKUP("9 NUGGETS",'FOOD COST'!$A:$Y,8,0),"") -> 6.80887 | F78: =IFERROR(VLOOKUP("9 NUGGETS",'FOOD COST'!$A:$Y,10,0),"") -> 19.81982 | G78: =IFERROR(VLOOKUP("9 NUGGETS",'FOOD COST'!$A:$Y,18,0),"") -> 20.045045 | H78: =IFERROR(VLOOKUP("9 NUGGETS",'FOOD COST'!$A:$Y,21,0),"") -> 20.27027 | I78: =IFERROR(VLOOKUP("9 NUGGETS",'FOOD COST'!$A:$Y,24,0),"") -> 20.711712 | J78: =IF(OR(C78="",NOT(ISNUMBER(D78))),"",C78*D78) -> 14904.616 | K78: =IF(OR(C78="",NOT(ISNUMBER(E78))),"",C78*E78) -> 14904.616 | L78: =IF(OR(C78="",NOT(ISNUMBER(F78))),"",C78*F78) -> 43385.586 | M78: =IF(OR(C78="",NOT(ISNUMBER(G78))),"",C78*G78) -> 43878.604 | N78: =IF(OR(C78="",NOT(ISNUMBER(H78))),"",C78*H78) -> 44371.622 | O78: =IF(OR(C78="",NOT(ISNUMBER(I78))),"",C78*I78) -> 45337.937
A79: 9 NUGGETS D | B79: Delivery | C79: 3196 | D79: =IFERROR(VLOOKUP("9 NUGGETS D",'FOOD COST'!$A:$Y,7,0),"") -> 7.25987 | E79: =IFERROR(VLOOKUP("9 NUGGETS D",'FOOD COST'!$A:$Y,8,0),"") -> 7.25987 | F79: =IFERROR(VLOOKUP("9 NUGGETS D",'FOOD COST'!$A:$Y,10,0),"") -> 23.423423 | G79: =IFERROR(VLOOKUP("9 NUGGETS D",'FOOD COST'!$A:$Y,18,0),"") -> 23.648649 | H79: =IFERROR(VLOOKUP("9 NUGGETS D",'FOOD COST'!$A:$Y,21,0),"") -> 23.873874 | I79: =IFERROR(VLOOKUP("9 NUGGETS D",'FOOD COST'!$A:$Y,24,0),"") -> 24.315315 | J79: =IF(OR(C79="",NOT(ISNUMBER(D79))),"",C79*D79) -> 23202.545 | K79: =IF(OR(C79="",NOT(ISNUMBER(E79))),"",C79*E79) -> 23202.545 | L79: =IF(OR(C79="",NOT(ISNUMBER(F79))),"",C79*F79) -> 74861.261 | M79: =IF(OR(C79="",NOT(ISNUMBER(G79))),"",C79*G79) -> 75581.081 | N79: =IF(OR(C79="",NOT(ISNUMBER(H79))),"",C79*H79) -> 76300.901 | O79: =IF(OR(C79="",NOT(ISNUMBER(I79))),"",C79*I79) -> 77711.748
A80: 3 COUNTRY WINGS | B80: Instore | C80: 1210 | D80: =IFERROR(VLOOKUP("3 COUNTRY WINGS",'FOOD COST'!$A:$Y,7,0),"") -> 4.86849 | E80: =IFERROR(VLOOKUP("3 COUNTRY WINGS",'FOOD COST'!$A:$Y,8,0),"") -> 4.86849 | F80: =IFERROR(VLOOKUP("3 COUNTRY WINGS",'FOOD COST'!$A:$Y,10,0),"") -> 13.063063 | G80: =IFERROR(VLOOKUP("3 COUNTRY WINGS",'FOOD COST'!$A:$Y,18,0),"") -> 13.288288 | H80: =IFERROR(VLOOKUP("3 COUNTRY WINGS",'FOOD COST'!$A:$Y,21,0),"") -> 13.513514 | I80: =IFERROR(VLOOKUP("3 COUNTRY WINGS",'FOOD COST'!$A:$Y,24,0),"") -> 13.954955 | J80: =IF(OR(C80="",NOT(ISNUMBER(D80))),"",C80*D80) -> 5890.8729 | K80: =IF(OR(C80="",NOT(ISNUMBER(E80))),"",C80*E80) -> 5890.8729 | L80: =IF(OR(C80="",NOT(ISNUMBER(F80))),"",C80*F80) -> 15806.306 | M80: =IF(OR(C80="",NOT(ISNUMBER(G80))),"",C80*G80) -> 16078.829 | N80: =IF(OR(C80="",NOT(ISNUMBER(H80))),"",C80*H80) -> 16351.351 | O80: =IF(OR(C80="",NOT(ISNUMBER(I80))),"",C80*I80) -> 16885.495
A81: 3 COUNTRY WINGS D | B81: Delivery | C81: 500 | D81: =IFERROR(VLOOKUP("3 COUNTRY WINGS D",'FOOD COST'!$A:$Y,7,0),"") -> 4.86849 | E81: =IFERROR(VLOOKUP("3 COUNTRY WINGS D",'FOOD COST'!$A:$Y,8,0),"") -> 4.86849 | F81: =IFERROR(VLOOKUP("3 COUNTRY WINGS D",'FOOD COST'!$A:$Y,10,0),"") -> 15.315315 | G81: =IFERROR(VLOOKUP("3 COUNTRY WINGS D",'FOOD COST'!$A:$Y,18,0),"") -> 15.540541 | H81: =IFERROR(VLOOKUP("3 COUNTRY WINGS D",'FOOD COST'!$A:$Y,21,0),"") -> 15.765766 | I81: =IFERROR(VLOOKUP("3 COUNTRY WINGS D",'FOOD COST'!$A:$Y,24,0),"") -> 16.207207 | J81: =IF(OR(C81="",NOT(ISNUMBER(D81))),"",C81*D81) -> 2434.245 | K81: =IF(OR(C81="",NOT(ISNUMBER(E81))),"",C81*E81) -> 2434.245 | L81: =IF(OR(C81="",NOT(ISNUMBER(F81))),"",C81*F81) -> 7657.6577 | M81: =IF(OR(C81="",NOT(ISNUMBER(G81))),"",C81*G81) -> 7770.2703 | N81: =IF(OR(C81="",NOT(ISNUMBER(H81))),"",C81*H81) -> 7882.8829 | O81: =IF(OR(C81="",NOT(ISNUMBER(I81))),"",C81*I81) -> 8103.6036
A82: 5 COUNTRY WINGS | B82: Instore | C82: 2175 | D82: =IFERROR(VLOOKUP("5 COUNTRY WINGS",'FOOD COST'!$A:$Y,7,0),"") -> 7.78615 | E82: =IFERROR(VLOOKUP("5 COUNTRY WINGS",'FOOD COST'!$A:$Y,8,0),"") -> 7.78615 | F82: =IFERROR(VLOOKUP("5 COUNTRY WINGS",'FOOD COST'!$A:$Y,10,0),"") -> 18.918919 | G82: =IFERROR(VLOOKUP("5 COUNTRY WINGS",'FOOD COST'!$A:$Y,18,0),"") -> 19.144144 | H82: =IFERROR(VLOOKUP("5 COUNTRY WINGS",'FOOD COST'!$A:$Y,21,0),"") -> 19.369369 | I82: =IFERROR(VLOOKUP("5 COUNTRY WINGS",'FOOD COST'!$A:$Y,24,0),"") -> 19.810811 | J82: =IF(OR(C82="",NOT(ISNUMBER(D82))),"",C82*D82) -> 16934.876 | K82: =IF(OR(C82="",NOT(ISNUMBER(E82))),"",C82*E82) -> 16934.876 | L82: =IF(OR(C82="",NOT(ISNUMBER(F82))),"",C82*F82) -> 41148.649 | M82: =IF(OR(C82="",NOT(ISNUMBER(G82))),"",C82*G82) -> 41638.514 | N82: =IF(OR(C82="",NOT(ISNUMBER(H82))),"",C82*H82) -> 42128.378 | O82: =IF(OR(C82="",NOT(ISNUMBER(I82))),"",C82*I82) -> 43088.514
A83: 5 COUNTRY WINGS D | B83: Delivery | C83: 531 | D83: =IFERROR(VLOOKUP("5 COUNTRY WINGS D",'FOOD COST'!$A:$Y,7,0),"") -> 7.78615 | E83: =IFERROR(VLOOKUP("5 COUNTRY WINGS D",'FOOD COST'!$A:$Y,8,0),"") -> 7.78615 | F83: =IFERROR(VLOOKUP("5 COUNTRY WINGS D",'FOOD COST'!$A:$Y,10,0),"") -> 24.774775 | G83: =IFERROR(VLOOKUP("5 COUNTRY WINGS D",'FOOD COST'!$A:$Y,18,0),"") -> 25 | H83: =IFERROR(VLOOKUP("5 COUNTRY WINGS D",'FOOD COST'!$A:$Y,21,0),"") -> 25.225225 | I83: =IFERROR(VLOOKUP("5 COUNTRY WINGS D",'FOOD COST'!$A:$Y,24,0),"") -> 25.666667 | J83: =IF(OR(C83="",NOT(ISNUMBER(D83))),"",C83*D83) -> 4134.4456 | K83: =IF(OR(C83="",NOT(ISNUMBER(E83))),"",C83*E83) -> 4134.4456 | L83: =IF(OR(C83="",NOT(ISNUMBER(F83))),"",C83*F83) -> 13155.405 | M83: =IF(OR(C83="",NOT(ISNUMBER(G83))),"",C83*G83) -> 13275 | N83: =IF(OR(C83="",NOT(ISNUMBER(H83))),"",C83*H83) -> 13394.595 | O83: =IF(OR(C83="",NOT(ISNUMBER(I83))),"",C83*I83) -> 13629
A84: 7 COUNTRY WINGS | B84: Instore | C84: 1436 | D84: =IFERROR(VLOOKUP("7 COUNTRY WINGS",'FOOD COST'!$A:$Y,7,0),"") -> 10.70381 | E84: =IFERROR(VLOOKUP("7 COUNTRY WINGS",'FOOD COST'!$A:$Y,8,0),"") -> 10.70381 | F84: =IFERROR(VLOOKUP("7 COUNTRY WINGS",'FOOD COST'!$A:$Y,10,0),"") -> 23.873874 | G84: =IFERROR(VLOOKUP("7 COUNTRY WINGS",'FOOD COST'!$A:$Y,18,0),"") -> 24.099099 | H84: =IFERROR(VLOOKUP("7 COUNTRY WINGS",'FOOD COST'!$A:$Y,21,0),"") -> 24.324324 | I84: =IFERROR(VLOOKUP("7 COUNTRY WINGS",'FOOD COST'!$A:$Y,24,0),"") -> 24.765766 | J84: =IF(OR(C84="",NOT(ISNUMBER(D84))),"",C84*D84) -> 15370.671 | K84: =IF(OR(C84="",NOT(ISNUMBER(E84))),"",C84*E84) -> 15370.671 | L84: =IF(OR(C84="",NOT(ISNUMBER(F84))),"",C84*F84) -> 34282.883 | M84: =IF(OR(C84="",NOT(ISNUMBER(G84))),"",C84*G84) -> 34606.306 | N84: =IF(OR(C84="",NOT(ISNUMBER(H84))),"",C84*H84) -> 34929.73 | O84: =IF(OR(C84="",NOT(ISNUMBER(I84))),"",C84*I84) -> 35563.64
A85: 7 COUNTRY WINGS D | B85: Delivery | C85: 701 | D85: =IFERROR(VLOOKUP("7 COUNTRY WINGS D",'FOOD COST'!$A:$Y,7,0),"") -> 10.70381 | E85: =IFERROR(VLOOKUP("7 COUNTRY WINGS D",'FOOD COST'!$A:$Y,8,0),"") -> 10.70381 | F85: =IFERROR(VLOOKUP("7 COUNTRY WINGS D",'FOOD COST'!$A:$Y,10,0),"") -> 27.477477 | G85: =IFERROR(VLOOKUP("7 COUNTRY WINGS D",'FOOD COST'!$A:$Y,18,0),"") -> 27.702703 | H85: =IFERROR(VLOOKUP("7 COUNTRY WINGS D",'FOOD COST'!$A:$Y,21,0),"") -> 27.927928 | I85: =IFERROR(VLOOKUP("7 COUNTRY WINGS D",'FOOD COST'!$A:$Y,24,0),"") -> 28.369369 | J85: =IF(OR(C85="",NOT(ISNUMBER(D85))),"",C85*D85) -> 7503.3708 | K85: =IF(OR(C85="",NOT(ISNUMBER(E85))),"",C85*E85) -> 7503.3708 | L85: =IF(OR(C85="",NOT(ISNUMBER(F85))),"",C85*F85) -> 19261.712 | M85: =IF(OR(C85="",NOT(ISNUMBER(G85))),"",C85*G85) -> 19419.595 | N85: =IF(OR(C85="",NOT(ISNUMBER(H85))),"",C85*H85) -> 19577.477 | O85: =IF(OR(C85="",NOT(ISNUMBER(I85))),"",C85*I85) -> 19886.928
A86: 9 COUNTRY WINGS | B86: Instore | C86: 1063 | D86: =IFERROR(VLOOKUP("9 COUNTRY WINGS",'FOOD COST'!$A:$Y,7,0),"") -> 13.62147 | E86: =IFERROR(VLOOKUP("9 COUNTRY WINGS",'FOOD COST'!$A:$Y,8,0),"") -> 13.62147 | F86: =IFERROR(VLOOKUP("9 COUNTRY WINGS",'FOOD COST'!$A:$Y,10,0),"") -> 28.378378 | G86: =IFERROR(VLOOKUP("9 COUNTRY WINGS",'FOOD COST'!$A:$Y,18,0),"") -> 28.603604 | H86: =IFERROR(VLOOKUP("9 COUNTRY WINGS",'FOOD COST'!$A:$Y,21,0),"") -> 28.828829 | I86: =IFERROR(VLOOKUP("9 COUNTRY WINGS",'FOOD COST'!$A:$Y,24,0),"") -> 29.27027 | J86: =IF(OR(C86="",NOT(ISNUMBER(D86))),"",C86*D86) -> 14479.623 | K86: =IF(OR(C86="",NOT(ISNUMBER(E86))),"",C86*E86) -> 14479.623 | L86: =IF(OR(C86="",NOT(ISNUMBER(F86))),"",C86*F86) -> 30166.216 | M86: =IF(OR(C86="",NOT(ISNUMBER(G86))),"",C86*G86) -> 30405.631 | N86: =IF(OR(C86="",NOT(ISNUMBER(H86))),"",C86*H86) -> 30645.045 | O86: =IF(OR(C86="",NOT(ISNUMBER(I86))),"",C86*I86) -> 31114.297
A87: 9 COUNTRY WINGS D | B87: Delivery | C87: 1224 | D87: =IFERROR(VLOOKUP("9 COUNTRY WINGS D",'FOOD COST'!$A:$Y,7,0),"") -> 13.62147 | E87: =IFERROR(VLOOKUP("9 COUNTRY WINGS D",'FOOD COST'!$A:$Y,8,0),"") -> 13.62147 | F87: =IFERROR(VLOOKUP("9 COUNTRY WINGS D",'FOOD COST'!$A:$Y,10,0),"") -> 32.432432 | G87: =IFERROR(VLOOKUP("9 COUNTRY WINGS D",'FOOD COST'!$A:$Y,18,0),"") -> 32.657658 | H87: =IFERROR(VLOOKUP("9 COUNTRY WINGS D",'FOOD COST'!$A:$Y,21,0),"") -> 32.882883 | I87: =IFERROR(VLOOKUP("9 COUNTRY WINGS D",'FOOD COST'!$A:$Y,24,0),"") -> 33.324324 | J87: =IF(OR(C87="",NOT(ISNUMBER(D87))),"",C87*D87) -> 16672.679 | K87: =IF(OR(C87="",NOT(ISNUMBER(E87))),"",C87*E87) -> 16672.679 | L87: =IF(OR(C87="",NOT(ISNUMBER(F87))),"",C87*F87) -> 39697.297 | M87: =IF(OR(C87="",NOT(ISNUMBER(G87))),"",C87*G87) -> 39972.973 | N87: =IF(OR(C87="",NOT(ISNUMBER(H87))),"",C87*H87) -> 40248.649 | O87: =IF(OR(C87="",NOT(ISNUMBER(I87))),"",C87*I87) -> 40788.973
A88: 3 HOT COUNTRY WINGS | B88: Instore | C88: 1527 | D88: =IFERROR(VLOOKUP("3 HOT COUNTRY WINGS",'FOOD COST'!$A:$Y,7,0),"") -> 5.25409 | E88: =IFERROR(VLOOKUP("3 HOT COUNTRY WINGS",'FOOD COST'!$A:$Y,8,0),"") -> 5.25409 | F88: =IFERROR(VLOOKUP("3 HOT COUNTRY WINGS",'FOOD COST'!$A:$Y,10,0),"") -> 13.063063 | G88: =IFERROR(VLOOKUP("3 HOT COUNTRY WINGS",'FOOD COST'!$A:$Y,18,0),"") -> 13.288288 | H88: =IFERROR(VLOOKUP("3 HOT COUNTRY WINGS",'FOOD COST'!$A:$Y,21,0),"") -> 13.513514 | I88: =IFERROR(VLOOKUP("3 HOT COUNTRY WINGS",'FOOD COST'!$A:$Y,24,0),"") -> 13.954955 | J88: =IF(OR(C88="",NOT(ISNUMBER(D88))),"",C88*D88) -> 8022.9954 | K88: =IF(OR(C88="",NOT(ISNUMBER(E88))),"",C88*E88) -> 8022.9954 | L88: =IF(OR(C88="",NOT(ISNUMBER(F88))),"",C88*F88) -> 19947.297 | M88: =IF(OR(C88="",NOT(ISNUMBER(G88))),"",C88*G88) -> 20291.216 | N88: =IF(OR(C88="",NOT(ISNUMBER(H88))),"",C88*H88) -> 20635.135 | O88: =IF(OR(C88="",NOT(ISNUMBER(I88))),"",C88*I88) -> 21309.216
A89: 3 HOT COUNTRY WINGS D | B89: Delivery | C89: 1121 | D89: =IFERROR(VLOOKUP("3 HOT COUNTRY WINGS D",'FOOD COST'!$A:$Y,7,0),"") -> 5.25409 | E89: =IFERROR(VLOOKUP("3 HOT COUNTRY WINGS D",'FOOD COST'!$A:$Y,8,0),"") -> 5.25409 | F89: =IFERROR(VLOOKUP("3 HOT COUNTRY WINGS D",'FOOD COST'!$A:$Y,10,0),"") -> 15.315315 | G89: =IFERROR(VLOOKUP("3 HOT COUNTRY WINGS D",'FOOD COST'!$A:$Y,18,0),"") -> 15.540541 | H89: =IFERROR(VLOOKUP("3 HOT COUNTRY WINGS D",'FOOD COST'!$A:$Y,21,0),"") -> 15.765766 | I89: =IFERROR(VLOOKUP("3 HOT COUNTRY WINGS D",'FOOD COST'!$A:$Y,24,0),"") -> 16.207207 | J89: =IF(OR(C89="",NOT(ISNUMBER(D89))),"",C89*D89) -> 5889.8349 | K89: =IF(OR(C89="",NOT(ISNUMBER(E89))),"",C89*E89) -> 5889.8349 | L89: =IF(OR(C89="",NOT(ISNUMBER(F89))),"",C89*F89) -> 17168.468 | M89: =IF(OR(C89="",NOT(ISNUMBER(G89))),"",C89*G89) -> 17420.946 | N89: =IF(OR(C89="",NOT(ISNUMBER(H89))),"",C89*H89) -> 17673.423 | O89: =IF(OR(C89="",NOT(ISNUMBER(I89))),"",C89*I89) -> 18168.279
A90: 5 HOT COUNTRY WINGS | B90: Instore | C90: 2717 | D90: =IFERROR(VLOOKUP("5 HOT COUNTRY WINGS",'FOOD COST'!$A:$Y,7,0),"") -> 8.39815 | E90: =IFERROR(VLOOKUP("5 HOT COUNTRY WINGS",'FOOD COST'!$A:$Y,8,0),"") -> 8.39815 | F90: =IFERROR(VLOOKUP("5 HOT COUNTRY WINGS",'FOOD COST'!$A:$Y,10,0),"") -> 18.918919 | G90: =IFERROR(VLOOKUP("5 HOT COUNTRY WINGS",'FOOD COST'!$A:$Y,18,0),"") -> 19.144144 | H90: =IFERROR(VLOOKUP("5 HOT COUNTRY WINGS",'FOOD COST'!$A:$Y,21,0),"") -> 19.369369 | I90: =IFERROR(VLOOKUP("5 HOT COUNTRY WINGS",'FOOD COST'!$A:$Y,24,0),"") -> 19.810811 | J90: =IF(OR(C90="",NOT(ISNUMBER(D90))),"",C90*D90) -> 22817.774 | K90: =IF(OR(C90="",NOT(ISNUMBER(E90))),"",C90*E90) -> 22817.774 | L90: =IF(OR(C90="",NOT(ISNUMBER(F90))),"",C90*F90) -> 51402.703 | M90: =IF(OR(C90="",NOT(ISNUMBER(G90))),"",C90*G90) -> 52014.64 | N90: =IF(OR(C90="",NOT(ISNUMBER(H90))),"",C90*H90) -> 52626.577 | O90: =IF(OR(C90="",NOT(ISNUMBER(I90))),"",C90*I90) -> 53825.973
A91: 5 HOT COUNTRY WINGS D | B91: Delivery | C91: 909 | D91: =IFERROR(VLOOKUP("5 HOT COUNTRY WINGS D",'FOOD COST'!$A:$Y,7,0),"") -> 8.39815 | E91: =IFERROR(VLOOKUP("5 HOT COUNTRY WINGS D",'FOOD COST'!$A:$Y,8,0),"") -> 8.39815 | F91: =IFERROR(VLOOKUP("5 HOT COUNTRY WINGS D",'FOOD COST'!$A:$Y,10,0),"") -> 24.774775 | G91: =IFERROR(VLOOKUP("5 HOT COUNTRY WINGS D",'FOOD COST'!$A:$Y,18,0),"") -> 25 | H91: =IFERROR(VLOOKUP("5 HOT COUNTRY WINGS D",'FOOD COST'!$A:$Y,21,0),"") -> 25.225225 | I91: =IFERROR(VLOOKUP("5 HOT COUNTRY WINGS D",'FOOD COST'!$A:$Y,24,0),"") -> 25.666667 | J91: =IF(OR(C91="",NOT(ISNUMBER(D91))),"",C91*D91) -> 7633.9183 | K91: =IF(OR(C91="",NOT(ISNUMBER(E91))),"",C91*E91) -> 7633.9183 | L91: =IF(OR(C91="",NOT(ISNUMBER(F91))),"",C91*F91) -> 22520.27 | M91: =IF(OR(C91="",NOT(ISNUMBER(G91))),"",C91*G91) -> 22725 | N91: =IF(OR(C91="",NOT(ISNUMBER(H91))),"",C91*H91) -> 22929.73 | O91: =IF(OR(C91="",NOT(ISNUMBER(I91))),"",C91*I91) -> 23331
A92: 7 HOT COUNTRY WINGS | B92: Instore | C92: 1324 | D92: =IFERROR(VLOOKUP("7 HOT COUNTRY WINGS",'FOOD COST'!$A:$Y,7,0),"") -> 11.54221 | E92: =IFERROR(VLOOKUP("7 HOT COUNTRY WINGS",'FOOD COST'!$A:$Y,8,0),"") -> 11.54221 | F92: =IFERROR(VLOOKUP("7 HOT COUNTRY WINGS",'FOOD COST'!$A:$Y,10,0),"") -> 23.873874 | G92: =IFERROR(VLOOKUP("7 HOT COUNTRY WINGS",'FOOD COST'!$A:$Y,18,0),"") -> 24.099099 | H92: =IFERROR(VLOOKUP("7 HOT COUNTRY WINGS",'FOOD COST'!$A:$Y,21,0),"") -> 24.324324 | I92: =IFERROR(VLOOKUP("7 HOT COUNTRY WINGS",'FOOD COST'!$A:$Y,24,0),"") -> 24.765766 | J92: =IF(OR(C92="",NOT(ISNUMBER(D92))),"",C92*D92) -> 15281.886 | K92: =IF(OR(C92="",NOT(ISNUMBER(E92))),"",C92*E92) -> 15281.886 | L92: =IF(OR(C92="",NOT(ISNUMBER(F92))),"",C92*F92) -> 31609.009 | M92: =IF(OR(C92="",NOT(ISNUMBER(G92))),"",C92*G92) -> 31907.207 | N92: =IF(OR(C92="",NOT(ISNUMBER(H92))),"",C92*H92) -> 32205.405 | O92: =IF(OR(C92="",NOT(ISNUMBER(I92))),"",C92*I92) -> 32789.874
